Workbook

Sheet Inicio
B2: PRESUPUESTO FINANCIERO — PredictIT · Entrega 1
B4: Sistema de mantenimiento predictivo de equipos informáticos
B5: Trabajo Final de Ingeniería · UAI · Pettini, Patricio Ezequiel — Legajo B00072710-T1
B6: Horizonte: 2027 a 2030, mensual · Generado el 17/09/2026
B8: Las celdas amarillas son supuestos que se pueden cambiar. Todo lo demás se calcula.
B10: Contenido
B11: Hipótesis | C11: Supuestos macro, mercado meta, embudo comercial y retención
B12: Planes | C12: Líneas de servicio: precio, equipos incluidos y costo variable unitario
B13: Proyección de ventas | C13: Altas, bajas y base activa de clientes por línea, mes a mes
B14: Modelo de ingresos | C14: Facturación por línea de servicio
B15: Modelo de Egresos | C15: Consolidado de las tres estructuras de costo
B16: Costos Fijos | C16: Costos que no dependen del volumen
B17: Costos Variables | C17: Costos que se mueven con cada cliente
B18: RRHH | C18: Sueldos, cargas sociales y evolución de la plantilla
B23: Gráficos | C23: La operación en cuatro imágenes
B25: Primera entrega de negocio: llega hasta los costos de recursos humanos.

Sheet Hipótesis
A1: « Inicio
B2: HIPÓTESIS
B3: Cada variable necesita valor, fuente y justificación. Las celdas amarillas son las que se cargan a mano.
B6: Supuestos macroeconómicos
C7: 2027 | D7: 2028 | E7: 2029 | F7: 2030 | H7: Fuente y justificación
B8: Inflación anual proyectada | C8: 0.205 | D8: 0.141 | E8: 0.12 | F8: 0.1 | H8: REM del BCRA, agosto de 2026 (mediana): 20,5 % para 2027 y 14,1 % para 2028. 2029 y 2030 son extrapolación propia de esa senda: el REM llega a tres períodos anuales
B9: Tipo de cambio promedio (ARS/USD) | C9: 1800 | D9: 2050 | E9: 2300 | F9: 2530 | H9: REM del BCRA, agosto de 2026 (mediana): 1.661 $/USD en ene-27 y 1.844 a doce meses. El promedio de 2027 sale de esa senda; de 2028 en adelante acompaña a la inflación
B10: Tasa de interés de referencia | C10: 0.21 | D10: 0.16 | E10: 0.135 | F10: 0.12 | H10: REM del BCRA, agosto de 2026: TAMAR de bancos privados 23,45 % TNA a dic-26. El promedio de 2027 sale de continuar esa baja; de 2028 en adelante, extrapolación propia
B11: Puntos de precio de lista sobre la inflación | C11: 0.03 | D11: 0.03 | E11: 0.03 | F11: 0.03 | H11: Política propia: la lista se revisa por trimestre y se ubica 3 puntos por encima de la inflación proyectada, para que el precio real no se licúe
B12: Aumento anual de precios de lista | C12: =$C$8+$C$11 | D12: =$D$8+$D$11 | E12: =$E$8+$E$11 | F12: =$F$8+$F$11 | H12: Calculado: inflación del año más los puntos de arriba. Antes estaba tipeado con la cuenta ya hecha, así que cambiar la inflación no lo movía
B13: Puntos de salario sobre la inflación | C13: 0.05 | D13: 0.05 | E13: 0.05 | F13: 0.05 | H13: Política propia: 5 puntos por encima de la inflación, que es la recomposición real que viene mostrando el sector. Contrastar contra la encuesta de sueldos de Sysarmy
B14: Aumento anual de salarios | C14: =$C$8+$C$13 | D14: =$D$8+$D$13 | E14: =$E$8+$E$13 | F14: =$F$8+$F$13 | H14: Calculado: inflación del año más los puntos de arriba
B16: Prima de riesgo del proyecto sobre la inflación | C16: 0.2 | H16: Decisión propia: 20 puntos reales es lo que un proyecto de software sin historial tiene que ofrecer por encima de la inflación para justificar el capital propio
B17: Tasa de corte para el VAN | C17: =$C$8+$C$16 | H17: Calculado: inflación del año 1 más la prima de riesgo. Es el costo de oportunidad del capital propio, nominal en pesos
B18: Cuánto le gana a la tasa de referencia | C18: =$C$17-$C$10 | H18: Control: si la tasa de corte no le gana a la TAMAR del REM, el proyecto no compite contra un plazo fijo y el VAN pierde sentido
B19: Múltiplo de ingresos anuales para el valor terminal | C19: 1.5 | H19: Cuántas veces los ingresos del último año vale la cartera al cierre del horizonte. Rango de mercado para un MSP chico: 1x a 3x
B21: Mercado meta
B22: PyMEs empleadoras en el país | C22: 549100 | H22: SEPYME / CEP XXI, datos de 2023. Es la base de todo el dimensionamiento
B23: de 10 a 49 empleados | C23: 0.12 | H23: SEPYME: 85 % microempresas de 1 a 9, 12 % pequeñas de 10 a 49, 2,5 % medianas
B24: microempresas de 1 a 9 empleados | C24: 0.85 | H24: SEPYME
B25: de esas microempresas, las de 5 a 9 | C25: 0.2 | H25: Supuesto propio: el tramo de 1 a 4 concentra la mayor parte de las microempresas. Es el supuesto que más mueve el resultado y por eso está declarado aparte
B26: Participación de CABA | C26: 0.172 | H26: SEPYME, 2023: CABA reúne el 17,2 % de los establecimientos del país
B27: Participación de la provincia de Buenos Aires | C27: 0.323 | H27: SEPYME, 2023: la Provincia reúne el 32,3 %
B28: de la Provincia, lo que cae dentro del AMBA | C28: 0.75 | H28: Supuesto propio: los 24 partidos del Gran Buenos Aires concentran la mayor parte de la actividad económica de la Provincia, más que su proporción de población
B29: PyMEs de 5 a 50 empleados en AMBA | C29: =ROUND(C22*(C23+C24*C25)*(C26+C27*C28),0) | H29: Calculado: (pequeñas de 10 a 49 + el tramo de 5 a 9 de las microempresas) por la participación del AMBA. Reemplaza a los 72.000 que el plan traía sin fuente citada
B30: % con dependencia operativa alta de sus equipos | C30: 0.32 | H30: Servicios profesionales, salud, educación privada y comercio digitalizado (documento, 4.2)
B31: Mercado meta alcanzable | C31: =ROUND(C29*C30,0) | H31: Calculado
B32: Participación objetivo al año 4 | C32: 0.014 | H32: Decisión propia. Punto intermedio entre el 1,1 % que declaraba el plan y el 1,66 % que proyecta el modelo: el objetivo estaba corto y la proyección es optimista, así que se corrigen los dos hacia el medio en lugar de forzar uno para que coincida con el otro
B34: Embudo comercial | H34: Tasas de la sección 5.3.5 del documento, tomando el punto medio de cada rango
B35: Visitas web mensuales al inicio | C35: 300 | H35: Supuesto propio de arranque
B36: Crecimiento mensual de visitas | C36: 0.12 | D36: 0.08 | E36: 0.05 | F36: 0.03 | H36: Por año. Se desacelera: sostener 12 % mensual durante cuatro años multiplicaría las visitas por 200, que no es defendible
B37: Visitas a prueba gratuita iniciada | C37: 0.02 | H37: Decisión propia. Es la tasa de alta autogestionada de un producto que se prueba sin hablar con nadie; el rango del sector va de 1 % a 3 %
B38: Prueba gratuita a cliente pago | C38: 0.12 | H38: Decisión propia. Convierte menos que una prueba precedida por demostración —el documento daba 25 % a 30 %— porque nadie califica al que se registra. Lo que se gana es que el volumen deja de depender de las horas de una persona
B39: Conversión total de visita a cliente | C39: =C37*C38 | H39: Calculado. Con 1.000 visitas mensuales da del orden de 2 a 3 clientes nuevos por mes, que es lo que proyecta el documento para la Etapa E3
B41: Pilotos y canal de partners
B42: Pilotos gratuitos en la Etapa E1 | C42: 5 | H42: Documento 5.3.4
B43: % de pilotos que convierten a plan pago | C43: 0.6 | H43: Documento 5.3.4: al menos 3 de 5
B44: Mes en que convierten los pilotos | C44: 6 | H44: Cierre de los 90 días de piloto
B45: Partners activos al cierre de cada año | C45: 3 | D45: 8 | E45: 15 | F45: 25 | H45: Documento 5.3.1: 3 partners operativos al mes 12
B46: Clientes gestionados por cada partner | C46: 3 | D46: 4 | E46: 5 | F46: 5 | H46: Documento 5.3.6: mínimo de 3 clientes gestionados para acceder al descuento. Es un stock, no un flujo: un partner tiene una cartera finita
B47: Altas anuales del Plan Estándar (Segmento B) | C47: 1.2 | D47: 4.8 | E47: 9.6 | F47: 14.4 | H47: Documento 5.3.5: ciclo de venta de 60 a 90 días y el primer cliente en la Etapa E3. Es un supuesto directo y no sale del embudo: al Segmento B se lo sale a buscar, no entra por la web
B49: Retención y parque administrado
B50: Baja mensual de clientes | C50: 0.07 | D50: 0.05 | E50: 0.04 | F50: 0.04 | H50: Documento 5.3.3: menor o igual a 7 % en E2 y a 5 % en E3
B51: Equipos promedio por cliente — Plan Inicial | C51: 18 | D51: 20 | E51: 22 | F51: 24 | H51: Segmento A: de 10 a 80 equipos (documento, 4.2). Por encima de los 15 que incluye el plan, así que genera facturación por equipo adicional
B52: Equipos promedio por cliente — Plan Estándar | C52: 90 | D52: 100 | E52: 110 | F52: 120 | H52: Segmento B: de 80 a 250 equipos
B53: Equipos promedio por cliente — Plan Partner | C53: 15 | D53: 16 | E53: 17 | F53: 18 | H53: Clientes chicos gestionados por el canal
B55: Las filas marcadas PENDIENTE no tienen valor cargado a propósito: son las que exigen fuente citada y no se completan a ojo.

Sheet Planes
A1: « Inicio
B2: LÍNEAS DE SERVICIO
B3: Precios revisados en D-14, no los de la sección 5.3.6 del documento. Costos variables unitarios de la sección 6.5.3.
B6: Plan | C6: Segmento | D6: Abono mensual | E6: Equipos incluidos | F6: Equipo adicional | G6: CV infraestructura | H6: CV soporte | I6: CV servicio de IA | J6: CV total | K6: Margen de contribución
B7: Plan Inicial | C7: A | D7: 89000 | E7: 15 | F7: 4200 | G7: 3000 | H7: 4000 | I7: 1500 | J7: =SUM(G7:I7) | K7: =(D7-J7)/D7 | L7: Precio revisado (D-14). USD 49,4 por 15 equipos: USD 3,3 por equipo
B8: Plan Estándar | C8: B | D8: 239000 | E8: 50 | F8: 3500 | G8: 9000 | H8: 12000 | I8: 4000 | J8: =SUM(G8:I8) | K8: =(D8-J8)/D8 | L8: Precio revisado (D-14). USD 132,8 por 50 equipos: USD 2,7 por equipo
B9: Plan Partner | C9: C | D9: 69000 | E9: 30 | F9: 2800 | G9: 2500 | H9: 2500 | I9: 2000 | J9: =SUM(G9:I9) | K9: =(D9-J9)/D9 | L9: Precio revisado (D-14). USD 38,3 por 30 equipos: USD 1,3 por equipo. Mas bajo porque el partner aporta el canal y la primera linea de soporte
B11: El margen de contribución de cada línea lo calcula la columna de la derecha y hoy da alrededor del 90 % en las tres. Es alto, y tiene una explicación: el costo variable de un cliente de software es infraestructura y soporte, no producto. Lo que se come ese margen no es el costo variable sino la estructura fija y los sueldos, que es donde se juega el punto de equilibrio. Hasta la revisión de precios de D-14 daba entre 74 % y 76 %, que es lo que todavía dice la sección 6.5.3 del documento: hay que actualizarla.

Sheet Proyección de ventas
A1: « Inicio
B2: PROYECCIÓN DE VENTAS
B3: Clientes por línea de servicio, mes a mes. Las altas salen del embudo comercial, de la conversión de pilotos y del canal de partners; las tres fuentes se modelan por separado. | Q3: Resumen anual
Q4: Los totales de cada año, que son los que alimentan el gráfico.
Q5: Concepto | R5: 2027 | S5: 2028 | T5: 2029 | U5: 2030
Q6: Plan Inicial — Segmento A | R6: =O20 | S6: =O50 | T6: =O80 | U6: =O110
C7: 2027 | Q7: Plan Estándar — Segmento B | R7: =O26 | S7: =O56 | T7: =O86 | U7: =O116
C8: Ene | D8: Feb | E8: Mar | F8: Abr | G8: May | H8: Jun | I8: Jul | J8: Ago | K8: Sep | L8: Oct | M8: Nov | N8: Dic | O8: Total 2027 | Q8: Plan Partner — Segmento C | R8: =O30 | S8: =O60 | T8: =O90 | U8: =O120
B10: Embudo comercial
A11: EMBUDO | B11: Visitas web | C11: =Hipótesis!$C$35 | D11: =C11*(1+Hipótesis!$C$36) | E11: =D11*(1+Hipótesis!$C$36) | F11: =E11*(1+Hipótesis!$C$36) | G11: =F11*(1+Hipótesis!$C$36) | H11: =G11*(1+Hipótesis!$C$36) | I11: =H11*(1+Hipótesis!$C$36) | J11: =I11*(1+Hipótesis!$C$36) | K11: =J11*(1+Hipótesis!$C$36) | ... N11: =M11*(1+Hipótesis!$C$36) | O11: =SUM(C11:N11)
B12: Pruebas gratuitas iniciadas | C12: =C11*Hipótesis!$C$37 | D12: =D11*Hipótesis!$C$37 | E12: =E11*Hipótesis!$C$37 | F12: =F11*Hipótesis!$C$37 | G12: =G11*Hipótesis!$C$37 | H12: =H11*Hipótesis!$C$37 | I12: =I11*Hipótesis!$C$37 | J12: =J11*Hipótesis!$C$37 | ... N12: =N11*Hipótesis!$C$37 | O12: =SUM(C12:N12)
B13: Clientes nuevos por embudo directo | C13: =IF(1<Hipótesis!$C$44,0,C12*Hipótesis!$C$38) | D13: =IF(2<Hipótesis!$C$44,0,D12*Hipótesis!$C$38) | E13: =IF(3<Hipótesis!$C$44,0,E12*Hipótesis!$C$38) | F13: =IF(4<Hipótesis!$C$44,0,F12*Hipótesis!$C$38) | G13: =IF(5<Hipótesis!$C$44,0,G12*Hipótesis!$C$38) | H13: =IF(6<Hipótesis!$C$44,0,H12*Hipótesis!$C$38) | I13: =IF(7<Hipótesis!$C$44,0,I12*Hipótesis!$C$38) | J13: =IF(8<Hipótesis!$C$44,0,J12*Hipótesis!$C$38) | K13: =IF(9<Hipótesis!$C$44,0,K12*Hipótesis!$C$38) | L13: =IF(10<Hipótesis!$C$44,0,L12*Hipótesis!$C$38) | M13: =IF(11<Hipótesis!$C$44,0,M12*Hipótesis!$C$38) | N13: =IF(12<Hipótesis!$C$44,0,N12*Hipótesis!$C$38) | O13: =SUM(C13:N13)
B15: Plan Inicial — Segmento A
A16: PLAN INICIAL | B16: Base al inicio del mes | C16: 0 | D16: =C20 | E16: =D20 | F16: =E20 | G16: =F20 | H16: =G20 | I16: =H20 | J16: =I20 | K16: =J20 | ... N16: =M20
B17: Altas por embudo directo | C17: =C13 | D17: =D13 | E17: =E13 | F17: =F13 | G17: =G13 | H17: =H13 | I17: =I13 | J17: =J13 | ... N17: =N13 | O17: =SUM(C17:N17)
B18: Altas por conversión de pilotos | C18: =IF(AND(1=Hipótesis!$C$44,1=1),Hipótesis!$C$42*Hipótesis!$C$43,0) | D18: =IF(AND(2=Hipótesis!$C$44,1=1),Hipótesis!$C$42*Hipótesis!$C$43,0) | E18: =IF(AND(3=Hipótesis!$C$44,1=1),Hipótesis!$C$42*Hipótesis!$C$43,0) | F18: =IF(AND(4=Hipótesis!$C$44,1=1),Hipótesis!$C$42*Hipótesis!$C$43,0) | G18: =IF(AND(5=Hipótesis!$C$44,1=1),Hipótesis!$C$42*Hipótesis!$C$43,0) | H18: =IF(AND(6=Hipótesis!$C$44,1=1),Hipótesis!$C$42*Hipótesis!$C$43,0) | I18: =IF(AND(7=Hipótesis!$C$44,1=1),Hipótesis!$C$42*Hipótesis!$C$43,0) | J18: =IF(AND(8=Hipótesis!$C$44,1=1),Hipótesis!$C$42*Hipótesis!$C$43,0) | K18: =IF(AND(9=Hipótesis!$C$44,1=1),Hipótesis!$C$42*Hipótesis!$C$43,0) | L18: =IF(AND(10=Hipótesis!$C$44,1=1),Hipótesis!$C$42*Hipótesis!$C$43,0) | M18: =IF(AND(11=Hipótesis!$C$44,1=1),Hipótesis!$C$42*Hipótesis!$C$43,0) | N18: =IF(AND(12=Hipótesis!$C$44,1=1),Hipótesis!$C$42*Hipótesis!$C$43,0) | O18: =SUM(C18:N18)
B19: Bajas | C19: =-C16*Hipótesis!$C$50 | D19: =-D16*Hipótesis!$C$50 | E19: =-E16*Hipótesis!$C$50 | F19: =-F16*Hipótesis!$C$50 | G19: =-G16*Hipótesis!$C$50 | H19: =-H16*Hipótesis!$C$50 | I19: =-I16*Hipótesis!$C$50 | J19: =-J16*Hipótesis!$C$50 | ... N19: =-N16*Hipótesis!$C$50 | O19: =SUM(C19:N19)
B20: Base activa al cierre | C20: =SUM(C16:C19) | D20: =SUM(D16:D19) | E20: =SUM(E16:E19) | F20: =SUM(F16:F19) | G20: =SUM(G16:G19) | H20: =SUM(H16:H19) | I20: =SUM(I16:I19) | J20: =SUM(J16:J19) | ... N20: =SUM(N16:N19) | O20: =N20
B22: Plan Estándar — Segmento B | H22: Las altas del Segmento B son un supuesto directo de la hoja Hipótesis: ciclo de venta de 60 a 90 días (5.3.5) y el primer cliente en la Etapa E3. En el año 1 se reparten entre los meses 9 y 12; de ahí en adelante, a lo largo de los doce.
A23: PLAN ESTÁNDAR | B23: Base al inicio del mes | C23: 0 | D23: =C26 | E23: =D26 | F23: =E26 | G23: =F26 | H23: =G26 | I23: =H26 | J23: =I26 | K23: =J26 | ... N23: =M26
B24: Altas | C24: =IF(1<9,0,Hipótesis!$C$47/IF(1=1,4,12)) | D24: =IF(2<9,0,Hipótesis!$C$47/IF(1=1,4,12)) | E24: =IF(3<9,0,Hipótesis!$C$47/IF(1=1,4,12)) | F24: =IF(4<9,0,Hipótesis!$C$47/IF(1=1,4,12)) | G24: =IF(5<9,0,Hipótesis!$C$47/IF(1=1,4,12)) | H24: =IF(6<9,0,Hipótesis!$C$47/IF(1=1,4,12)) | I24: =IF(7<9,0,Hipótesis!$C$47/IF(1=1,4,12)) | J24: =IF(8<9,0,Hipótesis!$C$47/IF(1=1,4,12)) | K24: =IF(9<9,0,Hipótesis!$C$47/IF(1=1,4,12)) | L24: =IF(10<9,0,Hipótesis!$C$47/IF(1=1,4,12)) | M24: =IF(11<9,0,Hipótesis!$C$47/IF(1=1,4,12)) | N24: =IF(12<9,0,Hipótesis!$C$47/IF(1=1,4,12)) | O24: =SUM(C24:N24)
B25: Bajas | C25: =-C23*Hipótesis!$C$50 | D25: =-D23*Hipótesis!$C$50 | E25: =-E23*Hipótesis!$C$50 | F25: =-F23*Hipótesis!$C$50 | G25: =-G23*Hipótesis!$C$50 | H25: =-H23*Hipótesis!$C$50 | I25: =-I23*Hipótesis!$C$50 | J25: =-J23*Hipótesis!$C$50 | ... N25: =-N23*Hipótesis!$C$50 | O25: =SUM(C25:N25)
B26: Base activa al cierre | C26: =SUM(C23:C25) | D26: =SUM(D23:D25) | E26: =SUM(E23:E25) | F26: =SUM(F23:F25) | G26: =SUM(G23:G25) | H26: =SUM(H23:H25) | I26: =SUM(I23:I25) | J26: =SUM(J23:J25) | ... N26: =SUM(N23:N25) | O26: =N26
B28: Plan Partner — Segmento C | H28: La cartera del canal es un stock, no un flujo: cada partner gestiona una cantidad finita de clientes. Modelarlo como altas mensuales perpetuas haría crecer el canal sin techo.
A29: PLAN PARTNER | B29: Partners activos | C29: =ROUND(Hipótesis!$C$45*1/12,0) | D29: =ROUND(Hipótesis!$C$45*2/12,0) | E29: =ROUND(Hipótesis!$C$45*3/12,0) | F29: =ROUND(Hipótesis!$C$45*4/12,0) | G29: =ROUND(Hipótesis!$C$45*5/12,0) | H29: =ROUND(Hipótesis!$C$45*6/12,0) | I29: =ROUND(Hipótesis!$C$45*7/12,0) | J29: =ROUND(Hipótesis!$C$45*8/12,0) | K29: =ROUND(Hipótesis!$C$45*9/12,0) | L29: =ROUND(Hipótesis!$C$45*10/12,0) | M29: =ROUND(Hipótesis!$C$45*11/12,0) | N29: =ROUND(Hipótesis!$C$45*12/12,0) | O29: =N29
B30: Clientes gestionados por el canal | C30: =IF(1<Hipótesis!$C$44,0,C29*Hipótesis!$C$46) | D30: =IF(2<Hipótesis!$C$44,0,D29*Hipótesis!$C$46) | E30: =IF(3<Hipótesis!$C$44,0,E29*Hipótesis!$C$46) | F30: =IF(4<Hipótesis!$C$44,0,F29*Hipótesis!$C$46) | G30: =IF(5<Hipótesis!$C$44,0,G29*Hipótesis!$C$46) | H30: =IF(6<Hipótesis!$C$44,0,H29*Hipótesis!$C$46) | I30: =IF(7<Hipótesis!$C$44,0,I29*Hipótesis!$C$46) | J30: =IF(8<Hipótesis!$C$44,0,J29*Hipótesis!$C$46) | K30: =IF(9<Hipótesis!$C$44,0,K29*Hipótesis!$C$46) | L30: =IF(10<Hipótesis!$C$44,0,L29*Hipótesis!$C$46) | M30: =IF(11<Hipótesis!$C$44,0,M29*Hipótesis!$C$46) | N30: =IF(12<Hipótesis!$C$44,0,N29*Hipótesis!$C$46) | O30: =N30
B32: Consolidado
A33: TOTAL | B33: Clientes pagos activos | C33: =C20+C26+C30 | D33: =D20+D26+D30 | E33: =E20+E26+E30 | F33: =F20+F26+F30 | G33: =G20+G26+G30 | H33: =H20+H26+H30 | I33: =I20+I26+I30 | J33: =J20+J26+J30 | ... N33: =N20+N26+N30 | O33: =N33
B34: Equipos administrados | C34: =C20*Hipótesis!$C$51+C26*Hipótesis!$C$52+C30*Hipótesis!$C$53 | D34: =D20*Hipótesis!$C$51+D26*Hipótesis!$C$52+D30*Hipótesis!$C$53 | E34: =E20*Hipótesis!$C$51+E26*Hipótesis!$C$52+E30*Hipótesis!$C$53 | F34: =F20*Hipótesis!$C$51+F26*Hipótesis!$C$52+F30*Hipótesis!$C$53 | G34: =G20*Hipótesis!$C$51+G26*Hipótesis!$C$52+G30*Hipótesis!$C$53 | H34: =H20*Hipótesis!$C$51+H26*Hipótesis!$C$52+H30*Hipótesis!$C$53 | I34: =I20*Hipótesis!$C$51+I26*Hipótesis!$C$52+I30*Hipótesis!$C$53 | J34: =J20*Hipótesis!$C$51+J26*Hipótesis!$C$52+J30*Hipótesis!$C$53 | ... N34: =N20*Hipótesis!$C$51+N26*Hipótesis!$C$52+N30*Hipótesis!$C$53 | O34: =N34
C37: 2028
C38: Ene | D38: Feb | E38: Mar | F38: Abr | G38: May | H38: Jun | I38: Jul | J38: Ago | K38: Sep | L38: Oct | M38: Nov | N38: Dic | O38: Total 2028
B40: Embudo comercial
A41: EMBUDO | B41: Visitas web | C41: =N11*(1+Hipótesis!$D$36) | D41: =C41*(1+Hipótesis!$D$36) | E41: =D41*(1+Hipótesis!$D$36) | F41: =E41*(1+Hipótesis!$D$36) | G41: =F41*(1+Hipótesis!$D$36) | H41: =G41*(1+Hipótesis!$D$36) | I41: =H41*(1+Hipótesis!$D$36) | J41: =I41*(1+Hipótesis!$D$36) | K41: =J41*(1+Hipótesis!$D$36) | ... N41: =M41*(1+Hipótesis!$D$36) | O41: =SUM(C41:N41)
B42: Pruebas gratuitas iniciadas | C42: =C41*Hipótesis!$C$37 | D42: =D41*Hipótesis!$C$37 | E42: =E41*Hipótesis!$C$37 | F42: =F41*Hipótesis!$C$37 | G42: =G41*Hipótesis!$C$37 | H42: =H41*Hipótesis!$C$37 | I42: =I41*Hipótesis!$C$37 | J42: =J41*Hipótesis!$C$37 | ... N42: =N41*Hipótesis!$C$37 | O42: =SUM(C42:N42)
B43: Clientes nuevos por embudo directo | C43: =IF(13<Hipótesis!$C$44,0,C42*Hipótesis!$C$38) | D43: =IF(14<Hipótesis!$C$44,0,D42*Hipótesis!$C$38) | E43: =IF(15<Hipótesis!$C$44,0,E42*Hipótesis!$C$38) | F43: =IF(16<Hipótesis!$C$44,0,F42*Hipótesis!$C$38) | G43: =IF(17<Hipótesis!$C$44,0,G42*Hipótesis!$C$38) | H43: =IF(18<Hipótesis!$C$44,0,H42*Hipótesis!$C$38) | I43: =IF(19<Hipótesis!$C$44,0,I42*Hipótesis!$C$38) | J43: =IF(20<Hipótesis!$C$44,0,J42*Hipótesis!$C$38) | K43: =IF(21<Hipótesis!$C$44,0,K42*Hipótesis!$C$38) | L43: =IF(22<Hipótesis!$C$44,0,L42*Hipótesis!$C$38) | M43: =IF(23<Hipótesis!$C$44,0,M42*Hipótesis!$C$38) | N43: =IF(24<Hipótesis!$C$44,0,N42*Hipótesis!$C$38) | O43: =SUM(C43:N43)
B45: Plan Inicial — Segmento A
A46: PLAN INICIAL | B46: Base al inicio del mes | C46: =N20 | D46: =C50 | E46: =D50 | F46: =E50 | G46: =F50 | H46: =G50 | I46: =H50 | J46: =I50 | K46: =J50 | ... N46: =M50
B47: Altas por embudo directo | C47: =C43 | D47: =D43 | E47: =E43 | F47: =F43 | G47: =G43 | H47: =H43 | I47: =I43 | J47: =J43 | ... N47: =N43 | O47: =SUM(C47:N47)
B48: Altas por conversión de pilotos | C48: =IF(AND(13=Hipótesis!$C$44,2=1),Hipótesis!$C$42*Hipótesis!$C$43,0) | D48: =IF(AND(14=Hipótesis!$C$44,2=1),Hipótesis!$C$42*Hipótesis!$C$43,0) | E48: =IF(AND(15=Hipótesis!$C$44,2=1),Hipótesis!$C$42*Hipótesis!$C$43,0) | F48: =IF(AND(16=Hipótesis!$C$44,2=1),Hipótesis!$C$42*Hipótesis!$C$43,0) | G48: =IF(AND(17=Hipótesis!$C$44,2=1),Hipótesis!$C$42*Hipótesis!$C$43,0) | H48: =IF(AND(18=Hipótesis!$C$44,2=1),Hipótesis!$C$42*Hipótesis!$C$43,0) | I48: =IF(AND(19=Hipótesis!$C$44,2=1),Hipótesis!$C$42*Hipótesis!$C$43,0) | J48: =IF(AND(20=Hipótesis!$C$44,2=1),Hipótesis!$C$42*Hipótesis!$C$43,0) | K48: =IF(AND(21=Hipótesis!$C$44,2=1),Hipótesis!$C$42*Hipótesis!$C$43,0) | L48: =IF(AND(22=Hipótesis!$C$44,2=1),Hipótesis!$C$42*Hipótesis!$C$43,0) | M48: =IF(AND(23=Hipótesis!$C$44,2=1),Hipótesis!$C$42*Hipótesis!$C$43,0) | N48: =IF(AND(24=Hipótesis!$C$44,2=1),Hipótesis!$C$42*Hipótesis!$C$43,0) | O48: =SUM(C48:N48)
B49: Bajas | C49: =-C46*Hipótesis!$D$50 | D49: =-D46*Hipótesis!$D$50 | E49: =-E46*Hipótesis!$D$50 | F49: =-F46*Hipótesis!$D$50 | G49: =-G46*Hipótesis!$D$50 | H49: =-H46*Hipótesis!$D$50 | I49: =-I46*Hipótesis!$D$50 | J49: =-J46*Hipótesis!$D$50 | ... N49: =-N46*Hipótesis!$D$50 | O49: =SUM(C49:N49)
B50: Base activa al cierre | C50: =SUM(C46:C49) | D50: =SUM(D46:D49) | E50: =SUM(E46:E49) | F50: =SUM(F46:F49) | G50: =SUM(G46:G49) | H50: =SUM(H46:H49) | I50: =SUM(I46:I49) | J50: =SUM(J46:J49) | ... N50: =SUM(N46:N49) | O50: =N50
B52: Plan Estándar — Segmento B
A53: PLAN ESTÁNDAR | B53: Base al inicio del mes | C53: =N26 | D53: =C56 | E53: =D56 | F53: =E56 | G53: =F56 | H53: =G56 | I53: =H56 | J53: =I56 | K53: =J56 | ... N53: =M56
B54: Altas | C54: =IF(13<9,0,Hipótesis!$D$47/IF(2=1,4,12)) | D54: =IF(14<9,0,Hipótesis!$D$47/IF(2=1,4,12)) | E54: =IF(15<9,0,Hipótesis!$D$47/IF(2=1,4,12)) | F54: =IF(16<9,0,Hipótesis!$D$47/IF(2=1,4,12)) | G54: =IF(17<9,0,Hipótesis!$D$47/IF(2=1,4,12)) | H54: =IF(18<9,0,Hipótesis!$D$47/IF(2=1,4,12)) | I54: =IF(19<9,0,Hipótesis!$D$47/IF(2=1,4,12)) | J54: =IF(20<9,0,Hipótesis!$D$47/IF(2=1,4,12)) | K54: =IF(21<9,0,Hipótesis!$D$47/IF(2=1,4,12)) | L54: =IF(22<9,0,Hipótesis!$D$47/IF(2=1,4,12)) | M54: =IF(23<9,0,Hipótesis!$D$47/IF(2=1,4,12)) | N54: =IF(24<9,0,Hipótesis!$D$47/IF(2=1,4,12)) | O54: =SUM(C54:N54)
B55: Bajas | C55: =-C53*Hipótesis!$D$50 | D55: =-D53*Hipótesis!$D$50 | E55: =-E53*Hipótesis!$D$50 | F55: =-F53*Hipótesis!$D$50 | G55: =-G53*Hipótesis!$D$50 | H55: =-H53*Hipótesis!$D$50 | I55: =-I53*Hipótesis!$D$50 | J55: =-J53*Hipótesis!$D$50 | ... N55: =-N53*Hipótesis!$D$50 | O55: =SUM(C55:N55)
B56: Base activa al cierre | C56: =SUM(C53:C55) | D56: =SUM(D53:D55) | E56: =SUM(E53:E55) | F56: =SUM(F53:F55) | G56: =SUM(G53:G55) | H56: =SUM(H53:H55) | I56: =SUM(I53:I55) | J56: =SUM(J53:J55) | ... N56: =SUM(N53:N55) | O56: =N56
B58: Plan Partner — Segmento C
A59: PLAN PARTNER | B59: Partners activos | C59: =ROUND(Hipótesis!$C$45+(Hipótesis!$D$45-Hipótesis!$C$45)*1/12,0) | D59: =ROUND(Hipótesis!$C$45+(Hipótesis!$D$45-Hipótesis!$C$45)*2/12,0) | E59: =ROUND(Hipótesis!$C$45+(Hipótesis!$D$45-Hipótesis!$C$45)*3/12,0) | F59: =ROUND(Hipótesis!$C$45+(Hipótesis!$D$45-Hipótesis!$C$45)*4/12,0) | G59: =ROUND(Hipótesis!$C$45+(Hipótesis!$D$45-Hipótesis!$C$45)*5/12,0) | H59: =ROUND(Hipótesis!$C$45+(Hipótesis!$D$45-Hipótesis!$C$45)*6/12,0) | I59: =ROUND(Hipótesis!$C$45+(Hipótesis!$D$45-Hipótesis!$C$45)*7/12,0) | J59: =ROUND(Hipótesis!$C$45+(Hipótesis!$D$45-Hipótesis!$C$45)*8/12,0) | K59: =ROUND(Hipótesis!$C$45+(Hipótesis!$D$45-Hipótesis!$C$45)*9/12,0) | L59: =ROUND(Hipótesis!$C$45+(Hipótesis!$D$45-Hipótesis!$C$45)*10/12,0) | M59: =ROUND(Hipótesis!$C$45+(Hipótesis!$D$45-Hipótesis!$C$45)*11/12,0) | N59: =ROUND(Hipótesis!$C$45+(Hipótesis!$D$45-Hipótesis!$C$45)*12/12,0) | O59: =N59
B60: Clientes gestionados por el canal | C60: =IF(13<Hipótesis!$C$44,0,C59*Hipótesis!$D$46) | D60: =IF(14<Hipótesis!$C$44,0,D59*Hipótesis!$D$46) | E60: =IF(15<Hipótesis!$C$44,0,E59*Hipótesis!$D$46) | F60: =IF(16<Hipótesis!$C$44,0,F59*Hipótesis!$D$46) | G60: =IF(17<Hipótesis!$C$44,0,G59*Hipótesis!$D$46) | H60: =IF(18<Hipótesis!$C$44,0,H59*Hipótesis!$D$46) | I60: =IF(19<Hipótesis!$C$44,0,I59*Hipótesis!$D$46) | J60: =IF(20<Hipótesis!$C$44,0,J59*Hipótesis!$D$46) | K60: =IF(21<Hipótesis!$C$44,0,K59*Hipótesis!$D$46) | L60: =IF(22<Hipótesis!$C$44,0,L59*Hipótesis!$D$46) | M60: =IF(23<Hipótesis!$C$44,0,M59*Hipótesis!$D$46) | N60: =IF(24<Hipótesis!$C$44,0,N59*Hipótesis!$D$46) | O60: =N60
B62: Consolidado
A63: TOTAL | B63: Clientes pagos activos | C63: =C50+C56+C60 | D63: =D50+D56+D60 | E63: =E50+E56+E60 | F63: =F50+F56+F60 | G63: =G50+G56+G60 | H63: =H50+H56+H60 | I63: =I50+I56+I60 | J63: =J50+J56+J60 | ... N63: =N50+N56+N60 | O63: =N63
B64: Equipos administrados | C64: =C50*Hipótesis!$D$51+C56*Hipótesis!$D$52+C60*Hipótesis!$D$53 | D64: =D50*Hipótesis!$D$51+D56*Hipótesis!$D$52+D60*Hipótesis!$D$53 | E64: =E50*Hipótesis!$D$51+E56*Hipótesis!$D$52+E60*Hipótesis!$D$53 | F64: =F50*Hipótesis!$D$51+F56*Hipótesis!$D$52+F60*Hipótesis!$D$53 | G64: =G50*Hipótesis!$D$51+G56*Hipótesis!$D$52+G60*Hipótesis!$D$53 | H64: =H50*Hipótesis!$D$51+H56*Hipótesis!$D$52+H60*Hipótesis!$D$53 | I64: =I50*Hipótesis!$D$51+I56*Hipótesis!$D$52+I60*Hipótesis!$D$53 | J64: =J50*Hipótesis!$D$51+J56*Hipótesis!$D$52+J60*Hipótesis!$D$53 | ... N64: =N50*Hipótesis!$D$51+N56*Hipótesis!$D$52+N60*Hipótesis!$D$53 | O64: =N64
C67: 2029
C68: Ene | D68: Feb | E68: Mar | F68: Abr | G68: May | H68: Jun | I68: Jul | J68: Ago | K68: Sep | L68: Oct | M68: Nov | N68: Dic | O68: Total 2029
B70: Embudo comercial
A71: EMBUDO | B71: Visitas web | C71: =N41*(1+Hipótesis!$E$36) | D71: =C71*(1+Hipótesis!$E$36) | E71: =D71*(1+Hipótesis!$E$36) | F71: =E71*(1+Hipótesis!$E$36) | G71: =F71*(1+Hipótesis!$E$36) | H71: =G71*(1+Hipótesis!$E$36) | I71: =H71*(1+Hipótesis!$E$36) | J71: =I71*(1+Hipótesis!$E$36) | K71: =J71*(1+Hipótesis!$E$36) | ... N71: =M71*(1+Hipótesis!$E$36) | O71: =SUM(C71:N71)
B72: Pruebas gratuitas iniciadas | C72: =C71*Hipótesis!$C$37 | D72: =D71*Hipótesis!$C$37 | E72: =E71*Hipótesis!$C$37 | F72: =F71*Hipótesis!$C$37 | G72: =G71*Hipótesis!$C$37 | H72: =H71*Hipótesis!$C$37 | I72: =I71*Hipótesis!$C$37 | J72: =J71*Hipótesis!$C$37 | ... N72: =N71*Hipótesis!$C$37 | O72: =SUM(C72:N72)
B73: Clientes nuevos por embudo directo | C73: =IF(25<Hipótesis!$C$44,0,C72*Hipótesis!$C$38) | D73: =IF(26<Hipótesis!$C$44,0,D72*Hipótesis!$C$38) | E73: =IF(27<Hipótesis!$C$44,0,E72*Hipótesis!$C$38) | F73: =IF(28<Hipótesis!$C$44,0,F72*Hipótesis!$C$38) | G73: =IF(29<Hipótesis!$C$44,0,G72*Hipótesis!$C$38) | H73: =IF(30<Hipótesis!$C$44,0,H72*Hipótesis!$C$38) | I73: =IF(31<Hipótesis!$C$44,0,I72*Hipótesis!$C$38) | J73: =IF(32<Hipótesis!$C$44,0,J72*Hipótesis!$C$38) | K73: =IF(33<Hipótesis!$C$44,0,K72*Hipótesis!$C$38) | L73: =IF(34<Hipótesis!$C$44,0,L72*Hipótesis!$C$38) | M73: =IF(35<Hipótesis!$C$44,0,M72*Hipótesis!$C$38) | N73: =IF(36<Hipótesis!$C$44,0,N72*Hipótesis!$C$38) | O73: =SUM(C73:N73)
B75: Plan Inicial — Segmento A
A76: PLAN INICIAL | B76: Base al inicio del mes | C76: =N50 | D76: =C80 | E76: =D80 | F76: =E80 | G76: =F80 | H76: =G80 | I76: =H80 | J76: =I80 | K76: =J80 | ... N76: =M80
B77: Altas por embudo directo | C77: =C73 | D77: =D73 | E77: =E73 | F77: =F73 | G77: =G73 | H77: =H73 | I77: =I73 | J77: =J73 | ... N77: =N73 | O77: =SUM(C77:N77)
B78: Altas por conversión de pilotos | C78: =IF(AND(25=Hipótesis!$C$44,3=1),Hipótesis!$C$42*Hipótesis!$C$43,0) | D78: =IF(AND(26=Hipótesis!$C$44,3=1),Hipótesis!$C$42*Hipótesis!$C$43,0) | E78: =IF(AND(27=Hipótesis!$C$44,3=1),Hipótesis!$C$42*Hipótesis!$C$43,0) | F78: =IF(AND(28=Hipótesis!$C$44,3=1),Hipótesis!$C$42*Hipótesis!$C$43,0) | G78: =IF(AND(29=Hipótesis!$C$44,3=1),Hipótesis!$C$42*Hipótesis!$C$43,0) | H78: =IF(AND(30=Hipótesis!$C$44,3=1),Hipótesis!$C$42*Hipótesis!$C$43,0) | I78: =IF(AND(31=Hipótesis!$C$44,3=1),Hipótesis!$C$42*Hipótesis!$C$43,0) | J78: =IF(AND(32=Hipótesis!$C$44,3=1),Hipótesis!$C$42*Hipótesis!$C$43,0) | K78: =IF(AND(33=Hipótesis!$C$44,3=1),Hipótesis!$C$42*Hipótesis!$C$43,0) | L78: =IF(AND(34=Hipótesis!$C$44,3=1),Hipótesis!$C$42*Hipótesis!$C$43,0) | M78: =IF(AND(35=Hipótesis!$C$44,3=1),Hipótesis!$C$42*Hipótesis!$C$43,0) | N78: =IF(AND(36=Hipótesis!$C$44,3=1),Hipótesis!$C$42*Hipótesis!$C$43,0) | O78: =SUM(C78:N78)
B79: Bajas | C79: =-C76*Hipótesis!$E$50 | D79: =-D76*Hipótesis!$E$50 | E79: =-E76*Hipótesis!$E$50 | F79: =-F76*Hipótesis!$E$50 | G79: =-G76*Hipótesis!$E$50 | H79: =-H76*Hipótesis!$E$50 | I79: =-I76*Hipótesis!$E$50 | J79: =-J76*Hipótesis!$E$50 | ... N79: =-N76*Hipótesis!$E$50 | O79: =SUM(C79:N79)
B80: Base activa al cierre | C80: =SUM(C76:C79) | D80: =SUM(D76:D79) | E80: =SUM(E76:E79) | F80: =SUM(F76:F79) | G80: =SUM(G76:G79) | H80: =SUM(H76:H79) | I80: =SUM(I76:I79) | J80: =SUM(J76:J79) | ... N80: =SUM(N76:N79) | O80: =N80
B82: Plan Estándar — Segmento B
A83: PLAN ESTÁNDAR | B83: Base al inicio del mes | C83: =N56 | D83: =C86 | E83: =D86 | F83: =E86 | G83: =F86 | H83: =G86 | I83: =H86 | J83: =I86 | K83: =J86 | ... N83: =M86
B84: Altas | C84: =IF(25<9,0,Hipótesis!$E$47/IF(3=1,4,12)) | D84: =IF(26<9,0,Hipótesis!$E$47/IF(3=1,4,12)) | E84: =IF(27<9,0,Hipótesis!$E$47/IF(3=1,4,12)) | F84: =IF(28<9,0,Hipótesis!$E$47/IF(3=1,4,12)) | G84: =IF(29<9,0,Hipótesis!$E$47/IF(3=1,4,12)) | H84: =IF(30<9,0,Hipótesis!$E$47/IF(3=1,4,12)) | I84: =IF(31<9,0,Hipótesis!$E$47/IF(3=1,4,12)) | J84: =IF(32<9,0,Hipótesis!$E$47/IF(3=1,4,12)) | K84: =IF(33<9,0,Hipótesis!$E$47/IF(3=1,4,12)) | L84: =IF(34<9,0,Hipótesis!$E$47/IF(3=1,4,12)) | M84: =IF(35<9,0,Hipótesis!$E$47/IF(3=1,4,12)) | N84: =IF(36<9,0,Hipótesis!$E$47/IF(3=1,4,12)) | O84: =SUM(C84:N84)
B85: Bajas | C85: =-C83*Hipótesis!$E$50 | D85: =-D83*Hipótesis!$E$50 | E85: =-E83*Hipótesis!$E$50 | F85: =-F83*Hipótesis!$E$50 | G85: =-G83*Hipótesis!$E$50 | H85: =-H83*Hipótesis!$E$50 | I85: =-I83*Hipótesis!$E$50 | J85: =-J83*Hipótesis!$E$50 | ... N85: =-N83*Hipótesis!$E$50 | O85: =SUM(C85:N85)
B86: Base activa al cierre | C86: =SUM(C83:C85) | D86: =SUM(D83:D85) | E86: =SUM(E83:E85) | F86: =SUM(F83:F85) | G86: =SUM(G83:G85) | H86: =SUM(H83:H85) | I86: =SUM(I83:I85) | J86: =SUM(J83:J85) | ... N86: =SUM(N83:N85) | O86: =N86
B88: Plan Partner — Segmento C
A89: PLAN PARTNER | B89: Partners activos | C89: =ROUND(Hipótesis!$D$45+(Hipótesis!$E$45-Hipótesis!$D$45)*1/12,0) | D89: =ROUND(Hipótesis!$D$45+(Hipótesis!$E$45-Hipótesis!$D$45)*2/12,0) | E89: =ROUND(Hipótesis!$D$45+(Hipótesis!$E$45-Hipótesis!$D$45)*3/12,0) | F89: =ROUND(Hipótesis!$D$45+(Hipótesis!$E$45-Hipótesis!$D$45)*4/12,0) | G89: =ROUND(Hipótesis!$D$45+(Hipótesis!$E$45-Hipótesis!$D$45)*5/12,0) | H89: =ROUND(Hipótesis!$D$45+(Hipótesis!$E$45-Hipótesis!$D$45)*6/12,0) | I89: =ROUND(Hipótesis!$D$45+(Hipótesis!$E$45-Hipótesis!$D$45)*7/12,0) | J89: =ROUND(Hipótesis!$D$45+(Hipótesis!$E$45-Hipótesis!$D$45)*8/12,0) | K89: =ROUND(Hipótesis!$D$45+(Hipótesis!$E$45-Hipótesis!$D$45)*9/12,0) | L89: =ROUND(Hipótesis!$D$45+(Hipótesis!$E$45-Hipótesis!$D$45)*10/12,0) | M89: =ROUND(Hipótesis!$D$45+(Hipótesis!$E$45-Hipótesis!$D$45)*11/12,0) | N89: =ROUND(Hipótesis!$D$45+(Hipótesis!$E$45-Hipótesis!$D$45)*12/12,0) | O89: =N89
B90: Clientes gestionados por el canal | C90: =IF(25<Hipótesis!$C$44,0,C89*Hipótesis!$E$46) | D90: =IF(26<Hipótesis!$C$44,0,D89*Hipótesis!$E$46) | E90: =IF(27<Hipótesis!$C$44,0,E89*Hipótesis!$E$46) | F90: =IF(28<Hipótesis!$C$44,0,F89*Hipótesis!$E$46) | G90: =IF(29<Hipótesis!$C$44,0,G89*Hipótesis!$E$46) | H90: =IF(30<Hipótesis!$C$44,0,H89*Hipótesis!$E$46) | I90: =IF(31<Hipótesis!$C$44,0,I89*Hipótesis!$E$46) | J90: =IF(32<Hipótesis!$C$44,0,J89*Hipótesis!$E$46) | K90: =IF(33<Hipótesis!$C$44,0,K89*Hipótesis!$E$46) | L90: =IF(34<Hipótesis!$C$44,0,L89*Hipótesis!$E$46) | M90: =IF(35<Hipótesis!$C$44,0,M89*Hipótesis!$E$46) | N90: =IF(36<Hipótesis!$C$44,0,N89*Hipótesis!$E$46) | O90: =N90
B92: Consolidado
A93: TOTAL | B93: Clientes pagos activos | C93: =C80+C86+C90 | D93: =D80+D86+D90 | E93: =E80+E86+E90 | F93: =F80+F86+F90 | G93: =G80+G86+G90 | H93: =H80+H86+H90 | I93: =I80+I86+I90 | J93: =J80+J86+J90 | ... N93: =N80+N86+N90 | O93: =N93
B94: Equipos administrados | C94: =C80*Hipótesis!$E$51+C86*Hipótesis!$E$52+C90*Hipótesis!$E$53 | D94: =D80*Hipótesis!$E$51+D86*Hipótesis!$E$52+D90*Hipótesis!$E$53 | E94: =E80*Hipótesis!$E$51+E86*Hipótesis!$E$52+E90*Hipótesis!$E$53 | F94: =F80*Hipótesis!$E$51+F86*Hipótesis!$E$52+F90*Hipótesis!$E$53 | G94: =G80*Hipótesis!$E$51+G86*Hipótesis!$E$52+G90*Hipótesis!$E$53 | H94: =H80*Hipótesis!$E$51+H86*Hipótesis!$E$52+H90*Hipótesis!$E$53 | I94: =I80*Hipótesis!$E$51+I86*Hipótesis!$E$52+I90*Hipótesis!$E$53 | J94: =J80*Hipótesis!$E$51+J86*Hipótesis!$E$52+J90*Hipótesis!$E$53 | ... N94: =N80*Hipótesis!$E$51+N86*Hipótesis!$E$52+N90*Hipótesis!$E$53 | O94: =N94
C97: 2030
C98: Ene | D98: Feb | E98: Mar | F98: Abr | G98: May | H98: Jun | I98: Jul | J98: Ago | K98: Sep | L98: Oct | M98: Nov | N98: Dic | O98: Total 2030
B100: Embudo comercial
A101: EMBUDO | B101: Visitas web | C101: =N71*(1+Hipótesis!$F$36) | D101: =C101*(1+Hipótesis!$F$36) | E101: =D101*(1+Hipótesis!$F$36) | F101: =E101*(1+Hipótesis!$F$36) | G101: =F101*(1+Hipótesis!$F$36) | H101: =G101*(1+Hipótesis!$F$36) | I101: =H101*(1+Hipótesis!$F$36) | J101: =I101*(1+Hipótesis!$F$36) | K101: =J101*(1+Hipótesis!$F$36) | ... N101: =M101*(1+Hipótesis!$F$36) | O101: =SUM(C101:N101)
B102: Pruebas gratuitas iniciadas | C102: =C101*Hipótesis!$C$37 | D102: =D101*Hipótesis!$C$37 | E102: =E101*Hipótesis!$C$37 | F102: =F101*Hipótesis!$C$37 | G102: =G101*Hipótesis!$C$37 | H102: =H101*Hipótesis!$C$37 | I102: =I101*Hipótesis!$C$37 | J102: =J101*Hipótesis!$C$37 | ... N102: =N101*Hipótesis!$C$37 | O102: =SUM(C102:N102)
B103: Clientes nuevos por embudo directo | C103: =IF(37<Hipótesis!$C$44,0,C102*Hipótesis!$C$38) | D103: =IF(38<Hipótesis!$C$44,0,D102*Hipótesis!$C$38) | E103: =IF(39<Hipótesis!$C$44,0,E102*Hipótesis!$C$38) | F103: =IF(40<Hipótesis!$C$44,0,F102*Hipótesis!$C$38) | G103: =IF(41<Hipótesis!$C$44,0,G102*Hipótesis!$C$38) | H103: =IF(42<Hipótesis!$C$44,0,H102*Hipótesis!$C$38) | I103: =IF(43<Hipótesis!$C$44,0,I102*Hipótesis!$C$38) | J103: =IF(44<Hipótesis!$C$44,0,J102*Hipótesis!$C$38) | K103: =IF(45<Hipótesis!$C$44,0,K102*Hipótesis!$C$38) | L103: =IF(46<Hipótesis!$C$44,0,L102*Hipótesis!$C$38) | M103: =IF(47<Hipótesis!$C$44,0,M102*Hipótesis!$C$38) | N103: =IF(48<Hipótesis!$C$44,0,N102*Hipótesis!$C$38) | O103: =SUM(C103:N103)
B105: Plan Inicial — Segmento A
A106: PLAN INICIAL | B106: Base al inicio del mes | C106: =N80 | D106: =C110 | E106: =D110 | F106: =E110 | G106: =F110 | H106: =G110 | I106: =H110 | J106: =I110 | K106: =J110 | ... N106: =M110
B107: Altas por embudo directo | C107: =C103 | D107: =D103 | E107: =E103 | F107: =F103 | G107: =G103 | H107: =H103 | I107: =I103 | J107: =J103 | ... N107: =N103 | O107: =SUM(C107:N107)
B108: Altas por conversión de pilotos | C108: =IF(AND(37=Hipótesis!$C$44,4=1),Hipótesis!$C$42*Hipótesis!$C$43,0) | D108: =IF(AND(38=Hipótesis!$C$44,4=1),Hipótesis!$C$42*Hipótesis!$C$43,0) | E108: =IF(AND(39=Hipótesis!$C$44,4=1),Hipótesis!$C$42*Hipótesis!$C$43,0) | F108: =IF(AND(40=Hipótesis!$C$44,4=1),Hipótesis!$C$42*Hipótesis!$C$43,0) | G108: =IF(AND(41=Hipótesis!$C$44,4=1),Hipótesis!$C$42*Hipótesis!$C$43,0) | H108: =IF(AND(42=Hipótesis!$C$44,4=1),Hipótesis!$C$42*Hipótesis!$C$43,0) | I108: =IF(AND(43=Hipótesis!$C$44,4=1),Hipótesis!$C$42*Hipótesis!$C$43,0) | J108: =IF(AND(44=Hipótesis!$C$44,4=1),Hipótesis!$C$42*Hipótesis!$C$43,0) | K108: =IF(AND(45=Hipótesis!$C$44,4=1),Hipótesis!$C$42*Hipótesis!$C$43,0) | L108: =IF(AND(46=Hipótesis!$C$44,4=1),Hipótesis!$C$42*Hipótesis!$C$43,0) | M108: =IF(AND(47=Hipótesis!$C$44,4=1),Hipótesis!$C$42*Hipótesis!$C$43,0) | N108: =IF(AND(48=Hipótesis!$C$44,4=1),Hipótesis!$C$42*Hipótesis!$C$43,0) | O108: =SUM(C108:N108)
B109: Bajas | C109: =-C106*Hipótesis!$F$50 | D109: =-D106*Hipótesis!$F$50 | E109: =-E106*Hipótesis!$F$50 | F109: =-F106*Hipótesis!$F$50 | G109: =-G106*Hipótesis!$F$50 | H109: =-H106*Hipótesis!$F$50 | I109: =-I106*Hipótesis!$F$50 | J109: =-J106*Hipótesis!$F$50 | ... N109: =-N106*Hipótesis!$F$50 | O109: =SUM(C109:N109)
B110: Base activa al cierre | C110: =SUM(C106:C109) | D110: =SUM(D106:D109) | E110: =SUM(E106:E109) | F110: =SUM(F106:F109) | G110: =SUM(G106:G109) | H110: =SUM(H106:H109) | I110: =SUM(I106:I109) | J110: =SUM(J106:J109) | ... N110: =SUM(N106:N109) | O110: =N110
B112: Plan Estándar — Segmento B
A113: PLAN ESTÁNDAR | B113: Base al inicio del mes | C113: =N86 | D113: =C116 | E113: =D116 | F113: =E116 | G113: =F116 | H113: =G116 | I113: =H116 | J113: =I116 | K113: =J116 | ... N113: =M116
B114: Altas | C114: =IF(37<9,0,Hipótesis!$F$47/IF(4=1,4,12)) | D114: =IF(38<9,0,Hipótesis!$F$47/IF(4=1,4,12)) | E114: =IF(39<9,0,Hipótesis!$F$47/IF(4=1,4,12)) | F114: =IF(40<9,0,Hipótesis!$F$47/IF(4=1,4,12)) | G114: =IF(41<9,0,Hipótesis!$F$47/IF(4=1,4,12)) | H114: =IF(42<9,0,Hipótesis!$F$47/IF(4=1,4,12)) | I114: =IF(43<9,0,Hipótesis!$F$47/IF(4=1,4,12)) | J114: =IF(44<9,0,Hipótesis!$F$47/IF(4=1,4,12)) | K114: =IF(45<9,0,Hipótesis!$F$47/IF(4=1,4,12)) | L114: =IF(46<9,0,Hipótesis!$F$47/IF(4=1,4,12)) | M114: =IF(47<9,0,Hipótesis!$F$47/IF(4=1,4,12)) | N114: =IF(48<9,0,Hipótesis!$F$47/IF(4=1,4,12)) | O114: =SUM(C114:N114)
B115: Bajas | C115: =-C113*Hipótesis!$F$50 | D115: =-D113*Hipótesis!$F$50 | E115: =-E113*Hipótesis!$F$50 | F115: =-F113*Hipótesis!$F$50 | G115: =-G113*Hipótesis!$F$50 | H115: =-H113*Hipótesis!$F$50 | I115: =-I113*Hipótesis!$F$50 | J115: =-J113*Hipótesis!$F$50 | ... N115: =-N113*Hipótesis!$F$50 | O115: =SUM(C115:N115)
B116: Base activa al cierre | C116: =SUM(C113:C115) | D116: =SUM(D113:D115) | E116: =SUM(E113:E115) | F116: =SUM(F113:F115) | G116: =SUM(G113:G115) | H116: =SUM(H113:H115) | I116: =SUM(I113:I115) | J116: =SUM(J113:J115) | ... N116: =SUM(N113:N115) | O116: =N116
B118: Plan Partner — Segmento C
A119: PLAN PARTNER | B119: Partners activos | C119: =ROUND(Hipótesis!$E$45+(Hipótesis!$F$45-Hipótesis!$E$45)*1/12,0) | D119: =ROUND(Hipótesis!$E$45+(Hipótesis!$F$45-Hipótesis!$E$45)*2/12,0) | E119: =ROUND(Hipótesis!$E$45+(Hipótesis!$F$45-Hipótesis!$E$45)*3/12,0) | F119: =ROUND(Hipótesis!$E$45+(Hipótesis!$F$45-Hipótesis!$E$45)*4/12,0) | G119: =ROUND(Hipótesis!$E$45+(Hipótesis!$F$45-Hipótesis!$E$45)*5/12,0) | H119: =ROUND(Hipótesis!$E$45+(Hipótesis!$F$45-Hipótesis!$E$45)*6/12,0) | I119: =ROUND(Hipótesis!$E$45+(Hipótesis!$F$45-Hipótesis!$E$45)*7/12,0) | J119: =ROUND(Hipótesis!$E$45+(Hipótesis!$F$45-Hipótesis!$E$45)*8/12,0) | K119: =ROUND(Hipótesis!$E$45+(Hipótesis!$F$45-Hipótesis!$E$45)*9/12,0) | L119: =ROUND(Hipótesis!$E$45+(Hipótesis!$F$45-Hipótesis!$E$45)*10/12,0) | M119: =ROUND(Hipótesis!$E$45+(Hipótesis!$F$45-Hipótesis!$E$45)*11/12,0) | N119: =ROUND(Hipótesis!$E$45+(Hipótesis!$F$45-Hipótesis!$E$45)*12/12,0) | O119: =N119
B120: Clientes gestionados por el canal | C120: =IF(37<Hipótesis!$C$44,0,C119*Hipótesis!$F$46) | D120: =IF(38<Hipótesis!$C$44,0,D119*Hipótesis!$F$46) | E120: =IF(39<Hipótesis!$C$44,0,E119*Hipótesis!$F$46) | F120: =IF(40<Hipótesis!$C$44,0,F119*Hipótesis!$F$46) | G120: =IF(41<Hipótesis!$C$44,0,G119*Hipótesis!$F$46) | H120: =IF(42<Hipótesis!$C$44,0,H119*Hipótesis!$F$46) | I120: =IF(43<Hipótesis!$C$44,0,I119*Hipótesis!$F$46) | J120: =IF(44<Hipótesis!$C$44,0,J119*Hipótesis!$F$46) | K120: =IF(45<Hipótesis!$C$44,0,K119*Hipótesis!$F$46) | L120: =IF(46<Hipótesis!$C$44,0,L119*Hipótesis!$F$46) | M120: =IF(47<Hipótesis!$C$44,0,M119*Hipótesis!$F$46) | N120: =IF(48<Hipótesis!$C$44,0,N119*Hipótesis!$F$46) | O120: =N120
B122: Consolidado
A123: TOTAL | B123: Clientes pagos activos | C123: =C110+C116+C120 | D123: =D110+D116+D120 | E123: =E110+E116+E120 | F123: =F110+F116+F120 | G123: =G110+G116+G120 | H123: =H110+H116+H120 | I123: =I110+I116+I120 | J123: =J110+J116+J120 | ... N123: =N110+N116+N120 | O123: =N123
B124: Equipos administrados | C124: =C110*Hipótesis!$F$51+C116*Hipótesis!$F$52+C120*Hipótesis!$F$53 | D124: =D110*Hipótesis!$F$51+D116*Hipótesis!$F$52+D120*Hipótesis!$F$53 | E124: =E110*Hipótesis!$F$51+E116*Hipótesis!$F$52+E120*Hipótesis!$F$53 | F124: =F110*Hipótesis!$F$51+F116*Hipótesis!$F$52+F120*Hipótesis!$F$53 | G124: =G110*Hipótesis!$F$51+G116*Hipótesis!$F$52+G120*Hipótesis!$F$53 | H124: =H110*Hipótesis!$F$51+H116*Hipótesis!$F$52+H120*Hipótesis!$F$53 | I124: =I110*Hipótesis!$F$51+I116*Hipótesis!$F$52+I120*Hipótesis!$F$53 | J124: =J110*Hipótesis!$F$51+J116*Hipótesis!$F$52+J120*Hipótesis!$F$53 | ... N124: =N110*Hipótesis!$F$51+N116*Hipótesis!$F$52+N120*Hipótesis!$F$53 | O124: =N124
B126: Verificación contra las metas del documento (5.3.3)
C127: Proyectado | D127: Meta | E127: Desvío
...

Sheet Modelo de ingresos
A1: « Inicio
B2: MODELO DE INGRESOS
B3: Facturación por línea: abono de la base activa más los equipos que exceden lo que incluye cada plan. Los precios se actualizan una vez por año según el supuesto de aumento de lista. | Q3: Resumen anual
Q4: Los totales de cada año, que son los que alimentan el gráfico.
Q5: Concepto | R5: 2027 | S5: 2028 | T5: 2029 | U5: 2030
Q6: Plan Inicial | R6: =O13 | S6: =O36 | T6: =O59 | U6: =O82
C7: 2027 | Q7: Plan Estándar | R7: =O18 | S7: =O41 | T7: =O64 | U7: =O87
C8: Ene | D8: Feb | E8: Mar | F8: Abr | G8: May | H8: Jun | I8: Jul | J8: Ago | K8: Sep | L8: Oct | M8: Nov | N8: Dic | O8: Total 2027 | Q8: Plan Partner | R8: =O23 | S8: =O46 | T8: =O69 | U8: =O92
B10: Plan Inicial
A11: PLAN INICIAL | B11: Ingreso por abono | C11: ='Proyección de ventas'!C20*Planes!$D$7*1 | D11: ='Proyección de ventas'!D20*Planes!$D$7*1 | E11: ='Proyección de ventas'!E20*Planes!$D$7*1 | F11: ='Proyección de ventas'!F20*Planes!$D$7*1 | G11: ='Proyección de ventas'!G20*Planes!$D$7*1 | H11: ='Proyección de ventas'!H20*Planes!$D$7*1 | I11: ='Proyección de ventas'!I20*Planes!$D$7*1 | J11: ='Proyección de ventas'!J20*Planes!$D$7*1 | ... N11: ='Proyección de ventas'!N20*Planes!$D$7*1 | O11: =SUM(C11:N11)
B12: Ingreso por equipos adicionales | C12: ='Proyección de ventas'!C20*MAX(0,Hipótesis!$C$51-Planes!$E$7)*Planes!$F$7*1 | D12: ='Proyección de ventas'!D20*MAX(0,Hipótesis!$C$51-Planes!$E$7)*Planes!$F$7*1 | E12: ='Proyección de ventas'!E20*MAX(0,Hipótesis!$C$51-Planes!$E$7)*Planes!$F$7*1 | F12: ='Proyección de ventas'!F20*MAX(0,Hipótesis!$C$51-Planes!$E$7)*Planes!$F$7*1 | G12: ='Proyección de ventas'!G20*MAX(0,Hipótesis!$C$51-Planes!$E$7)*Planes!$F$7*1 | H12: ='Proyección de ventas'!H20*MAX(0,Hipótesis!$C$51-Planes!$E$7)*Planes!$F$7*1 | I12: ='Proyección de ventas'!I20*MAX(0,Hipótesis!$C$51-Planes!$E$7)*Planes!$F$7*1 | J12: ='Proyección de ventas'!J20*MAX(0,Hipótesis!$C$51-Planes!$E$7)*Planes!$F$7*1 | ... N12: ='Proyección de ventas'!N20*MAX(0,Hipótesis!$C$51-Planes!$E$7)*Planes!$F$7*1 | O12: =SUM(C12:N12)
B13: Total de la línea | C13: =C11+C12 | D13: =D11+D12 | E13: =E11+E12 | F13: =F11+F12 | G13: =G11+G12 | H13: =H11+H12 | I13: =I11+I12 | J13: =J11+J12 | ... N13: =N11+N12 | O13: =SUM(C13:N13)
B15: Plan Estándar
A16: PLAN ESTÁNDAR | B16: Ingreso por abono | C16: ='Proyección de ventas'!C26*Planes!$D$8*1 | D16: ='Proyección de ventas'!D26*Planes!$D$8*1 | E16: ='Proyección de ventas'!E26*Planes!$D$8*1 | F16: ='Proyección de ventas'!F26*Planes!$D$8*1 | G16: ='Proyección de ventas'!G26*Planes!$D$8*1 | H16: ='Proyección de ventas'!H26*Planes!$D$8*1 | I16: ='Proyección de ventas'!I26*Planes!$D$8*1 | J16: ='Proyección de ventas'!J26*Planes!$D$8*1 | ... N16: ='Proyección de ventas'!N26*Planes!$D$8*1 | O16: =SUM(C16:N16)
B17: Ingreso por equipos adicionales | C17: ='Proyección de ventas'!C26*MAX(0,Hipótesis!$C$52-Planes!$E$8)*Planes!$F$8*1 | D17: ='Proyección de ventas'!D26*MAX(0,Hipótesis!$C$52-Planes!$E$8)*Planes!$F$8*1 | E17: ='Proyección de ventas'!E26*MAX(0,Hipótesis!$C$52-Planes!$E$8)*Planes!$F$8*1 | F17: ='Proyección de ventas'!F26*MAX(0,Hipótesis!$C$52-Planes!$E$8)*Planes!$F$8*1 | G17: ='Proyección de ventas'!G26*MAX(0,Hipótesis!$C$52-Planes!$E$8)*Planes!$F$8*1 | H17: ='Proyección de ventas'!H26*MAX(0,Hipótesis!$C$52-Planes!$E$8)*Planes!$F$8*1 | I17: ='Proyección de ventas'!I26*MAX(0,Hipótesis!$C$52-Planes!$E$8)*Planes!$F$8*1 | J17: ='Proyección de ventas'!J26*MAX(0,Hipótesis!$C$52-Planes!$E$8)*Planes!$F$8*1 | ... N17: ='Proyección de ventas'!N26*MAX(0,Hipótesis!$C$52-Planes!$E$8)*Planes!$F$8*1 | O17: =SUM(C17:N17)
B18: Total de la línea | C18: =C16+C17 | D18: =D16+D17 | E18: =E16+E17 | F18: =F16+F17 | G18: =G16+G17 | H18: =H16+H17 | I18: =I16+I17 | J18: =J16+J17 | ... N18: =N16+N17 | O18: =SUM(C18:N18)
B20: Plan Partner
A21: PLAN PARTNER | B21: Ingreso por abono | C21: ='Proyección de ventas'!C30*Planes!$D$9*1 | D21: ='Proyección de ventas'!D30*Planes!$D$9*1 | E21: ='Proyección de ventas'!E30*Planes!$D$9*1 | F21: ='Proyección de ventas'!F30*Planes!$D$9*1 | G21: ='Proyección de ventas'!G30*Planes!$D$9*1 | H21: ='Proyección de ventas'!H30*Planes!$D$9*1 | I21: ='Proyección de ventas'!I30*Planes!$D$9*1 | J21: ='Proyección de ventas'!J30*Planes!$D$9*1 | ... N21: ='Proyección de ventas'!N30*Planes!$D$9*1 | O21: =SUM(C21:N21)
B22: Ingreso por equipos adicionales | C22: ='Proyección de ventas'!C30*MAX(0,Hipótesis!$C$53-Planes!$E$9)*Planes!$F$9*1 | D22: ='Proyección de ventas'!D30*MAX(0,Hipótesis!$C$53-Planes!$E$9)*Planes!$F$9*1 | E22: ='Proyección de ventas'!E30*MAX(0,Hipótesis!$C$53-Planes!$E$9)*Planes!$F$9*1 | F22: ='Proyección de ventas'!F30*MAX(0,Hipótesis!$C$53-Planes!$E$9)*Planes!$F$9*1 | G22: ='Proyección de ventas'!G30*MAX(0,Hipótesis!$C$53-Planes!$E$9)*Planes!$F$9*1 | H22: ='Proyección de ventas'!H30*MAX(0,Hipótesis!$C$53-Planes!$E$9)*Planes!$F$9*1 | I22: ='Proyección de ventas'!I30*MAX(0,Hipótesis!$C$53-Planes!$E$9)*Planes!$F$9*1 | J22: ='Proyección de ventas'!J30*MAX(0,Hipótesis!$C$53-Planes!$E$9)*Planes!$F$9*1 | ... N22: ='Proyección de ventas'!N30*MAX(0,Hipótesis!$C$53-Planes!$E$9)*Planes!$F$9*1 | O22: =SUM(C22:N22)
B23: Total de la línea | C23: =C21+C22 | D23: =D21+D22 | E23: =E21+E22 | F23: =F21+F22 | G23: =G21+G22 | H23: =H21+H22 | I23: =I21+I22 | J23: =J21+J22 | ... N23: =N21+N22 | O23: =SUM(C23:N23)
B25: Total de ingresos
A26: TOTAL | B26: Ingresos del mes | C26: =C13+C18+C23 | D26: =D13+D18+D23 | E26: =E13+E18+E23 | F26: =F13+F18+F23 | G26: =G13+G18+G23 | H26: =H13+H18+H23 | I26: =I13+I18+I23 | J26: =J13+J18+J23 | ... N26: =N13+N18+N23 | O26: =SUM(C26:N26)
B27: Ingreso promedio por cliente | C27: =IFERROR(C26/'Proyección de ventas'!C33,0) | D27: =IFERROR(D26/'Proyección de ventas'!D33,0) | E27: =IFERROR(E26/'Proyección de ventas'!E33,0) | F27: =IFERROR(F26/'Proyección de ventas'!F33,0) | G27: =IFERROR(G26/'Proyección de ventas'!G33,0) | H27: =IFERROR(H26/'Proyección de ventas'!H33,0) | I27: =IFERROR(I26/'Proyección de ventas'!I33,0) | J27: =IFERROR(J26/'Proyección de ventas'!J33,0) | ... N27: =IFERROR(N26/'Proyección de ventas'!N33,0)
C30: 2028
C31: Ene | D31: Feb | E31: Mar | F31: Abr | G31: May | H31: Jun | I31: Jul | J31: Ago | K31: Sep | L31: Oct | M31: Nov | N31: Dic | O31: Total 2028
B33: Plan Inicial
A34: PLAN INICIAL | B34: Ingreso por abono | C34: ='Proyección de ventas'!C50*Planes!$D$7*(1+Hipótesis!$D$12) | D34: ='Proyección de ventas'!D50*Planes!$D$7*(1+Hipótesis!$D$12) | E34: ='Proyección de ventas'!E50*Planes!$D$7*(1+Hipótesis!$D$12) | F34: ='Proyección de ventas'!F50*Planes!$D$7*(1+Hipótesis!$D$12) | G34: ='Proyección de ventas'!G50*Planes!$D$7*(1+Hipótesis!$D$12) | H34: ='Proyección de ventas'!H50*Planes!$D$7*(1+Hipótesis!$D$12) | I34: ='Proyección de ventas'!I50*Planes!$D$7*(1+Hipótesis!$D$12) | J34: ='Proyección de ventas'!J50*Planes!$D$7*(1+Hipótesis!$D$12) | ... N34: ='Proyección de ventas'!N50*Planes!$D$7*(1+Hipótesis!$D$12) | O34: =SUM(C34:N34)
B35: Ingreso por equipos adicionales | C35: ='Proyección de ventas'!C50*MAX(0,Hipótesis!$D$51-Planes!$E$7)*Planes!$F$7*(1+Hipótesis!$D$12) | D35: ='Proyección de ventas'!D50*MAX(0,Hipótesis!$D$51-Planes!$E$7)*Planes!$F$7*(1+Hipótesis!$D$12) | E35: ='Proyección de ventas'!E50*MAX(0,Hipótesis!$D$51-Planes!$E$7)*Planes!$F$7*(1+Hipótesis!$D$12) | F35: ='Proyección de ventas'!F50*MAX(0,Hipótesis!$D$51-Planes!$E$7)*Planes!$F$7*(1+Hipótesis!$D$12) | G35: ='Proyección de ventas'!G50*MAX(0,Hipótesis!$D$51-Planes!$E$7)*Planes!$F$7*(1+Hipótesis!$D$12) | H35: ='Proyección de ventas'!H50*MAX(0,Hipótesis!$D$51-Planes!$E$7)*Planes!$F$7*(1+Hipótesis!$D$12) | I35: ='Proyección de ventas'!I50*MAX(0,Hipótesis!$D$51-Planes!$E$7)*Planes!$F$7*(1+Hipótesis!$D$12) | J35: ='Proyección de ventas'!J50*MAX(0,Hipótesis!$D$51-Planes!$E$7)*Planes!$F$7*(1+Hipótesis!$D$12) | ... N35: ='Proyección de ventas'!N50*MAX(0,Hipótesis!$D$51-Planes!$E$7)*Planes!$F$7*(1+Hipótesis!$D$12) | O35: =SUM(C35:N35)
B36: Total de la línea | C36: =C34+C35 | D36: =D34+D35 | E36: =E34+E35 | F36: =F34+F35 | G36: =G34+G35 | H36: =H34+H35 | I36: =I34+I35 | J36: =J34+J35 | ... N36: =N34+N35 | O36: =SUM(C36:N36)
B38: Plan Estándar
A39: PLAN ESTÁNDAR | B39: Ingreso por abono | C39: ='Proyección de ventas'!C56*Planes!$D$8*(1+Hipótesis!$D$12) | D39: ='Proyección de ventas'!D56*Planes!$D$8*(1+Hipótesis!$D$12) | E39: ='Proyección de ventas'!E56*Planes!$D$8*(1+Hipótesis!$D$12) | F39: ='Proyección de ventas'!F56*Planes!$D$8*(1+Hipótesis!$D$12) | G39: ='Proyección de ventas'!G56*Planes!$D$8*(1+Hipótesis!$D$12) | H39: ='Proyección de ventas'!H56*Planes!$D$8*(1+Hipótesis!$D$12) | I39: ='Proyección de ventas'!I56*Planes!$D$8*(1+Hipótesis!$D$12) | J39: ='Proyección de ventas'!J56*Planes!$D$8*(1+Hipótesis!$D$12) | ... N39: ='Proyección de ventas'!N56*Planes!$D$8*(1+Hipótesis!$D$12) | O39: =SUM(C39:N39)
B40: Ingreso por equipos adicionales | C40: ='Proyección de ventas'!C56*MAX(0,Hipótesis!$D$52-Planes!$E$8)*Planes!$F$8*(1+Hipótesis!$D$12) | D40: ='Proyección de ventas'!D56*MAX(0,Hipótesis!$D$52-Planes!$E$8)*Planes!$F$8*(1+Hipótesis!$D$12) | E40: ='Proyección de ventas'!E56*MAX(0,Hipótesis!$D$52-Planes!$E$8)*Planes!$F$8*(1+Hipótesis!$D$12) | F40: ='Proyección de ventas'!F56*MAX(0,Hipótesis!$D$52-Planes!$E$8)*Planes!$F$8*(1+Hipótesis!$D$12) | G40: ='Proyección de ventas'!G56*MAX(0,Hipótesis!$D$52-Planes!$E$8)*Planes!$F$8*(1+Hipótesis!$D$12) | H40: ='Proyección de ventas'!H56*MAX(0,Hipótesis!$D$52-Planes!$E$8)*Planes!$F$8*(1+Hipótesis!$D$12) | I40: ='Proyección de ventas'!I56*MAX(0,Hipótesis!$D$52-Planes!$E$8)*Planes!$F$8*(1+Hipótesis!$D$12) | J40: ='Proyección de ventas'!J56*MAX(0,Hipótesis!$D$52-Planes!$E$8)*Planes!$F$8*(1+Hipótesis!$D$12) | ... N40: ='Proyección de ventas'!N56*MAX(0,Hipótesis!$D$52-Planes!$E$8)*Planes!$F$8*(1+Hipótesis!$D$12) | O40: =SUM(C40:N40)
B41: Total de la línea | C41: =C39+C40 | D41: =D39+D40 | E41: =E39+E40 | F41: =F39+F40 | G41: =G39+G40 | H41: =H39+H40 | I41: =I39+I40 | J41: =J39+J40 | ... N41: =N39+N40 | O41: =SUM(C41:N41)
B43: Plan Partner
A44: PLAN PARTNER | B44: Ingreso por abono | C44: ='Proyección de ventas'!C60*Planes!$D$9*(1+Hipótesis!$D$12) | D44: ='Proyección de ventas'!D60*Planes!$D$9*(1+Hipótesis!$D$12) | E44: ='Proyección de ventas'!E60*Planes!$D$9*(1+Hipótesis!$D$12) | F44: ='Proyección de ventas'!F60*Planes!$D$9*(1+Hipótesis!$D$12) | G44: ='Proyección de ventas'!G60*Planes!$D$9*(1+Hipótesis!$D$12) | H44: ='Proyección de ventas'!H60*Planes!$D$9*(1+Hipótesis!$D$12) | I44: ='Proyección de ventas'!I60*Planes!$D$9*(1+Hipótesis!$D$12) | J44: ='Proyección de ventas'!J60*Planes!$D$9*(1+Hipótesis!$D$12) | ... N44: ='Proyección de ventas'!N60*Planes!$D$9*(1+Hipótesis!$D$12) | O44: =SUM(C44:N44)
B45: Ingreso por equipos adicionales | C45: ='Proyección de ventas'!C60*MAX(0,Hipótesis!$D$53-Planes!$E$9)*Planes!$F$9*(1+Hipótesis!$D$12) | D45: ='Proyección de ventas'!D60*MAX(0,Hipótesis!$D$53-Planes!$E$9)*Planes!$F$9*(1+Hipótesis!$D$12) | E45: ='Proyección de ventas'!E60*MAX(0,Hipótesis!$D$53-Planes!$E$9)*Planes!$F$9*(1+Hipótesis!$D$12) | F45: ='Proyección de ventas'!F60*MAX(0,Hipótesis!$D$53-Planes!$E$9)*Planes!$F$9*(1+Hipótesis!$D$12) | G45: ='Proyección de ventas'!G60*MAX(0,Hipótesis!$D$53-Planes!$E$9)*Planes!$F$9*(1+Hipótesis!$D$12) | H45: ='Proyección de ventas'!H60*MAX(0,Hipótesis!$D$53-Planes!$E$9)*Planes!$F$9*(1+Hipótesis!$D$12) | I45: ='Proyección de ventas'!I60*MAX(0,Hipótesis!$D$53-Planes!$E$9)*Planes!$F$9*(1+Hipótesis!$D$12) | J45: ='Proyección de ventas'!J60*MAX(0,Hipótesis!$D$53-Planes!$E$9)*Planes!$F$9*(1+Hipótesis!$D$12) | ... N45: ='Proyección de ventas'!N60*MAX(0,Hipótesis!$D$53-Planes!$E$9)*Planes!$F$9*(1+Hipótesis!$D$12) | O45: =SUM(C45:N45)
B46: Total de la línea | C46: =C44+C45 | D46: =D44+D45 | E46: =E44+E45 | F46: =F44+F45 | G46: =G44+G45 | H46: =H44+H45 | I46: =I44+I45 | J46: =J44+J45 | ... N46: =N44+N45 | O46: =SUM(C46:N46)
B48: Total de ingresos
A49: TOTAL | B49: Ingresos del mes | C49: =C36+C41+C46 | D49: =D36+D41+D46 | E49: =E36+E41+E46 | F49: =F36+F41+F46 | G49: =G36+G41+G46 | H49: =H36+H41+H46 | I49: =I36+I41+I46 | J49: =J36+J41+J46 | ... N49: =N36+N41+N46 | O49: =SUM(C49:N49)
B50: Ingreso promedio por cliente | C50: =IFERROR(C49/'Proyección de ventas'!C63,0) | D50: =IFERROR(D49/'Proyección de ventas'!D63,0) | E50: =IFERROR(E49/'Proyección de ventas'!E63,0) | F50: =IFERROR(F49/'Proyección de ventas'!F63,0) | G50: =IFERROR(G49/'Proyección de ventas'!G63,0) | H50: =IFERROR(H49/'Proyección de ventas'!H63,0) | I50: =IFERROR(I49/'Proyección de ventas'!I63,0) | J50: =IFERROR(J49/'Proyección de ventas'!J63,0) | ... N50: =IFERROR(N49/'Proyección de ventas'!N63,0)
C53: 2029
C54: Ene | D54: Feb | E54: Mar | F54: Abr | G54: May | H54: Jun | I54: Jul | J54: Ago | K54: Sep | L54: Oct | M54: Nov | N54: Dic | O54: Total 2029
B56: Plan Inicial
A57: PLAN INICIAL | B57: Ingreso por abono | C57: ='Proyección de ventas'!C80*Planes!$D$7*(1+Hipótesis!$D$12)*(1+Hipótesis!$E$12) | D57: ='Proyección de ventas'!D80*Planes!$D$7*(1+Hipótesis!$D$12)*(1+Hipótesis!$E$12) | E57: ='Proyección de ventas'!E80*Planes!$D$7*(1+Hipótesis!$D$12)*(1+Hipótesis!$E$12) | F57: ='Proyección de ventas'!F80*Planes!$D$7*(1+Hipótesis!$D$12)*(1+Hipótesis!$E$12) | G57: ='Proyección de ventas'!G80*Planes!$D$7*(1+Hipótesis!$D$12)*(1+Hipótesis!$E$12) | H57: ='Proyección de ventas'!H80*Planes!$D$7*(1+Hipótesis!$D$12)*(1+Hipótesis!$E$12) | I57: ='Proyección de ventas'!I80*Planes!$D$7*(1+Hipótesis!$D$12)*(1+Hipótesis!$E$12) | J57: ='Proyección de ventas'!J80*Planes!$D$7*(1+Hipótesis!$D$12)*(1+Hipótesis!$E$12) | ... N57: ='Proyección de ventas'!N80*Planes!$D$7*(1+Hipótesis!$D$12)*(1+Hipótesis!$E$12) | O57: =SUM(C57:N57)
B58: Ingreso por equipos adicionales | C58: ='Proyección de ventas'!C80*MAX(0,Hipótesis!$E$51-Planes!$E$7)*Planes!$F$7*(1+Hipótesis!$D$12)*(1+Hipótesis!$E$12) | D58: ='Proyección de ventas'!D80*MAX(0,Hipótesis!$E$51-Planes!$E$7)*Planes!$F$7*(1+Hipótesis!$D$12)*(1+Hipótesis!$E$12) | E58: ='Proyección de ventas'!E80*MAX(0,Hipótesis!$E$51-Planes!$E$7)*Planes!$F$7*(1+Hipótesis!$D$12)*(1+Hipótesis!$E$12) | F58: ='Proyección de ventas'!F80*MAX(0,Hipótesis!$E$51-Planes!$E$7)*Planes!$F$7*(1+Hipótesis!$D$12)*(1+Hipótesis!$E$12) | G58: ='Proyección de ventas'!G80*MAX(0,Hipótesis!$E$51-Planes!$E$7)*Planes!$F$7*(1+Hipótesis!$D$12)*(1+Hipótesis!$E$12) | H58: ='Proyección de ventas'!H80*MAX(0,Hipótesis!$E$51-Planes!$E$7)*Planes!$F$7*(1+Hipótesis!$D$12)*(1+Hipótesis!$E$12) | I58: ='Proyección de ventas'!I80*MAX(0,Hipótesis!$E$51-Planes!$E$7)*Planes!$F$7*(1+Hipótesis!$D$12)*(1+Hipótesis!$E$12) | J58: ='Proyección de ventas'!J80*MAX(0,Hipótesis!$E$51-Planes!$E$7)*Planes!$F$7*(1+Hipótesis!$D$12)*(1+Hipótesis!$E$12) | ... N58: ='Proyección de ventas'!N80*MAX(0,Hipótesis!$E$51-Planes!$E$7)*Planes!$F$7*(1+Hipótesis!$D$12)*(1+Hipótesis!$E$12) | O58: =SUM(C58:N58)
B59: Total de la línea | C59: =C57+C58 | D59: =D57+D58 | E59: =E57+E58 | F59: =F57+F58 | G59: =G57+G58 | H59: =H57+H58 | I59: =I57+I58 | J59: =J57+J58 | ... N59: =N57+N58 | O59: =SUM(C59:N59)
B61: Plan Estándar
A62: PLAN ESTÁNDAR | B62: Ingreso por abono | C62: ='Proyección de ventas'!C86*Planes!$D$8*(1+Hipótesis!$D$12)*(1+Hipótesis!$E$12) | D62: ='Proyección de ventas'!D86*Planes!$D$8*(1+Hipótesis!$D$12)*(1+Hipótesis!$E$12) | E62: ='Proyección de ventas'!E86*Planes!$D$8*(1+Hipótesis!$D$12)*(1+Hipótesis!$E$12) | F62: ='Proyección de ventas'!F86*Planes!$D$8*(1+Hipótesis!$D$12)*(1+Hipótesis!$E$12) | G62: ='Proyección de ventas'!G86*Planes!$D$8*(1+Hipótesis!$D$12)*(1+Hipótesis!$E$12) | H62: ='Proyección de ventas'!H86*Planes!$D$8*(1+Hipótesis!$D$12)*(1+Hipótesis!$E$12) | I62: ='Proyección de ventas'!I86*Planes!$D$8*(1+Hipótesis!$D$12)*(1+Hipótesis!$E$12) | J62: ='Proyección de ventas'!J86*Planes!$D$8*(1+Hipótesis!$D$12)*(1+Hipótesis!$E$12) | ... N62: ='Proyección de ventas'!N86*Planes!$D$8*(1+Hipótesis!$D$12)*(1+Hipótesis!$E$12) | O62: =SUM(C62:N62)
B63: Ingreso por equipos adicionales | C63: ='Proyección de ventas'!C86*MAX(0,Hipótesis!$E$52-Planes!$E$8)*Planes!$F$8*(1+Hipótesis!$D$12)*(1+Hipótesis!$E$12) | D63: ='Proyección de ventas'!D86*MAX(0,Hipótesis!$E$52-Planes!$E$8)*Planes!$F$8*(1+Hipótesis!$D$12)*(1+Hipótesis!$E$12) | E63: ='Proyección de ventas'!E86*MAX(0,Hipótesis!$E$52-Planes!$E$8)*Planes!$F$8*(1+Hipótesis!$D$12)*(1+Hipótesis!$E$12) | F63: ='Proyección de ventas'!F86*MAX(0,Hipótesis!$E$52-Planes!$E$8)*Planes!$F$8*(1+Hipótesis!$D$12)*(1+Hipótesis!$E$12) | G63: ='Proyección de ventas'!G86*MAX(0,Hipótesis!$E$52-Planes!$E$8)*Planes!$F$8*(1+Hipótesis!$D$12)*(1+Hipótesis!$E$12) | H63: ='Proyección de ventas'!H86*MAX(0,Hipótesis!$E$52-Planes!$E$8)*Planes!$F$8*(1+Hipótesis!$D$12)*(1+Hipótesis!$E$12) | I63: ='Proyección de ventas'!I86*MAX(0,Hipótesis!$E$52-Planes!$E$8)*Planes!$F$8*(1+Hipótesis!$D$12)*(1+Hipótesis!$E$12) | J63: ='Proyección de ventas'!J86*MAX(0,Hipótesis!$E$52-Planes!$E$8)*Planes!$F$8*(1+Hipótesis!$D$12)*(1+Hipótesis!$E$12) | ... N63: ='Proyección de ventas'!N86*MAX(0,Hipótesis!$E$52-Planes!$E$8)*Planes!$F$8*(1+Hipótesis!$D$12)*(1+Hipótesis!$E$12) | O63: =SUM(C63:N63)
B64: Total de la línea | C64: =C62+C63 | D64: =D62+D63 | E64: =E62+E63 | F64: =F62+F63 | G64: =G62+G63 | H64: =H62+H63 | I64: =I62+I63 | J64: =J62+J63 | ... N64: =N62+N63 | O64: =SUM(C64:N64)
B66: Plan Partner
A67: PLAN PARTNER | B67: Ingreso por abono | C67: ='Proyección de ventas'!C90*Planes!$D$9*(1+Hipótesis!$D$12)*(1+Hipótesis!$E$12) | D67: ='Proyección de ventas'!D90*Planes!$D$9*(1+Hipótesis!$D$12)*(1+Hipótesis!$E$12) | E67: ='Proyección de ventas'!E90*Planes!$D$9*(1+Hipótesis!$D$12)*(1+Hipótesis!$E$12) | F67: ='Proyección de ventas'!F90*Planes!$D$9*(1+Hipótesis!$D$12)*(1+Hipótesis!$E$12) | G67: ='Proyección de ventas'!G90*Planes!$D$9*(1+Hipótesis!$D$12)*(1+Hipótesis!$E$12) | H67: ='Proyección de ventas'!H90*Planes!$D$9*(1+Hipótesis!$D$12)*(1+Hipótesis!$E$12) | I67: ='Proyección de ventas'!I90*Planes!$D$9*(1+Hipótesis!$D$12)*(1+Hipótesis!$E$12) | J67: ='Proyección de ventas'!J90*Planes!$D$9*(1+Hipótesis!$D$12)*(1+Hipótesis!$E$12) | ... N67: ='Proyección de ventas'!N90*Planes!$D$9*(1+Hipótesis!$D$12)*(1+Hipótesis!$E$12) | O67: =SUM(C67:N67)
B68: Ingreso por equipos adicionales | C68: ='Proyección de ventas'!C90*MAX(0,Hipótesis!$E$53-Planes!$E$9)*Planes!$F$9*(1+Hipótesis!$D$12)*(1+Hipótesis!$E$12) | D68: ='Proyección de ventas'!D90*MAX(0,Hipótesis!$E$53-Planes!$E$9)*Planes!$F$9*(1+Hipótesis!$D$12)*(1+Hipótesis!$E$12) | E68: ='Proyección de ventas'!E90*MAX(0,Hipótesis!$E$53-Planes!$E$9)*Planes!$F$9*(1+Hipótesis!$D$12)*(1+Hipótesis!$E$12) | F68: ='Proyección de ventas'!F90*MAX(0,Hipótesis!$E$53-Planes!$E$9)*Planes!$F$9*(1+Hipótesis!$D$12)*(1+Hipótesis!$E$12) | G68: ='Proyección de ventas'!G90*MAX(0,Hipótesis!$E$53-Planes!$E$9)*Planes!$F$9*(1+Hipótesis!$D$12)*(1+Hipótesis!$E$12) | H68: ='Proyección de ventas'!H90*MAX(0,Hipótesis!$E$53-Planes!$E$9)*Planes!$F$9*(1+Hipótesis!$D$12)*(1+Hipótesis!$E$12) | I68: ='Proyección de ventas'!I90*MAX(0,Hipótesis!$E$53-Planes!$E$9)*Planes!$F$9*(1+Hipótesis!$D$12)*(1+Hipótesis!$E$12) | J68: ='Proyección de ventas'!J90*MAX(0,Hipótesis!$E$53-Planes!$E$9)*Planes!$F$9*(1+Hipótesis!$D$12)*(1+Hipótesis!$E$12) | ... N68: ='Proyección de ventas'!N90*MAX(0,Hipótesis!$E$53-Planes!$E$9)*Planes!$F$9*(1+Hipótesis!$D$12)*(1+Hipótesis!$E$12) | O68: =SUM(C68:N68)
B69: Total de la línea | C69: =C67+C68 | D69: =D67+D68 | E69: =E67+E68 | F69: =F67+F68 | G69: =G67+G68 | H69: =H67+H68 | I69: =I67+I68 | J69: =J67+J68 | ... N69: =N67+N68 | O69: =SUM(C69:N69)
B71: Total de ingresos
A72: TOTAL | B72: Ingresos del mes | C72: =C59+C64+C69 | D72: =D59+D64+D69 | E72: =E59+E64+E69 | F72: =F59+F64+F69 | G72: =G59+G64+G69 | H72: =H59+H64+H69 | I72: =I59+I64+I69 | J72: =J59+J64+J69 | ... N72: =N59+N64+N69 | O72: =SUM(C72:N72)
B73: Ingreso promedio por cliente | C73: =IFERROR(C72/'Proyección de ventas'!C93,0) | D73: =IFERROR(D72/'Proyección de ventas'!D93,0) | E73: =IFERROR(E72/'Proyección de ventas'!E93,0) | F73: =IFERROR(F72/'Proyección de ventas'!F93,0) | G73: =IFERROR(G72/'Proyección de ventas'!G93,0) | H73: =IFERROR(H72/'Proyección de ventas'!H93,0) | I73: =IFERROR(I72/'Proyección de ventas'!I93,0) | J73: =IFERROR(J72/'Proyección de ventas'!J93,0) | ... N73: =IFERROR(N72/'Proyección de ventas'!N93,0)
C76: 2030
C77: Ene | D77: Feb | E77: Mar | F77: Abr | G77: May | H77: Jun | I77: Jul | J77: Ago | K77: Sep | L77: Oct | M77: Nov | N77: Dic | O77: Total 2030
B79: Plan Inicial
A80: PLAN INICIAL | B80: Ingreso por abono | C80: ='Proyección de ventas'!C110*Planes!$D$7*(1+Hipótesis!$D$12)*(1+Hipótesis!$E$12)*(1+Hipótesis!$F$12) | D80: ='Proyección de ventas'!D110*Planes!$D$7*(1+Hipótesis!$D$12)*(1+Hipótesis!$E$12)*(1+Hipótesis!$F$12) | E80: ='Proyección de ventas'!E110*Planes!$D$7*(1+Hipótesis!$D$12)*(1+Hipótesis!$E$12)*(1+Hipótesis!$F$12) | F80: ='Proyección de ventas'!F110*Planes!$D$7*(1+Hipótesis!$D$12)*(1+Hipótesis!$E$12)*(1+Hipótesis!$F$12) | G80: ='Proyección de ventas'!G110*Planes!$D$7*(1+Hipótesis!$D$12)*(1+Hipótesis!$E$12)*(1+Hipótesis!$F$12) | H80: ='Proyección de ventas'!H110*Planes!$D$7*(1+Hipótesis!$D$12)*(1+Hipótesis!$E$12)*(1+Hipótesis!$F$12) | I80: ='Proyección de ventas'!I110*Planes!$D$7*(1+Hipótesis!$D$12)*(1+Hipótesis!$E$12)*(1+Hipótesis!$F$12) | J80: ='Proyección de ventas'!J110*Planes!$D$7*(1+Hipótesis!$D$12)*(1+Hipótesis!$E$12)*(1+Hipótesis!$F$12) | ... N80: ='Proyección de ventas'!N110*Planes!$D$7*(1+Hipótesis!$D$12)*(1+Hipótesis!$E$12)*(1+Hipótesis!$F$12) | O80: =SUM(C80:N80)
B81: Ingreso por equipos adicionales | C81: ='Proyección de ventas'!C110*MAX(0,Hipótesis!$F$51-Planes!$E$7)*Planes!$F$7*(1+Hipótesis!$D$12)*(1+Hipótesis!$E$12)*(1+Hipótesis!$F$12) | D81: ='Proyección de ventas'!D110*MAX(0,Hipótesis!$F$51-Planes!$E$7)*Planes!$F$7*(1+Hipótesis!$D$12)*(1+Hipótesis!$E$12)*(1+Hipótesis!$F$12) | E81: ='Proyección de ventas'!E110*MAX(0,Hipótesis!$F$51-Planes!$E$7)*Planes!$F$7*(1+Hipótesis!$D$12)*(1+Hipótesis!$E$12)*(1+Hipótesis!$F$12) | F81: ='Proyección de ventas'!F110*MAX(0,Hipótesis!$F$51-Planes!$E$7)*Planes!$F$7*(1+Hipótesis!$D$12)*(1+Hipótesis!$E$12)*(1+Hipótesis!$F$12) | G81: ='Proyección de ventas'!G110*MAX(0,Hipótesis!$F$51-Planes!$E$7)*Planes!$F$7*(1+Hipótesis!$D$12)*(1+Hipótesis!$E$12)*(1+Hipótesis!$F$12) | H81: ='Proyección de ventas'!H110*MAX(0,Hipótesis!$F$51-Planes!$E$7)*Planes!$F$7*(1+Hipótesis!$D$12)*(1+Hipótesis!$E$12)*(1+Hipótesis!$F$12) | I81: ='Proyección de ventas'!I110*MAX(0,Hipótesis!$F$51-Planes!$E$7)*Planes!$F$7*(1+Hipótesis!$D$12)*(1+Hipótesis!$E$12)*(1+Hipótesis!$F$12) | J81: ='Proyección de ventas'!J110*MAX(0,Hipótesis!$F$51-Planes!$E$7)*Planes!$F$7*(1+Hipótesis!$D$12)*(1+Hipótesis!$E$12)*(1+Hipótesis!$F$12) | ... N81: ='Proyección de ventas'!N110*MAX(0,Hipótesis!$F$51-Planes!$E$7)*Planes!$F$7*(1+Hipótesis!$D$12)*(1+Hipótesis!$E$12)*(1+Hipótesis!$F$12) | O81: =SUM(C81:N81)
B82: Total de la línea | C82: =C80+C81 | D82: =D80+D81 | E82: =E80+E81 | F82: =F80+F81 | G82: =G80+G81 | H82: =H80+H81 | I82: =I80+I81 | J82: =J80+J81 | ... N82: =N80+N81 | O82: =SUM(C82:N82)
B84: Plan Estándar
A85: PLAN ESTÁNDAR | B85: Ingreso por abono | C85: ='Proyección de ventas'!C116*Planes!$D$8*(1+Hipótesis!$D$12)*(1+Hipótesis!$E$12)*(1+Hipótesis!$F$12) | D85: ='Proyección de ventas'!D116*Planes!$D$8*(1+Hipótesis!$D$12)*(1+Hipótesis!$E$12)*(1+Hipótesis!$F$12) | E85: ='Proyección de ventas'!E116*Planes!$D$8*(1+Hipótesis!$D$12)*(1+Hipótesis!$E$12)*(1+Hipótesis!$F$12) | F85: ='Proyección de ventas'!F116*Planes!$D$8*(1+Hipótesis!$D$12)*(1+Hipótesis!$E$12)*(1+Hipótesis!$F$12) | G85: ='Proyección de ventas'!G116*Planes!$D$8*(1+Hipótesis!$D$12)*(1+Hipótesis!$E$12)*(1+Hipótesis!$F$12) | H85: ='Proyección de ventas'!H116*Planes!$D$8*(1+Hipótesis!$D$12)*(1+Hipótesis!$E$12)*(1+Hipótesis!$F$12) | I85: ='Proyección de ventas'!I116*Planes!$D$8*(1+Hipótesis!$D$12)*(1+Hipótesis!$E$12)*(1+Hipótesis!$F$12) | J85: ='Proyección de ventas'!J116*Planes!$D$8*(1+Hipótesis!$D$12)*(1+Hipótesis!$E$12)*(1+Hipótesis!$F$12) | ... N85: ='Proyección de ventas'!N116*Planes!$D$8*(1+Hipótesis!$D$12)*(1+Hipótesis!$E$12)*(1+Hipótesis!$F$12) | O85: =SUM(C85:N85)
B86: Ingreso por equipos adicionales | C86: ='Proyección de ventas'!C116*MAX(0,Hipótesis!$F$52-Planes!$E$8)*Planes!$F$8*(1+Hipótesis!$D$12)*(1+Hipótesis!$E$12)*(1+Hipótesis!$F$12) | D86: ='Proyección de ventas'!D116*MAX(0,Hipótesis!$F$52-Planes!$E$8)*Planes!$F$8*(1+Hipótesis!$D$12)*(1+Hipótesis!$E$12)*(1+Hipótesis!$F$12) | E86: ='Proyección de ventas'!E116*MAX(0,Hipótesis!$F$52-Planes!$E$8)*Planes!$F$8*(1+Hipótesis!$D$12)*(1+Hipótesis!$E$12)*(1+Hipótesis!$F$12) | F86: ='Proyección de ventas'!F116*MAX(0,Hipótesis!$F$52-Planes!$E$8)*Planes!$F$8*(1+Hipótesis!$D$12)*(1+Hipótesis!$E$12)*(1+Hipótesis!$F$12) | G86: ='Proyección de ventas'!G116*MAX(0,Hipótesis!$F$52-Planes!$E$8)*Planes!$F$8*(1+Hipótesis!$D$12)*(1+Hipótesis!$E$12)*(1+Hipótesis!$F$12) | H86: ='Proyección de ventas'!H116*MAX(0,Hipótesis!$F$52-Planes!$E$8)*Planes!$F$8*(1+Hipótesis!$D$12)*(1+Hipótesis!$E$12)*(1+Hipótesis!$F$12) | I86: ='Proyección de ventas'!I116*MAX(0,Hipótesis!$F$52-Planes!$E$8)*Planes!$F$8*(1+Hipótesis!$D$12)*(1+Hipótesis!$E$12)*(1+Hipótesis!$F$12) | J86: ='Proyección de ventas'!J116*MAX(0,Hipótesis!$F$52-Planes!$E$8)*Planes!$F$8*(1+Hipótesis!$D$12)*(1+Hipótesis!$E$12)*(1+Hipótesis!$F$12) | ... N86: ='Proyección de ventas'!N116*MAX(0,Hipótesis!$F$52-Planes!$E$8)*Planes!$F$8*(1+Hipótesis!$D$12)*(1+Hipótesis!$E$12)*(1+Hipótesis!$F$12) | O86: =SUM(C86:N86)
B87: Total de la línea | C87: =C85+C86 | D87: =D85+D86 | E87: =E85+E86 | F87: =F85+F86 | G87: =G85+G86 | H87: =H85+H86 | I87: =I85+I86 | J87: =J85+J86 | ... N87: =N85+N86 | O87: =SUM(C87:N87)
B89: Plan Partner
A90: PLAN PARTNER | B90: Ingreso por abono | C90: ='Proyección de ventas'!C120*Planes!$D$9*(1+Hipótesis!$D$12)*(1+Hipótesis!$E$12)*(1+Hipótesis!$F$12) | D90: ='Proyección de ventas'!D120*Planes!$D$9*(1+Hipótesis!$D$12)*(1+Hipótesis!$E$12)*(1+Hipótesis!$F$12) | E90: ='Proyección de ventas'!E120*Planes!$D$9*(1+Hipótesis!$D$12)*(1+Hipótesis!$E$12)*(1+Hipótesis!$F$12) | F90: ='Proyección de ventas'!F120*Planes!$D$9*(1+Hipótesis!$D$12)*(1+Hipótesis!$E$12)*(1+Hipótesis!$F$12) | G90: ='Proyección de ventas'!G120*Planes!$D$9*(1+Hipótesis!$D$12)*(1+Hipótesis!$E$12)*(1+Hipótesis!$F$12) | H90: ='Proyección de ventas'!H120*Planes!$D$9*(1+Hipótesis!$D$12)*(1+Hipótesis!$E$12)*(1+Hipótesis!$F$12) | I90: ='Proyección de ventas'!I120*Planes!$D$9*(1+Hipótesis!$D$12)*(1+Hipótesis!$E$12)*(1+Hipótesis!$F$12) | J90: ='Proyección de ventas'!J120*Planes!$D$9*(1+Hipótesis!$D$12)*(1+Hipótesis!$E$12)*(1+Hipótesis!$F$12) | ... N90: ='Proyección de ventas'!N120*Planes!$D$9*(1+Hipótesis!$D$12)*(1+Hipótesis!$E$12)*(1+Hipótesis!$F$12) | O90: =SUM(C90:N90)
B91: Ingreso por equipos adicionales | C91: ='Proyección de ventas'!C120*MAX(0,Hipótesis!$F$53-Planes!$E$9)*Planes!$F$9*(1+Hipótesis!$D$12)*(1+Hipótesis!$E$12)*(1+Hipótesis!$F$12) | D91: ='Proyección de ventas'!D120*MAX(0,Hipótesis!$F$53-Planes!$E$9)*Planes!$F$9*(1+Hipótesis!$D$12)*(1+Hipótesis!$E$12)*(1+Hipótesis!$F$12) | E91: ='Proyección de ventas'!E120*MAX(0,Hipótesis!$F$53-Planes!$E$9)*Planes!$F$9*(1+Hipótesis!$D$12)*(1+Hipótesis!$E$12)*(1+Hipótesis!$F$12) | F91: ='Proyección de ventas'!F120*MAX(0,Hipótesis!$F$53-Planes!$E$9)*Planes!$F$9*(1+Hipótesis!$D$12)*(1+Hipótesis!$E$12)*(1+Hipótesis!$F$12) | G91: ='Proyección de ventas'!G120*MAX(0,Hipótesis!$F$53-Planes!$E$9)*Planes!$F$9*(1+Hipótesis!$D$12)*(1+Hipótesis!$E$12)*(1+Hipótesis!$F$12) | H91: ='Proyección de ventas'!H120*MAX(0,Hipótesis!$F$53-Planes!$E$9)*Planes!$F$9*(1+Hipótesis!$D$12)*(1+Hipótesis!$E$12)*(1+Hipótesis!$F$12) | I91: ='Proyección de ventas'!I120*MAX(0,Hipótesis!$F$53-Planes!$E$9)*Planes!$F$9*(1+Hipótesis!$D$12)*(1+Hipótesis!$E$12)*(1+Hipótesis!$F$12) | J91: ='Proyección de ventas'!J120*MAX(0,Hipótesis!$F$53-Planes!$E$9)*Planes!$F$9*(1+Hipótesis!$D$12)*(1+Hipótesis!$E$12)*(1+Hipótesis!$F$12) | ... N91: ='Proyección de ventas'!N120*MAX(0,Hipótesis!$F$53-Planes!$E$9)*Planes!$F$9*(1+Hipótesis!$D$12)*(1+Hipótesis!$E$12)*(1+Hipótesis!$F$12) | O91: =SUM(C91:N91)
B92: Total de la línea | C92: =C90+C91 | D92: =D90+D91 | E92: =E90+E91 | F92: =F90+F91 | G92: =G90+G91 | H92: =H90+H91 | I92: =I90+I91 | J92: =J90+J91 | ... N92: =N90+N91 | O92: =SUM(C92:N92)
B94: Total de ingresos
A95: TOTAL | B95: Ingresos del mes | C95: =C82+C87+C92 | D95: =D82+D87+D92 | E95: =E82+E87+E92 | F95: =F82+F87+F92 | G95: =G82+G87+G92 | H95: =H82+H87+H92 | I95: =I82+I87+I92 | J95: =J82+J87+J92 | ... N95: =N82+N87+N92 | O95: =SUM(C95:N95)
B96: Ingreso promedio por cliente | C96: =IFERROR(C95/'Proyección de ventas'!C123,0) | D96: =IFERROR(D95/'Proyección de ventas'!D123,0) | E96: =IFERROR(E95/'Proyección de ventas'!E123,0) | F96: =IFERROR(F95/'Proyección de ventas'!F123,0) | G96: =IFERROR(G95/'Proyección de ventas'!G123,0) | H96: =IFERROR(H95/'Proyección de ventas'!H123,0) | I96: =IFERROR(I95/'Proyección de ventas'!I123,0) | J96: =IFERROR(J95/'Proyección de ventas'!J123,0) | ... N96: =IFERROR(N95/'Proyección de ventas'!N123,0)

Sheet Modelo de Egresos
A1: « Inicio
B2: MODELO DE EGRESOS
B3: Consolidado de las tres estructuras de costo. Cada una se carga en su propia hoja y acá sólo se suman. | Q3: Resumen anual
Q4: Los totales de cada año, que son los que alimentan el gráfico.
Q5: Concepto | R5: 2027 | S5: 2028 | T5: 2029 | U5: 2030
Q6: Costos fijos | R6: =O10 | S6: =O23 | T6: =O36 | U6: =O49
C7: 2027 | Q7: Costos variables | R7: =O11 | S7: =O24 | T7: =O37 | U7: =O50
C8: Ene | D8: Feb | E8: Mar | F8: Abr | G8: May | H8: Jun | I8: Jul | J8: Ago | K8: Sep | L8: Oct | M8: Nov | N8: Dic | O8: Total 2027 | Q8: Costos de RRHH | R8: =O12 | S8: =O25 | T8: =O38 | U8: =O51
A10: EGRESOS | B10: Costos fijos | C10: ='Costos Fijos'!C32 | D10: ='Costos Fijos'!D32 | E10: ='Costos Fijos'!E32 | F10: ='Costos Fijos'!F32 | G10: ='Costos Fijos'!G32 | H10: ='Costos Fijos'!H32 | I10: ='Costos Fijos'!I32 | J10: ='Costos Fijos'!J32 | ... N10: ='Costos Fijos'!N32 | O10: =SUM(C10:N10)
B11: Costos variables | C11: ='Costos Variables'!C14 | D11: ='Costos Variables'!D14 | E11: ='Costos Variables'!E14 | F11: ='Costos Variables'!F14 | G11: ='Costos Variables'!G14 | H11: ='Costos Variables'!H14 | I11: ='Costos Variables'!I14 | J11: ='Costos Variables'!J14 | ... N11: ='Costos Variables'!N14 | O11: =SUM(C11:N11)
B12: Costos de RRHH | C12: ='RRHH'!C48 | D12: ='RRHH'!D48 | E12: ='RRHH'!E48 | F12: ='RRHH'!F48 | G12: ='RRHH'!G48 | H12: ='RRHH'!H48 | I12: ='RRHH'!I48 | J12: ='RRHH'!J48 | ... N12: ='RRHH'!N48 | O12: =SUM(C12:N12)
B13: Total de egresos | C13: =SUM(C10:C12) | D13: =SUM(D10:D12) | E13: =SUM(E10:E12) | F13: =SUM(F10:F12) | G13: =SUM(G10:G12) | H13: =SUM(H10:H12) | I13: =SUM(I10:I12) | J13: =SUM(J10:J12) | ... N13: =SUM(N10:N12) | O13: =SUM(C13:N13)
B15: Margen
A16: MARGEN | B16: Resultado operativo (ingresos − egresos) | C16: ='Modelo de ingresos'!C26-C13 | D16: ='Modelo de ingresos'!D26-D13 | E16: ='Modelo de ingresos'!E26-E13 | F16: ='Modelo de ingresos'!F26-F13 | G16: ='Modelo de ingresos'!G26-G13 | H16: ='Modelo de ingresos'!H26-H13 | I16: ='Modelo de ingresos'!I26-I13 | J16: ='Modelo de ingresos'!J26-J13 | ... N16: ='Modelo de ingresos'!N26-N13 | O16: =SUM(C16:N16)
B17: Margen sobre ingresos | C17: =IFERROR(C16/'Modelo de ingresos'!C26,0) | D17: =IFERROR(D16/'Modelo de ingresos'!D26,0) | E17: =IFERROR(E16/'Modelo de ingresos'!E26,0) | F17: =IFERROR(F16/'Modelo de ingresos'!F26,0) | G17: =IFERROR(G16/'Modelo de ingresos'!G26,0) | H17: =IFERROR(H16/'Modelo de ingresos'!H26,0) | I17: =IFERROR(I16/'Modelo de ingresos'!I26,0) | J17: =IFERROR(J16/'Modelo de ingresos'!J26,0) | ... N17: =IFERROR(N16/'Modelo de ingresos'!N26,0)
C20: 2028
C21: Ene | D21: Feb | E21: Mar | F21: Abr | G21: May | H21: Jun | I21: Jul | J21: Ago | K21: Sep | L21: Oct | M21: Nov | N21: Dic | O21: Total 2028
A23: EGRESOS | B23: Costos fijos | C23: ='Costos Fijos'!C60 | D23: ='Costos Fijos'!D60 | E23: ='Costos Fijos'!E60 | F23: ='Costos Fijos'!F60 | G23: ='Costos Fijos'!G60 | H23: ='Costos Fijos'!H60 | I23: ='Costos Fijos'!I60 | J23: ='Costos Fijos'!J60 | ... N23: ='Costos Fijos'!N60 | O23: =SUM(C23:N23)
B24: Costos variables | C24: ='Costos Variables'!C24 | D24: ='Costos Variables'!D24 | E24: ='Costos Variables'!E24 | F24: ='Costos Variables'!F24 | G24: ='Costos Variables'!G24 | H24: ='Costos Variables'!H24 | I24: ='Costos Variables'!I24 | J24: ='Costos Variables'!J24 | ... N24: ='Costos Variables'!N24 | O24: =SUM(C24:N24)
B25: Costos de RRHH | C25: ='RRHH'!C63 | D25: ='RRHH'!D63 | E25: ='RRHH'!E63 | F25: ='RRHH'!F63 | G25: ='RRHH'!G63 | H25: ='RRHH'!H63 | I25: ='RRHH'!I63 | J25: ='RRHH'!J63 | ... N25: ='RRHH'!N63 | O25: =SUM(C25:N25)
B26: Total de egresos | C26: =SUM(C23:C25) | D26: =SUM(D23:D25) | E26: =SUM(E23:E25) | F26: =SUM(F23:F25) | G26: =SUM(G23:G25) | H26: =SUM(H23:H25) | I26: =SUM(I23:I25) | J26: =SUM(J23:J25) | ... N26: =SUM(N23:N25) | O26: =SUM(C26:N26)
B28: Margen
A29: MARGEN | B29: Resultado operativo (ingresos − egresos) | C29: ='Modelo de ingresos'!C49-C26 | D29: ='Modelo de ingresos'!D49-D26 | E29: ='Modelo de ingresos'!E49-E26 | F29: ='Modelo de ingresos'!F49-F26 | G29: ='Modelo de ingresos'!G49-G26 | H29: ='Modelo de ingresos'!H49-H26 | I29: ='Modelo de ingresos'!I49-I26 | J29: ='Modelo de ingresos'!J49-J26 | ... N29: ='Modelo de ingresos'!N49-N26 | O29: =SUM(C29:N29)
B30: Margen sobre ingresos | C30: =IFERROR(C29/'Modelo de ingresos'!C49,0) | D30: =IFERROR(D29/'Modelo de ingresos'!D49,0) | E30: =IFERROR(E29/'Modelo de ingresos'!E49,0) | F30: =IFERROR(F29/'Modelo de ingresos'!F49,0) | G30: =IFERROR(G29/'Modelo de ingresos'!G49,0) | H30: =IFERROR(H29/'Modelo de ingresos'!H49,0) | I30: =IFERROR(I29/'Modelo de ingresos'!I49,0) | J30: =IFERROR(J29/'Modelo de ingresos'!J49,0) | ... N30: =IFERROR(N29/'Modelo de ingresos'!N49,0)
C33: 2029
C34: Ene | D34: Feb | E34: Mar | F34: Abr | G34: May | H34: Jun | I34: Jul | J34: Ago | K34: Sep | L34: Oct | M34: Nov | N34: Dic | O34: Total 2029
A36: EGRESOS | B36: Costos fijos | C36: ='Costos Fijos'!C88 | D36: ='Costos Fijos'!D88 | E36: ='Costos Fijos'!E88 | F36: ='Costos Fijos'!F88 | G36: ='Costos Fijos'!G88 | H36: ='Costos Fijos'!H88 | I36: ='Costos Fijos'!I88 | J36: ='Costos Fijos'!J88 | ... N36: ='Costos Fijos'!N88 | O36: =SUM(C36:N36)
B37: Costos variables | C37: ='Costos Variables'!C34 | D37: ='Costos Variables'!D34 | E37: ='Costos Variables'!E34 | F37: ='Costos Variables'!F34 | G37: ='Costos Variables'!G34 | H37: ='Costos Variables'!H34 | I37: ='Costos Variables'!I34 | J37: ='Costos Variables'!J34 | ... N37: ='Costos Variables'!N34 | O37: =SUM(C37:N37)
B38: Costos de RRHH | C38: ='RRHH'!C78 | D38: ='RRHH'!D78 | E38: ='RRHH'!E78 | F38: ='RRHH'!F78 | G38: ='RRHH'!G78 | H38: ='RRHH'!H78 | I38: ='RRHH'!I78 | J38: ='RRHH'!J78 | ... N38: ='RRHH'!N78 | O38: =SUM(C38:N38)
B39: Total de egresos | C39: =SUM(C36:C38) | D39: =SUM(D36:D38) | E39: =SUM(E36:E38) | F39: =SUM(F36:F38) | G39: =SUM(G36:G38) | H39: =SUM(H36:H38) | I39: =SUM(I36:I38) | J39: =SUM(J36:J38) | ... N39: =SUM(N36:N38) | O39: =SUM(C39:N39)
B41: Margen
A42: MARGEN | B42: Resultado operativo (ingresos − egresos) | C42: ='Modelo de ingresos'!C72-C39 | D42: ='Modelo de ingresos'!D72-D39 | E42: ='Modelo de ingresos'!E72-E39 | F42: ='Modelo de ingresos'!F72-F39 | G42: ='Modelo de ingresos'!G72-G39 | H42: ='Modelo de ingresos'!H72-H39 | I42: ='Modelo de ingresos'!I72-I39 | J42: ='Modelo de ingresos'!J72-J39 | ... N42: ='Modelo de ingresos'!N72-N39 | O42: =SUM(C42:N42)
B43: Margen sobre ingresos | C43: =IFERROR(C42/'Modelo de ingresos'!C72,0) | D43: =IFERROR(D42/'Modelo de ingresos'!D72,0) | E43: =IFERROR(E42/'Modelo de ingresos'!E72,0) | F43: =IFERROR(F42/'Modelo de ingresos'!F72,0) | G43: =IFERROR(G42/'Modelo de ingresos'!G72,0) | H43: =IFERROR(H42/'Modelo de ingresos'!H72,0) | I43: =IFERROR(I42/'Modelo de ingresos'!I72,0) | J43: =IFERROR(J42/'Modelo de ingresos'!J72,0) | ... N43: =IFERROR(N42/'Modelo de ingresos'!N72,0)
C46: 2030
C47: Ene | D47: Feb | E47: Mar | F47: Abr | G47: May | H47: Jun | I47: Jul | J47: Ago | K47: Sep | L47: Oct | M47: Nov | N47: Dic | O47: Total 2030
A49: EGRESOS | B49: Costos fijos | C49: ='Costos Fijos'!C116 | D49: ='Costos Fijos'!D116 | E49: ='Costos Fijos'!E116 | F49: ='Costos Fijos'!F116 | G49: ='Costos Fijos'!G116 | H49: ='Costos Fijos'!H116 | I49: ='Costos Fijos'!I116 | J49: ='Costos Fijos'!J116 | ... N49: ='Costos Fijos'!N116 | O49: =SUM(C49:N49)
B50: Costos variables | C50: ='Costos Variables'!C44 | D50: ='Costos Variables'!D44 | E50: ='Costos Variables'!E44 | F50: ='Costos Variables'!F44 | G50: ='Costos Variables'!G44 | H50: ='Costos Variables'!H44 | I50: ='Costos Variables'!I44 | J50: ='Costos Variables'!J44 | ... N50: ='Costos Variables'!N44 | O50: =SUM(C50:N50)
B51: Costos de RRHH | C51: ='RRHH'!C93 | D51: ='RRHH'!D93 | E51: ='RRHH'!E93 | F51: ='RRHH'!F93 | G51: ='RRHH'!G93 | H51: ='RRHH'!H93 | I51: ='RRHH'!I93 | J51: ='RRHH'!J93 | ... N51: ='RRHH'!N93 | O51: =SUM(C51:N51)
B52: Total de egresos | C52: =SUM(C49:C51) | D52: =SUM(D49:D51) | E52: =SUM(E49:E51) | F52: =SUM(F49:F51) | G52: =SUM(G49:G51) | H52: =SUM(H49:H51) | I52: =SUM(I49:I51) | J52: =SUM(J49:J51) | ... N52: =SUM(N49:N51) | O52: =SUM(C52:N52)
B54: Margen
A55: MARGEN | B55: Resultado operativo (ingresos − egresos) | C55: ='Modelo de ingresos'!C95-C52 | D55: ='Modelo de ingresos'!D95-D52 | E55: ='Modelo de ingresos'!E95-E52 | F55: ='Modelo de ingresos'!F95-F52 | G55: ='Modelo de ingresos'!G95-G52 | H55: ='Modelo de ingresos'!H95-H52 | I55: ='Modelo de ingresos'!I95-I52 | J55: ='Modelo de ingresos'!J95-J52 | ... N55: ='Modelo de ingresos'!N95-N52 | O55: =SUM(C55:N55)
B56: Margen sobre ingresos | C56: =IFERROR(C55/'Modelo de ingresos'!C95,0) | D56: =IFERROR(D55/'Modelo de ingresos'!D95,0) | E56: =IFERROR(E55/'Modelo de ingresos'!E95,0) | F56: =IFERROR(F55/'Modelo de ingresos'!F95,0) | G56: =IFERROR(G55/'Modelo de ingresos'!G95,0) | H56: =IFERROR(H55/'Modelo de ingresos'!H95,0) | I56: =IFERROR(I55/'Modelo de ingresos'!I95,0) | J56: =IFERROR(J55/'Modelo de ingresos'!J95,0) | ... N56: =IFERROR(N55/'Modelo de ingresos'!N95,0)

Sheet Costos Fijos
A1: « Inicio
B2: COSTOS FIJOS
B3: No dependen del volumen de clientes. Se carga el importe mensual promedio de cada año y se mantiene plano dentro del año: el salto de un año al siguiente absorbe la inflación y el crecimiento de la estructura, que en estos conceptos no es gradual sino escalonado. | Q3: Resumen anual
Q4: Los totales de cada año, que son los que alimentan el gráfico.
Q5: Concepto | R5: 2027 | S5: 2028 | T5: 2029 | U5: 2030
Q6: Total de costos fijos | R6: =O32 | S6: =O60 | T6: =O88 | U6: =O116
C7: 2027
C8: Ene | D8: Feb | E8: Mar | F8: Abr | G8: May | H8: Jun | I8: Jul | J8: Ago | K8: Sep | L8: Oct | M8: Nov | N8: Dic | O8: Total 2027
B10: Importe mensual por año (celdas de entrada)
C11: 2027 | D11: 2028 | E11: 2029 | F11: 2030 | G11: CAPEX / OPEX | H11: Origen
A12: Infraestructura | B12: Infraestructura en la nube (base) | C12: 120000 | D12: 200000 | E12: 320000 | F12: 430000 | G12: OPEX | H12: Exterior | J12: AWS o Azure. La Clase 3 lo clasifica como OPEX: no se activa, se consume
A13: Infraestructura | B13: Herramientas y licencias de desarrollo | C13: 40000 | D13: 60000 | E13: 90000 | F13: 120000 | G13: OPEX | H13: Exterior | J13: GitHub, Jira y similares. SaaS del exterior
A14: Infraestructura | B14: Herramientas de IA del equipo | C14: 90000 | D14: 140000 | E14: 200000 | F14: 260000 | G14: OPEX | H14: Exterior | J14: Claude Teams y asistentes de código, una licencia por persona de desarrollo y soporte. Es el gasto que más creció en el sector y no estaba en el modelo
A15: Comercial | B15: Marketing y contenidos | C15: 175000 | D15: 260000 | E15: 340000 | F15: 420000 | G15: OPEX | H15: Local | J15: Pauta, contenidos y herramientas de campaña
A16: Administración | B16: Estudio contable y legales | C16: 105000 | D16: 130000 | E16: 170000 | F16: 210000 | G16: OPEX | H16: Local | J16: Honorarios mensuales del estudio
A17: Operación | B17: Espacio de trabajo y telefonía | C17: 45000 | D17: 68000 | E17: 105000 | F17: 145000 | G17: OPEX | H17: Local | J17: Coworking por puesto y telefonía. No hay inmueble propio, así que el modelo no tiene impuesto inmobiliario
A18: Operación | B18: Conectividad del equipo remoto | C18: 24000 | D18: 40000 | E18: 60000 | F18: 84000 | G18: OPEX | H18: Local | J18: Reintegro de internet a cada persona: el equipo trabaja remoto y la conexión es una condición de trabajo, no un gasto personal
A19: Operación | B19: Otros gastos operativos | C19: 40000 | D19: 60000 | E19: 90000 | F19: 120000 | G19: OPEX | H19: Local | J19: Bancarios, papelería, imprevistos menores
B20: Total mensual | C20: =SUM(C12:C19) | D20: =SUM(D12:D19) | E20: =SUM(E12:E19) | F20: =SUM(F12:F19)
B21: del cual se paga al exterior | C21: =SUMIF($H$12:$H$19,"Exterior",C12:C19) | D21: =SUMIF($H$12:$H$19,"Exterior",D12:D19) | E21: =SUMIF($H$12:$H$19,"Exterior",E12:E19) | F21: =SUMIF($H$12:$H$19,"Exterior",F12:F19) | J21: Servicios digitales importados: nube, licencias y herramientas de IA. La hoja Impuestos les aplica el IVA acrecentado y la retención a beneficiarios del exterior
B23: Desarrollo mensual
A24: Infraestructura | B24: Infraestructura en la nube (base) | C24: =$C$12 | D24: =$C$12 | E24: =$C$12 | F24: =$C$12 | G24: =$C$12 | H24: =$C$12 | I24: =$C$12 | J24: =$C$12 | ... N24: =$C$12 | O24: =SUM(C24:N24)
A25: Infraestructura | B25: Herramientas y licencias de desarrollo | C25: =$C$13 | D25: =$C$13 | E25: =$C$13 | F25: =$C$13 | G25: =$C$13 | H25: =$C$13 | I25: =$C$13 | J25: =$C$13 | ... N25: =$C$13 | O25: =SUM(C25:N25)
A26: Infraestructura | B26: Herramientas de IA del equipo | C26: =$C$14 | D26: =$C$14 | E26: =$C$14 | F26: =$C$14 | G26: =$C$14 | H26: =$C$14 | I26: =$C$14 | J26: =$C$14 | ... N26: =$C$14 | O26: =SUM(C26:N26)
A27: Comercial | B27: Marketing y contenidos | C27: =$C$15 | D27: =$C$15 | E27: =$C$15 | F27: =$C$15 | G27: =$C$15 | H27: =$C$15 | I27: =$C$15 | J27: =$C$15 | ... N27: =$C$15 | O27: =SUM(C27:N27)
A28: Administración | B28: Estudio contable y legales | C28: =$C$16 | D28: =$C$16 | E28: =$C$16 | F28: =$C$16 | G28: =$C$16 | H28: =$C$16 | I28: =$C$16 | J28: =$C$16 | ... N28: =$C$16 | O28: =SUM(C28:N28)
A29: Operación | B29: Espacio de trabajo y telefonía | C29: =$C$17 | D29: =$C$17 | E29: =$C$17 | F29: =$C$17 | G29: =$C$17 | H29: =$C$17 | I29: =$C$17 | J29: =$C$17 | ... N29: =$C$17 | O29: =SUM(C29:N29)
A30: Operación | B30: Conectividad del equipo remoto | C30: =$C$18 | D30: =$C$18 | E30: =$C$18 | F30: =$C$18 | G30: =$C$18 | H30: =$C$18 | I30: =$C$18 | J30: =$C$18 | ... N30: =$C$18 | O30: =SUM(C30:N30)
A31: Operación | B31: Otros gastos operativos | C31: =$C$19 | D31: =$C$19 | E31: =$C$19 | F31: =$C$19 | G31: =$C$19 | H31: =$C$19 | I31: =$C$19 | J31: =$C$19 | ... N31: =$C$19 | O31: =SUM(C31:N31)
A32: COSTOS FIJOS | B32: Total de costos fijos | C32: =SUM(C24:C31) | D32: =SUM(D24:D31) | E32: =SUM(E24:E31) | F32: =SUM(F24:F31) | G32: =SUM(G24:G31) | H32: =SUM(H24:H31) | I32: =SUM(I24:I31) | J32: =SUM(J24:J31) | ... N32: =SUM(N24:N31) | O32: =SUM(C32:N32)
C35: 2028
C36: Ene | D36: Feb | E36: Mar | F36: Abr | G36: May | H36: Jun | I36: Jul | J36: Ago | K36: Sep | L36: Oct | M36: Nov | N36: Dic | O36: Total 2028
B38: Importe mensual por año (celdas de entrada)
A40: Infraestructura | B40: Infraestructura en la nube (base)
A41: Infraestructura | B41: Herramientas y licencias de desarrollo
A42: Infraestructura | B42: Herramientas de IA del equipo
A43: Comercial | B43: Marketing y contenidos
A44: Administración | B44: Estudio contable y legales
A45: Operación | B45: Espacio de trabajo y telefonía
A46: Operación | B46: Conectividad del equipo remoto
A47: Operación | B47: Otros gastos operativos
B48: Total mensual
B49: del cual se paga al exterior
B51: Desarrollo mensual
A52: Infraestructura | B52: Infraestructura en la nube (base) | C52: =$D$12 | D52: =$D$12 | E52: =$D$12 | F52: =$D$12 | G52: =$D$12 | H52: =$D$12 | I52: =$D$12 | J52: =$D$12 | ... N52: =$D$12 | O52: =SUM(C52:N52)
A53: Infraestructura | B53: Herramientas y licencias de desarrollo | C53: =$D$13 | D53: =$D$13 | E53: =$D$13 | F53: =$D$13 | G53: =$D$13 | H53: =$D$13 | I53: =$D$13 | J53: =$D$13 | ... N53: =$D$13 | O53: =SUM(C53:N53)
A54: Infraestructura | B54: Herramientas de IA del equipo | C54: =$D$14 | D54: =$D$14 | E54: =$D$14 | F54: =$D$14 | G54: =$D$14 | H54: =$D$14 | I54: =$D$14 | J54: =$D$14 | ... N54: =$D$14 | O54: =SUM(C54:N54)
A55: Comercial | B55: Marketing y contenidos | C55: =$D$15 | D55: =$D$15 | E55: =$D$15 | F55: =$D$15 | G55: =$D$15 | H55: =$D$15 | I55: =$D$15 | J55: =$D$15 | ... N55: =$D$15 | O55: =SUM(C55:N55)
A56: Administración | B56: Estudio contable y legales | C56: =$D$16 | D56: =$D$16 | E56: =$D$16 | F56: =$D$16 | G56: =$D$16 | H56: =$D$16 | I56: =$D$16 | J56: =$D$16 | ... N56: =$D$16 | O56: =SUM(C56:N56)
A57: Operación | B57: Espacio de trabajo y telefonía | C57: =$D$17 | D57: =$D$17 | E57: =$D$17 | F57: =$D$17 | G57: =$D$17 | H57: =$D$17 | I57: =$D$17 | J57: =$D$17 | ... N57: =$D$17 | O57: =SUM(C57:N57)
A58: Operación | B58: Conectividad del equipo remoto | C58: =$D$18 | D58: =$D$18 | E58: =$D$18 | F58: =$D$18 | G58: =$D$18 | H58: =$D$18 | I58: =$D$18 | J58: =$D$18 | ... N58: =$D$18 | O58: =SUM(C58:N58)
A59: Operación | B59: Otros gastos operativos | C59: =$D$19 | D59: =$D$19 | E59: =$D$19 | F59: =$D$19 | G59: =$D$19 | H59: =$D$19 | I59: =$D$19 | J59: =$D$19 | ... N59: =$D$19 | O59: =SUM(C59:N59)
A60: COSTOS FIJOS | B60: Total de costos fijos | C60: =SUM(C52:C59) | D60: =SUM(D52:D59) | E60: =SUM(E52:E59) | F60: =SUM(F52:F59) | G60: =SUM(G52:G59) | H60: =SUM(H52:H59) | I60: =SUM(I52:I59) | J60: =SUM(J52:J59) | ... N60: =SUM(N52:N59) | O60: =SUM(C60:N60)
C63: 2029
C64: Ene | D64: Feb | E64: Mar | F64: Abr | G64: May | H64: Jun | I64: Jul | J64: Ago | K64: Sep | L64: Oct | M64: Nov | N64: Dic | O64: Total 2029
B66: Importe mensual por año (celdas de entrada)
A68: Infraestructura | B68: Infraestructura en la nube (base)
A69: Infraestructura | B69: Herramientas y licencias de desarrollo
A70: Infraestructura | B70: Herramientas de IA del equipo
A71: Comercial | B71: Marketing y contenidos
A72: Administración | B72: Estudio contable y legales
A73: Operación | B73: Espacio de trabajo y telefonía
A74: Operación | B74: Conectividad del equipo remoto
A75: Operación | B75: Otros gastos operativos
B76: Total mensual
B77: del cual se paga al exterior
B79: Desarrollo mensual
A80: Infraestructura | B80: Infraestructura en la nube (base) | C80: =$E$12 | D80: =$E$12 | E80: =$E$12 | F80: =$E$12 | G80: =$E$12 | H80: =$E$12 | I80: =$E$12 | J80: =$E$12 | ... N80: =$E$12 | O80: =SUM(C80:N80)
A81: Infraestructura | B81: Herramientas y licencias de desarrollo | C81: =$E$13 | D81: =$E$13 | E81: =$E$13 | F81: =$E$13 | G81: =$E$13 | H81: =$E$13 | I81: =$E$13 | J81: =$E$13 | ... N81: =$E$13 | O81: =SUM(C81:N81)
A82: Infraestructura | B82: Herramientas de IA del equipo | C82: =$E$14 | D82: =$E$14 | E82: =$E$14 | F82: =$E$14 | G82: =$E$14 | H82: =$E$14 | I82: =$E$14 | J82: =$E$14 | ... N82: =$E$14 | O82: =SUM(C82:N82)
A83: Comercial | B83: Marketing y contenidos | C83: =$E$15 | D83: =$E$15 | E83: =$E$15 | F83: =$E$15 | G83: =$E$15 | H83: =$E$15 | I83: =$E$15 | J83: =$E$15 | ... N83: =$E$15 | O83: =SUM(C83:N83)
A84: Administración | B84: Estudio contable y legales | C84: =$E$16 | D84: =$E$16 | E84: =$E$16 | F84: =$E$16 | G84: =$E$16 | H84: =$E$16 | I84: =$E$16 | J84: =$E$16 | ... N84: =$E$16 | O84: =SUM(C84:N84)
A85: Operación | B85: Espacio de trabajo y telefonía | C85: =$E$17 | D85: =$E$17 | E85: =$E$17 | F85: =$E$17 | G85: =$E$17 | H85: =$E$17 | I85: =$E$17 | J85: =$E$17 | ... N85: =$E$17 | O85: =SUM(C85:N85)
A86: Operación | B86: Conectividad del equipo remoto | C86: =$E$18 | D86: =$E$18 | E86: =$E$18 | F86: =$E$18 | G86: =$E$18 | H86: =$E$18 | I86: =$E$18 | J86: =$E$18 | ... N86: =$E$18 | O86: =SUM(C86:N86)
A87: Operación | B87: Otros gastos operativos | C87: =$E$19 | D87: =$E$19 | E87: =$E$19 | F87: =$E$19 | G87: =$E$19 | H87: =$E$19 | I87: =$E$19 | J87: =$E$19 | ... N87: =$E$19 | O87: =SUM(C87:N87)
A88: COSTOS FIJOS | B88: Total de costos fijos | C88: =SUM(C80:C87) | D88: =SUM(D80:D87) | E88: =SUM(E80:E87) | F88: =SUM(F80:F87) | G88: =SUM(G80:G87) | H88: =SUM(H80:H87) | I88: =SUM(I80:I87) | J88: =SUM(J80:J87) | ... N88: =SUM(N80:N87) | O88: =SUM(C88:N88)
C91: 2030
C92: Ene | D92: Feb | E92: Mar | F92: Abr | G92: May | H92: Jun | I92: Jul | J92: Ago | K92: Sep | L92: Oct | M92: Nov | N92: Dic | O92: Total 2030
B94: Importe mensual por año (celdas de entrada)
A96: Infraestructura | B96: Infraestructura en la nube (base)
A97: Infraestructura | B97: Herramientas y licencias de desarrollo
A98: Infraestructura | B98: Herramientas de IA del equipo
A99: Comercial | B99: Marketing y contenidos
A100: Administración | B100: Estudio contable y legales
A101: Operación | B101: Espacio de trabajo y telefonía
A102: Operación | B102: Conectividad del equipo remoto
A103: Operación | B103: Otros gastos operativos
B104: Total mensual
B105: del cual se paga al exterior
B107: Desarrollo mensual
A108: Infraestructura | B108: Infraestructura en la nube (base) | C108: =$F$12 | D108: =$F$12 | E108: =$F$12 | F108: =$F$12 | G108: =$F$12 | H108: =$F$12 | I108: =$F$12 | J108: =$F$12 | ... N108: =$F$12 | O108: =SUM(C108:N108)
A109: Infraestructura | B109: Herramientas y licencias de desarrollo | C109: =$F$13 | D109: =$F$13 | E109: =$F$13 | F109: =$F$13 | G109: =$F$13 | H109: =$F$13 | I109: =$F$13 | J109: =$F$13 | ... N109: =$F$13 | O109: =SUM(C109:N109)
A110: Infraestructura | B110: Herramientas de IA del equipo | C110: =$F$14 | D110: =$F$14 | E110: =$F$14 | F110: =$F$14 | G110: =$F$14 | H110: =$F$14 | I110: =$F$14 | J110: =$F$14 | ... N110: =$F$14 | O110: =SUM(C110:N110)
A111: Comercial | B111: Marketing y contenidos | C111: =$F$15 | D111: =$F$15 | E111: =$F$15 | F111: =$F$15 | G111: =$F$15 | H111: =$F$15 | I111: =$F$15 | J111: =$F$15 | ... N111: =$F$15 | O111: =SUM(C111:N111)
A112: Administración | B112: Estudio contable y legales | C112: =$F$16 | D112: =$F$16 | E112: =$F$16 | F112: =$F$16 | G112: =$F$16 | H112: =$F$16 | I112: =$F$16 | J112: =$F$16 | ... N112: =$F$16 | O112: =SUM(C112:N112)
A113: Operación | B113: Espacio de trabajo y telefonía | C113: =$F$17 | D113: =$F$17 | E113: =$F$17 | F113: =$F$17 | G113: =$F$17 | H113: =$F$17 | I113: =$F$17 | J113: =$F$17 | ... N113: =$F$17 | O113: =SUM(C113:N113)
A114: Operación | B114: Conectividad del equipo remoto | C114: =$F$18 | D114: =$F$18 | E114: =$F$18 | F114: =$F$18 | G114: =$F$18 | H114: =$F$18 | I114: =$F$18 | J114: =$F$18 | ... N114: =$F$18 | O114: =SUM(C114:N114)
A115: Operación | B115: Otros gastos operativos | C115: =$F$19 | D115: =$F$19 | E115: =$F$19 | F115: =$F$19 | G115: =$F$19 | H115: =$F$19 | I115: =$F$19 | J115: =$F$19 | ... N115: =$F$19 | O115: =SUM(C115:N115)
A116: COSTOS FIJOS | B116: Total de costos fijos | C116: =SUM(C108:C115) | D116: =SUM(D108:D115) | E116: =SUM(E108:E115) | F116: =SUM(F108:F115) | G116: =SUM(G108:G115) | H116: =SUM(H108:H115) | I116: =SUM(I108:I115) | J116: =SUM(J108:J115) | ... N116: =SUM(N108:N115) | O116: =SUM(C116:N116)

Sheet Costos Variables
A1: « Inicio
B2: COSTOS VARIABLES
B3: Se mueven con cada cliente. Los importes unitarios salen de la sección 6.5.3 del documento y se toman de la hoja Planes, para que no haya dos versiones del mismo número. Cada concepto se ajusta por el índice que le corresponde: los dos que se pagan en dólares siguen al tipo de cambio y el soporte, que es trabajo local, sigue a los salarios. | Q3: Resumen anual
Q4: Los totales de cada año, que son los que alimentan el gráfico.
Q5: Concepto | R5: 2027 | S5: 2028 | T5: 2029 | U5: 2030
Q6: Infraestructura en la nube | R6: =O11 | S6: =O21 | T6: =O31 | U6: =O41
C7: 2027 | Q7: Soporte | R7: =O12 | S7: =O22 | T7: =O32 | U7: =O42
C8: Ene | D8: Feb | E8: Mar | F8: Abr | G8: May | H8: Jun | I8: Jul | J8: Ago | K8: Sep | L8: Oct | M8: Nov | N8: Dic | O8: Total 2027 | Q8: Servicio externo de IA | R8: =O13 | S8: =O23 | T8: =O33 | U8: =O43
B10: Por concepto
A11: VARIABLES | B11: Infraestructura por cliente (sigue al dólar) | C11: =('Proyección de ventas'!C20*Planes!$G$7+'Proyección de ventas'!C26*Planes!$G$8+'Proyección de ventas'!C30*Planes!$G$9)*1 | D11: =('Proyección de ventas'!D20*Planes!$G$7+'Proyección de ventas'!D26*Planes!$G$8+'Proyección de ventas'!D30*Planes!$G$9)*1 | E11: =('Proyección de ventas'!E20*Planes!$G$7+'Proyección de ventas'!E26*Planes!$G$8+'Proyección de ventas'!E30*Planes!$G$9)*1 | F11: =('Proyección de ventas'!F20*Planes!$G$7+'Proyección de ventas'!F26*Planes!$G$8+'Proyección de ventas'!F30*Planes!$G$9)*1 | G11: =('Proyección de ventas'!G20*Planes!$G$7+'Proyección de ventas'!G26*Planes!$G$8+'Proyección de ventas'!G30*Planes!$G$9)*1 | H11: =('Proyección de ventas'!H20*Planes!$G$7+'Proyección de ventas'!H26*Planes!$G$8+'Proyección de ventas'!H30*Planes!$G$9)*1 | I11: =('Proyección de ventas'!I20*Planes!$G$7+'Proyección de ventas'!I26*Planes!$G$8+'Proyección de ventas'!I30*Planes!$G$9)*1 | J11: =('Proyección de ventas'!J20*Planes!$G$7+'Proyección de ventas'!J26*Planes!$G$8+'Proyección de ventas'!J30*Planes!$G$9)*1 | ... N11: =('Proyección de ventas'!N20*Planes!$G$7+'Proyección de ventas'!N26*Planes!$G$8+'Proyección de ventas'!N30*Planes!$G$9)*1 | O11: =SUM(C11:N11)
B12: Soporte y onboarding por cliente (sigue a los salarios) | C12: =('Proyección de ventas'!C20*Planes!$H$7+'Proyección de ventas'!C26*Planes!$H$8+'Proyección de ventas'!C30*Planes!$H$9)*1 | D12: =('Proyección de ventas'!D20*Planes!$H$7+'Proyección de ventas'!D26*Planes!$H$8+'Proyección de ventas'!D30*Planes!$H$9)*1 | E12: =('Proyección de ventas'!E20*Planes!$H$7+'Proyección de ventas'!E26*Planes!$H$8+'Proyección de ventas'!E30*Planes!$H$9)*1 | F12: =('Proyección de ventas'!F20*Planes!$H$7+'Proyección de ventas'!F26*Planes!$H$8+'Proyección de ventas'!F30*Planes!$H$9)*1 | G12: =('Proyección de ventas'!G20*Planes!$H$7+'Proyección de ventas'!G26*Planes!$H$8+'Proyección de ventas'!G30*Planes!$H$9)*1 | H12: =('Proyección de ventas'!H20*Planes!$H$7+'Proyección de ventas'!H26*Planes!$H$8+'Proyección de ventas'!H30*Planes!$H$9)*1 | I12: =('Proyección de ventas'!I20*Planes!$H$7+'Proyección de ventas'!I26*Planes!$H$8+'Proyección de ventas'!I30*Planes!$H$9)*1 | J12: =('Proyección de ventas'!J20*Planes!$H$7+'Proyección de ventas'!J26*Planes!$H$8+'Proyección de ventas'!J30*Planes!$H$9)*1 | ... N12: =('Proyección de ventas'!N20*Planes!$H$7+'Proyección de ventas'!N26*Planes!$H$8+'Proyección de ventas'!N30*Planes!$H$9)*1 | O12: =SUM(C12:N12)
B13: Servicio externo de inteligencia artificial (sigue al dólar) | C13: =('Proyección de ventas'!C20*Planes!$I$7+'Proyección de ventas'!C26*Planes!$I$8+'Proyección de ventas'!C30*Planes!$I$9)*1 | D13: =('Proyección de ventas'!D20*Planes!$I$7+'Proyección de ventas'!D26*Planes!$I$8+'Proyección de ventas'!D30*Planes!$I$9)*1 | E13: =('Proyección de ventas'!E20*Planes!$I$7+'Proyección de ventas'!E26*Planes!$I$8+'Proyección de ventas'!E30*Planes!$I$9)*1 | F13: =('Proyección de ventas'!F20*Planes!$I$7+'Proyección de ventas'!F26*Planes!$I$8+'Proyección de ventas'!F30*Planes!$I$9)*1 | G13: =('Proyección de ventas'!G20*Planes!$I$7+'Proyección de ventas'!G26*Planes!$I$8+'Proyección de ventas'!G30*Planes!$I$9)*1 | H13: =('Proyección de ventas'!H20*Planes!$I$7+'Proyección de ventas'!H26*Planes!$I$8+'Proyección de ventas'!H30*Planes!$I$9)*1 | I13: =('Proyección de ventas'!I20*Planes!$I$7+'Proyección de ventas'!I26*Planes!$I$8+'Proyección de ventas'!I30*Planes!$I$9)*1 | J13: =('Proyección de ventas'!J20*Planes!$I$7+'Proyección de ventas'!J26*Planes!$I$8+'Proyección de ventas'!J30*Planes!$I$9)*1 | ... N13: =('Proyección de ventas'!N20*Planes!$I$7+'Proyección de ventas'!N26*Planes!$I$8+'Proyección de ventas'!N30*Planes!$I$9)*1 | O13: =SUM(C13:N13)
B14: Total de costos variables | C14: =SUM(C11:C13) | D14: =SUM(D11:D13) | E14: =SUM(E11:E13) | F14: =SUM(F11:F13) | G14: =SUM(G11:G13) | H14: =SUM(H11:H13) | I14: =SUM(I11:I13) | J14: =SUM(J11:J13) | ... N14: =SUM(N11:N13) | O14: =SUM(C14:N14)
C17: 2028
C18: Ene | D18: Feb | E18: Mar | F18: Abr | G18: May | H18: Jun | I18: Jul | J18: Ago | K18: Sep | L18: Oct | M18: Nov | N18: Dic | O18: Total 2028
B20: Por concepto
A21: VARIABLES | B21: Infraestructura por cliente (sigue al dólar) | C21: =('Proyección de ventas'!C50*Planes!$G$7+'Proyección de ventas'!C56*Planes!$G$8+'Proyección de ventas'!C60*Planes!$G$9)*Hipótesis!$D$9/Hipótesis!$C$9 | D21: =('Proyección de ventas'!D50*Planes!$G$7+'Proyección de ventas'!D56*Planes!$G$8+'Proyección de ventas'!D60*Planes!$G$9)*Hipótesis!$D$9/Hipótesis!$C$9 | E21: =('Proyección de ventas'!E50*Planes!$G$7+'Proyección de ventas'!E56*Planes!$G$8+'Proyección de ventas'!E60*Planes!$G$9)*Hipótesis!$D$9/Hipótesis!$C$9 | F21: =('Proyección de ventas'!F50*Planes!$G$7+'Proyección de ventas'!F56*Planes!$G$8+'Proyección de ventas'!F60*Planes!$G$9)*Hipótesis!$D$9/Hipótesis!$C$9 | G21: =('Proyección de ventas'!G50*Planes!$G$7+'Proyección de ventas'!G56*Planes!$G$8+'Proyección de ventas'!G60*Planes!$G$9)*Hipótesis!$D$9/Hipótesis!$C$9 | H21: =('Proyección de ventas'!H50*Planes!$G$7+'Proyección de ventas'!H56*Planes!$G$8+'Proyección de ventas'!H60*Planes!$G$9)*Hipótesis!$D$9/Hipótesis!$C$9 | I21: =('Proyección de ventas'!I50*Planes!$G$7+'Proyección de ventas'!I56*Planes!$G$8+'Proyección de ventas'!I60*Planes!$G$9)*Hipótesis!$D$9/Hipótesis!$C$9 | J21: =('Proyección de ventas'!J50*Planes!$G$7+'Proyección de ventas'!J56*Planes!$G$8+'Proyección de ventas'!J60*Planes!$G$9)*Hipótesis!$D$9/Hipótesis!$C$9 | ... N21: =('Proyección de ventas'!N50*Planes!$G$7+'Proyección de ventas'!N56*Planes!$G$8+'Proyección de ventas'!N60*Planes!$G$9)*Hipótesis!$D$9/Hipótesis!$C$9 | O21: =SUM(C21:N21)
B22: Soporte y onboarding por cliente (sigue a los salarios) | C22: =('Proyección de ventas'!C50*Planes!$H$7+'Proyección de ventas'!C56*Planes!$H$8+'Proyección de ventas'!C60*Planes!$H$9)*(1+Hipótesis!$D$14) | D22: =('Proyección de ventas'!D50*Planes!$H$7+'Proyección de ventas'!D56*Planes!$H$8+'Proyección de ventas'!D60*Planes!$H$9)*(1+Hipótesis!$D$14) | E22: =('Proyección de ventas'!E50*Planes!$H$7+'Proyección de ventas'!E56*Planes!$H$8+'Proyección de ventas'!E60*Planes!$H$9)*(1+Hipótesis!$D$14) | F22: =('Proyección de ventas'!F50*Planes!$H$7+'Proyección de ventas'!F56*Planes!$H$8+'Proyección de ventas'!F60*Planes!$H$9)*(1+Hipótesis!$D$14) | G22: =('Proyección de ventas'!G50*Planes!$H$7+'Proyección de ventas'!G56*Planes!$H$8+'Proyección de ventas'!G60*Planes!$H$9)*(1+Hipótesis!$D$14) | H22: =('Proyección de ventas'!H50*Planes!$H$7+'Proyección de ventas'!H56*Planes!$H$8+'Proyección de ventas'!H60*Planes!$H$9)*(1+Hipótesis!$D$14) | I22: =('Proyección de ventas'!I50*Planes!$H$7+'Proyección de ventas'!I56*Planes!$H$8+'Proyección de ventas'!I60*Planes!$H$9)*(1+Hipótesis!$D$14) | J22: =('Proyección de ventas'!J50*Planes!$H$7+'Proyección de ventas'!J56*Planes!$H$8+'Proyección de ventas'!J60*Planes!$H$9)*(1+Hipótesis!$D$14) | ... N22: =('Proyección de ventas'!N50*Planes!$H$7+'Proyección de ventas'!N56*Planes!$H$8+'Proyección de ventas'!N60*Planes!$H$9)*(1+Hipótesis!$D$14) | O22: =SUM(C22:N22)
B23: Servicio externo de inteligencia artificial (sigue al dólar) | C23: =('Proyección de ventas'!C50*Planes!$I$7+'Proyección de ventas'!C56*Planes!$I$8+'Proyección de ventas'!C60*Planes!$I$9)*Hipótesis!$D$9/Hipótesis!$C$9 | D23: =('Proyección de ventas'!D50*Planes!$I$7+'Proyección de ventas'!D56*Planes!$I$8+'Proyección de ventas'!D60*Planes!$I$9)*Hipótesis!$D$9/Hipótesis!$C$9 | E23: =('Proyección de ventas'!E50*Planes!$I$7+'Proyección de ventas'!E56*Planes!$I$8+'Proyección de ventas'!E60*Planes!$I$9)*Hipótesis!$D$9/Hipótesis!$C$9 | F23: =('Proyección de ventas'!F50*Planes!$I$7+'Proyección de ventas'!F56*Planes!$I$8+'Proyección de ventas'!F60*Planes!$I$9)*Hipótesis!$D$9/Hipótesis!$C$9 | G23: =('Proyección de ventas'!G50*Planes!$I$7+'Proyección de ventas'!G56*Planes!$I$8+'Proyección de ventas'!G60*Planes!$I$9)*Hipótesis!$D$9/Hipótesis!$C$9 | H23: =('Proyección de ventas'!H50*Planes!$I$7+'Proyección de ventas'!H56*Planes!$I$8+'Proyección de ventas'!H60*Planes!$I$9)*Hipótesis!$D$9/Hipótesis!$C$9 | I23: =('Proyección de ventas'!I50*Planes!$I$7+'Proyección de ventas'!I56*Planes!$I$8+'Proyección de ventas'!I60*Planes!$I$9)*Hipótesis!$D$9/Hipótesis!$C$9 | J23: =('Proyección de ventas'!J50*Planes!$I$7+'Proyección de ventas'!J56*Planes!$I$8+'Proyección de ventas'!J60*Planes!$I$9)*Hipótesis!$D$9/Hipótesis!$C$9 | ... N23: =('Proyección de ventas'!N50*Planes!$I$7+'Proyección de ventas'!N56*Planes!$I$8+'Proyección de ventas'!N60*Planes!$I$9)*Hipótesis!$D$9/Hipótesis!$C$9 | O23: =SUM(C23:N23)
B24: Total de costos variables | C24: =SUM(C21:C23) | D24: =SUM(D21:D23) | E24: =SUM(E21:E23) | F24: =SUM(F21:F23) | G24: =SUM(G21:G23) | H24: =SUM(H21:H23) | I24: =SUM(I21:I23) | J24: =SUM(J21:J23) | ... N24: =SUM(N21:N23) | O24: =SUM(C24:N24)
C27: 2029
C28: Ene | D28: Feb | E28: Mar | F28: Abr | G28: May | H28: Jun | I28: Jul | J28: Ago | K28: Sep | L28: Oct | M28: Nov | N28: Dic | O28: Total 2029
B30: Por concepto
A31: VARIABLES | B31: Infraestructura por cliente (sigue al dólar) | C31: =('Proyección de ventas'!C80*Planes!$G$7+'Proyección de ventas'!C86*Planes!$G$8+'Proyección de ventas'!C90*Planes!$G$9)*Hipótesis!$E$9/Hipótesis!$C$9 | D31: =('Proyección de ventas'!D80*Planes!$G$7+'Proyección de ventas'!D86*Planes!$G$8+'Proyección de ventas'!D90*Planes!$G$9)*Hipótesis!$E$9/Hipótesis!$C$9 | E31: =('Proyección de ventas'!E80*Planes!$G$7+'Proyección de ventas'!E86*Planes!$G$8+'Proyección de ventas'!E90*Planes!$G$9)*Hipótesis!$E$9/Hipótesis!$C$9 | F31: =('Proyección de ventas'!F80*Planes!$G$7+'Proyección de ventas'!F86*Planes!$G$8+'Proyección de ventas'!F90*Planes!$G$9)*Hipótesis!$E$9/Hipótesis!$C$9 | G31: =('Proyección de ventas'!G80*Planes!$G$7+'Proyección de ventas'!G86*Planes!$G$8+'Proyección de ventas'!G90*Planes!$G$9)*Hipótesis!$E$9/Hipótesis!$C$9 | H31: =('Proyección de ventas'!H80*Planes!$G$7+'Proyección de ventas'!H86*Planes!$G$8+'Proyección de ventas'!H90*Planes!$G$9)*Hipótesis!$E$9/Hipótesis!$C$9 | I31: =('Proyección de ventas'!I80*Planes!$G$7+'Proyección de ventas'!I86*Planes!$G$8+'Proyección de ventas'!I90*Planes!$G$9)*Hipótesis!$E$9/Hipótesis!$C$9 | J31: =('Proyección de ventas'!J80*Planes!$G$7+'Proyección de ventas'!J86*Planes!$G$8+'Proyección de ventas'!J90*Planes!$G$9)*Hipótesis!$E$9/Hipótesis!$C$9 | ... N31: =('Proyección de ventas'!N80*Planes!$G$7+'Proyección de ventas'!N86*Planes!$G$8+'Proyección de ventas'!N90*Planes!$G$9)*Hipótesis!$E$9/Hipótesis!$C$9 | O31: =SUM(C31:N31)
B32: Soporte y onboarding por cliente (sigue a los salarios) | C32: =('Proyección de ventas'!C80*Planes!$H$7+'Proyección de ventas'!C86*Planes!$H$8+'Proyección de ventas'!C90*Planes!$H$9)*(1+Hipótesis!$D$14)*(1+Hipótesis!$E$14) | D32: =('Proyección de ventas'!D80*Planes!$H$7+'Proyección de ventas'!D86*Planes!$H$8+'Proyección de ventas'!D90*Planes!$H$9)*(1+Hipótesis!$D$14)*(1+Hipótesis!$E$14) | E32: =('Proyección de ventas'!E80*Planes!$H$7+'Proyección de ventas'!E86*Planes!$H$8+'Proyección de ventas'!E90*Planes!$H$9)*(1+Hipótesis!$D$14)*(1+Hipótesis!$E$14) | F32: =('Proyección de ventas'!F80*Planes!$H$7+'Proyección de ventas'!F86*Planes!$H$8+'Proyección de ventas'!F90*Planes!$H$9)*(1+Hipótesis!$D$14)*(1+Hipótesis!$E$14) | G32: =('Proyección de ventas'!G80*Planes!$H$7+'Proyección de ventas'!G86*Planes!$H$8+'Proyección de ventas'!G90*Planes!$H$9)*(1+Hipótesis!$D$14)*(1+Hipótesis!$E$14) | H32: =('Proyección de ventas'!H80*Planes!$H$7+'Proyección de ventas'!H86*Planes!$H$8+'Proyección de ventas'!H90*Planes!$H$9)*(1+Hipótesis!$D$14)*(1+Hipótesis!$E$14) | I32: =('Proyección de ventas'!I80*Planes!$H$7+'Proyección de ventas'!I86*Planes!$H$8+'Proyección de ventas'!I90*Planes!$H$9)*(1+Hipótesis!$D$14)*(1+Hipótesis!$E$14) | J32: =('Proyección de ventas'!J80*Planes!$H$7+'Proyección de ventas'!J86*Planes!$H$8+'Proyección de ventas'!J90*Planes!$H$9)*(1+Hipótesis!$D$14)*(1+Hipótesis!$E$14) | ... N32: =('Proyección de ventas'!N80*Planes!$H$7+'Proyección de ventas'!N86*Planes!$H$8+'Proyección de ventas'!N90*Planes!$H$9)*(1+Hipótesis!$D$14)*(1+Hipótesis!$E$14) | O32: =SUM(C32:N32)
B33: Servicio externo de inteligencia artificial (sigue al dólar) | C33: =('Proyección de ventas'!C80*Planes!$I$7+'Proyección de ventas'!C86*Planes!$I$8+'Proyección de ventas'!C90*Planes!$I$9)*Hipótesis!$E$9/Hipótesis!$C$9 | D33: =('Proyección de ventas'!D80*Planes!$I$7+'Proyección de ventas'!D86*Planes!$I$8+'Proyección de ventas'!D90*Planes!$I$9)*Hipótesis!$E$9/Hipótesis!$C$9 | E33: =('Proyección de ventas'!E80*Planes!$I$7+'Proyección de ventas'!E86*Planes!$I$8+'Proyección de ventas'!E90*Planes!$I$9)*Hipótesis!$E$9/Hipótesis!$C$9 | F33: =('Proyección de ventas'!F80*Planes!$I$7+'Proyección de ventas'!F86*Planes!$I$8+'Proyección de ventas'!F90*Planes!$I$9)*Hipótesis!$E$9/Hipótesis!$C$9 | G33: =('Proyección de ventas'!G80*Planes!$I$7+'Proyección de ventas'!G86*Planes!$I$8+'Proyección de ventas'!G90*Planes!$I$9)*Hipótesis!$E$9/Hipótesis!$C$9 | H33: =('Proyección de ventas'!H80*Planes!$I$7+'Proyección de ventas'!H86*Planes!$I$8+'Proyección de ventas'!H90*Planes!$I$9)*Hipótesis!$E$9/Hipótesis!$C$9 | I33: =('Proyección de ventas'!I80*Planes!$I$7+'Proyección de ventas'!I86*Planes!$I$8+'Proyección de ventas'!I90*Planes!$I$9)*Hipótesis!$E$9/Hipótesis!$C$9 | J33: =('Proyección de ventas'!J80*Planes!$I$7+'Proyección de ventas'!J86*Planes!$I$8+'Proyección de ventas'!J90*Planes!$I$9)*Hipótesis!$E$9/Hipótesis!$C$9 | ... N33: =('Proyección de ventas'!N80*Planes!$I$7+'Proyección de ventas'!N86*Planes!$I$8+'Proyección de ventas'!N90*Planes!$I$9)*Hipótesis!$E$9/Hipótesis!$C$9 | O33: =SUM(C33:N33)
B34: Total de costos variables | C34: =SUM(C31:C33) | D34: =SUM(D31:D33) | E34: =SUM(E31:E33) | F34: =SUM(F31:F33) | G34: =SUM(G31:G33) | H34: =SUM(H31:H33) | I34: =SUM(I31:I33) | J34: =SUM(J31:J33) | ... N34: =SUM(N31:N33) | O34: =SUM(C34:N34)
C37: 2030
C38: Ene | D38: Feb | E38: Mar | F38: Abr | G38: May | H38: Jun | I38: Jul | J38: Ago | K38: Sep | L38: Oct | M38: Nov | N38: Dic | O38: Total 2030
B40: Por concepto
A41: VARIABLES | B41: Infraestructura por cliente (sigue al dólar) | C41: =('Proyección de ventas'!C110*Planes!$G$7+'Proyección de ventas'!C116*Planes!$G$8+'Proyección de ventas'!C120*Planes!$G$9)*Hipótesis!$F$9/Hipótesis!$C$9 | D41: =('Proyección de ventas'!D110*Planes!$G$7+'Proyección de ventas'!D116*Planes!$G$8+'Proyección de ventas'!D120*Planes!$G$9)*Hipótesis!$F$9/Hipótesis!$C$9 | E41: =('Proyección de ventas'!E110*Planes!$G$7+'Proyección de ventas'!E116*Planes!$G$8+'Proyección de ventas'!E120*Planes!$G$9)*Hipótesis!$F$9/Hipótesis!$C$9 | F41: =('Proyección de ventas'!F110*Planes!$G$7+'Proyección de ventas'!F116*Planes!$G$8+'Proyección de ventas'!F120*Planes!$G$9)*Hipótesis!$F$9/Hipótesis!$C$9 | G41: =('Proyección de ventas'!G110*Planes!$G$7+'Proyección de ventas'!G116*Planes!$G$8+'Proyección de ventas'!G120*Planes!$G$9)*Hipótesis!$F$9/Hipótesis!$C$9 | H41: =('Proyección de ventas'!H110*Planes!$G$7+'Proyección de ventas'!H116*Planes!$G$8+'Proyección de ventas'!H120*Planes!$G$9)*Hipótesis!$F$9/Hipótesis!$C$9 | I41: =('Proyección de ventas'!I110*Planes!$G$7+'Proyección de ventas'!I116*Planes!$G$8+'Proyección de ventas'!I120*Planes!$G$9)*Hipótesis!$F$9/Hipótesis!$C$9 | J41: =('Proyección de ventas'!J110*Planes!$G$7+'Proyección de ventas'!J116*Planes!$G$8+'Proyección de ventas'!J120*Planes!$G$9)*Hipótesis!$F$9/Hipótesis!$C$9 | ... N41: =('Proyección de ventas'!N110*Planes!$G$7+'Proyección de ventas'!N116*Planes!$G$8+'Proyección de ventas'!N120*Planes!$G$9)*Hipótesis!$F$9/Hipótesis!$C$9 | O41: =SUM(C41:N41)
B42: Soporte y onboarding por cliente (sigue a los salarios) | C42: =('Proyección de ventas'!C110*Planes!$H$7+'Proyección de ventas'!C116*Planes!$H$8+'Proyección de ventas'!C120*Planes!$H$9)*(1+Hipótesis!$D$14)*(1+Hipótesis!$E$14)*(1+Hipótesis!$F$14) | D42: =('Proyección de ventas'!D110*Planes!$H$7+'Proyección de ventas'!D116*Planes!$H$8+'Proyección de ventas'!D120*Planes!$H$9)*(1+Hipótesis!$D$14)*(1+Hipótesis!$E$14)*(1+Hipótesis!$F$14) | E42: =('Proyección de ventas'!E110*Planes!$H$7+'Proyección de ventas'!E116*Planes!$H$8+'Proyección de ventas'!E120*Planes!$H$9)*(1+Hipótesis!$D$14)*(1+Hipótesis!$E$14)*(1+Hipótesis!$F$14) | F42: =('Proyección de ventas'!F110*Planes!$H$7+'Proyección de ventas'!F116*Planes!$H$8+'Proyección de ventas'!F120*Planes!$H$9)*(1+Hipótesis!$D$14)*(1+Hipótesis!$E$14)*(1+Hipótesis!$F$14) | G42: =('Proyección de ventas'!G110*Planes!$H$7+'Proyección de ventas'!G116*Planes!$H$8+'Proyección de ventas'!G120*Planes!$H$9)*(1+Hipótesis!$D$14)*(1+Hipótesis!$E$14)*(1+Hipótesis!$F$14) | H42: =('Proyección de ventas'!H110*Planes!$H$7+'Proyección de ventas'!H116*Planes!$H$8+'Proyección de ventas'!H120*Planes!$H$9)*(1+Hipótesis!$D$14)*(1+Hipótesis!$E$14)*(1+Hipótesis!$F$14) | I42: =('Proyección de ventas'!I110*Planes!$H$7+'Proyección de ventas'!I116*Planes!$H$8+'Proyección de ventas'!I120*Planes!$H$9)*(1+Hipótesis!$D$14)*(1+Hipótesis!$E$14)*(1+Hipótesis!$F$14) | J42: =('Proyección de ventas'!J110*Planes!$H$7+'Proyección de ventas'!J116*Planes!$H$8+'Proyección de ventas'!J120*Planes!$H$9)*(1+Hipótesis!$D$14)*(1+Hipótesis!$E$14)*(1+Hipótesis!$F$14) | ... N42: =('Proyección de ventas'!N110*Planes!$H$7+'Proyección de ventas'!N116*Planes!$H$8+'Proyección de ventas'!N120*Planes!$H$9)*(1+Hipótesis!$D$14)*(1+Hipótesis!$E$14)*(1+Hipótesis!$F$14) | O42: =SUM(C42:N42)
B43: Servicio externo de inteligencia artificial (sigue al dólar) | C43: =('Proyección de ventas'!C110*Planes!$I$7+'Proyección de ventas'!C116*Planes!$I$8+'Proyección de ventas'!C120*Planes!$I$9)*Hipótesis!$F$9/Hipótesis!$C$9 | D43: =('Proyección de ventas'!D110*Planes!$I$7+'Proyección de ventas'!D116*Planes!$I$8+'Proyección de ventas'!D120*Planes!$I$9)*Hipótesis!$F$9/Hipótesis!$C$9 | E43: =('Proyección de ventas'!E110*Planes!$I$7+'Proyección de ventas'!E116*Planes!$I$8+'Proyección de ventas'!E120*Planes!$I$9)*Hipótesis!$F$9/Hipótesis!$C$9 | F43: =('Proyección de ventas'!F110*Planes!$I$7+'Proyección de ventas'!F116*Planes!$I$8+'Proyección de ventas'!F120*Planes!$I$9)*Hipótesis!$F$9/Hipótesis!$C$9 | G43: =('Proyección de ventas'!G110*Planes!$I$7+'Proyección de ventas'!G116*Planes!$I$8+'Proyección de ventas'!G120*Planes!$I$9)*Hipótesis!$F$9/Hipótesis!$C$9 | H43: =('Proyección de ventas'!H110*Planes!$I$7+'Proyección de ventas'!H116*Planes!$I$8+'Proyección de ventas'!H120*Planes!$I$9)*Hipótesis!$F$9/Hipótesis!$C$9 | I43: =('Proyección de ventas'!I110*Planes!$I$7+'Proyección de ventas'!I116*Planes!$I$8+'Proyección de ventas'!I120*Planes!$I$9)*Hipótesis!$F$9/Hipótesis!$C$9 | J43: =('Proyección de ventas'!J110*Planes!$I$7+'Proyección de ventas'!J116*Planes!$I$8+'Proyección de ventas'!J120*Planes!$I$9)*Hipótesis!$F$9/Hipótesis!$C$9 | ... N43: =('Proyección de ventas'!N110*Planes!$I$7+'Proyección de ventas'!N116*Planes!$I$8+'Proyección de ventas'!N120*Planes!$I$9)*Hipótesis!$F$9/Hipótesis!$C$9 | O43: =SUM(C43:N43)
B44: Total de costos variables | C44: =SUM(C41:C43) | D44: =SUM(D41:D43) | E44: =SUM(E41:E43) | F44: =SUM(F41:F43) | G44: =SUM(G41:G43) | H44: =SUM(H41:H43) | I44: =SUM(I41:I43) | J44: =SUM(J41:J43) | ... N44: =SUM(N41:N43) | O44: =SUM(C44:N44)
B46: El costo del servicio de inteligencia artificial es el único que el sistema mide por sí mismo: cada consulta de clasificación, de asignación y de guía de reparación queda registrada, así que la estimación de la sección 6.5.3 se puede contrastar contra el consumo real.

Sheet RRHH
A1: « Inicio
B2: COSTOS DE RRHH
B3: Plantilla de la sección 7.6 del documento. Los cuatro roles funcionales se cubren de a poco: en las primeras etapas los socios fundadores asumen más de uno. | Q3: Resumen anual
Q4: Los totales de cada año, que son los que alimentan el gráfico.
Q5: Concepto | R5: 2027 | S5: 2028 | T5: 2029 | U5: 2030
B6: Salario bruto mensual y mes de incorporación | Q6: Sueldos brutos | R6: =O46 | S6: =O61 | T6: =O76 | U6: =O91
B7: Rol | C7: Salario bruto | D7: Mes de alta | Q7: Cargas sociales | R7: =O47 | S7: =O62 | T7: =O77 | U7: =O92
B8: Responsable de Producto y Desarrollo (socio) | C8: 4200000 | D8: 1 | E8: Socio
B9: Responsable Comercial y de Cuentas (socio) | C9: 3600000 | D9: 1 | E9: Socio | Q9: Personas en la plantilla | R9: =O49 | S9: =O64 | T9: =O79 | U9: =O94
B10: Responsable de Soporte y Onboarding | C10: 2400000 | D10: 12 | E10: Empleado
B11: Colaborador de desarrollo | C11: 2900000 | D11: 20 | E11: Empleado
B12: Responsable de Marketing y Contenidos | C12: 1100000 | D12: 30 | E12: Empleado
B13: Segundo colaborador de soporte | C13: 1800000 | D13: 42 | E13: Empleado
B16: Retiro de los socios como % de su salario de mercado
C17: 2027 | D17: 2028 | E17: 2029 | F17: 2030
B18: % del salario de mercado que retira cada socio | C18: 0.15 | D18: 0.35 | E18: 0.6 | F18: 1 | H18: Decisión propia. El año 1 es un retiro de subsistencia y supone que los socios sostienen ese año con otro ingreso; la brecha contra el 100 % es su aporte al proyecto
B20: Cargas sociales sobre el salario bruto
B21: Jubilación (SIPA) | C21: 0.1017 | H21: Decreto 814/01, inciso b
B22: PAMI (Ley 19.032) | C22: 0.015 | H22: Decreto 814/01, inciso b
B23: Asignaciones familiares | C23: 0.0444 | H23: Decreto 814/01, inciso b
B24: Fondo Nacional de Empleo | C24: 0.0089 | H24: Decreto 814/01, inciso b
B25: Obra social | C25: 0.06 | H25: Ley 23.660: 6 % a cargo del empleador
B26: ART (Ley 24.557) | C26: 0.035 | H26: Alícuota de una aseguradora para actividad de servicios informáticos, sin siniestralidad previa. Es el concepto que faltaba: sin él las cargas quedaban en 23 %
B27: Seguro de vida obligatorio | C27: 0.003 | H27: Decreto 1567/74, suma fija llevada a porcentaje sobre la nómina del modelo
B28: Total de cargas | C28: =SUM(C21:C27) | H28: La Clase 3 ubica las contribuciones patronales entre el 25 % y el 30 % de la nómina. Con la ART y el seguro de vida el modelo cae dentro de ese rango
B30: Encuadre laboral
B31: Convenio colectivo aplicable | C31: Ninguno. El personal de desarrollo y soporte de software se contrata fuera de convenio, bajo el régimen general de la Ley de Contrato de Trabajo 20.744
B32: Por qué no aplica un CCT | C32: No existe convenio colectivo propio de la actividad del software en la Argentina. El CCT 130/75 (Empleados de Comercio) alcanzaría sólo a personal administrativo, que esta plantilla no tiene
B33: Qué implica para el modelo | C33: Los aumentos salariales no siguen una paritaria: son política propia, y por eso el supuesto de la hoja Hipótesis los fija sobre la inflación en lugar de tomarlos de un acuerdo
B34: Aguinaldo (SAC, Ley 23.041) | C34: Medio sueldo en junio y medio en diciembre. Está en el modelo: esos dos meses pagan 1,5 sueldos
B35: Vacaciones | C35: No se modelan como costo aparte: el sueldo se paga igual durante la licencia y la plantilla no se reemplaza
C37: 2027
C38: Ene | D38: Feb | E38: Mar | F38: Abr | G38: May | H38: Jun | I38: Jul | J38: Ago | K38: Sep | L38: Oct | M38: Nov | N38: Dic | O38: Total 2027
B39: Salarios brutos por rol
A40: SUELDOS | B40: Responsable de Producto y Desarrollo (socio) | C40: =IF(1<$D$8,0,$C$8*1*1*$C$18) | D40: =IF(2<$D$8,0,$C$8*1*1*$C$18) | E40: =IF(3<$D$8,0,$C$8*1*1*$C$18) | F40: =IF(4<$D$8,0,$C$8*1*1*$C$18) | G40: =IF(5<$D$8,0,$C$8*1*1*$C$18) | H40: =IF(6<$D$8,0,$C$8*1*1.5*$C$18) | I40: =IF(7<$D$8,0,$C$8*1*1*$C$18) | J40: =IF(8<$D$8,0,$C$8*1*1*$C$18) | K40: =IF(9<$D$8,0,$C$8*1*1*$C$18) | L40: =IF(10<$D$8,0,$C$8*1*1*$C$18) | M40: =IF(11<$D$8,0,$C$8*1*1*$C$18) | N40: =IF(12<$D$8,0,$C$8*1*1.5*$C$18) | O40: =SUM(C40:N40)
B41: Responsable Comercial y de Cuentas (socio) | C41: =IF(1<$D$9,0,$C$9*1*1*$C$18) | D41: =IF(2<$D$9,0,$C$9*1*1*$C$18) | E41: =IF(3<$D$9,0,$C$9*1*1*$C$18) | F41: =IF(4<$D$9,0,$C$9*1*1*$C$18) | G41: =IF(5<$D$9,0,$C$9*1*1*$C$18) | H41: =IF(6<$D$9,0,$C$9*1*1.5*$C$18) | I41: =IF(7<$D$9,0,$C$9*1*1*$C$18) | J41: =IF(8<$D$9,0,$C$9*1*1*$C$18) | K41: =IF(9<$D$9,0,$C$9*1*1*$C$18) | L41: =IF(10<$D$9,0,$C$9*1*1*$C$18) | M41: =IF(11<$D$9,0,$C$9*1*1*$C$18) | N41: =IF(12<$D$9,0,$C$9*1*1.5*$C$18) | O41: =SUM(C41:N41)
B42: Responsable de Soporte y Onboarding | C42: =IF(1<$D$10,0,$C$10*1*1) | D42: =IF(2<$D$10,0,$C$10*1*1) | E42: =IF(3<$D$10,0,$C$10*1*1) | F42: =IF(4<$D$10,0,$C$10*1*1) | G42: =IF(5<$D$10,0,$C$10*1*1) | H42: =IF(6<$D$10,0,$C$10*1*1.5) | I42: =IF(7<$D$10,0,$C$10*1*1) | J42: =IF(8<$D$10,0,$C$10*1*1) | K42: =IF(9<$D$10,0,$C$10*1*1) | L42: =IF(10<$D$10,0,$C$10*1*1) | M42: =IF(11<$D$10,0,$C$10*1*1) | N42: =IF(12<$D$10,0,$C$10*1*1.5) | O42: =SUM(C42:N42)
B43: Colaborador de desarrollo | C43: =IF(1<$D$11,0,$C$11*1*1) | D43: =IF(2<$D$11,0,$C$11*1*1) | E43: =IF(3<$D$11,0,$C$11*1*1) | F43: =IF(4<$D$11,0,$C$11*1*1) | G43: =IF(5<$D$11,0,$C$11*1*1) | H43: =IF(6<$D$11,0,$C$11*1*1.5) | I43: =IF(7<$D$11,0,$C$11*1*1) | J43: =IF(8<$D$11,0,$C$11*1*1) | K43: =IF(9<$D$11,0,$C$11*1*1) | L43: =IF(10<$D$11,0,$C$11*1*1) | M43: =IF(11<$D$11,0,$C$11*1*1) | N43: =IF(12<$D$11,0,$C$11*1*1.5) | O43: =SUM(C43:N43)
B44: Responsable de Marketing y Contenidos | C44: =IF(1<$D$12,0,$C$12*1*1) | D44: =IF(2<$D$12,0,$C$12*1*1) | E44: =IF(3<$D$12,0,$C$12*1*1) | F44: =IF(4<$D$12,0,$C$12*1*1) | G44: =IF(5<$D$12,0,$C$12*1*1) | H44: =IF(6<$D$12,0,$C$12*1*1.5) | I44: =IF(7<$D$12,0,$C$12*1*1) | J44: =IF(8<$D$12,0,$C$12*1*1) | K44: =IF(9<$D$12,0,$C$12*1*1) | L44: =IF(10<$D$12,0,$C$12*1*1) | M44: =IF(11<$D$12,0,$C$12*1*1) | N44: =IF(12<$D$12,0,$C$12*1*1.5) | O44: =SUM(C44:N44)
B45: Segundo colaborador de soporte | C45: =IF(1<$D$13,0,$C$13*1*1) | D45: =IF(2<$D$13,0,$C$13*1*1) | E45: =IF(3<$D$13,0,$C$13*1*1) | F45: =IF(4<$D$13,0,$C$13*1*1) | G45: =IF(5<$D$13,0,$C$13*1*1) | H45: =IF(6<$D$13,0,$C$13*1*1.5) | I45: =IF(7<$D$13,0,$C$13*1*1) | J45: =IF(8<$D$13,0,$C$13*1*1) | K45: =IF(9<$D$13,0,$C$13*1*1) | L45: =IF(10<$D$13,0,$C$13*1*1) | M45: =IF(11<$D$13,0,$C$13*1*1) | N45: =IF(12<$D$13,0,$C$13*1*1.5) | O45: =SUM(C45:N45)
B46: Total de salarios brutos | C46: =SUM(C40:C45) | D46: =SUM(D40:D45) | E46: =SUM(E40:E45) | F46: =SUM(F40:F45) | G46: =SUM(G40:G45) | H46: =SUM(H40:H45) | I46: =SUM(I40:I45) | J46: =SUM(J40:J45) | ... N46: =SUM(N40:N45) | O46: =SUM(C46:N46)
B47: Cargas sociales | C47: =C46*$C$28 | D47: =D46*$C$28 | E47: =E46*$C$28 | F47: =F46*$C$28 | G47: =G46*$C$28 | H47: =H46*$C$28 | I47: =I46*$C$28 | J47: =J46*$C$28 | ... N47: =N46*$C$28 | O47: =SUM(C47:N47)
A48: TOTAL | B48: Costo total de RRHH | C48: =C46+C47 | D48: =D46+D47 | E48: =E46+E47 | F48: =F46+F47 | G48: =G46+G47 | H48: =H46+H47 | I48: =I46+I47 | J48: =J46+J47 | ... N48: =N46+N47 | O48: =SUM(C48:N48)
B49: Personas en la plantilla | C49: =COUNTIF(C40:C45,">0") | D49: =COUNTIF(D40:D45,">0") | E49: =COUNTIF(E40:E45,">0") | F49: =COUNTIF(F40:F45,">0") | G49: =COUNTIF(G40:G45,">0") | H49: =COUNTIF(H40:H45,">0") | I49: =COUNTIF(I40:I45,">0") | J49: =COUNTIF(J40:J45,">0") | ... N49: =COUNTIF(N40:N45,">0") | O49: =N49
C52: 2028
C53: Ene | D53: Feb | E53: Mar | F53: Abr | G53: May | H53: Jun | I53: Jul | J53: Ago | K53: Sep | L53: Oct | M53: Nov | N53: Dic | O53: Total 2028
B54: Salarios brutos por rol
A55: SUELDOS | B55: Responsable de Producto y Desarrollo (socio) | C55: =IF(13<$D$8,0,$C$8*(1+Hipótesis!$D$14)*1*$D$18) | D55: =IF(14<$D$8,0,$C$8*(1+Hipótesis!$D$14)*1*$D$18) | E55: =IF(15<$D$8,0,$C$8*(1+Hipótesis!$D$14)*1*$D$18) | F55: =IF(16<$D$8,0,$C$8*(1+Hipótesis!$D$14)*1*$D$18) | G55: =IF(17<$D$8,0,$C$8*(1+Hipótesis!$D$14)*1*$D$18) | H55: =IF(18<$D$8,0,$C$8*(1+Hipótesis!$D$14)*1.5*$D$18) | I55: =IF(19<$D$8,0,$C$8*(1+Hipótesis!$D$14)*1*$D$18) | J55: =IF(20<$D$8,0,$C$8*(1+Hipótesis!$D$14)*1*$D$18) | K55: =IF(21<$D$8,0,$C$8*(1+Hipótesis!$D$14)*1*$D$18) | L55: =IF(22<$D$8,0,$C$8*(1+Hipótesis!$D$14)*1*$D$18) | M55: =IF(23<$D$8,0,$C$8*(1+Hipótesis!$D$14)*1*$D$18) | N55: =IF(24<$D$8,0,$C$8*(1+Hipótesis!$D$14)*1.5*$D$18) | O55: =SUM(C55:N55)
B56: Responsable Comercial y de Cuentas (socio) | C56: =IF(13<$D$9,0,$C$9*(1+Hipótesis!$D$14)*1*$D$18) | D56: =IF(14<$D$9,0,$C$9*(1+Hipótesis!$D$14)*1*$D$18) | E56: =IF(15<$D$9,0,$C$9*(1+Hipótesis!$D$14)*1*$D$18) | F56: =IF(16<$D$9,0,$C$9*(1+Hipótesis!$D$14)*1*$D$18) | G56: =IF(17<$D$9,0,$C$9*(1+Hipótesis!$D$14)*1*$D$18) | H56: =IF(18<$D$9,0,$C$9*(1+Hipótesis!$D$14)*1.5*$D$18) | I56: =IF(19<$D$9,0,$C$9*(1+Hipótesis!$D$14)*1*$D$18) | J56: =IF(20<$D$9,0,$C$9*(1+Hipótesis!$D$14)*1*$D$18) | K56: =IF(21<$D$9,0,$C$9*(1+Hipótesis!$D$14)*1*$D$18) | L56: =IF(22<$D$9,0,$C$9*(1+Hipótesis!$D$14)*1*$D$18) | M56: =IF(23<$D$9,0,$C$9*(1+Hipótesis!$D$14)*1*$D$18) | N56: =IF(24<$D$9,0,$C$9*(1+Hipótesis!$D$14)*1.5*$D$18) | O56: =SUM(C56:N56)
B57: Responsable de Soporte y Onboarding | C57: =IF(13<$D$10,0,$C$10*(1+Hipótesis!$D$14)*1) | D57: =IF(14<$D$10,0,$C$10*(1+Hipótesis!$D$14)*1) | E57: =IF(15<$D$10,0,$C$10*(1+Hipótesis!$D$14)*1) | F57: =IF(16<$D$10,0,$C$10*(1+Hipótesis!$D$14)*1) | G57: =IF(17<$D$10,0,$C$10*(1+Hipótesis!$D$14)*1) | H57: =IF(18<$D$10,0,$C$10*(1+Hipótesis!$D$14)*1.5) | I57: =IF(19<$D$10,0,$C$10*(1+Hipótesis!$D$14)*1) | J57: =IF(20<$D$10,0,$C$10*(1+Hipótesis!$D$14)*1) | K57: =IF(21<$D$10,0,$C$10*(1+Hipótesis!$D$14)*1) | L57: =IF(22<$D$10,0,$C$10*(1+Hipótesis!$D$14)*1) | M57: =IF(23<$D$10,0,$C$10*(1+Hipótesis!$D$14)*1) | N57: =IF(24<$D$10,0,$C$10*(1+Hipótesis!$D$14)*1.5) | O57: =SUM(C57:N57)
B58: Colaborador de desarrollo | C58: =IF(13<$D$11,0,$C$11*(1+Hipótesis!$D$14)*1) | D58: =IF(14<$D$11,0,$C$11*(1+Hipótesis!$D$14)*1) | E58: =IF(15<$D$11,0,$C$11*(1+Hipótesis!$D$14)*1) | F58: =IF(16<$D$11,0,$C$11*(1+Hipótesis!$D$14)*1) | G58: =IF(17<$D$11,0,$C$11*(1+Hipótesis!$D$14)*1) | H58: =IF(18<$D$11,0,$C$11*(1+Hipótesis!$D$14)*1.5) | I58: =IF(19<$D$11,0,$C$11*(1+Hipótesis!$D$14)*1) | J58: =IF(20<$D$11,0,$C$11*(1+Hipótesis!$D$14)*1) | K58: =IF(21<$D$11,0,$C$11*(1+Hipótesis!$D$14)*1) | L58: =IF(22<$D$11,0,$C$11*(1+Hipótesis!$D$14)*1) | M58: =IF(23<$D$11,0,$C$11*(1+Hipótesis!$D$14)*1) | N58: =IF(24<$D$11,0,$C$11*(1+Hipótesis!$D$14)*1.5) | O58: =SUM(C58:N58)
B59: Responsable de Marketing y Contenidos | C59: =IF(13<$D$12,0,$C$12*(1+Hipótesis!$D$14)*1) | D59: =IF(14<$D$12,0,$C$12*(1+Hipótesis!$D$14)*1) | E59: =IF(15<$D$12,0,$C$12*(1+Hipótesis!$D$14)*1) | F59: =IF(16<$D$12,0,$C$12*(1+Hipótesis!$D$14)*1) | G59: =IF(17<$D$12,0,$C$12*(1+Hipótesis!$D$14)*1) | H59: =IF(18<$D$12,0,$C$12*(1+Hipótesis!$D$14)*1.5) | I59: =IF(19<$D$12,0,$C$12*(1+Hipótesis!$D$14)*1) | J59: =IF(20<$D$12,0,$C$12*(1+Hipótesis!$D$14)*1) | K59: =IF(21<$D$12,0,$C$12*(1+Hipótesis!$D$14)*1) | L59: =IF(22<$D$12,0,$C$12*(1+Hipótesis!$D$14)*1) | M59: =IF(23<$D$12,0,$C$12*(1+Hipótesis!$D$14)*1) | N59: =IF(24<$D$12,0,$C$12*(1+Hipótesis!$D$14)*1.5) | O59: =SUM(C59:N59)
B60: Segundo colaborador de soporte | C60: =IF(13<$D$13,0,$C$13*(1+Hipótesis!$D$14)*1) | D60: =IF(14<$D$13,0,$C$13*(1+Hipótesis!$D$14)*1) | E60: =IF(15<$D$13,0,$C$13*(1+Hipótesis!$D$14)*1) | F60: =IF(16<$D$13,0,$C$13*(1+Hipótesis!$D$14)*1) | G60: =IF(17<$D$13,0,$C$13*(1+Hipótesis!$D$14)*1) | H60: =IF(18<$D$13,0,$C$13*(1+Hipótesis!$D$14)*1.5) | I60: =IF(19<$D$13,0,$C$13*(1+Hipótesis!$D$14)*1) | J60: =IF(20<$D$13,0,$C$13*(1+Hipótesis!$D$14)*1) | K60: =IF(21<$D$13,0,$C$13*(1+Hipótesis!$D$14)*1) | L60: =IF(22<$D$13,0,$C$13*(1+Hipótesis!$D$14)*1) | M60: =IF(23<$D$13,0,$C$13*(1+Hipótesis!$D$14)*1) | N60: =IF(24<$D$13,0,$C$13*(1+Hipótesis!$D$14)*1.5) | O60: =SUM(C60:N60)
B61: Total de salarios brutos | C61: =SUM(C55:C60) | D61: =SUM(D55:D60) | E61: =SUM(E55:E60) | F61: =SUM(F55:F60) | G61: =SUM(G55:G60) | H61: =SUM(H55:H60) | I61: =SUM(I55:I60) | J61: =SUM(J55:J60) | ... N61: =SUM(N55:N60) | O61: =SUM(C61:N61)
B62: Cargas sociales | C62: =C61*$C$28 | D62: =D61*$C$28 | E62: =E61*$C$28 | F62: =F61*$C$28 | G62: =G61*$C$28 | H62: =H61*$C$28 | I62: =I61*$C$28 | J62: =J61*$C$28 | ... N62: =N61*$C$28 | O62: =SUM(C62:N62)
A63: TOTAL | B63: Costo total de RRHH | C63: =C61+C62 | D63: =D61+D62 | E63: =E61+E62 | F63: =F61+F62 | G63: =G61+G62 | H63: =H61+H62 | I63: =I61+I62 | J63: =J61+J62 | ... N63: =N61+N62 | O63: =SUM(C63:N63)
B64: Personas en la plantilla | C64: =COUNTIF(C55:C60,">0") | D64: =COUNTIF(D55:D60,">0") | E64: =COUNTIF(E55:E60,">0") | F64: =COUNTIF(F55:F60,">0") | G64: =COUNTIF(G55:G60,">0") | H64: =COUNTIF(H55:H60,">0") | I64: =COUNTIF(I55:I60,">0") | J64: =COUNTIF(J55:J60,">0") | ... N64: =COUNTIF(N55:N60,">0") | O64: =N64
C67: 2029
C68: Ene | D68: Feb | E68: Mar | F68: Abr | G68: May | H68: Jun | I68: Jul | J68: Ago | K68: Sep | L68: Oct | M68: Nov | N68: Dic | O68: Total 2029
B69: Salarios brutos por rol
A70: SUELDOS | B70: Responsable de Producto y Desarrollo (socio) | C70: =IF(25<$D$8,0,$C$8*(1+Hipótesis!$D$14)*(1+Hipótesis!$E$14)*1*$E$18) | D70: =IF(26<$D$8,0,$C$8*(1+Hipótesis!$D$14)*(1+Hipótesis!$E$14)*1*$E$18) | E70: =IF(27<$D$8,0,$C$8*(1+Hipótesis!$D$14)*(1+Hipótesis!$E$14)*1*$E$18) | F70: =IF(28<$D$8,0,$C$8*(1+Hipótesis!$D$14)*(1+Hipótesis!$E$14)*1*$E$18) | G70: =IF(29<$D$8,0,$C$8*(1+Hipótesis!$D$14)*(1+Hipótesis!$E$14)*1*$E$18) | H70: =IF(30<$D$8,0,$C$8*(1+Hipótesis!$D$14)*(1+Hipótesis!$E$14)*1.5*$E$18) | I70: =IF(31<$D$8,0,$C$8*(1+Hipótesis!$D$14)*(1+Hipótesis!$E$14)*1*$E$18) | J70: =IF(32<$D$8,0,$C$8*(1+Hipótesis!$D$14)*(1+Hipótesis!$E$14)*1*$E$18) | K70: =IF(33<$D$8,0,$C$8*(1+Hipótesis!$D$14)*(1+Hipótesis!$E$14)*1*$E$18) | L70: =IF(34<$D$8,0,$C$8*(1+Hipótesis!$D$14)*(1+Hipótesis!$E$14)*1*$E$18) | M70: =IF(35<$D$8,0,$C$8*(1+Hipótesis!$D$14)*(1+Hipótesis!$E$14)*1*$E$18) | N70: =IF(36<$D$8,0,$C$8*(1+Hipótesis!$D$14)*(1+Hipótesis!$E$14)*1.5*$E$18) | O70: =SUM(C70:N70)
B71: Responsable Comercial y de Cuentas (socio) | C71: =IF(25<$D$9,0,$C$9*(1+Hipótesis!$D$14)*(1+Hipótesis!$E$14)*1*$E$18) | D71: =IF(26<$D$9,0,$C$9*(1+Hipótesis!$D$14)*(1+Hipótesis!$E$14)*1*$E$18) | E71: =IF(27<$D$9,0,$C$9*(1+Hipótesis!$D$14)*(1+Hipótesis!$E$14)*1*$E$18) | F71: =IF(28<$D$9,0,$C$9*(1+Hipótesis!$D$14)*(1+Hipótesis!$E$14)*1*$E$18) | G71: =IF(29<$D$9,0,$C$9*(1+Hipótesis!$D$14)*(1+Hipótesis!$E$14)*1*$E$18) | H71: =IF(30<$D$9,0,$C$9*(1+Hipótesis!$D$14)*(1+Hipótesis!$E$14)*1.5*$E$18) | I71: =IF(31<$D$9,0,$C$9*(1+Hipótesis!$D$14)*(1+Hipótesis!$E$14)*1*$E$18) | J71: =IF(32<$D$9,0,$C$9*(1+Hipótesis!$D$14)*(1+Hipótesis!$E$14)*1*$E$18) | K71: =IF(33<$D$9,0,$C$9*(1+Hipótesis!$D$14)*(1+Hipótesis!$E$14)*1*$E$18) | L71: =IF(34<$D$9,0,$C$9*(1+Hipótesis!$D$14)*(1+Hipótesis!$E$14)*1*$E$18) | M71: =IF(35<$D$9,0,$C$9*(1+Hipótesis!$D$14)*(1+Hipótesis!$E$14)*1*$E$18) | N71: =IF(36<$D$9,0,$C$9*(1+Hipótesis!$D$14)*(1+Hipótesis!$E$14)*1.5*$E$18) | O71: =SUM(C71:N71)
B72: Responsable de Soporte y Onboarding | C72: =IF(25<$D$10,0,$C$10*(1+Hipótesis!$D$14)*(1+Hipótesis!$E$14)*1) | D72: =IF(26<$D$10,0,$C$10*(1+Hipótesis!$D$14)*(1+Hipótesis!$E$14)*1) | E72: =IF(27<$D$10,0,$C$10*(1+Hipótesis!$D$14)*(1+Hipótesis!$E$14)*1) | F72: =IF(28<$D$10,0,$C$10*(1+Hipótesis!$D$14)*(1+Hipótesis!$E$14)*1) | G72: =IF(29<$D$10,0,$C$10*(1+Hipótesis!$D$14)*(1+Hipótesis!$E$14)*1) | H72: =IF(30<$D$10,0,$C$10*(1+Hipótesis!$D$14)*(1+Hipótesis!$E$14)*1.5) | I72: =IF(31<$D$10,0,$C$10*(1+Hipótesis!$D$14)*(1+Hipótesis!$E$14)*1) | J72: =IF(32<$D$10,0,$C$10*(1+Hipótesis!$D$14)*(1+Hipótesis!$E$14)*1) | K72: =IF(33<$D$10,0,$C$10*(1+Hipótesis!$D$14)*(1+Hipótesis!$E$14)*1) | L72: =IF(34<$D$10,0,$C$10*(1+Hipótesis!$D$14)*(1+Hipótesis!$E$14)*1) | M72: =IF(35<$D$10,0,$C$10*(1+Hipótesis!$D$14)*(1+Hipótesis!$E$14)*1) | N72: =IF(36<$D$10,0,$C$10*(1+Hipótesis!$D$14)*(1+Hipótesis!$E$14)*1.5) | O72: =SUM(C72:N72)
B73: Colaborador de desarrollo | C73: =IF(25<$D$11,0,$C$11*(1+Hipótesis!$D$14)*(1+Hipótesis!$E$14)*1) | D73: =IF(26<$D$11,0,$C$11*(1+Hipótesis!$D$14)*(1+Hipótesis!$E$14)*1) | E73: =IF(27<$D$11,0,$C$11*(1+Hipótesis!$D$14)*(1+Hipótesis!$E$14)*1) | F73: =IF(28<$D$11,0,$C$11*(1+Hipótesis!$D$14)*(1+Hipótesis!$E$14)*1) | G73: =IF(29<$D$11,0,$C$11*(1+Hipótesis!$D$14)*(1+Hipótesis!$E$14)*1) | H73: =IF(30<$D$11,0,$C$11*(1+Hipótesis!$D$14)*(1+Hipótesis!$E$14)*1.5) | I73: =IF(31<$D$11,0,$C$11*(1+Hipótesis!$D$14)*(1+Hipótesis!$E$14)*1) | J73: =IF(32<$D$11,0,$C$11*(1+Hipótesis!$D$14)*(1+Hipótesis!$E$14)*1) | K73: =IF(33<$D$11,0,$C$11*(1+Hipótesis!$D$14)*(1+Hipótesis!$E$14)*1) | L73: =IF(34<$D$11,0,$C$11*(1+Hipótesis!$D$14)*(1+Hipótesis!$E$14)*1) | M73: =IF(35<$D$11,0,$C$11*(1+Hipótesis!$D$14)*(1+Hipótesis!$E$14)*1) | N73: =IF(36<$D$11,0,$C$11*(1+Hipótesis!$D$14)*(1+Hipótesis!$E$14)*1.5) | O73: =SUM(C73:N73)
B74: Responsable de Marketing y Contenidos | C74: =IF(25<$D$12,0,$C$12*(1+Hipótesis!$D$14)*(1+Hipótesis!$E$14)*1) | D74: =IF(26<$D$12,0,$C$12*(1+Hipótesis!$D$14)*(1+Hipótesis!$E$14)*1) | E74: =IF(27<$D$12,0,$C$12*(1+Hipótesis!$D$14)*(1+Hipótesis!$E$14)*1) | F74: =IF(28<$D$12,0,$C$12*(1+Hipótesis!$D$14)*(1+Hipótesis!$E$14)*1) | G74: =IF(29<$D$12,0,$C$12*(1+Hipótesis!$D$14)*(1+Hipótesis!$E$14)*1) | H74: =IF(30<$D$12,0,$C$12*(1+Hipótesis!$D$14)*(1+Hipótesis!$E$14)*1.5) | I74: =IF(31<$D$12,0,$C$12*(1+Hipótesis!$D$14)*(1+Hipótesis!$E$14)*1) | J74: =IF(32<$D$12,0,$C$12*(1+Hipótesis!$D$14)*(1+Hipótesis!$E$14)*1) | K74: =IF(33<$D$12,0,$C$12*(1+Hipótesis!$D$14)*(1+Hipótesis!$E$14)*1) | L74: =IF(34<$D$12,0,$C$12*(1+Hipótesis!$D$14)*(1+Hipótesis!$E$14)*1) | M74: =IF(35<$D$12,0,$C$12*(1+Hipótesis!$D$14)*(1+Hipótesis!$E$14)*1) | N74: =IF(36<$D$12,0,$C$12*(1+Hipótesis!$D$14)*(1+Hipótesis!$E$14)*1.5) | O74: =SUM(C74:N74)
B75: Segundo colaborador de soporte | C75: =IF(25<$D$13,0,$C$13*(1+Hipótesis!$D$14)*(1+Hipótesis!$E$14)*1) | D75: =IF(26<$D$13,0,$C$13*(1+Hipótesis!$D$14)*(1+Hipótesis!$E$14)*1) | E75: =IF(27<$D$13,0,$C$13*(1+Hipótesis!$D$14)*(1+Hipótesis!$E$14)*1) | F75: =IF(28<$D$13,0,$C$13*(1+Hipótesis!$D$14)*(1+Hipótesis!$E$14)*1) | G75: =IF(29<$D$13,0,$C$13*(1+Hipótesis!$D$14)*(1+Hipótesis!$E$14)*1) | H75: =IF(30<$D$13,0,$C$13*(1+Hipótesis!$D$14)*(1+Hipótesis!$E$14)*1.5) | I75: =IF(31<$D$13,0,$C$13*(1+Hipótesis!$D$14)*(1+Hipótesis!$E$14)*1) | J75: =IF(32<$D$13,0,$C$13*(1+Hipótesis!$D$14)*(1+Hipótesis!$E$14)*1) | K75: =IF(33<$D$13,0,$C$13*(1+Hipótesis!$D$14)*(1+Hipótesis!$E$14)*1) | L75: =IF(34<$D$13,0,$C$13*(1+Hipótesis!$D$14)*(1+Hipótesis!$E$14)*1) | M75: =IF(35<$D$13,0,$C$13*(1+Hipótesis!$D$14)*(1+Hipótesis!$E$14)*1) | N75: =IF(36<$D$13,0,$C$13*(1+Hipótesis!$D$14)*(1+Hipótesis!$E$14)*1.5) | O75: =SUM(C75:N75)
B76: Total de salarios brutos | C76: =SUM(C70:C75) | D76: =SUM(D70:D75) | E76: =SUM(E70:E75) | F76: =SUM(F70:F75) | G76: =SUM(G70:G75) | H76: =SUM(H70:H75) | I76: =SUM(I70:I75) | J76: =SUM(J70:J75) | ... N76: =SUM(N70:N75) | O76: =SUM(C76:N76)
B77: Cargas sociales | C77: =C76*$C$28 | D77: =D76*$C$28 | E77: =E76*$C$28 | F77: =F76*$C$28 | G77: =G76*$C$28 | H77: =H76*$C$28 | I77: =I76*$C$28 | J77: =J76*$C$28 | ... N77: =N76*$C$28 | O77: =SUM(C77:N77)
A78: TOTAL | B78: Costo total de RRHH | C78: =C76+C77 | D78: =D76+D77 | E78: =E76+E77 | F78: =F76+F77 | G78: =G76+G77 | H78: =H76+H77 | I78: =I76+I77 | J78: =J76+J77 | ... N78: =N76+N77 | O78: =SUM(C78:N78)
B79: Personas en la plantilla | C79: =COUNTIF(C70:C75,">0") | D79: =COUNTIF(D70:D75,">0") | E79: =COUNTIF(E70:E75,">0") | F79: =COUNTIF(F70:F75,">0") | G79: =COUNTIF(G70:G75,">0") | H79: =COUNTIF(H70:H75,">0") | I79: =COUNTIF(I70:I75,">0") | J79: =COUNTIF(J70:J75,">0") | ... N79: =COUNTIF(N70:N75,">0") | O79: =N79
C82: 2030
C83: Ene | D83: Feb | E83: Mar | F83: Abr | G83: May | H83: Jun | I83: Jul | J83: Ago | K83: Sep | L83: Oct | M83: Nov | N83: Dic | O83: Total 2030
B84: Salarios brutos por rol
A85: SUELDOS | B85: Responsable de Producto y Desarrollo (socio) | C85: =IF(37<$D$8,0,$C$8*(1+Hipótesis!$D$14)*(1+Hipótesis!$E$14)*(1+Hipótesis!$F$14)*1*$F$18) | D85: =IF(38<$D$8,0,$C$8*(1+Hipótesis!$D$14)*(1+Hipótesis!$E$14)*(1+Hipótesis!$F$14)*1*$F$18) | E85: =IF(39<$D$8,0,$C$8*(1+Hipótesis!$D$14)*(1+Hipótesis!$E$14)*(1+Hipótesis!$F$14)*1*$F$18) | F85: =IF(40<$D$8,0,$C$8*(1+Hipótesis!$D$14)*(1+Hipótesis!$E$14)*(1+Hipótesis!$F$14)*1*$F$18) | G85: =IF(41<$D$8,0,$C$8*(1+Hipótesis!$D$14)*(1+Hipótesis!$E$14)*(1+Hipótesis!$F$14)*1*$F$18) | H85: =IF(42<$D$8,0,$C$8*(1+Hipótesis!$D$14)*(1+Hipótesis!$E$14)*(1+Hipótesis!$F$14)*1.5*$F$18) | I85: =IF(43<$D$8,0,$C$8*(1+Hipótesis!$D$14)*(1+Hipótesis!$E$14)*(1+Hipótesis!$F$14)*1*$F$18) | J85: =IF(44<$D$8,0,$C$8*(1+Hipótesis!$D$14)*(1+Hipótesis!$E$14)*(1+Hipótesis!$F$14)*1*$F$18) | K85: =IF(45<$D$8,0,$C$8*(1+Hipótesis!$D$14)*(1+Hipótesis!$E$14)*(1+Hipótesis!$F$14)*1*$F$18) | L85: =IF(46<$D$8,0,$C$8*(1+Hipótesis!$D$14)*(1+Hipótesis!$E$14)*(1+Hipótesis!$F$14)*1*$F$18) | M85: =IF(47<$D$8,0,$C$8*(1+Hipótesis!$D$14)*(1+Hipótesis!$E$14)*(1+Hipótesis!$F$14)*1*$F$18) | N85: =IF(48<$D$8,0,$C$8*(1+Hipótesis!$D$14)*(1+Hipótesis!$E$14)*(1+Hipótesis!$F$14)*1.5*$F$18) | O85: =SUM(C85:N85)
B86: Responsable Comercial y de Cuentas (socio) | C86: =IF(37<$D$9,0,$C$9*(1+Hipótesis!$D$14)*(1+Hipótesis!$E$14)*(1+Hipótesis!$F$14)*1*$F$18) | D86: =IF(38<$D$9,0,$C$9*(1+Hipótesis!$D$14)*(1+Hipótesis!$E$14)*(1+Hipótesis!$F$14)*1*$F$18) | E86: =IF(39<$D$9,0,$C$9*(1+Hipótesis!$D$14)*(1+Hipótesis!$E$14)*(1+Hipótesis!$F$14)*1*$F$18) | F86: =IF(40<$D$9,0,$C$9*(1+Hipótesis!$D$14)*(1+Hipótesis!$E$14)*(1+Hipótesis!$F$14)*1*$F$18) | G86: =IF(41<$D$9,0,$C$9*(1+Hipótesis!$D$14)*(1+Hipótesis!$E$14)*(1+Hipótesis!$F$14)*1*$F$18) | H86: =IF(42<$D$9,0,$C$9*(1+Hipótesis!$D$14)*(1+Hipótesis!$E$14)*(1+Hipótesis!$F$14)*1.5*$F$18) | I86: =IF(43<$D$9,0,$C$9*(1+Hipótesis!$D$14)*(1+Hipótesis!$E$14)*(1+Hipótesis!$F$14)*1*$F$18) | J86: =IF(44<$D$9,0,$C$9*(1+Hipótesis!$D$14)*(1+Hipótesis!$E$14)*(1+Hipótesis!$F$14)*1*$F$18) | K86: =IF(45<$D$9,0,$C$9*(1+Hipótesis!$D$14)*(1+Hipótesis!$E$14)*(1+Hipótesis!$F$14)*1*$F$18) | L86: =IF(46<$D$9,0,$C$9*(1+Hipótesis!$D$14)*(1+Hipótesis!$E$14)*(1+Hipótesis!$F$14)*1*$F$18) | M86: =IF(47<$D$9,0,$C$9*(1+Hipótesis!$D$14)*(1+Hipótesis!$E$14)*(1+Hipótesis!$F$14)*1*$F$18) | N86: =IF(48<$D$9,0,$C$9*(1+Hipótesis!$D$14)*(1+Hipótesis!$E$14)*(1+Hipótesis!$F$14)*1.5*$F$18) | O86: =SUM(C86:N86)
B87: Responsable de Soporte y Onboarding | C87: =IF(37<$D$10,0,$C$10*(1+Hipótesis!$D$14)*(1+Hipótesis!$E$14)*(1+Hipótesis!$F$14)*1) | D87: =IF(38<$D$10,0,$C$10*(1+Hipótesis!$D$14)*(1+Hipótesis!$E$14)*(1+Hipótesis!$F$14)*1) | E87: =IF(39<$D$10,0,$C$10*(1+Hipótesis!$D$14)*(1+Hipótesis!$E$14)*(1+Hipótesis!$F$14)*1) | F87: =IF(40<$D$10,0,$C$10*(1+Hipótesis!$D$14)*(1+Hipótesis!$E$14)*(1+Hipótesis!$F$14)*1) | G87: =IF(41<$D$10,0,$C$10*(1+Hipótesis!$D$14)*(1+Hipótesis!$E$14)*(1+Hipótesis!$F$14)*1) | H87: =IF(42<$D$10,0,$C$10*(1+Hipótesis!$D$14)*(1+Hipótesis!$E$14)*(1+Hipótesis!$F$14)*1.5) | I87: =IF(43<$D$10,0,$C$10*(1+Hipótesis!$D$14)*(1+Hipótesis!$E$14)*(1+Hipótesis!$F$14)*1) | J87: =IF(44<$D$10,0,$C$10*(1+Hipótesis!$D$14)*(1+Hipótesis!$E$14)*(1+Hipótesis!$F$14)*1) | K87: =IF(45<$D$10,0,$C$10*(1+Hipótesis!$D$14)*(1+Hipótesis!$E$14)*(1+Hipótesis!$F$14)*1) | L87: =IF(46<$D$10,0,$C$10*(1+Hipótesis!$D$14)*(1+Hipótesis!$E$14)*(1+Hipótesis!$F$14)*1) | M87: =IF(47<$D$10,0,$C$10*(1+Hipótesis!$D$14)*(1+Hipótesis!$E$14)*(1+Hipótesis!$F$14)*1) | N87: =IF(48<$D$10,0,$C$10*(1+Hipótesis!$D$14)*(1+Hipótesis!$E$14)*(1+Hipótesis!$F$14)*1.5) | O87: =SUM(C87:N87)
B88: Colaborador de desarrollo | C88: =IF(37<$D$11,0,$C$11*(1+Hipótesis!$D$14)*(1+Hipótesis!$E$14)*(1+Hipótesis!$F$14)*1) | D88: =IF(38<$D$11,0,$C$11*(1+Hipótesis!$D$14)*(1+Hipótesis!$E$14)*(1+Hipótesis!$F$14)*1) | E88: =IF(39<$D$11,0,$C$11*(1+Hipótesis!$D$14)*(1+Hipótesis!$E$14)*(1+Hipótesis!$F$14)*1) | F88: =IF(40<$D$11,0,$C$11*(1+Hipótesis!$D$14)*(1+Hipótesis!$E$14)*(1+Hipótesis!$F$14)*1) | G88: =IF(41<$D$11,0,$C$11*(1+Hipótesis!$D$14)*(1+Hipótesis!$E$14)*(1+Hipótesis!$F$14)*1) | H88: =IF(42<$D$11,0,$C$11*(1+Hipótesis!$D$14)*(1+Hipótesis!$E$14)*(1+Hipótesis!$F$14)*1.5) | I88: =IF(43<$D$11,0,$C$11*(1+Hipótesis!$D$14)*(1+Hipótesis!$E$14)*(1+Hipótesis!$F$14)*1) | J88: =IF(44<$D$11,0,$C$11*(1+Hipótesis!$D$14)*(1+Hipótesis!$E$14)*(1+Hipótesis!$F$14)*1) | K88: =IF(45<$D$11,0,$C$11*(1+Hipótesis!$D$14)*(1+Hipótesis!$E$14)*(1+Hipótesis!$F$14)*1) | L88: =IF(46<$D$11,0,$C$11*(1+Hipótesis!$D$14)*(1+Hipótesis!$E$14)*(1+Hipótesis!$F$14)*1) | M88: =IF(47<$D$11,0,$C$11*(1+Hipótesis!$D$14)*(1+Hipótesis!$E$14)*(1+Hipótesis!$F$14)*1) | N88: =IF(48<$D$11,0,$C$11*(1+Hipótesis!$D$14)*(1+Hipótesis!$E$14)*(1+Hipótesis!$F$14)*1.5) | O88: =SUM(C88:N88)
B89: Responsable de Marketing y Contenidos | C89: =IF(37<$D$12,0,$C$12*(1+Hipótesis!$D$14)*(1+Hipótesis!$E$14)*(1+Hipótesis!$F$14)*1) | D89: =IF(38<$D$12,0,$C$12*(1+Hipótesis!$D$14)*(1+Hipótesis!$E$14)*(1+Hipótesis!$F$14)*1) | E89: =IF(39<$D$12,0,$C$12*(1+Hipótesis!$D$14)*(1+Hipótesis!$E$14)*(1+Hipótesis!$F$14)*1) | F89: =IF(40<$D$12,0,$C$12*(1+Hipótesis!$D$14)*(1+Hipótesis!$E$14)*(1+Hipótesis!$F$14)*1) | G89: =IF(41<$D$12,0,$C$12*(1+Hipótesis!$D$14)*(1+Hipótesis!$E$14)*(1+Hipótesis!$F$14)*1) | H89: =IF(42<$D$12,0,$C$12*(1+Hipótesis!$D$14)*(1+Hipótesis!$E$14)*(1+Hipótesis!$F$14)*1.5) | I89: =IF(43<$D$12,0,$C$12*(1+Hipótesis!$D$14)*(1+Hipótesis!$E$14)*(1+Hipótesis!$F$14)*1) | J89: =IF(44<$D$12,0,$C$12*(1+Hipótesis!$D$14)*(1+Hipótesis!$E$14)*(1+Hipótesis!$F$14)*1) | K89: =IF(45<$D$12,0,$C$12*(1+Hipótesis!$D$14)*(1+Hipótesis!$E$14)*(1+Hipótesis!$F$14)*1) | L89: =IF(46<$D$12,0,$C$12*(1+Hipótesis!$D$14)*(1+Hipótesis!$E$14)*(1+Hipótesis!$F$14)*1) | M89: =IF(47<$D$12,0,$C$12*(1+Hipótesis!$D$14)*(1+Hipótesis!$E$14)*(1+Hipótesis!$F$14)*1) | N89: =IF(48<$D$12,0,$C$12*(1+Hipótesis!$D$14)*(1+Hipótesis!$E$14)*(1+Hipótesis!$F$14)*1.5) | O89: =SUM(C89:N89)
B90: Segundo colaborador de soporte | C90: =IF(37<$D$13,0,$C$13*(1+Hipótesis!$D$14)*(1+Hipótesis!$E$14)*(1+Hipótesis!$F$14)*1) | D90: =IF(38<$D$13,0,$C$13*(1+Hipótesis!$D$14)*(1+Hipótesis!$E$14)*(1+Hipótesis!$F$14)*1) | E90: =IF(39<$D$13,0,$C$13*(1+Hipótesis!$D$14)*(1+Hipótesis!$E$14)*(1+Hipótesis!$F$14)*1) | F90: =IF(40<$D$13,0,$C$13*(1+Hipótesis!$D$14)*(1+Hipótesis!$E$14)*(1+Hipótesis!$F$14)*1) | G90: =IF(41<$D$13,0,$C$13*(1+Hipótesis!$D$14)*(1+Hipótesis!$E$14)*(1+Hipótesis!$F$14)*1) | H90: =IF(42<$D$13,0,$C$13*(1+Hipótesis!$D$14)*(1+Hipótesis!$E$14)*(1+Hipótesis!$F$14)*1.5) | I90: =IF(43<$D$13,0,$C$13*(1+Hipótesis!$D$14)*(1+Hipótesis!$E$14)*(1+Hipótesis!$F$14)*1) | J90: =IF(44<$D$13,0,$C$13*(1+Hipótesis!$D$14)*(1+Hipótesis!$E$14)*(1+Hipótesis!$F$14)*1) | K90: =IF(45<$D$13,0,$C$13*(1+Hipótesis!$D$14)*(1+Hipótesis!$E$14)*(1+Hipótesis!$F$14)*1) | L90: =IF(46<$D$13,0,$C$13*(1+Hipótesis!$D$14)*(1+Hipótesis!$E$14)*(1+Hipótesis!$F$14)*1) | M90: =IF(47<$D$13,0,$C$13*(1+Hipótesis!$D$14)*(1+Hipótesis!$E$14)*(1+Hipótesis!$F$14)*1) | N90: =IF(48<$D$13,0,$C$13*(1+Hipótesis!$D$14)*(1+Hipótesis!$E$14)*(1+Hipótesis!$F$14)*1.5) | O90: =SUM(C90:N90)
B91: Total de salarios brutos | C91: =SUM(C85:C90) | D91: =SUM(D85:D90) | E91: =SUM(E85:E90) | F91: =SUM(F85:F90) | G91: =SUM(G85:G90) | H91: =SUM(H85:H90) | I91: =SUM(I85:I90) | J91: =SUM(J85:J90) | ... N91: =SUM(N85:N90) | O91: =SUM(C91:N91)
B92: Cargas sociales | C92: =C91*$C$28 | D92: =D91*$C$28 | E92: =E91*$C$28 | F92: =F91*$C$28 | G92: =G91*$C$28 | H92: =H91*$C$28 | I92: =I91*$C$28 | J92: =J91*$C$28 | ... N92: =N91*$C$28 | O92: =SUM(C92:N92)
A93: TOTAL | B93: Costo total de RRHH | C93: =C91+C92 | D93: =D91+D92 | E93: =E91+E92 | F93: =F91+F92 | G93: =G91+G92 | H93: =H91+H92 | I93: =I91+I92 | J93: =J91+J92 | ... N93: =N91+N92 | O93: =SUM(C93:N93)
B94: Personas en la plantilla | C94: =COUNTIF(C85:C90,">0") | D94: =COUNTIF(D85:D90,">0") | E94: =COUNTIF(E85:E90,">0") | F94: =COUNTIF(F85:F90,">0") | G94: =COUNTIF(G85:G90,">0") | H94: =COUNTIF(H85:H90,">0") | I94: =COUNTIF(I85:I90,">0") | J94: =COUNTIF(J85:J90,">0") | ... N94: =COUNTIF(N85:N90,">0") | O94: =N94

Sheet Gráficos
A1: « Inicio
B2: GRÁFICOS
B3: La operación en cuatro imágenes. Los datos de abajo no están tipeados: son fórmulas que apuntan a las hojas de origen, así que los gráficos siguen al modelo cuando cambia un supuesto. Sólo usan hojas de esta entrega, para que viajen con ella.
B5: Datos de los gráficos
B6: Concepto | C6: 2027 | D6: 2028 | E6: 2029 | F6: 2030
B7: Ingresos | C7: ='Modelo de ingresos'!O26 | D7: ='Modelo de ingresos'!O49 | E7: ='Modelo de ingresos'!O72 | F7: ='Modelo de ingresos'!O95
B8: Egresos | C8: ='Modelo de Egresos'!O13 | D8: ='Modelo de Egresos'!O26 | E8: ='Modelo de Egresos'!O39 | F8: ='Modelo de Egresos'!O52
B9: Resultado operativo | C9: ='Modelo de Egresos'!O16 | D9: ='Modelo de Egresos'!O29 | E9: ='Modelo de Egresos'!O42 | F9: ='Modelo de Egresos'!O55
B10: Costos fijos | C10: ='Modelo de Egresos'!O10 | D10: ='Modelo de Egresos'!O23 | E10: ='Modelo de Egresos'!O36 | F10: ='Modelo de Egresos'!O49
B11: Costos variables | C11: ='Modelo de Egresos'!O11 | D11: ='Modelo de Egresos'!O24 | E11: ='Modelo de Egresos'!O37 | F11: ='Modelo de Egresos'!O50
B12: Costos de RRHH | C12: ='Modelo de Egresos'!O12 | D12: ='Modelo de Egresos'!O25 | E12: ='Modelo de Egresos'!O38 | F12: ='Modelo de Egresos'!O51
B13: Clientes al cierre | C13: ='Proyección de ventas'!N33 | D13: ='Proyección de ventas'!N63 | E13: ='Proyección de ventas'!N93 | F13: ='Proyección de ventas'!N123
B14: Equipos administrados | C14: ='Proyección de ventas'!N34 | D14: ='Proyección de ventas'!N64 | E14: ='Proyección de ventas'!N94 | F14: ='Proyección de ventas'!N124
B15: Personas en la plantilla | C15: ='RRHH'!N49 | D15: ='RRHH'!N64 | E15: ='RRHH'!N79 | F15: ='RRHH'!N94
