Workbook

Sheet Inicio
B2: PRESUPUESTO FINANCIERO — PredictIT · Entrega 1
B4: Sistema de mantenimiento predictivo de equipos informáticos
B5: Trabajo Final de Ingeniería · UAI · Pettini, Patricio Ezequiel — Legajo B00072710-T1
B6: Horizonte: 2027 a 2030, mensual · Generado el 07/09/2026
B8: Las celdas amarillas son supuestos que se pueden cambiar. Todo lo demás se calcula.
B10: Contenido
B11: Hipótesis | C11: Supuestos macro, mercado meta, embudo comercial y retención
B12: Planes | C12: Líneas de servicio: precio, equipos incluidos y costo variable unitario
B13: Proyección de ventas | C13: Altas, bajas y base activa de clientes por línea, mes a mes
B14: Modelo de ingresos | C14: Facturación por línea de servicio
B15: Modelo de Egresos | C15: Consolidado de las tres estructuras de costo
B16: Costos Fijos | C16: Costos que no dependen del volumen
B17: Costos Variables | C17: Costos que se mueven con cada cliente
B18: RRHH | C18: Sueldos, cargas sociales y evolución de la plantilla
B20: Primera entrega de negocio: llega hasta los costos de recursos humanos.

Sheet Hipótesis
A1: « Inicio
B2: HIPÓTESIS
B3: Cada variable necesita valor, fuente y justificación. Las celdas amarillas son las que se cargan a mano.
B6: Supuestos macroeconómicos
C7: 2027 | D7: 2028 | E7: 2029 | F7: 2030 | H7: Fuente y justificación
B8: Inflación anual proyectada | C8: 0.35 | D8: 0.25 | E8: 0.18 | F8: 0.15 | H8: PROVISORIO — reemplazar por el REM del BCRA citando la fecha del informe
B9: Tipo de cambio promedio (ARS/USD) | C9: 1900 | D9: 2350 | E9: 2750 | F9: 3150 | H9: PROVISORIO — reemplazar por el REM del BCRA. Afecta la infraestructura en la nube y el servicio de IA
B10: Tasa de interés de referencia | C10: 0.3 | D10: 0.22 | E10: 0.17 | F10: 0.14 | H10: PROVISORIO — tasa de política monetaria del BCRA
B11: Aumento anual de precios de lista | C11: 0.38 | D11: 0.27 | E11: 0.2 | F11: 0.16 | H11: Política propia: revisión trimestral (documento, 5.3.6). Va apenas arriba de la inflación
B12: Aumento anual de salarios | C12: 0.4 | D12: 0.3 | E12: 0.22 | F12: 0.18 | H12: Paritarias del sector. Es el costo que más pesa a partir de la Etapa E3
B14: Tasa de corte para el VAN | C14: 0.6 | H14: PROVISORIO — costo de oportunidad del capital propio, nominal en pesos. Debe superar a la tasa libre de riesgo más la prima por riesgo del proyecto
B15: Múltiplo de ingresos anuales para el valor terminal | C15: 1.5 | H15: Cuántas veces los ingresos del último año vale la cartera al cierre del horizonte. Rango de mercado para un MSP chico: 1x a 3x
B17: Mercado meta
B18: PyMEs de 5 a 50 empleados en AMBA | C18: 72000 | H18: PROVISORIO — reemplazar por Fundación Observatorio PyME / censo. Es el universo del Segmento A
B19: % con dependencia operativa alta de sus equipos | C19: 0.32 | H19: Servicios profesionales, salud, educación privada y comercio digitalizado (documento, 4.2)
B20: Mercado meta alcanzable | C20: =C18*C19 | H20: Calculado
B21: Participación objetivo al año 4 | C21: 0.011 | H21: Objetivo propio. Contrastar contra los 220 clientes del punto de equilibrio (documento, 7.7)
B23: Embudo comercial | H23: Tasas de la sección 5.3.5 del documento, tomando el punto medio de cada rango
B24: Visitas web mensuales al inicio | C24: 300 | H24: Supuesto propio de arranque
B25: Crecimiento mensual de visitas | C25: 0.12 | D25: 0.08 | E25: 0.05 | F25: 0.03 | H25: Por año. Se desacelera: sostener 12 % mensual durante cuatro años multiplicaría las visitas por 200, que no es defendible
B26: Visitas → leads | C26: 0.04 | H26: Documento 5.3.5: rango 3 % a 5 %
B27: Leads → demos calificadas | C27: 0.4 | H27: Documento 5.3.5: rango 35 % a 45 %
B28: Demos → pruebas gratuitas | C28: 0.6 | H28: Documento 5.3.5: rango 55 % a 65 %
B29: Pruebas → cliente pago | C29: 0.275 | H29: Documento 5.3.5: rango 25 % a 30 % para el Segmento A
B30: Conversión total visita → cliente | C30: =C26*C27*C28*C29 | H30: Calculado. Con 1.000 visitas mensuales da del orden de 2 a 3 clientes nuevos por mes, que es lo que proyecta el documento para la Etapa E3
B32: Pilotos y canal de partners
B33: Pilotos gratuitos en la Etapa E1 | C33: 5 | H33: Documento 5.3.4
B34: % de pilotos que convierten a plan pago | C34: 0.6 | H34: Documento 5.3.4: al menos 3 de 5
B35: Mes en que convierten los pilotos | C35: 6 | H35: Cierre de los 90 días de piloto
B36: Partners activos al cierre de cada año | C36: 3 | D36: 8 | E36: 15 | F36: 25 | H36: Documento 5.3.1: 3 partners operativos al mes 12
B37: Clientes gestionados por cada partner | C37: 3 | D37: 4 | E37: 5 | F37: 5 | H37: Documento 5.3.6: mínimo de 3 clientes gestionados para acceder al descuento. Es un stock, no un flujo: un partner tiene una cartera finita
B39: Retención y parque administrado
B40: Baja mensual de clientes | C40: 0.07 | D40: 0.05 | E40: 0.04 | F40: 0.04 | H40: Documento 5.3.3: menor o igual a 7 % en E2 y a 5 % en E3
B41: Equipos promedio por cliente — Plan Inicial | C41: 18 | D41: 20 | E41: 22 | F41: 24 | H41: Segmento A: de 10 a 80 equipos (documento, 4.2). Por encima de los 15 que incluye el plan, así que genera facturación por equipo adicional
B42: Equipos promedio por cliente — Plan Estándar | C42: 90 | D42: 100 | E42: 110 | F42: 120 | H42: Segmento B: de 80 a 250 equipos
B43: Equipos promedio por cliente — Plan Partner | C43: 15 | D43: 16 | E43: 17 | F43: 18 | H43: Clientes chicos gestionados por el canal
B45: Las filas marcadas PENDIENTE no tienen valor cargado a propósito: son las que exigen fuente citada y no se completan a ojo.

Sheet Planes
A1: « Inicio
B2: LÍNEAS DE SERVICIO
B3: Precios de la sección 5.3.6 del documento. Costos variables unitarios de la sección 6.5.3.
B6: Plan | C6: Segmento | D6: Abono mensual | E6: Equipos incluidos | F6: Equipo adicional | G6: CV infraestructura | H6: CV soporte | I6: CV servicio de IA | J6: CV total | K6: Margen de contribución
B7: Plan Inicial | C7: A | D7: 89000 | E7: 15 | F7: 4200 | G7: 3000 | H7: 4000 | I7: 1500 | J7: =SUM(G7:I7) | K7: =(D7-J7)/D7 | L7: Precio revisado (D-14). USD 46,8 por 15 equipos: USD 3,1 por equipo
B8: Plan Estándar | C8: B | D8: 239000 | E8: 50 | F8: 3500 | G8: 9000 | H8: 12000 | I8: 4000 | J8: =SUM(G8:I8) | K8: =(D8-J8)/D8 | L8: Precio revisado (D-14). USD 125,8 por 50 equipos: USD 2,5 por equipo
B9: Plan Partner | C9: C | D9: 69000 | E9: 30 | F9: 2800 | G9: 2500 | H9: 2500 | I9: 2000 | J9: =SUM(G9:I9) | K9: =(D9-J9)/D9 | L9: Precio revisado (D-14). Mas bajo por equipo: el partner aporta el canal y la primera linea de soporte
B11: El margen de contribución de las tres líneas queda entre el 74 % y el 76 %, que es lo que sostiene la sección 6.5.3. Si al cambiar un supuesto alguno se aparta de ese rango, hay que corregir el documento o el supuesto: no pueden decir cosas distintas.

Sheet Proyección de ventas
A1: « Inicio
B2: PROYECCIÓN DE VENTAS
B3: Clientes por línea de servicio, mes a mes. Las altas salen del embudo comercial, de la conversión de pilotos y del canal de partners; las tres fuentes se modelan por separado.
C7: 2027 | P7: 2028 | AC7: 2029 | AP7: 2030
C8: Ene | D8: Feb | E8: Mar | F8: Abr | G8: May | H8: Jun | I8: Jul | J8: Ago | K8: Sep | L8: Oct | M8: Nov | N8: Dic | O8: Total 2027 | P8: Ene | Q8: Feb | R8: Mar | S8: Abr | T8: May | U8: Jun | V8: Jul | W8: Ago | X8: Sep | Y8: Oct | Z8: Nov | AA8: Dic | AB8: Total 2028 | AC8: Ene | AD8: Feb | AE8: Mar | AF8: Abr | AG8: May | AH8: Jun | AI8: Jul | AJ8: Ago | AK8: Sep | AL8: Oct | AM8: Nov | AN8: Dic | AO8: Total 2029 | AP8: Ene | AQ8: Feb | AR8: Mar | AS8: Abr | AT8: May | AU8: Jun | AV8: Jul | AW8: Ago | AX8: Sep | AY8: Oct | AZ8: Nov | BA8: Dic | BB8: Total 2030
B10: Embudo comercial
A11: EMBUDO | B11: Visitas web | C11: =Hipótesis!$C$24 | D11: =C11*(1+Hipótesis!$C$25) | E11: =D11*(1+Hipótesis!$C$25) | F11: =E11*(1+Hipótesis!$C$25) | G11: =F11*(1+Hipótesis!$C$25) | H11: =G11*(1+Hipótesis!$C$25) | I11: =H11*(1+Hipótesis!$C$25) | J11: =I11*(1+Hipótesis!$C$25) | K11: =J11*(1+Hipótesis!$C$25) | ... N11: =M11*(1+Hipótesis!$C$25) | O11: =SUM(C11:N11) | P11: =N11*(1+Hipótesis!$D$25) | Q11: =P11*(1+Hipótesis!$D$25) | R11: =Q11*(1+Hipótesis!$D$25) | S11: =R11*(1+Hipótesis!$D$25) | T11: =S11*(1+Hipótesis!$D$25) | U11: =T11*(1+Hipótesis!$D$25) | V11: =U11*(1+Hipótesis!$D$25) | W11: =V11*(1+Hipótesis!$D$25) | X11: =W11*(1+Hipótesis!$D$25) | ... AA11: =Z11*(1+Hipótesis!$D$25) | AB11: =SUM(P11:AA11) | AC11: =AA11*(1+Hipótesis!$E$25) | AD11: =AC11*(1+Hipótesis!$E$25) | AE11: =AD11*(1+Hipótesis!$E$25) | AF11: =AE11*(1+Hipótesis!$E$25) | AG11: =AF11*(1+Hipótesis!$E$25) | AH11: =AG11*(1+Hipótesis!$E$25) | AI11: =AH11*(1+Hipótesis!$E$25) | AJ11: =AI11*(1+Hipótesis!$E$25) | AK11: =AJ11*(1+Hipótesis!$E$25) | ... AN11: =AM11*(1+Hipótesis!$E$25) | AO11: =SUM(AC11:AN11) | AP11: =AN11*(1+Hipótesis!$F$25) | AQ11: =AP11*(1+Hipótesis!$F$25) | AR11: =AQ11*(1+Hipótesis!$F$25) | AS11: =AR11*(1+Hipótesis!$F$25) | AT11: =AS11*(1+Hipótesis!$F$25) | AU11: =AT11*(1+Hipótesis!$F$25) | AV11: =AU11*(1+Hipótesis!$F$25) | AW11: =AV11*(1+Hipótesis!$F$25) | AX11: =AW11*(1+Hipótesis!$F$25) | ... BA11: =AZ11*(1+Hipótesis!$F$25) | BB11: =SUM(AP11:BA11)
B12: Leads | C12: =C11*Hipótesis!$C$26 | D12: =D11*Hipótesis!$C$26 | E12: =E11*Hipótesis!$C$26 | F12: =F11*Hipótesis!$C$26 | G12: =G11*Hipótesis!$C$26 | H12: =H11*Hipótesis!$C$26 | I12: =I11*Hipótesis!$C$26 | J12: =J11*Hipótesis!$C$26 | ... N12: =N11*Hipótesis!$C$26 | O12: =SUM(C12:N12) | P12: =P11*Hipótesis!$C$26 | Q12: =Q11*Hipótesis!$C$26 | R12: =R11*Hipótesis!$C$26 | S12: =S11*Hipótesis!$C$26 | T12: =T11*Hipótesis!$C$26 | U12: =U11*Hipótesis!$C$26 | V12: =V11*Hipótesis!$C$26 | W12: =W11*Hipótesis!$C$26 | ... AA12: =AA11*Hipótesis!$C$26 | AB12: =SUM(P12:AA12) | AC12: =AC11*Hipótesis!$C$26 | AD12: =AD11*Hipótesis!$C$26 | AE12: =AE11*Hipótesis!$C$26 | AF12: =AF11*Hipótesis!$C$26 | AG12: =AG11*Hipótesis!$C$26 | AH12: =AH11*Hipótesis!$C$26 | AI12: =AI11*Hipótesis!$C$26 | AJ12: =AJ11*Hipótesis!$C$26 | ... AN12: =AN11*Hipótesis!$C$26 | AO12: =SUM(AC12:AN12) | AP12: =AP11*Hipótesis!$C$26 | AQ12: =AQ11*Hipótesis!$C$26 | AR12: =AR11*Hipótesis!$C$26 | AS12: =AS11*Hipótesis!$C$26 | AT12: =AT11*Hipótesis!$C$26 | AU12: =AU11*Hipótesis!$C$26 | AV12: =AV11*Hipótesis!$C$26 | AW12: =AW11*Hipótesis!$C$26 | ... BA12: =BA11*Hipótesis!$C$26 | BB12: =SUM(AP12:BA12)
B13: Demos calificadas | C13: =C12*Hipótesis!$C$27 | D13: =D12*Hipótesis!$C$27 | E13: =E12*Hipótesis!$C$27 | F13: =F12*Hipótesis!$C$27 | G13: =G12*Hipótesis!$C$27 | H13: =H12*Hipótesis!$C$27 | I13: =I12*Hipótesis!$C$27 | J13: =J12*Hipótesis!$C$27 | ... N13: =N12*Hipótesis!$C$27 | O13: =SUM(C13:N13) | P13: =P12*Hipótesis!$C$27 | Q13: =Q12*Hipótesis!$C$27 | R13: =R12*Hipótesis!$C$27 | S13: =S12*Hipótesis!$C$27 | T13: =T12*Hipótesis!$C$27 | U13: =U12*Hipótesis!$C$27 | V13: =V12*Hipótesis!$C$27 | W13: =W12*Hipótesis!$C$27 | ... AA13: =AA12*Hipótesis!$C$27 | AB13: =SUM(P13:AA13) | AC13: =AC12*Hipótesis!$C$27 | AD13: =AD12*Hipótesis!$C$27 | AE13: =AE12*Hipótesis!$C$27 | AF13: =AF12*Hipótesis!$C$27 | AG13: =AG12*Hipótesis!$C$27 | AH13: =AH12*Hipótesis!$C$27 | AI13: =AI12*Hipótesis!$C$27 | AJ13: =AJ12*Hipótesis!$C$27 | ... AN13: =AN12*Hipótesis!$C$27 | AO13: =SUM(AC13:AN13) | AP13: =AP12*Hipótesis!$C$27 | AQ13: =AQ12*Hipótesis!$C$27 | AR13: =AR12*Hipótesis!$C$27 | AS13: =AS12*Hipótesis!$C$27 | AT13: =AT12*Hipótesis!$C$27 | AU13: =AU12*Hipótesis!$C$27 | AV13: =AV12*Hipótesis!$C$27 | AW13: =AW12*Hipótesis!$C$27 | ... BA13: =BA12*Hipótesis!$C$27 | BB13: =SUM(AP13:BA13)
B14: Pruebas gratuitas iniciadas | C14: =C13*Hipótesis!$C$28 | D14: =D13*Hipótesis!$C$28 | E14: =E13*Hipótesis!$C$28 | F14: =F13*Hipótesis!$C$28 | G14: =G13*Hipótesis!$C$28 | H14: =H13*Hipótesis!$C$28 | I14: =I13*Hipótesis!$C$28 | J14: =J13*Hipótesis!$C$28 | ... N14: =N13*Hipótesis!$C$28 | O14: =SUM(C14:N14) | P14: =P13*Hipótesis!$C$28 | Q14: =Q13*Hipótesis!$C$28 | R14: =R13*Hipótesis!$C$28 | S14: =S13*Hipótesis!$C$28 | T14: =T13*Hipótesis!$C$28 | U14: =U13*Hipótesis!$C$28 | V14: =V13*Hipótesis!$C$28 | W14: =W13*Hipótesis!$C$28 | ... AA14: =AA13*Hipótesis!$C$28 | AB14: =SUM(P14:AA14) | AC14: =AC13*Hipótesis!$C$28 | AD14: =AD13*Hipótesis!$C$28 | AE14: =AE13*Hipótesis!$C$28 | AF14: =AF13*Hipótesis!$C$28 | AG14: =AG13*Hipótesis!$C$28 | AH14: =AH13*Hipótesis!$C$28 | AI14: =AI13*Hipótesis!$C$28 | AJ14: =AJ13*Hipótesis!$C$28 | ... AN14: =AN13*Hipótesis!$C$28 | AO14: =SUM(AC14:AN14) | AP14: =AP13*Hipótesis!$C$28 | AQ14: =AQ13*Hipótesis!$C$28 | AR14: =AR13*Hipótesis!$C$28 | AS14: =AS13*Hipótesis!$C$28 | AT14: =AT13*Hipótesis!$C$28 | AU14: =AU13*Hipótesis!$C$28 | AV14: =AV13*Hipótesis!$C$28 | AW14: =AW13*Hipótesis!$C$28 | ... BA14: =BA13*Hipótesis!$C$28 | BB14: =SUM(AP14:BA14)
B15: Clientes nuevos por embudo directo | C15: =IF(1<Hipótesis!$C$35,0,C14*Hipótesis!$C$29) | D15: =IF(2<Hipótesis!$C$35,0,D14*Hipótesis!$C$29) | E15: =IF(3<Hipótesis!$C$35,0,E14*Hipótesis!$C$29) | F15: =IF(4<Hipótesis!$C$35,0,F14*Hipótesis!$C$29) | G15: =IF(5<Hipótesis!$C$35,0,G14*Hipótesis!$C$29) | H15: =IF(6<Hipótesis!$C$35,0,H14*Hipótesis!$C$29) | I15: =IF(7<Hipótesis!$C$35,0,I14*Hipótesis!$C$29) | J15: =IF(8<Hipótesis!$C$35,0,J14*Hipótesis!$C$29) | K15: =IF(9<Hipótesis!$C$35,0,K14*Hipótesis!$C$29) | L15: =IF(10<Hipótesis!$C$35,0,L14*Hipótesis!$C$29) | M15: =IF(11<Hipótesis!$C$35,0,M14*Hipótesis!$C$29) | N15: =IF(12<Hipótesis!$C$35,0,N14*Hipótesis!$C$29) | O15: =SUM(C15:N15) | P15: =IF(13<Hipótesis!$C$35,0,P14*Hipótesis!$C$29) | Q15: =IF(14<Hipótesis!$C$35,0,Q14*Hipótesis!$C$29) | R15: =IF(15<Hipótesis!$C$35,0,R14*Hipótesis!$C$29) | S15: =IF(16<Hipótesis!$C$35,0,S14*Hipótesis!$C$29) | T15: =IF(17<Hipótesis!$C$35,0,T14*Hipótesis!$C$29) | U15: =IF(18<Hipótesis!$C$35,0,U14*Hipótesis!$C$29) | V15: =IF(19<Hipótesis!$C$35,0,V14*Hipótesis!$C$29) | W15: =IF(20<Hipótesis!$C$35,0,W14*Hipótesis!$C$29) | X15: =IF(21<Hipótesis!$C$35,0,X14*Hipótesis!$C$29) | Y15: =IF(22<Hipótesis!$C$35,0,Y14*Hipótesis!$C$29) | Z15: =IF(23<Hipótesis!$C$35,0,Z14*Hipótesis!$C$29) | AA15: =IF(24<Hipótesis!$C$35,0,AA14*Hipótesis!$C$29) | AB15: =SUM(P15:AA15) | AC15: =IF(25<Hipótesis!$C$35,0,AC14*Hipótesis!$C$29) | AD15: =IF(26<Hipótesis!$C$35,0,AD14*Hipótesis!$C$29) | AE15: =IF(27<Hipótesis!$C$35,0,AE14*Hipótesis!$C$29) | AF15: =IF(28<Hipótesis!$C$35,0,AF14*Hipótesis!$C$29) | AG15: =IF(29<Hipótesis!$C$35,0,AG14*Hipótesis!$C$29) | AH15: =IF(30<Hipótesis!$C$35,0,AH14*Hipótesis!$C$29) | AI15: =IF(31<Hipótesis!$C$35,0,AI14*Hipótesis!$C$29) | AJ15: =IF(32<Hipótesis!$C$35,0,AJ14*Hipótesis!$C$29) | AK15: =IF(33<Hipótesis!$C$35,0,AK14*Hipótesis!$C$29) | AL15: =IF(34<Hipótesis!$C$35,0,AL14*Hipótesis!$C$29) | AM15: =IF(35<Hipótesis!$C$35,0,AM14*Hipótesis!$C$29) | AN15: =IF(36<Hipótesis!$C$35,0,AN14*Hipótesis!$C$29) | AO15: =SUM(AC15:AN15) | AP15: =IF(37<Hipótesis!$C$35,0,AP14*Hipótesis!$C$29) | AQ15: =IF(38<Hipótesis!$C$35,0,AQ14*Hipótesis!$C$29) | AR15: =IF(39<Hipótesis!$C$35,0,AR14*Hipótesis!$C$29) | AS15: =IF(40<Hipótesis!$C$35,0,AS14*Hipótesis!$C$29) | AT15: =IF(41<Hipótesis!$C$35,0,AT14*Hipótesis!$C$29) | AU15: =IF(42<Hipótesis!$C$35,0,AU14*Hipótesis!$C$29) | AV15: =IF(43<Hipótesis!$C$35,0,AV14*Hipótesis!$C$29) | AW15: =IF(44<Hipótesis!$C$35,0,AW14*Hipótesis!$C$29) | AX15: =IF(45<Hipótesis!$C$35,0,AX14*Hipótesis!$C$29) | AY15: =IF(46<Hipótesis!$C$35,0,AY14*Hipótesis!$C$29) | AZ15: =IF(47<Hipótesis!$C$35,0,AZ14*Hipótesis!$C$29) | BA15: =IF(48<Hipótesis!$C$35,0,BA14*Hipótesis!$C$29) | BB15: =SUM(AP15:BA15)
B17: Plan Inicial — Segmento A
A18: PLAN INICIAL | B18: Base al inicio del mes | C18: 0 | D18: =C22 | E18: =D22 | F18: =E22 | G18: =F22 | H18: =G22 | I18: =H22 | J18: =I22 | K18: =J22 | ... N18: =M22 | P18: =N22 | Q18: =P22 | R18: =Q22 | S18: =R22 | T18: =S22 | U18: =T22 | V18: =U22 | W18: =V22 | X18: =W22 | ... AA18: =Z22 | AC18: =AA22 | AD18: =AC22 | AE18: =AD22 | AF18: =AE22 | AG18: =AF22 | AH18: =AG22 | AI18: =AH22 | AJ18: =AI22 | AK18: =AJ22 | ... AN18: =AM22 | AP18: =AN22 | AQ18: =AP22 | AR18: =AQ22 | AS18: =AR22 | AT18: =AS22 | AU18: =AT22 | AV18: =AU22 | AW18: =AV22 | AX18: =AW22 | ... BA18: =AZ22
B19: Altas por embudo directo | C19: =C15 | D19: =D15 | E19: =E15 | F19: =F15 | G19: =G15 | H19: =H15 | I19: =I15 | J19: =J15 | ... N19: =N15 | O19: =SUM(C19:N19) | P19: =P15 | Q19: =Q15 | R19: =R15 | S19: =S15 | T19: =T15 | U19: =U15 | V19: =V15 | W19: =W15 | ... AA19: =AA15 | AB19: =SUM(P19:AA19) | AC19: =AC15 | AD19: =AD15 | AE19: =AE15 | AF19: =AF15 | AG19: =AG15 | AH19: =AH15 | AI19: =AI15 | AJ19: =AJ15 | ... AN19: =AN15 | AO19: =SUM(AC19:AN19) | AP19: =AP15 | AQ19: =AQ15 | AR19: =AR15 | AS19: =AS15 | AT19: =AT15 | AU19: =AU15 | AV19: =AV15 | AW19: =AW15 | ... BA19: =BA15 | BB19: =SUM(AP19:BA19)
B20: Altas por conversión de pilotos | C20: =IF(AND(1=Hipótesis!$C$35,1=1),Hipótesis!$C$33*Hipótesis!$C$34,0) | D20: =IF(AND(2=Hipótesis!$C$35,1=1),Hipótesis!$C$33*Hipótesis!$C$34,0) | E20: =IF(AND(3=Hipótesis!$C$35,1=1),Hipótesis!$C$33*Hipótesis!$C$34,0) | F20: =IF(AND(4=Hipótesis!$C$35,1=1),Hipótesis!$C$33*Hipótesis!$C$34,0) | G20: =IF(AND(5=Hipótesis!$C$35,1=1),Hipótesis!$C$33*Hipótesis!$C$34,0) | H20: =IF(AND(6=Hipótesis!$C$35,1=1),Hipótesis!$C$33*Hipótesis!$C$34,0) | I20: =IF(AND(7=Hipótesis!$C$35,1=1),Hipótesis!$C$33*Hipótesis!$C$34,0) | J20: =IF(AND(8=Hipótesis!$C$35,1=1),Hipótesis!$C$33*Hipótesis!$C$34,0) | K20: =IF(AND(9=Hipótesis!$C$35,1=1),Hipótesis!$C$33*Hipótesis!$C$34,0) | L20: =IF(AND(10=Hipótesis!$C$35,1=1),Hipótesis!$C$33*Hipótesis!$C$34,0) | M20: =IF(AND(11=Hipótesis!$C$35,1=1),Hipótesis!$C$33*Hipótesis!$C$34,0) | N20: =IF(AND(12=Hipótesis!$C$35,1=1),Hipótesis!$C$33*Hipótesis!$C$34,0) | O20: =SUM(C20:N20) | P20: =IF(AND(13=Hipótesis!$C$35,2=1),Hipótesis!$C$33*Hipótesis!$C$34,0) | Q20: =IF(AND(14=Hipótesis!$C$35,2=1),Hipótesis!$C$33*Hipótesis!$C$34,0) | R20: =IF(AND(15=Hipótesis!$C$35,2=1),Hipótesis!$C$33*Hipótesis!$C$34,0) | S20: =IF(AND(16=Hipótesis!$C$35,2=1),Hipótesis!$C$33*Hipótesis!$C$34,0) | T20: =IF(AND(17=Hipótesis!$C$35,2=1),Hipótesis!$C$33*Hipótesis!$C$34,0) | U20: =IF(AND(18=Hipótesis!$C$35,2=1),Hipótesis!$C$33*Hipótesis!$C$34,0) | V20: =IF(AND(19=Hipótesis!$C$35,2=1),Hipótesis!$C$33*Hipótesis!$C$34,0) | W20: =IF(AND(20=Hipótesis!$C$35,2=1),Hipótesis!$C$33*Hipótesis!$C$34,0) | X20: =IF(AND(21=Hipótesis!$C$35,2=1),Hipótesis!$C$33*Hipótesis!$C$34,0) | Y20: =IF(AND(22=Hipótesis!$C$35,2=1),Hipótesis!$C$33*Hipótesis!$C$34,0) | Z20: =IF(AND(23=Hipótesis!$C$35,2=1),Hipótesis!$C$33*Hipótesis!$C$34,0) | AA20: =IF(AND(24=Hipótesis!$C$35,2=1),Hipótesis!$C$33*Hipótesis!$C$34,0) | AB20: =SUM(P20:AA20) | AC20: =IF(AND(25=Hipótesis!$C$35,3=1),Hipótesis!$C$33*Hipótesis!$C$34,0) | AD20: =IF(AND(26=Hipótesis!$C$35,3=1),Hipótesis!$C$33*Hipótesis!$C$34,0) | AE20: =IF(AND(27=Hipótesis!$C$35,3=1),Hipótesis!$C$33*Hipótesis!$C$34,0) | AF20: =IF(AND(28=Hipótesis!$C$35,3=1),Hipótesis!$C$33*Hipótesis!$C$34,0) | AG20: =IF(AND(29=Hipótesis!$C$35,3=1),Hipótesis!$C$33*Hipótesis!$C$34,0) | AH20: =IF(AND(30=Hipótesis!$C$35,3=1),Hipótesis!$C$33*Hipótesis!$C$34,0) | AI20: =IF(AND(31=Hipótesis!$C$35,3=1),Hipótesis!$C$33*Hipótesis!$C$34,0) | AJ20: =IF(AND(32=Hipótesis!$C$35,3=1),Hipótesis!$C$33*Hipótesis!$C$34,0) | AK20: =IF(AND(33=Hipótesis!$C$35,3=1),Hipótesis!$C$33*Hipótesis!$C$34,0) | AL20: =IF(AND(34=Hipótesis!$C$35,3=1),Hipótesis!$C$33*Hipótesis!$C$34,0) | AM20: =IF(AND(35=Hipótesis!$C$35,3=1),Hipótesis!$C$33*Hipótesis!$C$34,0) | AN20: =IF(AND(36=Hipótesis!$C$35,3=1),Hipótesis!$C$33*Hipótesis!$C$34,0) | AO20: =SUM(AC20:AN20) | AP20: =IF(AND(37=Hipótesis!$C$35,4=1),Hipótesis!$C$33*Hipótesis!$C$34,0) | AQ20: =IF(AND(38=Hipótesis!$C$35,4=1),Hipótesis!$C$33*Hipótesis!$C$34,0) | AR20: =IF(AND(39=Hipótesis!$C$35,4=1),Hipótesis!$C$33*Hipótesis!$C$34,0) | AS20: =IF(AND(40=Hipótesis!$C$35,4=1),Hipótesis!$C$33*Hipótesis!$C$34,0) | AT20: =IF(AND(41=Hipótesis!$C$35,4=1),Hipótesis!$C$33*Hipótesis!$C$34,0) | AU20: =IF(AND(42=Hipótesis!$C$35,4=1),Hipótesis!$C$33*Hipótesis!$C$34,0) | AV20: =IF(AND(43=Hipótesis!$C$35,4=1),Hipótesis!$C$33*Hipótesis!$C$34,0) | AW20: =IF(AND(44=Hipótesis!$C$35,4=1),Hipótesis!$C$33*Hipótesis!$C$34,0) | AX20: =IF(AND(45=Hipótesis!$C$35,4=1),Hipótesis!$C$33*Hipótesis!$C$34,0) | AY20: =IF(AND(46=Hipótesis!$C$35,4=1),Hipótesis!$C$33*Hipótesis!$C$34,0) | AZ20: =IF(AND(47=Hipótesis!$C$35,4=1),Hipótesis!$C$33*Hipótesis!$C$34,0) | BA20: =IF(AND(48=Hipótesis!$C$35,4=1),Hipótesis!$C$33*Hipótesis!$C$34,0) | BB20: =SUM(AP20:BA20)
B21: Bajas | C21: =-C18*Hipótesis!$C$40 | D21: =-D18*Hipótesis!$C$40 | E21: =-E18*Hipótesis!$C$40 | F21: =-F18*Hipótesis!$C$40 | G21: =-G18*Hipótesis!$C$40 | H21: =-H18*Hipótesis!$C$40 | I21: =-I18*Hipótesis!$C$40 | J21: =-J18*Hipótesis!$C$40 | ... N21: =-N18*Hipótesis!$C$40 | O21: =SUM(C21:N21) | P21: =-P18*Hipótesis!$D$40 | Q21: =-Q18*Hipótesis!$D$40 | R21: =-R18*Hipótesis!$D$40 | S21: =-S18*Hipótesis!$D$40 | T21: =-T18*Hipótesis!$D$40 | U21: =-U18*Hipótesis!$D$40 | V21: =-V18*Hipótesis!$D$40 | W21: =-W18*Hipótesis!$D$40 | ... AA21: =-AA18*Hipótesis!$D$40 | AB21: =SUM(P21:AA21) | AC21: =-AC18*Hipótesis!$E$40 | AD21: =-AD18*Hipótesis!$E$40 | AE21: =-AE18*Hipótesis!$E$40 | AF21: =-AF18*Hipótesis!$E$40 | AG21: =-AG18*Hipótesis!$E$40 | AH21: =-AH18*Hipótesis!$E$40 | AI21: =-AI18*Hipótesis!$E$40 | AJ21: =-AJ18*Hipótesis!$E$40 | ... AN21: =-AN18*Hipótesis!$E$40 | AO21: =SUM(AC21:AN21) | AP21: =-AP18*Hipótesis!$F$40 | AQ21: =-AQ18*Hipótesis!$F$40 | AR21: =-AR18*Hipótesis!$F$40 | AS21: =-AS18*Hipótesis!$F$40 | AT21: =-AT18*Hipótesis!$F$40 | AU21: =-AU18*Hipótesis!$F$40 | AV21: =-AV18*Hipótesis!$F$40 | AW21: =-AW18*Hipótesis!$F$40 | ... BA21: =-BA18*Hipótesis!$F$40 | BB21: =SUM(AP21:BA21)
B22: Base activa al cierre | C22: =SUM(C18:C21) | D22: =SUM(D18:D21) | E22: =SUM(E18:E21) | F22: =SUM(F18:F21) | G22: =SUM(G18:G21) | H22: =SUM(H18:H21) | I22: =SUM(I18:I21) | J22: =SUM(J18:J21) | ... N22: =SUM(N18:N21) | O22: =N22 | P22: =SUM(P18:P21) | Q22: =SUM(Q18:Q21) | R22: =SUM(R18:R21) | S22: =SUM(S18:S21) | T22: =SUM(T18:T21) | U22: =SUM(U18:U21) | V22: =SUM(V18:V21) | W22: =SUM(W18:W21) | ... AA22: =SUM(AA18:AA21) | AB22: =AA22 | AC22: =SUM(AC18:AC21) | AD22: =SUM(AD18:AD21) | AE22: =SUM(AE18:AE21) | AF22: =SUM(AF18:AF21) | AG22: =SUM(AG18:AG21) | AH22: =SUM(AH18:AH21) | AI22: =SUM(AI18:AI21) | AJ22: =SUM(AJ18:AJ21) | ... AN22: =SUM(AN18:AN21) | AO22: =AN22 | AP22: =SUM(AP18:AP21) | AQ22: =SUM(AQ18:AQ21) | AR22: =SUM(AR18:AR21) | AS22: =SUM(AS18:AS21) | AT22: =SUM(AT18:AT21) | AU22: =SUM(AU18:AU21) | AV22: =SUM(AV18:AV21) | AW22: =SUM(AW18:AW21) | ... BA22: =SUM(BA18:BA21) | BB22: =BA22
B24: Plan Estándar — Segmento B | H24: Las altas del Segmento B son un supuesto directo: ciclo de venta de 60 a 90 días (5.3.5) y el primer cliente en la Etapa E3.
B25: Altas por año (supuesto) | C25: 1.2 | D25: 4.8 | E25: 9.6 | F25: 14.4 | H25: Total de clientes nuevos del Plan Estándar en cada año
A26: PLAN ESTÁNDAR | B26: Base al inicio del mes | C26: 0 | D26: =C29 | E26: =D29 | F26: =E29 | G26: =F29 | H26: =G29 | I26: =H29 | J26: =I29 | K26: =J29 | ... N26: =M29 | P26: =N29 | Q26: =P29 | R26: =Q29 | S26: =R29 | T26: =S29 | U26: =T29 | V26: =U29 | W26: =V29 | X26: =W29 | ... AA26: =Z29 | AC26: =AA29 | AD26: =AC29 | AE26: =AD29 | AF26: =AE29 | AG26: =AF29 | AH26: =AG29 | AI26: =AH29 | AJ26: =AI29 | AK26: =AJ29 | ... AN26: =AM29 | AP26: =AN29 | AQ26: =AP29 | AR26: =AQ29 | AS26: =AR29 | AT26: =AS29 | AU26: =AT29 | AV26: =AU29 | AW26: =AV29 | AX26: =AW29 | ... BA26: =AZ29
B27: Altas | C27: =IF(1<9,0,Hipótesis!$C$25/IF(1=1,4,12)) | D27: =IF(2<9,0,Hipótesis!$C$25/IF(1=1,4,12)) | E27: =IF(3<9,0,Hipótesis!$C$25/IF(1=1,4,12)) | F27: =IF(4<9,0,Hipótesis!$C$25/IF(1=1,4,12)) | G27: =IF(5<9,0,Hipótesis!$C$25/IF(1=1,4,12)) | H27: =IF(6<9,0,Hipótesis!$C$25/IF(1=1,4,12)) | I27: =IF(7<9,0,Hipótesis!$C$25/IF(1=1,4,12)) | J27: =IF(8<9,0,Hipótesis!$C$25/IF(1=1,4,12)) | K27: =IF(9<9,0,Hipótesis!$C$25/IF(1=1,4,12)) | L27: =IF(10<9,0,Hipótesis!$C$25/IF(1=1,4,12)) | M27: =IF(11<9,0,Hipótesis!$C$25/IF(1=1,4,12)) | N27: =IF(12<9,0,Hipótesis!$C$25/IF(1=1,4,12)) | O27: =SUM(C27:N27) | P27: =IF(13<9,0,Hipótesis!$D$25/IF(2=1,4,12)) | Q27: =IF(14<9,0,Hipótesis!$D$25/IF(2=1,4,12)) | R27: =IF(15<9,0,Hipótesis!$D$25/IF(2=1,4,12)) | S27: =IF(16<9,0,Hipótesis!$D$25/IF(2=1,4,12)) | T27: =IF(17<9,0,Hipótesis!$D$25/IF(2=1,4,12)) | U27: =IF(18<9,0,Hipótesis!$D$25/IF(2=1,4,12)) | V27: =IF(19<9,0,Hipótesis!$D$25/IF(2=1,4,12)) | W27: =IF(20<9,0,Hipótesis!$D$25/IF(2=1,4,12)) | X27: =IF(21<9,0,Hipótesis!$D$25/IF(2=1,4,12)) | Y27: =IF(22<9,0,Hipótesis!$D$25/IF(2=1,4,12)) | Z27: =IF(23<9,0,Hipótesis!$D$25/IF(2=1,4,12)) | AA27: =IF(24<9,0,Hipótesis!$D$25/IF(2=1,4,12)) | AB27: =SUM(P27:AA27) | AC27: =IF(25<9,0,Hipótesis!$E$25/IF(3=1,4,12)) | AD27: =IF(26<9,0,Hipótesis!$E$25/IF(3=1,4,12)) | AE27: =IF(27<9,0,Hipótesis!$E$25/IF(3=1,4,12)) | AF27: =IF(28<9,0,Hipótesis!$E$25/IF(3=1,4,12)) | AG27: =IF(29<9,0,Hipótesis!$E$25/IF(3=1,4,12)) | AH27: =IF(30<9,0,Hipótesis!$E$25/IF(3=1,4,12)) | AI27: =IF(31<9,0,Hipótesis!$E$25/IF(3=1,4,12)) | AJ27: =IF(32<9,0,Hipótesis!$E$25/IF(3=1,4,12)) | AK27: =IF(33<9,0,Hipótesis!$E$25/IF(3=1,4,12)) | AL27: =IF(34<9,0,Hipótesis!$E$25/IF(3=1,4,12)) | AM27: =IF(35<9,0,Hipótesis!$E$25/IF(3=1,4,12)) | AN27: =IF(36<9,0,Hipótesis!$E$25/IF(3=1,4,12)) | AO27: =SUM(AC27:AN27) | AP27: =IF(37<9,0,Hipótesis!$F$25/IF(4=1,4,12)) | AQ27: =IF(38<9,0,Hipótesis!$F$25/IF(4=1,4,12)) | AR27: =IF(39<9,0,Hipótesis!$F$25/IF(4=1,4,12)) | AS27: =IF(40<9,0,Hipótesis!$F$25/IF(4=1,4,12)) | AT27: =IF(41<9,0,Hipótesis!$F$25/IF(4=1,4,12)) | AU27: =IF(42<9,0,Hipótesis!$F$25/IF(4=1,4,12)) | AV27: =IF(43<9,0,Hipótesis!$F$25/IF(4=1,4,12)) | AW27: =IF(44<9,0,Hipótesis!$F$25/IF(4=1,4,12)) | AX27: =IF(45<9,0,Hipótesis!$F$25/IF(4=1,4,12)) | AY27: =IF(46<9,0,Hipótesis!$F$25/IF(4=1,4,12)) | AZ27: =IF(47<9,0,Hipótesis!$F$25/IF(4=1,4,12)) | BA27: =IF(48<9,0,Hipótesis!$F$25/IF(4=1,4,12)) | BB27: =SUM(AP27:BA27)
B28: Bajas | C28: =-C26*Hipótesis!$C$40 | D28: =-D26*Hipótesis!$C$40 | E28: =-E26*Hipótesis!$C$40 | F28: =-F26*Hipótesis!$C$40 | G28: =-G26*Hipótesis!$C$40 | H28: =-H26*Hipótesis!$C$40 | I28: =-I26*Hipótesis!$C$40 | J28: =-J26*Hipótesis!$C$40 | ... N28: =-N26*Hipótesis!$C$40 | O28: =SUM(C28:N28) | P28: =-P26*Hipótesis!$D$40 | Q28: =-Q26*Hipótesis!$D$40 | R28: =-R26*Hipótesis!$D$40 | S28: =-S26*Hipótesis!$D$40 | T28: =-T26*Hipótesis!$D$40 | U28: =-U26*Hipótesis!$D$40 | V28: =-V26*Hipótesis!$D$40 | W28: =-W26*Hipótesis!$D$40 | ... AA28: =-AA26*Hipótesis!$D$40 | AB28: =SUM(P28:AA28) | AC28: =-AC26*Hipótesis!$E$40 | AD28: =-AD26*Hipótesis!$E$40 | AE28: =-AE26*Hipótesis!$E$40 | AF28: =-AF26*Hipótesis!$E$40 | AG28: =-AG26*Hipótesis!$E$40 | AH28: =-AH26*Hipótesis!$E$40 | AI28: =-AI26*Hipótesis!$E$40 | AJ28: =-AJ26*Hipótesis!$E$40 | ... AN28: =-AN26*Hipótesis!$E$40 | AO28: =SUM(AC28:AN28) | AP28: =-AP26*Hipótesis!$F$40 | AQ28: =-AQ26*Hipótesis!$F$40 | AR28: =-AR26*Hipótesis!$F$40 | AS28: =-AS26*Hipótesis!$F$40 | AT28: =-AT26*Hipótesis!$F$40 | AU28: =-AU26*Hipótesis!$F$40 | AV28: =-AV26*Hipótesis!$F$40 | AW28: =-AW26*Hipótesis!$F$40 | ... BA28: =-BA26*Hipótesis!$F$40 | BB28: =SUM(AP28:BA28)
B29: Base activa al cierre | C29: =SUM(C26:C28) | D29: =SUM(D26:D28) | E29: =SUM(E26:E28) | F29: =SUM(F26:F28) | G29: =SUM(G26:G28) | H29: =SUM(H26:H28) | I29: =SUM(I26:I28) | J29: =SUM(J26:J28) | ... N29: =SUM(N26:N28) | O29: =N29 | P29: =SUM(P26:P28) | Q29: =SUM(Q26:Q28) | R29: =SUM(R26:R28) | S29: =SUM(S26:S28) | T29: =SUM(T26:T28) | U29: =SUM(U26:U28) | V29: =SUM(V26:V28) | W29: =SUM(W26:W28) | ... AA29: =SUM(AA26:AA28) | AB29: =AA29 | AC29: =SUM(AC26:AC28) | AD29: =SUM(AD26:AD28) | AE29: =SUM(AE26:AE28) | AF29: =SUM(AF26:AF28) | AG29: =SUM(AG26:AG28) | AH29: =SUM(AH26:AH28) | AI29: =SUM(AI26:AI28) | AJ29: =SUM(AJ26:AJ28) | ... AN29: =SUM(AN26:AN28) | AO29: =AN29 | AP29: =SUM(AP26:AP28) | AQ29: =SUM(AQ26:AQ28) | AR29: =SUM(AR26:AR28) | AS29: =SUM(AS26:AS28) | AT29: =SUM(AT26:AT28) | AU29: =SUM(AU26:AU28) | AV29: =SUM(AV26:AV28) | AW29: =SUM(AW26:AW28) | ... BA29: =SUM(BA26:BA28) | BB29: =BA29
B31: Plan Partner — Segmento C | H31: La cartera del canal es un stock, no un flujo: cada partner gestiona una cantidad finita de clientes. Modelarlo como altas mensuales perpetuas haría crecer el canal sin techo.
A32: PLAN PARTNER | B32: Partners activos | C32: =ROUND(Hipótesis!$C$36*1/12,0) | D32: =ROUND(Hipótesis!$C$36*2/12,0) | E32: =ROUND(Hipótesis!$C$36*3/12,0) | F32: =ROUND(Hipótesis!$C$36*4/12,0) | G32: =ROUND(Hipótesis!$C$36*5/12,0) | H32: =ROUND(Hipótesis!$C$36*6/12,0) | I32: =ROUND(Hipótesis!$C$36*7/12,0) | J32: =ROUND(Hipótesis!$C$36*8/12,0) | K32: =ROUND(Hipótesis!$C$36*9/12,0) | L32: =ROUND(Hipótesis!$C$36*10/12,0) | M32: =ROUND(Hipótesis!$C$36*11/12,0) | N32: =ROUND(Hipótesis!$C$36*12/12,0) | O32: =N32 | P32: =ROUND(Hipótesis!$C$36+(Hipótesis!$D$36-Hipótesis!$C$36)*1/12,0) | Q32: =ROUND(Hipótesis!$C$36+(Hipótesis!$D$36-Hipótesis!$C$36)*2/12,0) | R32: =ROUND(Hipótesis!$C$36+(Hipótesis!$D$36-Hipótesis!$C$36)*3/12,0) | S32: =ROUND(Hipótesis!$C$36+(Hipótesis!$D$36-Hipótesis!$C$36)*4/12,0) | T32: =ROUND(Hipótesis!$C$36+(Hipótesis!$D$36-Hipótesis!$C$36)*5/12,0) | U32: =ROUND(Hipótesis!$C$36+(Hipótesis!$D$36-Hipótesis!$C$36)*6/12,0) | V32: =ROUND(Hipótesis!$C$36+(Hipótesis!$D$36-Hipótesis!$C$36)*7/12,0) | W32: =ROUND(Hipótesis!$C$36+(Hipótesis!$D$36-Hipótesis!$C$36)*8/12,0) | X32: =ROUND(Hipótesis!$C$36+(Hipótesis!$D$36-Hipótesis!$C$36)*9/12,0) | Y32: =ROUND(Hipótesis!$C$36+(Hipótesis!$D$36-Hipótesis!$C$36)*10/12,0) | Z32: =ROUND(Hipótesis!$C$36+(Hipótesis!$D$36-Hipótesis!$C$36)*11/12,0) | AA32: =ROUND(Hipótesis!$C$36+(Hipótesis!$D$36-Hipótesis!$C$36)*12/12,0) | AB32: =AA32 | AC32: =ROUND(Hipótesis!$D$36+(Hipótesis!$E$36-Hipótesis!$D$36)*1/12,0) | AD32: =ROUND(Hipótesis!$D$36+(Hipótesis!$E$36-Hipótesis!$D$36)*2/12,0) | AE32: =ROUND(Hipótesis!$D$36+(Hipótesis!$E$36-Hipótesis!$D$36)*3/12,0) | AF32: =ROUND(Hipótesis!$D$36+(Hipótesis!$E$36-Hipótesis!$D$36)*4/12,0) | AG32: =ROUND(Hipótesis!$D$36+(Hipótesis!$E$36-Hipótesis!$D$36)*5/12,0) | AH32: =ROUND(Hipótesis!$D$36+(Hipótesis!$E$36-Hipótesis!$D$36)*6/12,0) | AI32: =ROUND(Hipótesis!$D$36+(Hipótesis!$E$36-Hipótesis!$D$36)*7/12,0) | AJ32: =ROUND(Hipótesis!$D$36+(Hipótesis!$E$36-Hipótesis!$D$36)*8/12,0) | AK32: =ROUND(Hipótesis!$D$36+(Hipótesis!$E$36-Hipótesis!$D$36)*9/12,0) | AL32: =ROUND(Hipótesis!$D$36+(Hipótesis!$E$36-Hipótesis!$D$36)*10/12,0) | AM32: =ROUND(Hipótesis!$D$36+(Hipótesis!$E$36-Hipótesis!$D$36)*11/12,0) | AN32: =ROUND(Hipótesis!$D$36+(Hipótesis!$E$36-Hipótesis!$D$36)*12/12,0) | AO32: =AN32 | AP32: =ROUND(Hipótesis!$E$36+(Hipótesis!$F$36-Hipótesis!$E$36)*1/12,0) | AQ32: =ROUND(Hipótesis!$E$36+(Hipótesis!$F$36-Hipótesis!$E$36)*2/12,0) | AR32: =ROUND(Hipótesis!$E$36+(Hipótesis!$F$36-Hipótesis!$E$36)*3/12,0) | AS32: =ROUND(Hipótesis!$E$36+(Hipótesis!$F$36-Hipótesis!$E$36)*4/12,0) | AT32: =ROUND(Hipótesis!$E$36+(Hipótesis!$F$36-Hipótesis!$E$36)*5/12,0) | AU32: =ROUND(Hipótesis!$E$36+(Hipótesis!$F$36-Hipótesis!$E$36)*6/12,0) | AV32: =ROUND(Hipótesis!$E$36+(Hipótesis!$F$36-Hipótesis!$E$36)*7/12,0) | AW32: =ROUND(Hipótesis!$E$36+(Hipótesis!$F$36-Hipótesis!$E$36)*8/12,0) | AX32: =ROUND(Hipótesis!$E$36+(Hipótesis!$F$36-Hipótesis!$E$36)*9/12,0) | AY32: =ROUND(Hipótesis!$E$36+(Hipótesis!$F$36-Hipótesis!$E$36)*10/12,0) | AZ32: =ROUND(Hipótesis!$E$36+(Hipótesis!$F$36-Hipótesis!$E$36)*11/12,0) | BA32: =ROUND(Hipótesis!$E$36+(Hipótesis!$F$36-Hipótesis!$E$36)*12/12,0) | BB32: =BA32
B33: Clientes gestionados por el canal | C33: =IF(1<Hipótesis!$C$35,0,C32*Hipótesis!$C$37) | D33: =IF(2<Hipótesis!$C$35,0,D32*Hipótesis!$C$37) | E33: =IF(3<Hipótesis!$C$35,0,E32*Hipótesis!$C$37) | F33: =IF(4<Hipótesis!$C$35,0,F32*Hipótesis!$C$37) | G33: =IF(5<Hipótesis!$C$35,0,G32*Hipótesis!$C$37) | H33: =IF(6<Hipótesis!$C$35,0,H32*Hipótesis!$C$37) | I33: =IF(7<Hipótesis!$C$35,0,I32*Hipótesis!$C$37) | J33: =IF(8<Hipótesis!$C$35,0,J32*Hipótesis!$C$37) | K33: =IF(9<Hipótesis!$C$35,0,K32*Hipótesis!$C$37) | L33: =IF(10<Hipótesis!$C$35,0,L32*Hipótesis!$C$37) | M33: =IF(11<Hipótesis!$C$35,0,M32*Hipótesis!$C$37) | N33: =IF(12<Hipótesis!$C$35,0,N32*Hipótesis!$C$37) | O33: =N33 | P33: =IF(13<Hipótesis!$C$35,0,P32*Hipótesis!$D$37) | Q33: =IF(14<Hipótesis!$C$35,0,Q32*Hipótesis!$D$37) | R33: =IF(15<Hipótesis!$C$35,0,R32*Hipótesis!$D$37) | S33: =IF(16<Hipótesis!$C$35,0,S32*Hipótesis!$D$37) | T33: =IF(17<Hipótesis!$C$35,0,T32*Hipótesis!$D$37) | U33: =IF(18<Hipótesis!$C$35,0,U32*Hipótesis!$D$37) | V33: =IF(19<Hipótesis!$C$35,0,V32*Hipótesis!$D$37) | W33: =IF(20<Hipótesis!$C$35,0,W32*Hipótesis!$D$37) | X33: =IF(21<Hipótesis!$C$35,0,X32*Hipótesis!$D$37) | Y33: =IF(22<Hipótesis!$C$35,0,Y32*Hipótesis!$D$37) | Z33: =IF(23<Hipótesis!$C$35,0,Z32*Hipótesis!$D$37) | AA33: =IF(24<Hipótesis!$C$35,0,AA32*Hipótesis!$D$37) | AB33: =AA33 | AC33: =IF(25<Hipótesis!$C$35,0,AC32*Hipótesis!$E$37) | AD33: =IF(26<Hipótesis!$C$35,0,AD32*Hipótesis!$E$37) | AE33: =IF(27<Hipótesis!$C$35,0,AE32*Hipótesis!$E$37) | AF33: =IF(28<Hipótesis!$C$35,0,AF32*Hipótesis!$E$37) | AG33: =IF(29<Hipótesis!$C$35,0,AG32*Hipótesis!$E$37) | AH33: =IF(30<Hipótesis!$C$35,0,AH32*Hipótesis!$E$37) | AI33: =IF(31<Hipótesis!$C$35,0,AI32*Hipótesis!$E$37) | AJ33: =IF(32<Hipótesis!$C$35,0,AJ32*Hipótesis!$E$37) | AK33: =IF(33<Hipótesis!$C$35,0,AK32*Hipótesis!$E$37) | AL33: =IF(34<Hipótesis!$C$35,0,AL32*Hipótesis!$E$37) | AM33: =IF(35<Hipótesis!$C$35,0,AM32*Hipótesis!$E$37) | AN33: =IF(36<Hipótesis!$C$35,0,AN32*Hipótesis!$E$37) | AO33: =AN33 | AP33: =IF(37<Hipótesis!$C$35,0,AP32*Hipótesis!$F$37) | AQ33: =IF(38<Hipótesis!$C$35,0,AQ32*Hipótesis!$F$37) | AR33: =IF(39<Hipótesis!$C$35,0,AR32*Hipótesis!$F$37) | AS33: =IF(40<Hipótesis!$C$35,0,AS32*Hipótesis!$F$37) | AT33: =IF(41<Hipótesis!$C$35,0,AT32*Hipótesis!$F$37) | AU33: =IF(42<Hipótesis!$C$35,0,AU32*Hipótesis!$F$37) | AV33: =IF(43<Hipótesis!$C$35,0,AV32*Hipótesis!$F$37) | AW33: =IF(44<Hipótesis!$C$35,0,AW32*Hipótesis!$F$37) | AX33: =IF(45<Hipótesis!$C$35,0,AX32*Hipótesis!$F$37) | AY33: =IF(46<Hipótesis!$C$35,0,AY32*Hipótesis!$F$37) | AZ33: =IF(47<Hipótesis!$C$35,0,AZ32*Hipótesis!$F$37) | BA33: =IF(48<Hipótesis!$C$35,0,BA32*Hipótesis!$F$37) | BB33: =BA33
B35: Consolidado
A36: TOTAL | B36: Clientes pagos activos | C36: =C22+C29+C33 | D36: =D22+D29+D33 | E36: =E22+E29+E33 | F36: =F22+F29+F33 | G36: =G22+G29+G33 | H36: =H22+H29+H33 | I36: =I22+I29+I33 | J36: =J22+J29+J33 | ... N36: =N22+N29+N33 | O36: =N36 | P36: =P22+P29+P33 | Q36: =Q22+Q29+Q33 | R36: =R22+R29+R33 | S36: =S22+S29+S33 | T36: =T22+T29+T33 | U36: =U22+U29+U33 | V36: =V22+V29+V33 | W36: =W22+W29+W33 | ... AA36: =AA22+AA29+AA33 | AB36: =AA36 | AC36: =AC22+AC29+AC33 | AD36: =AD22+AD29+AD33 | AE36: =AE22+AE29+AE33 | AF36: =AF22+AF29+AF33 | AG36: =AG22+AG29+AG33 | AH36: =AH22+AH29+AH33 | AI36: =AI22+AI29+AI33 | AJ36: =AJ22+AJ29+AJ33 | ... AN36: =AN22+AN29+AN33 | AO36: =AN36 | AP36: =AP22+AP29+AP33 | AQ36: =AQ22+AQ29+AQ33 | AR36: =AR22+AR29+AR33 | AS36: =AS22+AS29+AS33 | AT36: =AT22+AT29+AT33 | AU36: =AU22+AU29+AU33 | AV36: =AV22+AV29+AV33 | AW36: =AW22+AW29+AW33 | ... BA36: =BA22+BA29+BA33 | BB36: =BA36
B37: Equipos administrados | C37: =C22*Hipótesis!$C$41+C29*Hipótesis!$C$42+C33*Hipótesis!$C$43 | D37: =D22*Hipótesis!$C$41+D29*Hipótesis!$C$42+D33*Hipótesis!$C$43 | E37: =E22*Hipótesis!$C$41+E29*Hipótesis!$C$42+E33*Hipótesis!$C$43 | F37: =F22*Hipótesis!$C$41+F29*Hipótesis!$C$42+F33*Hipótesis!$C$43 | G37: =G22*Hipótesis!$C$41+G29*Hipótesis!$C$42+G33*Hipótesis!$C$43 | H37: =H22*Hipótesis!$C$41+H29*Hipótesis!$C$42+H33*Hipótesis!$C$43 | I37: =I22*Hipótesis!$C$41+I29*Hipótesis!$C$42+I33*Hipótesis!$C$43 | J37: =J22*Hipótesis!$C$41+J29*Hipótesis!$C$42+J33*Hipótesis!$C$43 | ... N37: =N22*Hipótesis!$C$41+N29*Hipótesis!$C$42+N33*Hipótesis!$C$43 | O37: =N37 | P37: =P22*Hipótesis!$D$41+P29*Hipótesis!$D$42+P33*Hipótesis!$D$43 | Q37: =Q22*Hipótesis!$D$41+Q29*Hipótesis!$D$42+Q33*Hipótesis!$D$43 | R37: =R22*Hipótesis!$D$41+R29*Hipótesis!$D$42+R33*Hipótesis!$D$43 | S37: =S22*Hipótesis!$D$41+S29*Hipótesis!$D$42+S33*Hipótesis!$D$43 | T37: =T22*Hipótesis!$D$41+T29*Hipótesis!$D$42+T33*Hipótesis!$D$43 | U37: =U22*Hipótesis!$D$41+U29*Hipótesis!$D$42+U33*Hipótesis!$D$43 | V37: =V22*Hipótesis!$D$41+V29*Hipótesis!$D$42+V33*Hipótesis!$D$43 | W37: =W22*Hipótesis!$D$41+W29*Hipótesis!$D$42+W33*Hipótesis!$D$43 | ... AA37: =AA22*Hipótesis!$D$41+AA29*Hipótesis!$D$42+AA33*Hipótesis!$D$43 | AB37: =AA37 | AC37: =AC22*Hipótesis!$E$41+AC29*Hipótesis!$E$42+AC33*Hipótesis!$E$43 | AD37: =AD22*Hipótesis!$E$41+AD29*Hipótesis!$E$42+AD33*Hipótesis!$E$43 | AE37: =AE22*Hipótesis!$E$41+AE29*Hipótesis!$E$42+AE33*Hipótesis!$E$43 | AF37: =AF22*Hipótesis!$E$41+AF29*Hipótesis!$E$42+AF33*Hipótesis!$E$43 | AG37: =AG22*Hipótesis!$E$41+AG29*Hipótesis!$E$42+AG33*Hipótesis!$E$43 | AH37: =AH22*Hipótesis!$E$41+AH29*Hipótesis!$E$42+AH33*Hipótesis!$E$43 | AI37: =AI22*Hipótesis!$E$41+AI29*Hipótesis!$E$42+AI33*Hipótesis!$E$43 | AJ37: =AJ22*Hipótesis!$E$41+AJ29*Hipótesis!$E$42+AJ33*Hipótesis!$E$43 | ... AN37: =AN22*Hipótesis!$E$41+AN29*Hipótesis!$E$42+AN33*Hipótesis!$E$43 | AO37: =AN37 | AP37: =AP22*Hipótesis!$F$41+AP29*Hipótesis!$F$42+AP33*Hipótesis!$F$43 | AQ37: =AQ22*Hipótesis!$F$41+AQ29*Hipótesis!$F$42+AQ33*Hipótesis!$F$43 | AR37: =AR22*Hipótesis!$F$41+AR29*Hipótesis!$F$42+AR33*Hipótesis!$F$43 | AS37: =AS22*Hipótesis!$F$41+AS29*Hipótesis!$F$42+AS33*Hipótesis!$F$43 | AT37: =AT22*Hipótesis!$F$41+AT29*Hipótesis!$F$42+AT33*Hipótesis!$F$43 | AU37: =AU22*Hipótesis!$F$41+AU29*Hipótesis!$F$42+AU33*Hipótesis!$F$43 | AV37: =AV22*Hipótesis!$F$41+AV29*Hipótesis!$F$42+AV33*Hipótesis!$F$43 | AW37: =AW22*Hipótesis!$F$41+AW29*Hipótesis!$F$42+AW33*Hipótesis!$F$43 | ... BA37: =BA22*Hipótesis!$F$41+BA29*Hipótesis!$F$42+BA33*Hipótesis!$F$43 | BB37: =BA37
B39: Verificación contra las metas del documento (5.3.3)
C40: Proyectado | D40: Meta | E40: Desvío
B41: Clientes pagos al mes 8 (Etapa E2) | C41: =J36 | D41: 10 | E41: =C41/D41-1
B42: Clientes pagos al mes 12 (Etapa E3) | C42: =N36 | D42: 25 | E42: =C42/D42-1
B43: Equipos administrados al mes 12 | C43: =N37 | D43: 1000 | E43: =C43/D43-1

Sheet Modelo de ingresos
A1: « Inicio
B2: MODELO DE INGRESOS
B3: Facturación por línea: abono de la base activa más los equipos que exceden lo que incluye cada plan. Los precios se actualizan una vez por año según el supuesto de aumento de lista.
C7: 2027 | P7: 2028 | AC7: 2029 | AP7: 2030
C8: Ene | D8: Feb | E8: Mar | F8: Abr | G8: May | H8: Jun | I8: Jul | J8: Ago | K8: Sep | L8: Oct | M8: Nov | N8: Dic | O8: Total 2027 | P8: Ene | Q8: Feb | R8: Mar | S8: Abr | T8: May | U8: Jun | V8: Jul | W8: Ago | X8: Sep | Y8: Oct | Z8: Nov | AA8: Dic | AB8: Total 2028 | AC8: Ene | AD8: Feb | AE8: Mar | AF8: Abr | AG8: May | AH8: Jun | AI8: Jul | AJ8: Ago | AK8: Sep | AL8: Oct | AM8: Nov | AN8: Dic | AO8: Total 2029 | AP8: Ene | AQ8: Feb | AR8: Mar | AS8: Abr | AT8: May | AU8: Jun | AV8: Jul | AW8: Ago | AX8: Sep | AY8: Oct | AZ8: Nov | BA8: Dic | BB8: Total 2030
B10: Plan Inicial
A11: PLAN INICIAL | B11: Ingreso por abono | C11: ='Proyección de ventas'!C22*Planes!$D$7*1 | D11: ='Proyección de ventas'!D22*Planes!$D$7*1 | E11: ='Proyección de ventas'!E22*Planes!$D$7*1 | F11: ='Proyección de ventas'!F22*Planes!$D$7*1 | G11: ='Proyección de ventas'!G22*Planes!$D$7*1 | H11: ='Proyección de ventas'!H22*Planes!$D$7*1 | I11: ='Proyección de ventas'!I22*Planes!$D$7*1 | J11: ='Proyección de ventas'!J22*Planes!$D$7*1 | ... N11: ='Proyección de ventas'!N22*Planes!$D$7*1 | O11: =SUM(C11:N11) | P11: ='Proyección de ventas'!P22*Planes!$D$7*(1+Hipótesis!$D$11) | Q11: ='Proyección de ventas'!Q22*Planes!$D$7*(1+Hipótesis!$D$11) | R11: ='Proyección de ventas'!R22*Planes!$D$7*(1+Hipótesis!$D$11) | S11: ='Proyección de ventas'!S22*Planes!$D$7*(1+Hipótesis!$D$11) | T11: ='Proyección de ventas'!T22*Planes!$D$7*(1+Hipótesis!$D$11) | U11: ='Proyección de ventas'!U22*Planes!$D$7*(1+Hipótesis!$D$11) | V11: ='Proyección de ventas'!V22*Planes!$D$7*(1+Hipótesis!$D$11) | W11: ='Proyección de ventas'!W22*Planes!$D$7*(1+Hipótesis!$D$11) | ... AA11: ='Proyección de ventas'!AA22*Planes!$D$7*(1+Hipótesis!$D$11) | AB11: =SUM(P11:AA11) | AC11: ='Proyección de ventas'!AC22*Planes!$D$7*(1+Hipótesis!$D$11)*(1+Hipótesis!$E$11) | AD11: ='Proyección de ventas'!AD22*Planes!$D$7*(1+Hipótesis!$D$11)*(1+Hipótesis!$E$11) | AE11: ='Proyección de ventas'!AE22*Planes!$D$7*(1+Hipótesis!$D$11)*(1+Hipótesis!$E$11) | AF11: ='Proyección de ventas'!AF22*Planes!$D$7*(1+Hipótesis!$D$11)*(1+Hipótesis!$E$11) | AG11: ='Proyección de ventas'!AG22*Planes!$D$7*(1+Hipótesis!$D$11)*(1+Hipótesis!$E$11) | AH11: ='Proyección de ventas'!AH22*Planes!$D$7*(1+Hipótesis!$D$11)*(1+Hipótesis!$E$11) | AI11: ='Proyección de ventas'!AI22*Planes!$D$7*(1+Hipótesis!$D$11)*(1+Hipótesis!$E$11) | AJ11: ='Proyección de ventas'!AJ22*Planes!$D$7*(1+Hipótesis!$D$11)*(1+Hipótesis!$E$11) | ... AN11: ='Proyección de ventas'!AN22*Planes!$D$7*(1+Hipótesis!$D$11)*(1+Hipótesis!$E$11) | AO11: =SUM(AC11:AN11) | AP11: ='Proyección de ventas'!AP22*Planes!$D$7*(1+Hipótesis!$D$11)*(1+Hipótesis!$E$11)*(1+Hipótesis!$F$11) | AQ11: ='Proyección de ventas'!AQ22*Planes!$D$7*(1+Hipótesis!$D$11)*(1+Hipótesis!$E$11)*(1+Hipótesis!$F$11) | AR11: ='Proyección de ventas'!AR22*Planes!$D$7*(1+Hipótesis!$D$11)*(1+Hipótesis!$E$11)*(1+Hipótesis!$F$11) | AS11: ='Proyección de ventas'!AS22*Planes!$D$7*(1+Hipótesis!$D$11)*(1+Hipótesis!$E$11)*(1+Hipótesis!$F$11) | AT11: ='Proyección de ventas'!AT22*Planes!$D$7*(1+Hipótesis!$D$11)*(1+Hipótesis!$E$11)*(1+Hipótesis!$F$11) | AU11: ='Proyección de ventas'!AU22*Planes!$D$7*(1+Hipótesis!$D$11)*(1+Hipótesis!$E$11)*(1+Hipótesis!$F$11) | AV11: ='Proyección de ventas'!AV22*Planes!$D$7*(1+Hipótesis!$D$11)*(1+Hipótesis!$E$11)*(1+Hipótesis!$F$11) | AW11: ='Proyección de ventas'!AW22*Planes!$D$7*(1+Hipótesis!$D$11)*(1+Hipótesis!$E$11)*(1+Hipótesis!$F$11) | ... BA11: ='Proyección de ventas'!BA22*Planes!$D$7*(1+Hipótesis!$D$11)*(1+Hipótesis!$E$11)*(1+Hipótesis!$F$11) | BB11: =SUM(AP11:BA11)
B12: Ingreso por equipos adicionales | C12: ='Proyección de ventas'!C22*MAX(0,Hipótesis!$C$41-Planes!$E$7)*Planes!$F$7*1 | D12: ='Proyección de ventas'!D22*MAX(0,Hipótesis!$C$41-Planes!$E$7)*Planes!$F$7*1 | E12: ='Proyección de ventas'!E22*MAX(0,Hipótesis!$C$41-Planes!$E$7)*Planes!$F$7*1 | F12: ='Proyección de ventas'!F22*MAX(0,Hipótesis!$C$41-Planes!$E$7)*Planes!$F$7*1 | G12: ='Proyección de ventas'!G22*MAX(0,Hipótesis!$C$41-Planes!$E$7)*Planes!$F$7*1 | H12: ='Proyección de ventas'!H22*MAX(0,Hipótesis!$C$41-Planes!$E$7)*Planes!$F$7*1 | I12: ='Proyección de ventas'!I22*MAX(0,Hipótesis!$C$41-Planes!$E$7)*Planes!$F$7*1 | J12: ='Proyección de ventas'!J22*MAX(0,Hipótesis!$C$41-Planes!$E$7)*Planes!$F$7*1 | ... N12: ='Proyección de ventas'!N22*MAX(0,Hipótesis!$C$41-Planes!$E$7)*Planes!$F$7*1 | O12: =SUM(C12:N12) | P12: ='Proyección de ventas'!P22*MAX(0,Hipótesis!$D$41-Planes!$E$7)*Planes!$F$7*(1+Hipótesis!$D$11) | Q12: ='Proyección de ventas'!Q22*MAX(0,Hipótesis!$D$41-Planes!$E$7)*Planes!$F$7*(1+Hipótesis!$D$11) | R12: ='Proyección de ventas'!R22*MAX(0,Hipótesis!$D$41-Planes!$E$7)*Planes!$F$7*(1+Hipótesis!$D$11) | S12: ='Proyección de ventas'!S22*MAX(0,Hipótesis!$D$41-Planes!$E$7)*Planes!$F$7*(1+Hipótesis!$D$11) | T12: ='Proyección de ventas'!T22*MAX(0,Hipótesis!$D$41-Planes!$E$7)*Planes!$F$7*(1+Hipótesis!$D$11) | U12: ='Proyección de ventas'!U22*MAX(0,Hipótesis!$D$41-Planes!$E$7)*Planes!$F$7*(1+Hipótesis!$D$11) | V12: ='Proyección de ventas'!V22*MAX(0,Hipótesis!$D$41-Planes!$E$7)*Planes!$F$7*(1+Hipótesis!$D$11) | W12: ='Proyección de ventas'!W22*MAX(0,Hipótesis!$D$41-Planes!$E$7)*Planes!$F$7*(1+Hipótesis!$D$11) | ... AA12: ='Proyección de ventas'!AA22*MAX(0,Hipótesis!$D$41-Planes!$E$7)*Planes!$F$7*(1+Hipótesis!$D$11) | AB12: =SUM(P12:AA12) | AC12: ='Proyección de ventas'!AC22*MAX(0,Hipótesis!$E$41-Planes!$E$7)*Planes!$F$7*(1+Hipótesis!$D$11)*(1+Hipótesis!$E$11) | AD12: ='Proyección de ventas'!AD22*MAX(0,Hipótesis!$E$41-Planes!$E$7)*Planes!$F$7*(1+Hipótesis!$D$11)*(1+Hipótesis!$E$11) | AE12: ='Proyección de ventas'!AE22*MAX(0,Hipótesis!$E$41-Planes!$E$7)*Planes!$F$7*(1+Hipótesis!$D$11)*(1+Hipótesis!$E$11) | AF12: ='Proyección de ventas'!AF22*MAX(0,Hipótesis!$E$41-Planes!$E$7)*Planes!$F$7*(1+Hipótesis!$D$11)*(1+Hipótesis!$E$11) | AG12: ='Proyección de ventas'!AG22*MAX(0,Hipótesis!$E$41-Planes!$E$7)*Planes!$F$7*(1+Hipótesis!$D$11)*(1+Hipótesis!$E$11) | AH12: ='Proyección de ventas'!AH22*MAX(0,Hipótesis!$E$41-Planes!$E$7)*Planes!$F$7*(1+Hipótesis!$D$11)*(1+Hipótesis!$E$11) | AI12: ='Proyección de ventas'!AI22*MAX(0,Hipótesis!$E$41-Planes!$E$7)*Planes!$F$7*(1+Hipótesis!$D$11)*(1+Hipótesis!$E$11) | AJ12: ='Proyección de ventas'!AJ22*MAX(0,Hipótesis!$E$41-Planes!$E$7)*Planes!$F$7*(1+Hipótesis!$D$11)*(1+Hipótesis!$E$11) | ... AN12: ='Proyección de ventas'!AN22*MAX(0,Hipótesis!$E$41-Planes!$E$7)*Planes!$F$7*(1+Hipótesis!$D$11)*(1+Hipótesis!$E$11) | AO12: =SUM(AC12:AN12) | AP12: ='Proyección de ventas'!AP22*MAX(0,Hipótesis!$F$41-Planes!$E$7)*Planes!$F$7*(1+Hipótesis!$D$11)*(1+Hipótesis!$E$11)*(1+Hipótesis!$F$11) | AQ12: ='Proyección de ventas'!AQ22*MAX(0,Hipótesis!$F$41-Planes!$E$7)*Planes!$F$7*(1+Hipótesis!$D$11)*(1+Hipótesis!$E$11)*(1+Hipótesis!$F$11) | AR12: ='Proyección de ventas'!AR22*MAX(0,Hipótesis!$F$41-Planes!$E$7)*Planes!$F$7*(1+Hipótesis!$D$11)*(1+Hipótesis!$E$11)*(1+Hipótesis!$F$11) | AS12: ='Proyección de ventas'!AS22*MAX(0,Hipótesis!$F$41-Planes!$E$7)*Planes!$F$7*(1+Hipótesis!$D$11)*(1+Hipótesis!$E$11)*(1+Hipótesis!$F$11) | AT12: ='Proyección de ventas'!AT22*MAX(0,Hipótesis!$F$41-Planes!$E$7)*Planes!$F$7*(1+Hipótesis!$D$11)*(1+Hipótesis!$E$11)*(1+Hipótesis!$F$11) | AU12: ='Proyección de ventas'!AU22*MAX(0,Hipótesis!$F$41-Planes!$E$7)*Planes!$F$7*(1+Hipótesis!$D$11)*(1+Hipótesis!$E$11)*(1+Hipótesis!$F$11) | AV12: ='Proyección de ventas'!AV22*MAX(0,Hipótesis!$F$41-Planes!$E$7)*Planes!$F$7*(1+Hipótesis!$D$11)*(1+Hipótesis!$E$11)*(1+Hipótesis!$F$11) | AW12: ='Proyección de ventas'!AW22*MAX(0,Hipótesis!$F$41-Planes!$E$7)*Planes!$F$7*(1+Hipótesis!$D$11)*(1+Hipótesis!$E$11)*(1+Hipótesis!$F$11) | ... BA12: ='Proyección de ventas'!BA22*MAX(0,Hipótesis!$F$41-Planes!$E$7)*Planes!$F$7*(1+Hipótesis!$D$11)*(1+Hipótesis!$E$11)*(1+Hipótesis!$F$11) | BB12: =SUM(AP12:BA12)
B13: Total de la línea | C13: =C11+C12 | D13: =D11+D12 | E13: =E11+E12 | F13: =F11+F12 | G13: =G11+G12 | H13: =H11+H12 | I13: =I11+I12 | J13: =J11+J12 | ... N13: =N11+N12 | O13: =SUM(C13:N13) | P13: =P11+P12 | Q13: =Q11+Q12 | R13: =R11+R12 | S13: =S11+S12 | T13: =T11+T12 | U13: =U11+U12 | V13: =V11+V12 | W13: =W11+W12 | ... AA13: =AA11+AA12 | AB13: =SUM(P13:AA13) | AC13: =AC11+AC12 | AD13: =AD11+AD12 | AE13: =AE11+AE12 | AF13: =AF11+AF12 | AG13: =AG11+AG12 | AH13: =AH11+AH12 | AI13: =AI11+AI12 | AJ13: =AJ11+AJ12 | ... AN13: =AN11+AN12 | AO13: =SUM(AC13:AN13) | AP13: =AP11+AP12 | AQ13: =AQ11+AQ12 | AR13: =AR11+AR12 | AS13: =AS11+AS12 | AT13: =AT11+AT12 | AU13: =AU11+AU12 | AV13: =AV11+AV12 | AW13: =AW11+AW12 | ... BA13: =BA11+BA12 | BB13: =SUM(AP13:BA13)
B15: Plan Estándar
A16: PLAN ESTÁNDAR | B16: Ingreso por abono | C16: ='Proyección de ventas'!C29*Planes!$D$8*1 | D16: ='Proyección de ventas'!D29*Planes!$D$8*1 | E16: ='Proyección de ventas'!E29*Planes!$D$8*1 | F16: ='Proyección de ventas'!F29*Planes!$D$8*1 | G16: ='Proyección de ventas'!G29*Planes!$D$8*1 | H16: ='Proyección de ventas'!H29*Planes!$D$8*1 | I16: ='Proyección de ventas'!I29*Planes!$D$8*1 | J16: ='Proyección de ventas'!J29*Planes!$D$8*1 | ... N16: ='Proyección de ventas'!N29*Planes!$D$8*1 | O16: =SUM(C16:N16) | P16: ='Proyección de ventas'!P29*Planes!$D$8*(1+Hipótesis!$D$11) | Q16: ='Proyección de ventas'!Q29*Planes!$D$8*(1+Hipótesis!$D$11) | R16: ='Proyección de ventas'!R29*Planes!$D$8*(1+Hipótesis!$D$11) | S16: ='Proyección de ventas'!S29*Planes!$D$8*(1+Hipótesis!$D$11) | T16: ='Proyección de ventas'!T29*Planes!$D$8*(1+Hipótesis!$D$11) | U16: ='Proyección de ventas'!U29*Planes!$D$8*(1+Hipótesis!$D$11) | V16: ='Proyección de ventas'!V29*Planes!$D$8*(1+Hipótesis!$D$11) | W16: ='Proyección de ventas'!W29*Planes!$D$8*(1+Hipótesis!$D$11) | ... AA16: ='Proyección de ventas'!AA29*Planes!$D$8*(1+Hipótesis!$D$11) | AB16: =SUM(P16:AA16) | AC16: ='Proyección de ventas'!AC29*Planes!$D$8*(1+Hipótesis!$D$11)*(1+Hipótesis!$E$11) | AD16: ='Proyección de ventas'!AD29*Planes!$D$8*(1+Hipótesis!$D$11)*(1+Hipótesis!$E$11) | AE16: ='Proyección de ventas'!AE29*Planes!$D$8*(1+Hipótesis!$D$11)*(1+Hipótesis!$E$11) | AF16: ='Proyección de ventas'!AF29*Planes!$D$8*(1+Hipótesis!$D$11)*(1+Hipótesis!$E$11) | AG16: ='Proyección de ventas'!AG29*Planes!$D$8*(1+Hipótesis!$D$11)*(1+Hipótesis!$E$11) | AH16: ='Proyección de ventas'!AH29*Planes!$D$8*(1+Hipótesis!$D$11)*(1+Hipótesis!$E$11) | AI16: ='Proyección de ventas'!AI29*Planes!$D$8*(1+Hipótesis!$D$11)*(1+Hipótesis!$E$11) | AJ16: ='Proyección de ventas'!AJ29*Planes!$D$8*(1+Hipótesis!$D$11)*(1+Hipótesis!$E$11) | ... AN16: ='Proyección de ventas'!AN29*Planes!$D$8*(1+Hipótesis!$D$11)*(1+Hipótesis!$E$11) | AO16: =SUM(AC16:AN16) | AP16: ='Proyección de ventas'!AP29*Planes!$D$8*(1+Hipótesis!$D$11)*(1+Hipótesis!$E$11)*(1+Hipótesis!$F$11) | AQ16: ='Proyección de ventas'!AQ29*Planes!$D$8*(1+Hipótesis!$D$11)*(1+Hipótesis!$E$11)*(1+Hipótesis!$F$11) | AR16: ='Proyección de ventas'!AR29*Planes!$D$8*(1+Hipótesis!$D$11)*(1+Hipótesis!$E$11)*(1+Hipótesis!$F$11) | AS16: ='Proyección de ventas'!AS29*Planes!$D$8*(1+Hipótesis!$D$11)*(1+Hipótesis!$E$11)*(1+Hipótesis!$F$11) | AT16: ='Proyección de ventas'!AT29*Planes!$D$8*(1+Hipótesis!$D$11)*(1+Hipótesis!$E$11)*(1+Hipótesis!$F$11) | AU16: ='Proyección de ventas'!AU29*Planes!$D$8*(1+Hipótesis!$D$11)*(1+Hipótesis!$E$11)*(1+Hipótesis!$F$11) | AV16: ='Proyección de ventas'!AV29*Planes!$D$8*(1+Hipótesis!$D$11)*(1+Hipótesis!$E$11)*(1+Hipótesis!$F$11) | AW16: ='Proyección de ventas'!AW29*Planes!$D$8*(1+Hipótesis!$D$11)*(1+Hipótesis!$E$11)*(1+Hipótesis!$F$11) | ... BA16: ='Proyección de ventas'!BA29*Planes!$D$8*(1+Hipótesis!$D$11)*(1+Hipótesis!$E$11)*(1+Hipótesis!$F$11) | BB16: =SUM(AP16:BA16)
B17: Ingreso por equipos adicionales | C17: ='Proyección de ventas'!C29*MAX(0,Hipótesis!$C$42-Planes!$E$8)*Planes!$F$8*1 | D17: ='Proyección de ventas'!D29*MAX(0,Hipótesis!$C$42-Planes!$E$8)*Planes!$F$8*1 | E17: ='Proyección de ventas'!E29*MAX(0,Hipótesis!$C$42-Planes!$E$8)*Planes!$F$8*1 | F17: ='Proyección de ventas'!F29*MAX(0,Hipótesis!$C$42-Planes!$E$8)*Planes!$F$8*1 | G17: ='Proyección de ventas'!G29*MAX(0,Hipótesis!$C$42-Planes!$E$8)*Planes!$F$8*1 | H17: ='Proyección de ventas'!H29*MAX(0,Hipótesis!$C$42-Planes!$E$8)*Planes!$F$8*1 | I17: ='Proyección de ventas'!I29*MAX(0,Hipótesis!$C$42-Planes!$E$8)*Planes!$F$8*1 | J17: ='Proyección de ventas'!J29*MAX(0,Hipótesis!$C$42-Planes!$E$8)*Planes!$F$8*1 | ... N17: ='Proyección de ventas'!N29*MAX(0,Hipótesis!$C$42-Planes!$E$8)*Planes!$F$8*1 | O17: =SUM(C17:N17) | P17: ='Proyección de ventas'!P29*MAX(0,Hipótesis!$D$42-Planes!$E$8)*Planes!$F$8*(1+Hipótesis!$D$11) | Q17: ='Proyección de ventas'!Q29*MAX(0,Hipótesis!$D$42-Planes!$E$8)*Planes!$F$8*(1+Hipótesis!$D$11) | R17: ='Proyección de ventas'!R29*MAX(0,Hipótesis!$D$42-Planes!$E$8)*Planes!$F$8*(1+Hipótesis!$D$11) | S17: ='Proyección de ventas'!S29*MAX(0,Hipótesis!$D$42-Planes!$E$8)*Planes!$F$8*(1+Hipótesis!$D$11) | T17: ='Proyección de ventas'!T29*MAX(0,Hipótesis!$D$42-Planes!$E$8)*Planes!$F$8*(1+Hipótesis!$D$11) | U17: ='Proyección de ventas'!U29*MAX(0,Hipótesis!$D$42-Planes!$E$8)*Planes!$F$8*(1+Hipótesis!$D$11) | V17: ='Proyección de ventas'!V29*MAX(0,Hipótesis!$D$42-Planes!$E$8)*Planes!$F$8*(1+Hipótesis!$D$11) | W17: ='Proyección de ventas'!W29*MAX(0,Hipótesis!$D$42-Planes!$E$8)*Planes!$F$8*(1+Hipótesis!$D$11) | ... AA17: ='Proyección de ventas'!AA29*MAX(0,Hipótesis!$D$42-Planes!$E$8)*Planes!$F$8*(1+Hipótesis!$D$11) | AB17: =SUM(P17:AA17) | AC17: ='Proyección de ventas'!AC29*MAX(0,Hipótesis!$E$42-Planes!$E$8)*Planes!$F$8*(1+Hipótesis!$D$11)*(1+Hipótesis!$E$11) | AD17: ='Proyección de ventas'!AD29*MAX(0,Hipótesis!$E$42-Planes!$E$8)*Planes!$F$8*(1+Hipótesis!$D$11)*(1+Hipótesis!$E$11) | AE17: ='Proyección de ventas'!AE29*MAX(0,Hipótesis!$E$42-Planes!$E$8)*Planes!$F$8*(1+Hipótesis!$D$11)*(1+Hipótesis!$E$11) | AF17: ='Proyección de ventas'!AF29*MAX(0,Hipótesis!$E$42-Planes!$E$8)*Planes!$F$8*(1+Hipótesis!$D$11)*(1+Hipótesis!$E$11) | AG17: ='Proyección de ventas'!AG29*MAX(0,Hipótesis!$E$42-Planes!$E$8)*Planes!$F$8*(1+Hipótesis!$D$11)*(1+Hipótesis!$E$11) | AH17: ='Proyección de ventas'!AH29*MAX(0,Hipótesis!$E$42-Planes!$E$8)*Planes!$F$8*(1+Hipótesis!$D$11)*(1+Hipótesis!$E$11) | AI17: ='Proyección de ventas'!AI29*MAX(0,Hipótesis!$E$42-Planes!$E$8)*Planes!$F$8*(1+Hipótesis!$D$11)*(1+Hipótesis!$E$11) | AJ17: ='Proyección de ventas'!AJ29*MAX(0,Hipótesis!$E$42-Planes!$E$8)*Planes!$F$8*(1+Hipótesis!$D$11)*(1+Hipótesis!$E$11) | ... AN17: ='Proyección de ventas'!AN29*MAX(0,Hipótesis!$E$42-Planes!$E$8)*Planes!$F$8*(1+Hipótesis!$D$11)*(1+Hipótesis!$E$11) | AO17: =SUM(AC17:AN17) | AP17: ='Proyección de ventas'!AP29*MAX(0,Hipótesis!$F$42-Planes!$E$8)*Planes!$F$8*(1+Hipótesis!$D$11)*(1+Hipótesis!$E$11)*(1+Hipótesis!$F$11) | AQ17: ='Proyección de ventas'!AQ29*MAX(0,Hipótesis!$F$42-Planes!$E$8)*Planes!$F$8*(1+Hipótesis!$D$11)*(1+Hipótesis!$E$11)*(1+Hipótesis!$F$11) | AR17: ='Proyección de ventas'!AR29*MAX(0,Hipótesis!$F$42-Planes!$E$8)*Planes!$F$8*(1+Hipótesis!$D$11)*(1+Hipótesis!$E$11)*(1+Hipótesis!$F$11) | AS17: ='Proyección de ventas'!AS29*MAX(0,Hipótesis!$F$42-Planes!$E$8)*Planes!$F$8*(1+Hipótesis!$D$11)*(1+Hipótesis!$E$11)*(1+Hipótesis!$F$11) | AT17: ='Proyección de ventas'!AT29*MAX(0,Hipótesis!$F$42-Planes!$E$8)*Planes!$F$8*(1+Hipótesis!$D$11)*(1+Hipótesis!$E$11)*(1+Hipótesis!$F$11) | AU17: ='Proyección de ventas'!AU29*MAX(0,Hipótesis!$F$42-Planes!$E$8)*Planes!$F$8*(1+Hipótesis!$D$11)*(1+Hipótesis!$E$11)*(1+Hipótesis!$F$11) | AV17: ='Proyección de ventas'!AV29*MAX(0,Hipótesis!$F$42-Planes!$E$8)*Planes!$F$8*(1+Hipótesis!$D$11)*(1+Hipótesis!$E$11)*(1+Hipótesis!$F$11) | AW17: ='Proyección de ventas'!AW29*MAX(0,Hipótesis!$F$42-Planes!$E$8)*Planes!$F$8*(1+Hipótesis!$D$11)*(1+Hipótesis!$E$11)*(1+Hipótesis!$F$11) | ... BA17: ='Proyección de ventas'!BA29*MAX(0,Hipótesis!$F$42-Planes!$E$8)*Planes!$F$8*(1+Hipótesis!$D$11)*(1+Hipótesis!$E$11)*(1+Hipótesis!$F$11) | BB17: =SUM(AP17:BA17)
B18: Total de la línea | C18: =C16+C17 | D18: =D16+D17 | E18: =E16+E17 | F18: =F16+F17 | G18: =G16+G17 | H18: =H16+H17 | I18: =I16+I17 | J18: =J16+J17 | ... N18: =N16+N17 | O18: =SUM(C18:N18) | P18: =P16+P17 | Q18: =Q16+Q17 | R18: =R16+R17 | S18: =S16+S17 | T18: =T16+T17 | U18: =U16+U17 | V18: =V16+V17 | W18: =W16+W17 | ... AA18: =AA16+AA17 | AB18: =SUM(P18:AA18) | AC18: =AC16+AC17 | AD18: =AD16+AD17 | AE18: =AE16+AE17 | AF18: =AF16+AF17 | AG18: =AG16+AG17 | AH18: =AH16+AH17 | AI18: =AI16+AI17 | AJ18: =AJ16+AJ17 | ... AN18: =AN16+AN17 | AO18: =SUM(AC18:AN18) | AP18: =AP16+AP17 | AQ18: =AQ16+AQ17 | AR18: =AR16+AR17 | AS18: =AS16+AS17 | AT18: =AT16+AT17 | AU18: =AU16+AU17 | AV18: =AV16+AV17 | AW18: =AW16+AW17 | ... BA18: =BA16+BA17 | BB18: =SUM(AP18:BA18)
B20: Plan Partner
A21: PLAN PARTNER | B21: Ingreso por abono | C21: ='Proyección de ventas'!C33*Planes!$D$9*1 | D21: ='Proyección de ventas'!D33*Planes!$D$9*1 | E21: ='Proyección de ventas'!E33*Planes!$D$9*1 | F21: ='Proyección de ventas'!F33*Planes!$D$9*1 | G21: ='Proyección de ventas'!G33*Planes!$D$9*1 | H21: ='Proyección de ventas'!H33*Planes!$D$9*1 | I21: ='Proyección de ventas'!I33*Planes!$D$9*1 | J21: ='Proyección de ventas'!J33*Planes!$D$9*1 | ... N21: ='Proyección de ventas'!N33*Planes!$D$9*1 | O21: =SUM(C21:N21) | P21: ='Proyección de ventas'!P33*Planes!$D$9*(1+Hipótesis!$D$11) | Q21: ='Proyección de ventas'!Q33*Planes!$D$9*(1+Hipótesis!$D$11) | R21: ='Proyección de ventas'!R33*Planes!$D$9*(1+Hipótesis!$D$11) | S21: ='Proyección de ventas'!S33*Planes!$D$9*(1+Hipótesis!$D$11) | T21: ='Proyección de ventas'!T33*Planes!$D$9*(1+Hipótesis!$D$11) | U21: ='Proyección de ventas'!U33*Planes!$D$9*(1+Hipótesis!$D$11) | V21: ='Proyección de ventas'!V33*Planes!$D$9*(1+Hipótesis!$D$11) | W21: ='Proyección de ventas'!W33*Planes!$D$9*(1+Hipótesis!$D$11) | ... AA21: ='Proyección de ventas'!AA33*Planes!$D$9*(1+Hipótesis!$D$11) | AB21: =SUM(P21:AA21) | AC21: ='Proyección de ventas'!AC33*Planes!$D$9*(1+Hipótesis!$D$11)*(1+Hipótesis!$E$11) | AD21: ='Proyección de ventas'!AD33*Planes!$D$9*(1+Hipótesis!$D$11)*(1+Hipótesis!$E$11) | AE21: ='Proyección de ventas'!AE33*Planes!$D$9*(1+Hipótesis!$D$11)*(1+Hipótesis!$E$11) | AF21: ='Proyección de ventas'!AF33*Planes!$D$9*(1+Hipótesis!$D$11)*(1+Hipótesis!$E$11) | AG21: ='Proyección de ventas'!AG33*Planes!$D$9*(1+Hipótesis!$D$11)*(1+Hipótesis!$E$11) | AH21: ='Proyección de ventas'!AH33*Planes!$D$9*(1+Hipótesis!$D$11)*(1+Hipótesis!$E$11) | AI21: ='Proyección de ventas'!AI33*Planes!$D$9*(1+Hipótesis!$D$11)*(1+Hipótesis!$E$11) | AJ21: ='Proyección de ventas'!AJ33*Planes!$D$9*(1+Hipótesis!$D$11)*(1+Hipótesis!$E$11) | ... AN21: ='Proyección de ventas'!AN33*Planes!$D$9*(1+Hipótesis!$D$11)*(1+Hipótesis!$E$11) | AO21: =SUM(AC21:AN21) | AP21: ='Proyección de ventas'!AP33*Planes!$D$9*(1+Hipótesis!$D$11)*(1+Hipótesis!$E$11)*(1+Hipótesis!$F$11) | AQ21: ='Proyección de ventas'!AQ33*Planes!$D$9*(1+Hipótesis!$D$11)*(1+Hipótesis!$E$11)*(1+Hipótesis!$F$11) | AR21: ='Proyección de ventas'!AR33*Planes!$D$9*(1+Hipótesis!$D$11)*(1+Hipótesis!$E$11)*(1+Hipótesis!$F$11) | AS21: ='Proyección de ventas'!AS33*Planes!$D$9*(1+Hipótesis!$D$11)*(1+Hipótesis!$E$11)*(1+Hipótesis!$F$11) | AT21: ='Proyección de ventas'!AT33*Planes!$D$9*(1+Hipótesis!$D$11)*(1+Hipótesis!$E$11)*(1+Hipótesis!$F$11) | AU21: ='Proyección de ventas'!AU33*Planes!$D$9*(1+Hipótesis!$D$11)*(1+Hipótesis!$E$11)*(1+Hipótesis!$F$11) | AV21: ='Proyección de ventas'!AV33*Planes!$D$9*(1+Hipótesis!$D$11)*(1+Hipótesis!$E$11)*(1+Hipótesis!$F$11) | AW21: ='Proyección de ventas'!AW33*Planes!$D$9*(1+Hipótesis!$D$11)*(1+Hipótesis!$E$11)*(1+Hipótesis!$F$11) | ... BA21: ='Proyección de ventas'!BA33*Planes!$D$9*(1+Hipótesis!$D$11)*(1+Hipótesis!$E$11)*(1+Hipótesis!$F$11) | BB21: =SUM(AP21:BA21)
B22: Ingreso por equipos adicionales | C22: ='Proyección de ventas'!C33*MAX(0,Hipótesis!$C$43-Planes!$E$9)*Planes!$F$9*1 | D22: ='Proyección de ventas'!D33*MAX(0,Hipótesis!$C$43-Planes!$E$9)*Planes!$F$9*1 | E22: ='Proyección de ventas'!E33*MAX(0,Hipótesis!$C$43-Planes!$E$9)*Planes!$F$9*1 | F22: ='Proyección de ventas'!F33*MAX(0,Hipótesis!$C$43-Planes!$E$9)*Planes!$F$9*1 | G22: ='Proyección de ventas'!G33*MAX(0,Hipótesis!$C$43-Planes!$E$9)*Planes!$F$9*1 | H22: ='Proyección de ventas'!H33*MAX(0,Hipótesis!$C$43-Planes!$E$9)*Planes!$F$9*1 | I22: ='Proyección de ventas'!I33*MAX(0,Hipótesis!$C$43-Planes!$E$9)*Planes!$F$9*1 | J22: ='Proyección de ventas'!J33*MAX(0,Hipótesis!$C$43-Planes!$E$9)*Planes!$F$9*1 | ... N22: ='Proyección de ventas'!N33*MAX(0,Hipótesis!$C$43-Planes!$E$9)*Planes!$F$9*1 | O22: =SUM(C22:N22) | P22: ='Proyección de ventas'!P33*MAX(0,Hipótesis!$D$43-Planes!$E$9)*Planes!$F$9*(1+Hipótesis!$D$11) | Q22: ='Proyección de ventas'!Q33*MAX(0,Hipótesis!$D$43-Planes!$E$9)*Planes!$F$9*(1+Hipótesis!$D$11) | R22: ='Proyección de ventas'!R33*MAX(0,Hipótesis!$D$43-Planes!$E$9)*Planes!$F$9*(1+Hipótesis!$D$11) | S22: ='Proyección de ventas'!S33*MAX(0,Hipótesis!$D$43-Planes!$E$9)*Planes!$F$9*(1+Hipótesis!$D$11) | T22: ='Proyección de ventas'!T33*MAX(0,Hipótesis!$D$43-Planes!$E$9)*Planes!$F$9*(1+Hipótesis!$D$11) | U22: ='Proyección de ventas'!U33*MAX(0,Hipótesis!$D$43-Planes!$E$9)*Planes!$F$9*(1+Hipótesis!$D$11) | V22: ='Proyección de ventas'!V33*MAX(0,Hipótesis!$D$43-Planes!$E$9)*Planes!$F$9*(1+Hipótesis!$D$11) | W22: ='Proyección de ventas'!W33*MAX(0,Hipótesis!$D$43-Planes!$E$9)*Planes!$F$9*(1+Hipótesis!$D$11) | ... AA22: ='Proyección de ventas'!AA33*MAX(0,Hipótesis!$D$43-Planes!$E$9)*Planes!$F$9*(1+Hipótesis!$D$11) | AB22: =SUM(P22:AA22) | AC22: ='Proyección de ventas'!AC33*MAX(0,Hipótesis!$E$43-Planes!$E$9)*Planes!$F$9*(1+Hipótesis!$D$11)*(1+Hipótesis!$E$11) | AD22: ='Proyección de ventas'!AD33*MAX(0,Hipótesis!$E$43-Planes!$E$9)*Planes!$F$9*(1+Hipótesis!$D$11)*(1+Hipótesis!$E$11) | AE22: ='Proyección de ventas'!AE33*MAX(0,Hipótesis!$E$43-Planes!$E$9)*Planes!$F$9*(1+Hipótesis!$D$11)*(1+Hipótesis!$E$11) | AF22: ='Proyección de ventas'!AF33*MAX(0,Hipótesis!$E$43-Planes!$E$9)*Planes!$F$9*(1+Hipótesis!$D$11)*(1+Hipótesis!$E$11) | AG22: ='Proyección de ventas'!AG33*MAX(0,Hipótesis!$E$43-Planes!$E$9)*Planes!$F$9*(1+Hipótesis!$D$11)*(1+Hipótesis!$E$11) | AH22: ='Proyección de ventas'!AH33*MAX(0,Hipótesis!$E$43-Planes!$E$9)*Planes!$F$9*(1+Hipótesis!$D$11)*(1+Hipótesis!$E$11) | AI22: ='Proyección de ventas'!AI33*MAX(0,Hipótesis!$E$43-Planes!$E$9)*Planes!$F$9*(1+Hipótesis!$D$11)*(1+Hipótesis!$E$11) | AJ22: ='Proyección de ventas'!AJ33*MAX(0,Hipótesis!$E$43-Planes!$E$9)*Planes!$F$9*(1+Hipótesis!$D$11)*(1+Hipótesis!$E$11) | ... AN22: ='Proyección de ventas'!AN33*MAX(0,Hipótesis!$E$43-Planes!$E$9)*Planes!$F$9*(1+Hipótesis!$D$11)*(1+Hipótesis!$E$11) | AO22: =SUM(AC22:AN22) | AP22: ='Proyección de ventas'!AP33*MAX(0,Hipótesis!$F$43-Planes!$E$9)*Planes!$F$9*(1+Hipótesis!$D$11)*(1+Hipótesis!$E$11)*(1+Hipótesis!$F$11) | AQ22: ='Proyección de ventas'!AQ33*MAX(0,Hipótesis!$F$43-Planes!$E$9)*Planes!$F$9*(1+Hipótesis!$D$11)*(1+Hipótesis!$E$11)*(1+Hipótesis!$F$11) | AR22: ='Proyección de ventas'!AR33*MAX(0,Hipótesis!$F$43-Planes!$E$9)*Planes!$F$9*(1+Hipótesis!$D$11)*(1+Hipótesis!$E$11)*(1+Hipótesis!$F$11) | AS22: ='Proyección de ventas'!AS33*MAX(0,Hipótesis!$F$43-Planes!$E$9)*Planes!$F$9*(1+Hipótesis!$D$11)*(1+Hipótesis!$E$11)*(1+Hipótesis!$F$11) | AT22: ='Proyección de ventas'!AT33*MAX(0,Hipótesis!$F$43-Planes!$E$9)*Planes!$F$9*(1+Hipótesis!$D$11)*(1+Hipótesis!$E$11)*(1+Hipótesis!$F$11) | AU22: ='Proyección de ventas'!AU33*MAX(0,Hipótesis!$F$43-Planes!$E$9)*Planes!$F$9*(1+Hipótesis!$D$11)*(1+Hipótesis!$E$11)*(1+Hipótesis!$F$11) | AV22: ='Proyección de ventas'!AV33*MAX(0,Hipótesis!$F$43-Planes!$E$9)*Planes!$F$9*(1+Hipótesis!$D$11)*(1+Hipótesis!$E$11)*(1+Hipótesis!$F$11) | AW22: ='Proyección de ventas'!AW33*MAX(0,Hipótesis!$F$43-Planes!$E$9)*Planes!$F$9*(1+Hipótesis!$D$11)*(1+Hipótesis!$E$11)*(1+Hipótesis!$F$11) | ... BA22: ='Proyección de ventas'!BA33*MAX(0,Hipótesis!$F$43-Planes!$E$9)*Planes!$F$9*(1+Hipótesis!$D$11)*(1+Hipótesis!$E$11)*(1+Hipótesis!$F$11) | BB22: =SUM(AP22:BA22)
B23: Total de la línea | C23: =C21+C22 | D23: =D21+D22 | E23: =E21+E22 | F23: =F21+F22 | G23: =G21+G22 | H23: =H21+H22 | I23: =I21+I22 | J23: =J21+J22 | ... N23: =N21+N22 | O23: =SUM(C23:N23) | P23: =P21+P22 | Q23: =Q21+Q22 | R23: =R21+R22 | S23: =S21+S22 | T23: =T21+T22 | U23: =U21+U22 | V23: =V21+V22 | W23: =W21+W22 | ... AA23: =AA21+AA22 | AB23: =SUM(P23:AA23) | AC23: =AC21+AC22 | AD23: =AD21+AD22 | AE23: =AE21+AE22 | AF23: =AF21+AF22 | AG23: =AG21+AG22 | AH23: =AH21+AH22 | AI23: =AI21+AI22 | AJ23: =AJ21+AJ22 | ... AN23: =AN21+AN22 | AO23: =SUM(AC23:AN23) | AP23: =AP21+AP22 | AQ23: =AQ21+AQ22 | AR23: =AR21+AR22 | AS23: =AS21+AS22 | AT23: =AT21+AT22 | AU23: =AU21+AU22 | AV23: =AV21+AV22 | AW23: =AW21+AW22 | ... BA23: =BA21+BA22 | BB23: =SUM(AP23:BA23)
B25: Total de ingresos
A26: TOTAL | B26: Ingresos del mes | C26: =C13+C18+C23 | D26: =D13+D18+D23 | E26: =E13+E18+E23 | F26: =F13+F18+F23 | G26: =G13+G18+G23 | H26: =H13+H18+H23 | I26: =I13+I18+I23 | J26: =J13+J18+J23 | ... N26: =N13+N18+N23 | O26: =SUM(C26:N26) | P26: =P13+P18+P23 | Q26: =Q13+Q18+Q23 | R26: =R13+R18+R23 | S26: =S13+S18+S23 | T26: =T13+T18+T23 | U26: =U13+U18+U23 | V26: =V13+V18+V23 | W26: =W13+W18+W23 | ... AA26: =AA13+AA18+AA23 | AB26: =SUM(P26:AA26) | AC26: =AC13+AC18+AC23 | AD26: =AD13+AD18+AD23 | AE26: =AE13+AE18+AE23 | AF26: =AF13+AF18+AF23 | AG26: =AG13+AG18+AG23 | AH26: =AH13+AH18+AH23 | AI26: =AI13+AI18+AI23 | AJ26: =AJ13+AJ18+AJ23 | ... AN26: =AN13+AN18+AN23 | AO26: =SUM(AC26:AN26) | AP26: =AP13+AP18+AP23 | AQ26: =AQ13+AQ18+AQ23 | AR26: =AR13+AR18+AR23 | AS26: =AS13+AS18+AS23 | AT26: =AT13+AT18+AT23 | AU26: =AU13+AU18+AU23 | AV26: =AV13+AV18+AV23 | AW26: =AW13+AW18+AW23 | ... BA26: =BA13+BA18+BA23 | BB26: =SUM(AP26:BA26)
B27: Ingreso promedio por cliente | C27: =IFERROR(C26/'Proyección de ventas'!C36,0) | D27: =IFERROR(D26/'Proyección de ventas'!D36,0) | E27: =IFERROR(E26/'Proyección de ventas'!E36,0) | F27: =IFERROR(F26/'Proyección de ventas'!F36,0) | G27: =IFERROR(G26/'Proyección de ventas'!G36,0) | H27: =IFERROR(H26/'Proyección de ventas'!H36,0) | I27: =IFERROR(I26/'Proyección de ventas'!I36,0) | J27: =IFERROR(J26/'Proyección de ventas'!J36,0) | ... N27: =IFERROR(N26/'Proyección de ventas'!N36,0) | P27: =IFERROR(P26/'Proyección de ventas'!P36,0) | Q27: =IFERROR(Q26/'Proyección de ventas'!Q36,0) | R27: =IFERROR(R26/'Proyección de ventas'!R36,0) | S27: =IFERROR(S26/'Proyección de ventas'!S36,0) | T27: =IFERROR(T26/'Proyección de ventas'!T36,0) | U27: =IFERROR(U26/'Proyección de ventas'!U36,0) | V27: =IFERROR(V26/'Proyección de ventas'!V36,0) | W27: =IFERROR(W26/'Proyección de ventas'!W36,0) | ... AA27: =IFERROR(AA26/'Proyección de ventas'!AA36,0) | AC27: =IFERROR(AC26/'Proyección de ventas'!AC36,0) | AD27: =IFERROR(AD26/'Proyección de ventas'!AD36,0) | AE27: =IFERROR(AE26/'Proyección de ventas'!AE36,0) | AF27: =IFERROR(AF26/'Proyección de ventas'!AF36,0) | AG27: =IFERROR(AG26/'Proyección de ventas'!AG36,0) | AH27: =IFERROR(AH26/'Proyección de ventas'!AH36,0) | AI27: =IFERROR(AI26/'Proyección de ventas'!AI36,0) | AJ27: =IFERROR(AJ26/'Proyección de ventas'!AJ36,0) | ... AN27: =IFERROR(AN26/'Proyección de ventas'!AN36,0) | AP27: =IFERROR(AP26/'Proyección de ventas'!AP36,0) | AQ27: =IFERROR(AQ26/'Proyección de ventas'!AQ36,0) | AR27: =IFERROR(AR26/'Proyección de ventas'!AR36,0) | AS27: =IFERROR(AS26/'Proyección de ventas'!AS36,0) | AT27: =IFERROR(AT26/'Proyección de ventas'!AT36,0) | AU27: =IFERROR(AU26/'Proyección de ventas'!AU36,0) | AV27: =IFERROR(AV26/'Proyección de ventas'!AV36,0) | AW27: =IFERROR(AW26/'Proyección de ventas'!AW36,0) | ... BA27: =IFERROR(BA26/'Proyección de ventas'!BA36,0)

Sheet Modelo de Egresos
A1: « Inicio
B2: MODELO DE EGRESOS
B3: Consolidado de las tres estructuras de costo. Cada una se carga en su propia hoja y acá sólo se suman.
C7: 2027 | P7: 2028 | AC7: 2029 | AP7: 2030
C8: Ene | D8: Feb | E8: Mar | F8: Abr | G8: May | H8: Jun | I8: Jul | J8: Ago | K8: Sep | L8: Oct | M8: Nov | N8: Dic | O8: Total 2027 | P8: Ene | Q8: Feb | R8: Mar | S8: Abr | T8: May | U8: Jun | V8: Jul | W8: Ago | X8: Sep | Y8: Oct | Z8: Nov | AA8: Dic | AB8: Total 2028 | AC8: Ene | AD8: Feb | AE8: Mar | AF8: Abr | AG8: May | AH8: Jun | AI8: Jul | AJ8: Ago | AK8: Sep | AL8: Oct | AM8: Nov | AN8: Dic | AO8: Total 2029 | AP8: Ene | AQ8: Feb | AR8: Mar | AS8: Abr | AT8: May | AU8: Jun | AV8: Jul | AW8: Ago | AX8: Sep | AY8: Oct | AZ8: Nov | BA8: Dic | BB8: Total 2030
A10: EGRESOS | B10: Costos fijos | C10: ='Costos Fijos'!C27 | D10: ='Costos Fijos'!D27 | E10: ='Costos Fijos'!E27 | F10: ='Costos Fijos'!F27 | G10: ='Costos Fijos'!G27 | H10: ='Costos Fijos'!H27 | I10: ='Costos Fijos'!I27 | J10: ='Costos Fijos'!J27 | ... N10: ='Costos Fijos'!N27 | O10: =SUM(C10:N10) | P10: ='Costos Fijos'!P27 | Q10: ='Costos Fijos'!Q27 | R10: ='Costos Fijos'!R27 | S10: ='Costos Fijos'!S27 | T10: ='Costos Fijos'!T27 | U10: ='Costos Fijos'!U27 | V10: ='Costos Fijos'!V27 | W10: ='Costos Fijos'!W27 | ... AA10: ='Costos Fijos'!AA27 | AB10: =SUM(P10:AA10) | AC10: ='Costos Fijos'!AC27 | AD10: ='Costos Fijos'!AD27 | AE10: ='Costos Fijos'!AE27 | AF10: ='Costos Fijos'!AF27 | AG10: ='Costos Fijos'!AG27 | AH10: ='Costos Fijos'!AH27 | AI10: ='Costos Fijos'!AI27 | AJ10: ='Costos Fijos'!AJ27 | ... AN10: ='Costos Fijos'!AN27 | AO10: =SUM(AC10:AN10) | AP10: ='Costos Fijos'!AP27 | AQ10: ='Costos Fijos'!AQ27 | AR10: ='Costos Fijos'!AR27 | AS10: ='Costos Fijos'!AS27 | AT10: ='Costos Fijos'!AT27 | AU10: ='Costos Fijos'!AU27 | AV10: ='Costos Fijos'!AV27 | AW10: ='Costos Fijos'!AW27 | ... BA10: ='Costos Fijos'!BA27 | BB10: =SUM(AP10:BA10)
B11: Costos variables | C11: ='Costos Variables'!C14 | D11: ='Costos Variables'!D14 | E11: ='Costos Variables'!E14 | F11: ='Costos Variables'!F14 | G11: ='Costos Variables'!G14 | H11: ='Costos Variables'!H14 | I11: ='Costos Variables'!I14 | J11: ='Costos Variables'!J14 | ... N11: ='Costos Variables'!N14 | O11: =SUM(C11:N11) | P11: ='Costos Variables'!P14 | Q11: ='Costos Variables'!Q14 | R11: ='Costos Variables'!R14 | S11: ='Costos Variables'!S14 | T11: ='Costos Variables'!T14 | U11: ='Costos Variables'!U14 | V11: ='Costos Variables'!V14 | W11: ='Costos Variables'!W14 | ... AA11: ='Costos Variables'!AA14 | AB11: =SUM(P11:AA11) | AC11: ='Costos Variables'!AC14 | AD11: ='Costos Variables'!AD14 | AE11: ='Costos Variables'!AE14 | AF11: ='Costos Variables'!AF14 | AG11: ='Costos Variables'!AG14 | AH11: ='Costos Variables'!AH14 | AI11: ='Costos Variables'!AI14 | AJ11: ='Costos Variables'!AJ14 | ... AN11: ='Costos Variables'!AN14 | AO11: =SUM(AC11:AN11) | AP11: ='Costos Variables'!AP14 | AQ11: ='Costos Variables'!AQ14 | AR11: ='Costos Variables'!AR14 | AS11: ='Costos Variables'!AS14 | AT11: ='Costos Variables'!AT14 | AU11: ='Costos Variables'!AU14 | AV11: ='Costos Variables'!AV14 | AW11: ='Costos Variables'!AW14 | ... BA11: ='Costos Variables'!BA14 | BB11: =SUM(AP11:BA11)
B12: Costos de RRHH | C12: ='RRHH'!C39 | D12: ='RRHH'!D39 | E12: ='RRHH'!E39 | F12: ='RRHH'!F39 | G12: ='RRHH'!G39 | H12: ='RRHH'!H39 | I12: ='RRHH'!I39 | J12: ='RRHH'!J39 | ... N12: ='RRHH'!N39 | O12: =SUM(C12:N12) | P12: ='RRHH'!P39 | Q12: ='RRHH'!Q39 | R12: ='RRHH'!R39 | S12: ='RRHH'!S39 | T12: ='RRHH'!T39 | U12: ='RRHH'!U39 | V12: ='RRHH'!V39 | W12: ='RRHH'!W39 | ... AA12: ='RRHH'!AA39 | AB12: =SUM(P12:AA12) | AC12: ='RRHH'!AC39 | AD12: ='RRHH'!AD39 | AE12: ='RRHH'!AE39 | AF12: ='RRHH'!AF39 | AG12: ='RRHH'!AG39 | AH12: ='RRHH'!AH39 | AI12: ='RRHH'!AI39 | AJ12: ='RRHH'!AJ39 | ... AN12: ='RRHH'!AN39 | AO12: =SUM(AC12:AN12) | AP12: ='RRHH'!AP39 | AQ12: ='RRHH'!AQ39 | AR12: ='RRHH'!AR39 | AS12: ='RRHH'!AS39 | AT12: ='RRHH'!AT39 | AU12: ='RRHH'!AU39 | AV12: ='RRHH'!AV39 | AW12: ='RRHH'!AW39 | ... BA12: ='RRHH'!BA39 | BB12: =SUM(AP12:BA12)
B13: Total de egresos | C13: =SUM(C10:C12) | D13: =SUM(D10:D12) | E13: =SUM(E10:E12) | F13: =SUM(F10:F12) | G13: =SUM(G10:G12) | H13: =SUM(H10:H12) | I13: =SUM(I10:I12) | J13: =SUM(J10:J12) | ... N13: =SUM(N10:N12) | O13: =SUM(C13:N13) | P13: =SUM(P10:P12) | Q13: =SUM(Q10:Q12) | R13: =SUM(R10:R12) | S13: =SUM(S10:S12) | T13: =SUM(T10:T12) | U13: =SUM(U10:U12) | V13: =SUM(V10:V12) | W13: =SUM(W10:W12) | ... AA13: =SUM(AA10:AA12) | AB13: =SUM(P13:AA13) | AC13: =SUM(AC10:AC12) | AD13: =SUM(AD10:AD12) | AE13: =SUM(AE10:AE12) | AF13: =SUM(AF10:AF12) | AG13: =SUM(AG10:AG12) | AH13: =SUM(AH10:AH12) | AI13: =SUM(AI10:AI12) | AJ13: =SUM(AJ10:AJ12) | ... AN13: =SUM(AN10:AN12) | AO13: =SUM(AC13:AN13) | AP13: =SUM(AP10:AP12) | AQ13: =SUM(AQ10:AQ12) | AR13: =SUM(AR10:AR12) | AS13: =SUM(AS10:AS12) | AT13: =SUM(AT10:AT12) | AU13: =SUM(AU10:AU12) | AV13: =SUM(AV10:AV12) | AW13: =SUM(AW10:AW12) | ... BA13: =SUM(BA10:BA12) | BB13: =SUM(AP13:BA13)
B15: Margen
A16: MARGEN | B16: Resultado operativo (ingresos − egresos) | C16: ='Modelo de ingresos'!C26-C13 | D16: ='Modelo de ingresos'!D26-D13 | E16: ='Modelo de ingresos'!E26-E13 | F16: ='Modelo de ingresos'!F26-F13 | G16: ='Modelo de ingresos'!G26-G13 | H16: ='Modelo de ingresos'!H26-H13 | I16: ='Modelo de ingresos'!I26-I13 | J16: ='Modelo de ingresos'!J26-J13 | ... N16: ='Modelo de ingresos'!N26-N13 | O16: =SUM(C16:N16) | P16: ='Modelo de ingresos'!P26-P13 | Q16: ='Modelo de ingresos'!Q26-Q13 | R16: ='Modelo de ingresos'!R26-R13 | S16: ='Modelo de ingresos'!S26-S13 | T16: ='Modelo de ingresos'!T26-T13 | U16: ='Modelo de ingresos'!U26-U13 | V16: ='Modelo de ingresos'!V26-V13 | W16: ='Modelo de ingresos'!W26-W13 | ... AA16: ='Modelo de ingresos'!AA26-AA13 | AB16: =SUM(P16:AA16) | AC16: ='Modelo de ingresos'!AC26-AC13 | AD16: ='Modelo de ingresos'!AD26-AD13 | AE16: ='Modelo de ingresos'!AE26-AE13 | AF16: ='Modelo de ingresos'!AF26-AF13 | AG16: ='Modelo de ingresos'!AG26-AG13 | AH16: ='Modelo de ingresos'!AH26-AH13 | AI16: ='Modelo de ingresos'!AI26-AI13 | AJ16: ='Modelo de ingresos'!AJ26-AJ13 | ... AN16: ='Modelo de ingresos'!AN26-AN13 | AO16: =SUM(AC16:AN16) | AP16: ='Modelo de ingresos'!AP26-AP13 | AQ16: ='Modelo de ingresos'!AQ26-AQ13 | AR16: ='Modelo de ingresos'!AR26-AR13 | AS16: ='Modelo de ingresos'!AS26-AS13 | AT16: ='Modelo de ingresos'!AT26-AT13 | AU16: ='Modelo de ingresos'!AU26-AU13 | AV16: ='Modelo de ingresos'!AV26-AV13 | AW16: ='Modelo de ingresos'!AW26-AW13 | ... BA16: ='Modelo de ingresos'!BA26-BA13 | BB16: =SUM(AP16:BA16)
B17: Margen sobre ingresos | C17: =IFERROR(C16/'Modelo de ingresos'!C26,0) | D17: =IFERROR(D16/'Modelo de ingresos'!D26,0) | E17: =IFERROR(E16/'Modelo de ingresos'!E26,0) | F17: =IFERROR(F16/'Modelo de ingresos'!F26,0) | G17: =IFERROR(G16/'Modelo de ingresos'!G26,0) | H17: =IFERROR(H16/'Modelo de ingresos'!H26,0) | I17: =IFERROR(I16/'Modelo de ingresos'!I26,0) | J17: =IFERROR(J16/'Modelo de ingresos'!J26,0) | ... N17: =IFERROR(N16/'Modelo de ingresos'!N26,0) | P17: =IFERROR(P16/'Modelo de ingresos'!P26,0) | Q17: =IFERROR(Q16/'Modelo de ingresos'!Q26,0) | R17: =IFERROR(R16/'Modelo de ingresos'!R26,0) | S17: =IFERROR(S16/'Modelo de ingresos'!S26,0) | T17: =IFERROR(T16/'Modelo de ingresos'!T26,0) | U17: =IFERROR(U16/'Modelo de ingresos'!U26,0) | V17: =IFERROR(V16/'Modelo de ingresos'!V26,0) | W17: =IFERROR(W16/'Modelo de ingresos'!W26,0) | ... AA17: =IFERROR(AA16/'Modelo de ingresos'!AA26,0) | AC17: =IFERROR(AC16/'Modelo de ingresos'!AC26,0) | AD17: =IFERROR(AD16/'Modelo de ingresos'!AD26,0) | AE17: =IFERROR(AE16/'Modelo de ingresos'!AE26,0) | AF17: =IFERROR(AF16/'Modelo de ingresos'!AF26,0) | AG17: =IFERROR(AG16/'Modelo de ingresos'!AG26,0) | AH17: =IFERROR(AH16/'Modelo de ingresos'!AH26,0) | AI17: =IFERROR(AI16/'Modelo de ingresos'!AI26,0) | AJ17: =IFERROR(AJ16/'Modelo de ingresos'!AJ26,0) | ... AN17: =IFERROR(AN16/'Modelo de ingresos'!AN26,0) | AP17: =IFERROR(AP16/'Modelo de ingresos'!AP26,0) | AQ17: =IFERROR(AQ16/'Modelo de ingresos'!AQ26,0) | AR17: =IFERROR(AR16/'Modelo de ingresos'!AR26,0) | AS17: =IFERROR(AS16/'Modelo de ingresos'!AS26,0) | AT17: =IFERROR(AT16/'Modelo de ingresos'!AT26,0) | AU17: =IFERROR(AU16/'Modelo de ingresos'!AU26,0) | AV17: =IFERROR(AV16/'Modelo de ingresos'!AV26,0) | AW17: =IFERROR(AW16/'Modelo de ingresos'!AW26,0) | ... BA17: =IFERROR(BA16/'Modelo de ingresos'!BA26,0)

Sheet Costos Fijos
A1: « Inicio
B2: COSTOS FIJOS
B3: No dependen del volumen de clientes. El importe mensual se carga por año y dentro del año se ajusta por el supuesto de inflación.
C7: 2027 | P7: 2028 | AC7: 2029 | AP7: 2030
C8: Ene | D8: Feb | E8: Mar | F8: Abr | G8: May | H8: Jun | I8: Jul | J8: Ago | K8: Sep | L8: Oct | M8: Nov | N8: Dic | O8: Total 2027 | P8: Ene | Q8: Feb | R8: Mar | S8: Abr | T8: May | U8: Jun | V8: Jul | W8: Ago | X8: Sep | Y8: Oct | Z8: Nov | AA8: Dic | AB8: Total 2028 | AC8: Ene | AD8: Feb | AE8: Mar | AF8: Abr | AG8: May | AH8: Jun | AI8: Jul | AJ8: Ago | AK8: Sep | AL8: Oct | AM8: Nov | AN8: Dic | AO8: Total 2029 | AP8: Ene | AQ8: Feb | AR8: Mar | AS8: Abr | AT8: May | AU8: Jun | AV8: Jul | AW8: Ago | AX8: Sep | AY8: Oct | AZ8: Nov | BA8: Dic | BB8: Total 2030
B10: Importe mensual por año (celdas de entrada)
C11: 2027 | D11: 2028 | E11: 2029 | F11: 2030
A12: Infraestructura | B12: Infraestructura en la nube (base) | C12: 120000 | D12: 200000 | E12: 320000 | F12: 430000
A13: Infraestructura | B13: Herramientas y licencias de desarrollo | C13: 40000 | D13: 60000 | E13: 90000 | F13: 120000
A14: Comercial | B14: Marketing y contenidos | C14: 175000 | D14: 260000 | E14: 340000 | F14: 420000
A15: Administración | B15: Estudio contable y legales | C15: 105000 | D15: 130000 | E15: 170000 | F15: 210000
A16: Operación | B16: Espacio de trabajo, internet y telefonía | C16: 60000 | D16: 90000 | E16: 140000 | F16: 190000
A17: Operación | B17: Otros gastos operativos | C17: 40000 | D17: 60000 | E17: 90000 | F17: 120000
B18: Total mensual | C18: =SUM(C12:C17) | D18: =SUM(D12:D17) | E18: =SUM(E12:E17) | F18: =SUM(F12:F17)
B20: Desarrollo mensual
A21: Infraestructura | B21: Infraestructura en la nube (base) | C21: =$C$12 | D21: =$C$12 | E21: =$C$12 | F21: =$C$12 | G21: =$C$12 | H21: =$C$12 | I21: =$C$12 | J21: =$C$12 | ... N21: =$C$12 | O21: =SUM(C21:N21) | P21: =$D$12 | Q21: =$D$12 | R21: =$D$12 | S21: =$D$12 | T21: =$D$12 | U21: =$D$12 | V21: =$D$12 | W21: =$D$12 | ... AA21: =$D$12 | AB21: =SUM(P21:AA21) | AC21: =$E$12 | AD21: =$E$12 | AE21: =$E$12 | AF21: =$E$12 | AG21: =$E$12 | AH21: =$E$12 | AI21: =$E$12 | AJ21: =$E$12 | ... AN21: =$E$12 | AO21: =SUM(AC21:AN21) | AP21: =$F$12 | AQ21: =$F$12 | AR21: =$F$12 | AS21: =$F$12 | AT21: =$F$12 | AU21: =$F$12 | AV21: =$F$12 | AW21: =$F$12 | ... BA21: =$F$12 | BB21: =SUM(AP21:BA21)
A22: Infraestructura | B22: Herramientas y licencias de desarrollo | C22: =$C$13 | D22: =$C$13 | E22: =$C$13 | F22: =$C$13 | G22: =$C$13 | H22: =$C$13 | I22: =$C$13 | J22: =$C$13 | ... N22: =$C$13 | O22: =SUM(C22:N22) | P22: =$D$13 | Q22: =$D$13 | R22: =$D$13 | S22: =$D$13 | T22: =$D$13 | U22: =$D$13 | V22: =$D$13 | W22: =$D$13 | ... AA22: =$D$13 | AB22: =SUM(P22:AA22) | AC22: =$E$13 | AD22: =$E$13 | AE22: =$E$13 | AF22: =$E$13 | AG22: =$E$13 | AH22: =$E$13 | AI22: =$E$13 | AJ22: =$E$13 | ... AN22: =$E$13 | AO22: =SUM(AC22:AN22) | AP22: =$F$13 | AQ22: =$F$13 | AR22: =$F$13 | AS22: =$F$13 | AT22: =$F$13 | AU22: =$F$13 | AV22: =$F$13 | AW22: =$F$13 | ... BA22: =$F$13 | BB22: =SUM(AP22:BA22)
A23: Comercial | B23: Marketing y contenidos | C23: =$C$14 | D23: =$C$14 | E23: =$C$14 | F23: =$C$14 | G23: =$C$14 | H23: =$C$14 | I23: =$C$14 | J23: =$C$14 | ... N23: =$C$14 | O23: =SUM(C23:N23) | P23: =$D$14 | Q23: =$D$14 | R23: =$D$14 | S23: =$D$14 | T23: =$D$14 | U23: =$D$14 | V23: =$D$14 | W23: =$D$14 | ... AA23: =$D$14 | AB23: =SUM(P23:AA23) | AC23: =$E$14 | AD23: =$E$14 | AE23: =$E$14 | AF23: =$E$14 | AG23: =$E$14 | AH23: =$E$14 | AI23: =$E$14 | AJ23: =$E$14 | ... AN23: =$E$14 | AO23: =SUM(AC23:AN23) | AP23: =$F$14 | AQ23: =$F$14 | AR23: =$F$14 | AS23: =$F$14 | AT23: =$F$14 | AU23: =$F$14 | AV23: =$F$14 | AW23: =$F$14 | ... BA23: =$F$14 | BB23: =SUM(AP23:BA23)
A24: Administración | B24: Estudio contable y legales | C24: =$C$15 | D24: =$C$15 | E24: =$C$15 | F24: =$C$15 | G24: =$C$15 | H24: =$C$15 | I24: =$C$15 | J24: =$C$15 | ... N24: =$C$15 | O24: =SUM(C24:N24) | P24: =$D$15 | Q24: =$D$15 | R24: =$D$15 | S24: =$D$15 | T24: =$D$15 | U24: =$D$15 | V24: =$D$15 | W24: =$D$15 | ... AA24: =$D$15 | AB24: =SUM(P24:AA24) | AC24: =$E$15 | AD24: =$E$15 | AE24: =$E$15 | AF24: =$E$15 | AG24: =$E$15 | AH24: =$E$15 | AI24: =$E$15 | AJ24: =$E$15 | ... AN24: =$E$15 | AO24: =SUM(AC24:AN24) | AP24: =$F$15 | AQ24: =$F$15 | AR24: =$F$15 | AS24: =$F$15 | AT24: =$F$15 | AU24: =$F$15 | AV24: =$F$15 | AW24: =$F$15 | ... BA24: =$F$15 | BB24: =SUM(AP24:BA24)
A25: Operación | B25: Espacio de trabajo, internet y telefonía | C25: =$C$16 | D25: =$C$16 | E25: =$C$16 | F25: =$C$16 | G25: =$C$16 | H25: =$C$16 | I25: =$C$16 | J25: =$C$16 | ... N25: =$C$16 | O25: =SUM(C25:N25) | P25: =$D$16 | Q25: =$D$16 | R25: =$D$16 | S25: =$D$16 | T25: =$D$16 | U25: =$D$16 | V25: =$D$16 | W25: =$D$16 | ... AA25: =$D$16 | AB25: =SUM(P25:AA25) | AC25: =$E$16 | AD25: =$E$16 | AE25: =$E$16 | AF25: =$E$16 | AG25: =$E$16 | AH25: =$E$16 | AI25: =$E$16 | AJ25: =$E$16 | ... AN25: =$E$16 | AO25: =SUM(AC25:AN25) | AP25: =$F$16 | AQ25: =$F$16 | AR25: =$F$16 | AS25: =$F$16 | AT25: =$F$16 | AU25: =$F$16 | AV25: =$F$16 | AW25: =$F$16 | ... BA25: =$F$16 | BB25: =SUM(AP25:BA25)
A26: Operación | B26: Otros gastos operativos | C26: =$C$17 | D26: =$C$17 | E26: =$C$17 | F26: =$C$17 | G26: =$C$17 | H26: =$C$17 | I26: =$C$17 | J26: =$C$17 | ... N26: =$C$17 | O26: =SUM(C26:N26) | P26: =$D$17 | Q26: =$D$17 | R26: =$D$17 | S26: =$D$17 | T26: =$D$17 | U26: =$D$17 | V26: =$D$17 | W26: =$D$17 | ... AA26: =$D$17 | AB26: =SUM(P26:AA26) | AC26: =$E$17 | AD26: =$E$17 | AE26: =$E$17 | AF26: =$E$17 | AG26: =$E$17 | AH26: =$E$17 | AI26: =$E$17 | AJ26: =$E$17 | ... AN26: =$E$17 | AO26: =SUM(AC26:AN26) | AP26: =$F$17 | AQ26: =$F$17 | AR26: =$F$17 | AS26: =$F$17 | AT26: =$F$17 | AU26: =$F$17 | AV26: =$F$17 | AW26: =$F$17 | ... BA26: =$F$17 | BB26: =SUM(AP26:BA26)
A27: COSTOS FIJOS | B27: Total de costos fijos | C27: =SUM(C21:C26) | D27: =SUM(D21:D26) | E27: =SUM(E21:E26) | F27: =SUM(F21:F26) | G27: =SUM(G21:G26) | H27: =SUM(H21:H26) | I27: =SUM(I21:I26) | J27: =SUM(J21:J26) | ... N27: =SUM(N21:N26) | O27: =SUM(C27:N27) | P27: =SUM(P21:P26) | Q27: =SUM(Q21:Q26) | R27: =SUM(R21:R26) | S27: =SUM(S21:S26) | T27: =SUM(T21:T26) | U27: =SUM(U21:U26) | V27: =SUM(V21:V26) | W27: =SUM(W21:W26) | ... AA27: =SUM(AA21:AA26) | AB27: =SUM(P27:AA27) | AC27: =SUM(AC21:AC26) | AD27: =SUM(AD21:AD26) | AE27: =SUM(AE21:AE26) | AF27: =SUM(AF21:AF26) | AG27: =SUM(AG21:AG26) | AH27: =SUM(AH21:AH26) | AI27: =SUM(AI21:AI26) | AJ27: =SUM(AJ21:AJ26) | ... AN27: =SUM(AN21:AN26) | AO27: =SUM(AC27:AN27) | AP27: =SUM(AP21:AP26) | AQ27: =SUM(AQ21:AQ26) | AR27: =SUM(AR21:AR26) | AS27: =SUM(AS21:AS26) | AT27: =SUM(AT21:AT26) | AU27: =SUM(AU21:AU26) | AV27: =SUM(AV21:AV26) | AW27: =SUM(AW21:AW26) | ... BA27: =SUM(BA21:BA26) | BB27: =SUM(AP27:BA27)

Sheet Costos Variables
A1: « Inicio
B2: COSTOS VARIABLES
B3: Se mueven con cada cliente. Los importes unitarios salen de la sección 6.5.3 del documento y se toman de la hoja Planes, para que no haya dos versiones del mismo número.
C7: 2027 | P7: 2028 | AC7: 2029 | AP7: 2030
C8: Ene | D8: Feb | E8: Mar | F8: Abr | G8: May | H8: Jun | I8: Jul | J8: Ago | K8: Sep | L8: Oct | M8: Nov | N8: Dic | O8: Total 2027 | P8: Ene | Q8: Feb | R8: Mar | S8: Abr | T8: May | U8: Jun | V8: Jul | W8: Ago | X8: Sep | Y8: Oct | Z8: Nov | AA8: Dic | AB8: Total 2028 | AC8: Ene | AD8: Feb | AE8: Mar | AF8: Abr | AG8: May | AH8: Jun | AI8: Jul | AJ8: Ago | AK8: Sep | AL8: Oct | AM8: Nov | AN8: Dic | AO8: Total 2029 | AP8: Ene | AQ8: Feb | AR8: Mar | AS8: Abr | AT8: May | AU8: Jun | AV8: Jul | AW8: Ago | AX8: Sep | AY8: Oct | AZ8: Nov | BA8: Dic | BB8: Total 2030
B10: Por concepto
A11: VARIABLES | B11: Infraestructura por cliente | C11: =('Proyección de ventas'!C22*Planes!$G$7+'Proyección de ventas'!C29*Planes!$G$8+'Proyección de ventas'!C33*Planes!$G$9)*1 | D11: =('Proyección de ventas'!D22*Planes!$G$7+'Proyección de ventas'!D29*Planes!$G$8+'Proyección de ventas'!D33*Planes!$G$9)*1 | E11: =('Proyección de ventas'!E22*Planes!$G$7+'Proyección de ventas'!E29*Planes!$G$8+'Proyección de ventas'!E33*Planes!$G$9)*1 | F11: =('Proyección de ventas'!F22*Planes!$G$7+'Proyección de ventas'!F29*Planes!$G$8+'Proyección de ventas'!F33*Planes!$G$9)*1 | G11: =('Proyección de ventas'!G22*Planes!$G$7+'Proyección de ventas'!G29*Planes!$G$8+'Proyección de ventas'!G33*Planes!$G$9)*1 | H11: =('Proyección de ventas'!H22*Planes!$G$7+'Proyección de ventas'!H29*Planes!$G$8+'Proyección de ventas'!H33*Planes!$G$9)*1 | I11: =('Proyección de ventas'!I22*Planes!$G$7+'Proyección de ventas'!I29*Planes!$G$8+'Proyección de ventas'!I33*Planes!$G$9)*1 | J11: =('Proyección de ventas'!J22*Planes!$G$7+'Proyección de ventas'!J29*Planes!$G$8+'Proyección de ventas'!J33*Planes!$G$9)*1 | ... N11: =('Proyección de ventas'!N22*Planes!$G$7+'Proyección de ventas'!N29*Planes!$G$8+'Proyección de ventas'!N33*Planes!$G$9)*1 | O11: =SUM(C11:N11) | P11: =('Proyección de ventas'!P22*Planes!$G$7+'Proyección de ventas'!P29*Planes!$G$8+'Proyección de ventas'!P33*Planes!$G$9)*(1+Hipótesis!$D$8) | Q11: =('Proyección de ventas'!Q22*Planes!$G$7+'Proyección de ventas'!Q29*Planes!$G$8+'Proyección de ventas'!Q33*Planes!$G$9)*(1+Hipótesis!$D$8) | R11: =('Proyección de ventas'!R22*Planes!$G$7+'Proyección de ventas'!R29*Planes!$G$8+'Proyección de ventas'!R33*Planes!$G$9)*(1+Hipótesis!$D$8) | S11: =('Proyección de ventas'!S22*Planes!$G$7+'Proyección de ventas'!S29*Planes!$G$8+'Proyección de ventas'!S33*Planes!$G$9)*(1+Hipótesis!$D$8) | T11: =('Proyección de ventas'!T22*Planes!$G$7+'Proyección de ventas'!T29*Planes!$G$8+'Proyección de ventas'!T33*Planes!$G$9)*(1+Hipótesis!$D$8) | U11: =('Proyección de ventas'!U22*Planes!$G$7+'Proyección de ventas'!U29*Planes!$G$8+'Proyección de ventas'!U33*Planes!$G$9)*(1+Hipótesis!$D$8) | V11: =('Proyección de ventas'!V22*Planes!$G$7+'Proyección de ventas'!V29*Planes!$G$8+'Proyección de ventas'!V33*Planes!$G$9)*(1+Hipótesis!$D$8) | W11: =('Proyección de ventas'!W22*Planes!$G$7+'Proyección de ventas'!W29*Planes!$G$8+'Proyección de ventas'!W33*Planes!$G$9)*(1+Hipótesis!$D$8) | ... AA11: =('Proyección de ventas'!AA22*Planes!$G$7+'Proyección de ventas'!AA29*Planes!$G$8+'Proyección de ventas'!AA33*Planes!$G$9)*(1+Hipótesis!$D$8) | AB11: =SUM(P11:AA11) | AC11: =('Proyección de ventas'!AC22*Planes!$G$7+'Proyección de ventas'!AC29*Planes!$G$8+'Proyección de ventas'!AC33*Planes!$G$9)*(1+Hipótesis!$D$8)*(1+Hipótesis!$E$8) | AD11: =('Proyección de ventas'!AD22*Planes!$G$7+'Proyección de ventas'!AD29*Planes!$G$8+'Proyección de ventas'!AD33*Planes!$G$9)*(1+Hipótesis!$D$8)*(1+Hipótesis!$E$8) | AE11: =('Proyección de ventas'!AE22*Planes!$G$7+'Proyección de ventas'!AE29*Planes!$G$8+'Proyección de ventas'!AE33*Planes!$G$9)*(1+Hipótesis!$D$8)*(1+Hipótesis!$E$8) | AF11: =('Proyección de ventas'!AF22*Planes!$G$7+'Proyección de ventas'!AF29*Planes!$G$8+'Proyección de ventas'!AF33*Planes!$G$9)*(1+Hipótesis!$D$8)*(1+Hipótesis!$E$8) | AG11: =('Proyección de ventas'!AG22*Planes!$G$7+'Proyección de ventas'!AG29*Planes!$G$8+'Proyección de ventas'!AG33*Planes!$G$9)*(1+Hipótesis!$D$8)*(1+Hipótesis!$E$8) | AH11: =('Proyección de ventas'!AH22*Planes!$G$7+'Proyección de ventas'!AH29*Planes!$G$8+'Proyección de ventas'!AH33*Planes!$G$9)*(1+Hipótesis!$D$8)*(1+Hipótesis!$E$8) | AI11: =('Proyección de ventas'!AI22*Planes!$G$7+'Proyección de ventas'!AI29*Planes!$G$8+'Proyección de ventas'!AI33*Planes!$G$9)*(1+Hipótesis!$D$8)*(1+Hipótesis!$E$8) | AJ11: =('Proyección de ventas'!AJ22*Planes!$G$7+'Proyección de ventas'!AJ29*Planes!$G$8+'Proyección de ventas'!AJ33*Planes!$G$9)*(1+Hipótesis!$D$8)*(1+Hipótesis!$E$8) | ... AN11: =('Proyección de ventas'!AN22*Planes!$G$7+'Proyección de ventas'!AN29*Planes!$G$8+'Proyección de ventas'!AN33*Planes!$G$9)*(1+Hipótesis!$D$8)*(1+Hipótesis!$E$8) | AO11: =SUM(AC11:AN11) | AP11: =('Proyección de ventas'!AP22*Planes!$G$7+'Proyección de ventas'!AP29*Planes!$G$8+'Proyección de ventas'!AP33*Planes!$G$9)*(1+Hipótesis!$D$8)*(1+Hipótesis!$E$8)*(1+Hipótesis!$F$8) | AQ11: =('Proyección de ventas'!AQ22*Planes!$G$7+'Proyección de ventas'!AQ29*Planes!$G$8+'Proyección de ventas'!AQ33*Planes!$G$9)*(1+Hipótesis!$D$8)*(1+Hipótesis!$E$8)*(1+Hipótesis!$F$8) | AR11: =('Proyección de ventas'!AR22*Planes!$G$7+'Proyección de ventas'!AR29*Planes!$G$8+'Proyección de ventas'!AR33*Planes!$G$9)*(1+Hipótesis!$D$8)*(1+Hipótesis!$E$8)*(1+Hipótesis!$F$8) | AS11: =('Proyección de ventas'!AS22*Planes!$G$7+'Proyección de ventas'!AS29*Planes!$G$8+'Proyección de ventas'!AS33*Planes!$G$9)*(1+Hipótesis!$D$8)*(1+Hipótesis!$E$8)*(1+Hipótesis!$F$8) | AT11: =('Proyección de ventas'!AT22*Planes!$G$7+'Proyección de ventas'!AT29*Planes!$G$8+'Proyección de ventas'!AT33*Planes!$G$9)*(1+Hipótesis!$D$8)*(1+Hipótesis!$E$8)*(1+Hipótesis!$F$8) | AU11: =('Proyección de ventas'!AU22*Planes!$G$7+'Proyección de ventas'!AU29*Planes!$G$8+'Proyección de ventas'!AU33*Planes!$G$9)*(1+Hipótesis!$D$8)*(1+Hipótesis!$E$8)*(1+Hipótesis!$F$8) | AV11: =('Proyección de ventas'!AV22*Planes!$G$7+'Proyección de ventas'!AV29*Planes!$G$8+'Proyección de ventas'!AV33*Planes!$G$9)*(1+Hipótesis!$D$8)*(1+Hipótesis!$E$8)*(1+Hipótesis!$F$8) | AW11: =('Proyección de ventas'!AW22*Planes!$G$7+'Proyección de ventas'!AW29*Planes!$G$8+'Proyección de ventas'!AW33*Planes!$G$9)*(1+Hipótesis!$D$8)*(1+Hipótesis!$E$8)*(1+Hipótesis!$F$8) | ... BA11: =('Proyección de ventas'!BA22*Planes!$G$7+'Proyección de ventas'!BA29*Planes!$G$8+'Proyección de ventas'!BA33*Planes!$G$9)*(1+Hipótesis!$D$8)*(1+Hipótesis!$E$8)*(1+Hipótesis!$F$8) | BB11: =SUM(AP11:BA11)
B12: Soporte y onboarding por cliente | C12: =('Proyección de ventas'!C22*Planes!$H$7+'Proyección de ventas'!C29*Planes!$H$8+'Proyección de ventas'!C33*Planes!$H$9)*1 | D12: =('Proyección de ventas'!D22*Planes!$H$7+'Proyección de ventas'!D29*Planes!$H$8+'Proyección de ventas'!D33*Planes!$H$9)*1 | E12: =('Proyección de ventas'!E22*Planes!$H$7+'Proyección de ventas'!E29*Planes!$H$8+'Proyección de ventas'!E33*Planes!$H$9)*1 | F12: =('Proyección de ventas'!F22*Planes!$H$7+'Proyección de ventas'!F29*Planes!$H$8+'Proyección de ventas'!F33*Planes!$H$9)*1 | G12: =('Proyección de ventas'!G22*Planes!$H$7+'Proyección de ventas'!G29*Planes!$H$8+'Proyección de ventas'!G33*Planes!$H$9)*1 | H12: =('Proyección de ventas'!H22*Planes!$H$7+'Proyección de ventas'!H29*Planes!$H$8+'Proyección de ventas'!H33*Planes!$H$9)*1 | I12: =('Proyección de ventas'!I22*Planes!$H$7+'Proyección de ventas'!I29*Planes!$H$8+'Proyección de ventas'!I33*Planes!$H$9)*1 | J12: =('Proyección de ventas'!J22*Planes!$H$7+'Proyección de ventas'!J29*Planes!$H$8+'Proyección de ventas'!J33*Planes!$H$9)*1 | ... N12: =('Proyección de ventas'!N22*Planes!$H$7+'Proyección de ventas'!N29*Planes!$H$8+'Proyección de ventas'!N33*Planes!$H$9)*1 | O12: =SUM(C12:N12) | P12: =('Proyección de ventas'!P22*Planes!$H$7+'Proyección de ventas'!P29*Planes!$H$8+'Proyección de ventas'!P33*Planes!$H$9)*(1+Hipótesis!$D$8) | Q12: =('Proyección de ventas'!Q22*Planes!$H$7+'Proyección de ventas'!Q29*Planes!$H$8+'Proyección de ventas'!Q33*Planes!$H$9)*(1+Hipótesis!$D$8) | R12: =('Proyección de ventas'!R22*Planes!$H$7+'Proyección de ventas'!R29*Planes!$H$8+'Proyección de ventas'!R33*Planes!$H$9)*(1+Hipótesis!$D$8) | S12: =('Proyección de ventas'!S22*Planes!$H$7+'Proyección de ventas'!S29*Planes!$H$8+'Proyección de ventas'!S33*Planes!$H$9)*(1+Hipótesis!$D$8) | T12: =('Proyección de ventas'!T22*Planes!$H$7+'Proyección de ventas'!T29*Planes!$H$8+'Proyección de ventas'!T33*Planes!$H$9)*(1+Hipótesis!$D$8) | U12: =('Proyección de ventas'!U22*Planes!$H$7+'Proyección de ventas'!U29*Planes!$H$8+'Proyección de ventas'!U33*Planes!$H$9)*(1+Hipótesis!$D$8) | V12: =('Proyección de ventas'!V22*Planes!$H$7+'Proyección de ventas'!V29*Planes!$H$8+'Proyección de ventas'!V33*Planes!$H$9)*(1+Hipótesis!$D$8) | W12: =('Proyección de ventas'!W22*Planes!$H$7+'Proyección de ventas'!W29*Planes!$H$8+'Proyección de ventas'!W33*Planes!$H$9)*(1+Hipótesis!$D$8) | ... AA12: =('Proyección de ventas'!AA22*Planes!$H$7+'Proyección de ventas'!AA29*Planes!$H$8+'Proyección de ventas'!AA33*Planes!$H$9)*(1+Hipótesis!$D$8) | AB12: =SUM(P12:AA12) | AC12: =('Proyección de ventas'!AC22*Planes!$H$7+'Proyección de ventas'!AC29*Planes!$H$8+'Proyección de ventas'!AC33*Planes!$H$9)*(1+Hipótesis!$D$8)*(1+Hipótesis!$E$8) | AD12: =('Proyección de ventas'!AD22*Planes!$H$7+'Proyección de ventas'!AD29*Planes!$H$8+'Proyección de ventas'!AD33*Planes!$H$9)*(1+Hipótesis!$D$8)*(1+Hipótesis!$E$8) | AE12: =('Proyección de ventas'!AE22*Planes!$H$7+'Proyección de ventas'!AE29*Planes!$H$8+'Proyección de ventas'!AE33*Planes!$H$9)*(1+Hipótesis!$D$8)*(1+Hipótesis!$E$8) | AF12: =('Proyección de ventas'!AF22*Planes!$H$7+'Proyección de ventas'!AF29*Planes!$H$8+'Proyección de ventas'!AF33*Planes!$H$9)*(1+Hipótesis!$D$8)*(1+Hipótesis!$E$8) | AG12: =('Proyección de ventas'!AG22*Planes!$H$7+'Proyección de ventas'!AG29*Planes!$H$8+'Proyección de ventas'!AG33*Planes!$H$9)*(1+Hipótesis!$D$8)*(1+Hipótesis!$E$8) | AH12: =('Proyección de ventas'!AH22*Planes!$H$7+'Proyección de ventas'!AH29*Planes!$H$8+'Proyección de ventas'!AH33*Planes!$H$9)*(1+Hipótesis!$D$8)*(1+Hipótesis!$E$8) | AI12: =('Proyección de ventas'!AI22*Planes!$H$7+'Proyección de ventas'!AI29*Planes!$H$8+'Proyección de ventas'!AI33*Planes!$H$9)*(1+Hipótesis!$D$8)*(1+Hipótesis!$E$8) | AJ12: =('Proyección de ventas'!AJ22*Planes!$H$7+'Proyección de ventas'!AJ29*Planes!$H$8+'Proyección de ventas'!AJ33*Planes!$H$9)*(1+Hipótesis!$D$8)*(1+Hipótesis!$E$8) | ... AN12: =('Proyección de ventas'!AN22*Planes!$H$7+'Proyección de ventas'!AN29*Planes!$H$8+'Proyección de ventas'!AN33*Planes!$H$9)*(1+Hipótesis!$D$8)*(1+Hipótesis!$E$8) | AO12: =SUM(AC12:AN12) | AP12: =('Proyección de ventas'!AP22*Planes!$H$7+'Proyección de ventas'!AP29*Planes!$H$8+'Proyección de ventas'!AP33*Planes!$H$9)*(1+Hipótesis!$D$8)*(1+Hipótesis!$E$8)*(1+Hipótesis!$F$8) | AQ12: =('Proyección de ventas'!AQ22*Planes!$H$7+'Proyección de ventas'!AQ29*Planes!$H$8+'Proyección de ventas'!AQ33*Planes!$H$9)*(1+Hipótesis!$D$8)*(1+Hipótesis!$E$8)*(1+Hipótesis!$F$8) | AR12: =('Proyección de ventas'!AR22*Planes!$H$7+'Proyección de ventas'!AR29*Planes!$H$8+'Proyección de ventas'!AR33*Planes!$H$9)*(1+Hipótesis!$D$8)*(1+Hipótesis!$E$8)*(1+Hipótesis!$F$8) | AS12: =('Proyección de ventas'!AS22*Planes!$H$7+'Proyección de ventas'!AS29*Planes!$H$8+'Proyección de ventas'!AS33*Planes!$H$9)*(1+Hipótesis!$D$8)*(1+Hipótesis!$E$8)*(1+Hipótesis!$F$8) | AT12: =('Proyección de ventas'!AT22*Planes!$H$7+'Proyección de ventas'!AT29*Planes!$H$8+'Proyección de ventas'!AT33*Planes!$H$9)*(1+Hipótesis!$D$8)*(1+Hipótesis!$E$8)*(1+Hipótesis!$F$8) | AU12: =('Proyección de ventas'!AU22*Planes!$H$7+'Proyección de ventas'!AU29*Planes!$H$8+'Proyección de ventas'!AU33*Planes!$H$9)*(1+Hipótesis!$D$8)*(1+Hipótesis!$E$8)*(1+Hipótesis!$F$8) | AV12: =('Proyección de ventas'!AV22*Planes!$H$7+'Proyección de ventas'!AV29*Planes!$H$8+'Proyección de ventas'!AV33*Planes!$H$9)*(1+Hipótesis!$D$8)*(1+Hipótesis!$E$8)*(1+Hipótesis!$F$8) | AW12: =('Proyección de ventas'!AW22*Planes!$H$7+'Proyección de ventas'!AW29*Planes!$H$8+'Proyección de ventas'!AW33*Planes!$H$9)*(1+Hipótesis!$D$8)*(1+Hipótesis!$E$8)*(1+Hipótesis!$F$8) | ... BA12: =('Proyección de ventas'!BA22*Planes!$H$7+'Proyección de ventas'!BA29*Planes!$H$8+'Proyección de ventas'!BA33*Planes!$H$9)*(1+Hipótesis!$D$8)*(1+Hipótesis!$E$8)*(1+Hipótesis!$F$8) | BB12: =SUM(AP12:BA12)
B13: Servicio externo de inteligencia artificial | C13: =('Proyección de ventas'!C22*Planes!$I$7+'Proyección de ventas'!C29*Planes!$I$8+'Proyección de ventas'!C33*Planes!$I$9)*1 | D13: =('Proyección de ventas'!D22*Planes!$I$7+'Proyección de ventas'!D29*Planes!$I$8+'Proyección de ventas'!D33*Planes!$I$9)*1 | E13: =('Proyección de ventas'!E22*Planes!$I$7+'Proyección de ventas'!E29*Planes!$I$8+'Proyección de ventas'!E33*Planes!$I$9)*1 | F13: =('Proyección de ventas'!F22*Planes!$I$7+'Proyección de ventas'!F29*Planes!$I$8+'Proyección de ventas'!F33*Planes!$I$9)*1 | G13: =('Proyección de ventas'!G22*Planes!$I$7+'Proyección de ventas'!G29*Planes!$I$8+'Proyección de ventas'!G33*Planes!$I$9)*1 | H13: =('Proyección de ventas'!H22*Planes!$I$7+'Proyección de ventas'!H29*Planes!$I$8+'Proyección de ventas'!H33*Planes!$I$9)*1 | I13: =('Proyección de ventas'!I22*Planes!$I$7+'Proyección de ventas'!I29*Planes!$I$8+'Proyección de ventas'!I33*Planes!$I$9)*1 | J13: =('Proyección de ventas'!J22*Planes!$I$7+'Proyección de ventas'!J29*Planes!$I$8+'Proyección de ventas'!J33*Planes!$I$9)*1 | ... N13: =('Proyección de ventas'!N22*Planes!$I$7+'Proyección de ventas'!N29*Planes!$I$8+'Proyección de ventas'!N33*Planes!$I$9)*1 | O13: =SUM(C13:N13) | P13: =('Proyección de ventas'!P22*Planes!$I$7+'Proyección de ventas'!P29*Planes!$I$8+'Proyección de ventas'!P33*Planes!$I$9)*(1+Hipótesis!$D$8) | Q13: =('Proyección de ventas'!Q22*Planes!$I$7+'Proyección de ventas'!Q29*Planes!$I$8+'Proyección de ventas'!Q33*Planes!$I$9)*(1+Hipótesis!$D$8) | R13: =('Proyección de ventas'!R22*Planes!$I$7+'Proyección de ventas'!R29*Planes!$I$8+'Proyección de ventas'!R33*Planes!$I$9)*(1+Hipótesis!$D$8) | S13: =('Proyección de ventas'!S22*Planes!$I$7+'Proyección de ventas'!S29*Planes!$I$8+'Proyección de ventas'!S33*Planes!$I$9)*(1+Hipótesis!$D$8) | T13: =('Proyección de ventas'!T22*Planes!$I$7+'Proyección de ventas'!T29*Planes!$I$8+'Proyección de ventas'!T33*Planes!$I$9)*(1+Hipótesis!$D$8) | U13: =('Proyección de ventas'!U22*Planes!$I$7+'Proyección de ventas'!U29*Planes!$I$8+'Proyección de ventas'!U33*Planes!$I$9)*(1+Hipótesis!$D$8) | V13: =('Proyección de ventas'!V22*Planes!$I$7+'Proyección de ventas'!V29*Planes!$I$8+'Proyección de ventas'!V33*Planes!$I$9)*(1+Hipótesis!$D$8) | W13: =('Proyección de ventas'!W22*Planes!$I$7+'Proyección de ventas'!W29*Planes!$I$8+'Proyección de ventas'!W33*Planes!$I$9)*(1+Hipótesis!$D$8) | ... AA13: =('Proyección de ventas'!AA22*Planes!$I$7+'Proyección de ventas'!AA29*Planes!$I$8+'Proyección de ventas'!AA33*Planes!$I$9)*(1+Hipótesis!$D$8) | AB13: =SUM(P13:AA13) | AC13: =('Proyección de ventas'!AC22*Planes!$I$7+'Proyección de ventas'!AC29*Planes!$I$8+'Proyección de ventas'!AC33*Planes!$I$9)*(1+Hipótesis!$D$8)*(1+Hipótesis!$E$8) | AD13: =('Proyección de ventas'!AD22*Planes!$I$7+'Proyección de ventas'!AD29*Planes!$I$8+'Proyección de ventas'!AD33*Planes!$I$9)*(1+Hipótesis!$D$8)*(1+Hipótesis!$E$8) | AE13: =('Proyección de ventas'!AE22*Planes!$I$7+'Proyección de ventas'!AE29*Planes!$I$8+'Proyección de ventas'!AE33*Planes!$I$9)*(1+Hipótesis!$D$8)*(1+Hipótesis!$E$8) | AF13: =('Proyección de ventas'!AF22*Planes!$I$7+'Proyección de ventas'!AF29*Planes!$I$8+'Proyección de ventas'!AF33*Planes!$I$9)*(1+Hipótesis!$D$8)*(1+Hipótesis!$E$8) | AG13: =('Proyección de ventas'!AG22*Planes!$I$7+'Proyección de ventas'!AG29*Planes!$I$8+'Proyección de ventas'!AG33*Planes!$I$9)*(1+Hipótesis!$D$8)*(1+Hipótesis!$E$8) | AH13: =('Proyección de ventas'!AH22*Planes!$I$7+'Proyección de ventas'!AH29*Planes!$I$8+'Proyección de ventas'!AH33*Planes!$I$9)*(1+Hipótesis!$D$8)*(1+Hipótesis!$E$8) | AI13: =('Proyección de ventas'!AI22*Planes!$I$7+'Proyección de ventas'!AI29*Planes!$I$8+'Proyección de ventas'!AI33*Planes!$I$9)*(1+Hipótesis!$D$8)*(1+Hipótesis!$E$8) | AJ13: =('Proyección de ventas'!AJ22*Planes!$I$7+'Proyección de ventas'!AJ29*Planes!$I$8+'Proyección de ventas'!AJ33*Planes!$I$9)*(1+Hipótesis!$D$8)*(1+Hipótesis!$E$8) | ... AN13: =('Proyección de ventas'!AN22*Planes!$I$7+'Proyección de ventas'!AN29*Planes!$I$8+'Proyección de ventas'!AN33*Planes!$I$9)*(1+Hipótesis!$D$8)*(1+Hipótesis!$E$8) | AO13: =SUM(AC13:AN13) | AP13: =('Proyección de ventas'!AP22*Planes!$I$7+'Proyección de ventas'!AP29*Planes!$I$8+'Proyección de ventas'!AP33*Planes!$I$9)*(1+Hipótesis!$D$8)*(1+Hipótesis!$E$8)*(1+Hipótesis!$F$8) | AQ13: =('Proyección de ventas'!AQ22*Planes!$I$7+'Proyección de ventas'!AQ29*Planes!$I$8+'Proyección de ventas'!AQ33*Planes!$I$9)*(1+Hipótesis!$D$8)*(1+Hipótesis!$E$8)*(1+Hipótesis!$F$8) | AR13: =('Proyección de ventas'!AR22*Planes!$I$7+'Proyección de ventas'!AR29*Planes!$I$8+'Proyección de ventas'!AR33*Planes!$I$9)*(1+Hipótesis!$D$8)*(1+Hipótesis!$E$8)*(1+Hipótesis!$F$8) | AS13: =('Proyección de ventas'!AS22*Planes!$I$7+'Proyección de ventas'!AS29*Planes!$I$8+'Proyección de ventas'!AS33*Planes!$I$9)*(1+Hipótesis!$D$8)*(1+Hipótesis!$E$8)*(1+Hipótesis!$F$8) | AT13: =('Proyección de ventas'!AT22*Planes!$I$7+'Proyección de ventas'!AT29*Planes!$I$8+'Proyección de ventas'!AT33*Planes!$I$9)*(1+Hipótesis!$D$8)*(1+Hipótesis!$E$8)*(1+Hipótesis!$F$8) | AU13: =('Proyección de ventas'!AU22*Planes!$I$7+'Proyección de ventas'!AU29*Planes!$I$8+'Proyección de ventas'!AU33*Planes!$I$9)*(1+Hipótesis!$D$8)*(1+Hipótesis!$E$8)*(1+Hipótesis!$F$8) | AV13: =('Proyección de ventas'!AV22*Planes!$I$7+'Proyección de ventas'!AV29*Planes!$I$8+'Proyección de ventas'!AV33*Planes!$I$9)*(1+Hipótesis!$D$8)*(1+Hipótesis!$E$8)*(1+Hipótesis!$F$8) | AW13: =('Proyección de ventas'!AW22*Planes!$I$7+'Proyección de ventas'!AW29*Planes!$I$8+'Proyección de ventas'!AW33*Planes!$I$9)*(1+Hipótesis!$D$8)*(1+Hipótesis!$E$8)*(1+Hipótesis!$F$8) | ... BA13: =('Proyección de ventas'!BA22*Planes!$I$7+'Proyección de ventas'!BA29*Planes!$I$8+'Proyección de ventas'!BA33*Planes!$I$9)*(1+Hipótesis!$D$8)*(1+Hipótesis!$E$8)*(1+Hipótesis!$F$8) | BB13: =SUM(AP13:BA13)
B14: Total de costos variables | C14: =SUM(C11:C13) | D14: =SUM(D11:D13) | E14: =SUM(E11:E13) | F14: =SUM(F11:F13) | G14: =SUM(G11:G13) | H14: =SUM(H11:H13) | I14: =SUM(I11:I13) | J14: =SUM(J11:J13) | ... N14: =SUM(N11:N13) | O14: =SUM(C14:N14) | P14: =SUM(P11:P13) | Q14: =SUM(Q11:Q13) | R14: =SUM(R11:R13) | S14: =SUM(S11:S13) | T14: =SUM(T11:T13) | U14: =SUM(U11:U13) | V14: =SUM(V11:V13) | W14: =SUM(W11:W13) | ... AA14: =SUM(AA11:AA13) | AB14: =SUM(P14:AA14) | AC14: =SUM(AC11:AC13) | AD14: =SUM(AD11:AD13) | AE14: =SUM(AE11:AE13) | AF14: =SUM(AF11:AF13) | AG14: =SUM(AG11:AG13) | AH14: =SUM(AH11:AH13) | AI14: =SUM(AI11:AI13) | AJ14: =SUM(AJ11:AJ13) | ... AN14: =SUM(AN11:AN13) | AO14: =SUM(AC14:AN14) | AP14: =SUM(AP11:AP13) | AQ14: =SUM(AQ11:AQ13) | AR14: =SUM(AR11:AR13) | AS14: =SUM(AS11:AS13) | AT14: =SUM(AT11:AT13) | AU14: =SUM(AU11:AU13) | AV14: =SUM(AV11:AV13) | AW14: =SUM(AW11:AW13) | ... BA14: =SUM(BA11:BA13) | BB14: =SUM(AP14:BA14)
B16: El costo del servicio de inteligencia artificial es el único que el sistema mide por sí mismo: cada consulta de clasificación y de asignación queda registrada, así que la estimación de la sección 6.5.3 se puede contrastar contra el consumo real.

Sheet RRHH
A1: « Inicio
B2: COSTOS DE RRHH
B3: Plantilla de la sección 7.6 del documento. Los cuatro roles funcionales se cubren de a poco: en las primeras etapas los socios fundadores asumen más de uno.
B6: Salario bruto mensual y mes de incorporación
B7: Rol | C7: Salario bruto | D7: Mes de alta
B8: Responsable de Producto y Desarrollo (socio) | C8: 4200000 | D8: 1 | E8: Socio
B9: Responsable Comercial y de Cuentas (socio) | C9: 3600000 | D9: 1 | E9: Socio
B10: Responsable de Soporte y Onboarding | C10: 2400000 | D10: 6 | E10: Empleado
B11: Responsable de Marketing y Contenidos | C11: 2200000 | D11: 9 | E11: Empleado
B12: Colaborador de desarrollo | C12: 2900000 | D12: 9 | E12: Empleado
B13: Segundo colaborador de soporte | C13: 1800000 | D13: 18 | E13: Empleado
B16: Retiro de los socios como % de su salario de mercado
C17: 2027 | D17: 2028 | E17: 2029 | F17: 2030
B18: % del salario de mercado que retira cada socio | C18: 0.3 | D18: 0.55 | E18: 0.8 | F18: 1 | H18: Decision propia. El ano 1 es un retiro de subsistencia; la brecha contra el 100 % es el aporte de los socios
B20: Cargas sociales sobre el salario bruto
B21: Jubilación | C21: 0.1017
B22: PAMI (Ley 19.032) | C22: 0.015
B23: Asignaciones familiares | C23: 0.0444
B24: Fondo Nacional de Empleo | C24: 0.0089
B25: Obra social | C25: 0.06
B26: Total de cargas | C26: =SUM(C21:C25)
C28: 2027 | P28: 2028 | AC28: 2029 | AP28: 2030
C29: Ene | D29: Feb | E29: Mar | F29: Abr | G29: May | H29: Jun | I29: Jul | J29: Ago | K29: Sep | L29: Oct | M29: Nov | N29: Dic | O29: Total 2027 | P29: Ene | Q29: Feb | R29: Mar | S29: Abr | T29: May | U29: Jun | V29: Jul | W29: Ago | X29: Sep | Y29: Oct | Z29: Nov | AA29: Dic | AB29: Total 2028 | AC29: Ene | AD29: Feb | AE29: Mar | AF29: Abr | AG29: May | AH29: Jun | AI29: Jul | AJ29: Ago | AK29: Sep | AL29: Oct | AM29: Nov | AN29: Dic | AO29: Total 2029 | AP29: Ene | AQ29: Feb | AR29: Mar | AS29: Abr | AT29: May | AU29: Jun | AV29: Jul | AW29: Ago | AX29: Sep | AY29: Oct | AZ29: Nov | BA29: Dic | BB29: Total 2030
B30: Salarios brutos por rol
A31: SUELDOS | B31: Responsable de Producto y Desarrollo (socio) | C31: =IF(1<$D$8,0,$C$8*1*1*$C$18) | D31: =IF(2<$D$8,0,$C$8*1*1*$C$18) | E31: =IF(3<$D$8,0,$C$8*1*1*$C$18) | F31: =IF(4<$D$8,0,$C$8*1*1*$C$18) | G31: =IF(5<$D$8,0,$C$8*1*1*$C$18) | H31: =IF(6<$D$8,0,$C$8*1*1.5*$C$18) | I31: =IF(7<$D$8,0,$C$8*1*1*$C$18) | J31: =IF(8<$D$8,0,$C$8*1*1*$C$18) | K31: =IF(9<$D$8,0,$C$8*1*1*$C$18) | L31: =IF(10<$D$8,0,$C$8*1*1*$C$18) | M31: =IF(11<$D$8,0,$C$8*1*1*$C$18) | N31: =IF(12<$D$8,0,$C$8*1*1.5*$C$18) | O31: =SUM(C31:N31) | P31: =IF(13<$D$8,0,$C$8*(1+Hipótesis!$D$12)*1*$D$18) | Q31: =IF(14<$D$8,0,$C$8*(1+Hipótesis!$D$12)*1*$D$18) | R31: =IF(15<$D$8,0,$C$8*(1+Hipótesis!$D$12)*1*$D$18) | S31: =IF(16<$D$8,0,$C$8*(1+Hipótesis!$D$12)*1*$D$18) | T31: =IF(17<$D$8,0,$C$8*(1+Hipótesis!$D$12)*1*$D$18) | U31: =IF(18<$D$8,0,$C$8*(1+Hipótesis!$D$12)*1.5*$D$18) | V31: =IF(19<$D$8,0,$C$8*(1+Hipótesis!$D$12)*1*$D$18) | W31: =IF(20<$D$8,0,$C$8*(1+Hipótesis!$D$12)*1*$D$18) | X31: =IF(21<$D$8,0,$C$8*(1+Hipótesis!$D$12)*1*$D$18) | Y31: =IF(22<$D$8,0,$C$8*(1+Hipótesis!$D$12)*1*$D$18) | Z31: =IF(23<$D$8,0,$C$8*(1+Hipótesis!$D$12)*1*$D$18) | AA31: =IF(24<$D$8,0,$C$8*(1+Hipótesis!$D$12)*1.5*$D$18) | AB31: =SUM(P31:AA31) | AC31: =IF(25<$D$8,0,$C$8*(1+Hipótesis!$D$12)*(1+Hipótesis!$E$12)*1*$E$18) | AD31: =IF(26<$D$8,0,$C$8*(1+Hipótesis!$D$12)*(1+Hipótesis!$E$12)*1*$E$18) | AE31: =IF(27<$D$8,0,$C$8*(1+Hipótesis!$D$12)*(1+Hipótesis!$E$12)*1*$E$18) | AF31: =IF(28<$D$8,0,$C$8*(1+Hipótesis!$D$12)*(1+Hipótesis!$E$12)*1*$E$18) | AG31: =IF(29<$D$8,0,$C$8*(1+Hipótesis!$D$12)*(1+Hipótesis!$E$12)*1*$E$18) | AH31: =IF(30<$D$8,0,$C$8*(1+Hipótesis!$D$12)*(1+Hipótesis!$E$12)*1.5*$E$18) | AI31: =IF(31<$D$8,0,$C$8*(1+Hipótesis!$D$12)*(1+Hipótesis!$E$12)*1*$E$18) | AJ31: =IF(32<$D$8,0,$C$8*(1+Hipótesis!$D$12)*(1+Hipótesis!$E$12)*1*$E$18) | AK31: =IF(33<$D$8,0,$C$8*(1+Hipótesis!$D$12)*(1+Hipótesis!$E$12)*1*$E$18) | AL31: =IF(34<$D$8,0,$C$8*(1+Hipótesis!$D$12)*(1+Hipótesis!$E$12)*1*$E$18) | AM31: =IF(35<$D$8,0,$C$8*(1+Hipótesis!$D$12)*(1+Hipótesis!$E$12)*1*$E$18) | AN31: =IF(36<$D$8,0,$C$8*(1+Hipótesis!$D$12)*(1+Hipótesis!$E$12)*1.5*$E$18) | AO31: =SUM(AC31:AN31) | AP31: =IF(37<$D$8,0,$C$8*(1+Hipótesis!$D$12)*(1+Hipótesis!$E$12)*(1+Hipótesis!$F$12)*1*$F$18) | AQ31: =IF(38<$D$8,0,$C$8*(1+Hipótesis!$D$12)*(1+Hipótesis!$E$12)*(1+Hipótesis!$F$12)*1*$F$18) | AR31: =IF(39<$D$8,0,$C$8*(1+Hipótesis!$D$12)*(1+Hipótesis!$E$12)*(1+Hipótesis!$F$12)*1*$F$18) | AS31: =IF(40<$D$8,0,$C$8*(1+Hipótesis!$D$12)*(1+Hipótesis!$E$12)*(1+Hipótesis!$F$12)*1*$F$18) | AT31: =IF(41<$D$8,0,$C$8*(1+Hipótesis!$D$12)*(1+Hipótesis!$E$12)*(1+Hipótesis!$F$12)*1*$F$18) | AU31: =IF(42<$D$8,0,$C$8*(1+Hipótesis!$D$12)*(1+Hipótesis!$E$12)*(1+Hipótesis!$F$12)*1.5*$F$18) | AV31: =IF(43<$D$8,0,$C$8*(1+Hipótesis!$D$12)*(1+Hipótesis!$E$12)*(1+Hipótesis!$F$12)*1*$F$18) | AW31: =IF(44<$D$8,0,$C$8*(1+Hipótesis!$D$12)*(1+Hipótesis!$E$12)*(1+Hipótesis!$F$12)*1*$F$18) | AX31: =IF(45<$D$8,0,$C$8*(1+Hipótesis!$D$12)*(1+Hipótesis!$E$12)*(1+Hipótesis!$F$12)*1*$F$18) | AY31: =IF(46<$D$8,0,$C$8*(1+Hipótesis!$D$12)*(1+Hipótesis!$E$12)*(1+Hipótesis!$F$12)*1*$F$18) | AZ31: =IF(47<$D$8,0,$C$8*(1+Hipótesis!$D$12)*(1+Hipótesis!$E$12)*(1+Hipótesis!$F$12)*1*$F$18) | BA31: =IF(48<$D$8,0,$C$8*(1+Hipótesis!$D$12)*(1+Hipótesis!$E$12)*(1+Hipótesis!$F$12)*1.5*$F$18) | BB31: =SUM(AP31:BA31)
B32: Responsable Comercial y de Cuentas (socio) | C32: =IF(1<$D$9,0,$C$9*1*1*$C$18) | D32: =IF(2<$D$9,0,$C$9*1*1*$C$18) | E32: =IF(3<$D$9,0,$C$9*1*1*$C$18) | F32: =IF(4<$D$9,0,$C$9*1*1*$C$18) | G32: =IF(5<$D$9,0,$C$9*1*1*$C$18) | H32: =IF(6<$D$9,0,$C$9*1*1.5*$C$18) | I32: =IF(7<$D$9,0,$C$9*1*1*$C$18) | J32: =IF(8<$D$9,0,$C$9*1*1*$C$18) | K32: =IF(9<$D$9,0,$C$9*1*1*$C$18) | L32: =IF(10<$D$9,0,$C$9*1*1*$C$18) | M32: =IF(11<$D$9,0,$C$9*1*1*$C$18) | N32: =IF(12<$D$9,0,$C$9*1*1.5*$C$18) | O32: =SUM(C32:N32) | P32: =IF(13<$D$9,0,$C$9*(1+Hipótesis!$D$12)*1*$D$18) | Q32: =IF(14<$D$9,0,$C$9*(1+Hipótesis!$D$12)*1*$D$18) | R32: =IF(15<$D$9,0,$C$9*(1+Hipótesis!$D$12)*1*$D$18) | S32: =IF(16<$D$9,0,$C$9*(1+Hipótesis!$D$12)*1*$D$18) | T32: =IF(17<$D$9,0,$C$9*(1+Hipótesis!$D$12)*1*$D$18) | U32: =IF(18<$D$9,0,$C$9*(1+Hipótesis!$D$12)*1.5*$D$18) | V32: =IF(19<$D$9,0,$C$9*(1+Hipótesis!$D$12)*1*$D$18) | W32: =IF(20<$D$9,0,$C$9*(1+Hipótesis!$D$12)*1*$D$18) | X32: =IF(21<$D$9,0,$C$9*(1+Hipótesis!$D$12)*1*$D$18) | Y32: =IF(22<$D$9,0,$C$9*(1+Hipótesis!$D$12)*1*$D$18) | Z32: =IF(23<$D$9,0,$C$9*(1+Hipótesis!$D$12)*1*$D$18) | AA32: =IF(24<$D$9,0,$C$9*(1+Hipótesis!$D$12)*1.5*$D$18) | AB32: =SUM(P32:AA32) | AC32: =IF(25<$D$9,0,$C$9*(1+Hipótesis!$D$12)*(1+Hipótesis!$E$12)*1*$E$18) | AD32: =IF(26<$D$9,0,$C$9*(1+Hipótesis!$D$12)*(1+Hipótesis!$E$12)*1*$E$18) | AE32: =IF(27<$D$9,0,$C$9*(1+Hipótesis!$D$12)*(1+Hipótesis!$E$12)*1*$E$18) | AF32: =IF(28<$D$9,0,$C$9*(1+Hipótesis!$D$12)*(1+Hipótesis!$E$12)*1*$E$18) | AG32: =IF(29<$D$9,0,$C$9*(1+Hipótesis!$D$12)*(1+Hipótesis!$E$12)*1*$E$18) | AH32: =IF(30<$D$9,0,$C$9*(1+Hipótesis!$D$12)*(1+Hipótesis!$E$12)*1.5*$E$18) | AI32: =IF(31<$D$9,0,$C$9*(1+Hipótesis!$D$12)*(1+Hipótesis!$E$12)*1*$E$18) | AJ32: =IF(32<$D$9,0,$C$9*(1+Hipótesis!$D$12)*(1+Hipótesis!$E$12)*1*$E$18) | AK32: =IF(33<$D$9,0,$C$9*(1+Hipótesis!$D$12)*(1+Hipótesis!$E$12)*1*$E$18) | AL32: =IF(34<$D$9,0,$C$9*(1+Hipótesis!$D$12)*(1+Hipótesis!$E$12)*1*$E$18) | AM32: =IF(35<$D$9,0,$C$9*(1+Hipótesis!$D$12)*(1+Hipótesis!$E$12)*1*$E$18) | AN32: =IF(36<$D$9,0,$C$9*(1+Hipótesis!$D$12)*(1+Hipótesis!$E$12)*1.5*$E$18) | AO32: =SUM(AC32:AN32) | AP32: =IF(37<$D$9,0,$C$9*(1+Hipótesis!$D$12)*(1+Hipótesis!$E$12)*(1+Hipótesis!$F$12)*1*$F$18) | AQ32: =IF(38<$D$9,0,$C$9*(1+Hipótesis!$D$12)*(1+Hipótesis!$E$12)*(1+Hipótesis!$F$12)*1*$F$18) | AR32: =IF(39<$D$9,0,$C$9*(1+Hipótesis!$D$12)*(1+Hipótesis!$E$12)*(1+Hipótesis!$F$12)*1*$F$18) | AS32: =IF(40<$D$9,0,$C$9*(1+Hipótesis!$D$12)*(1+Hipótesis!$E$12)*(1+Hipótesis!$F$12)*1*$F$18) | AT32: =IF(41<$D$9,0,$C$9*(1+Hipótesis!$D$12)*(1+Hipótesis!$E$12)*(1+Hipótesis!$F$12)*1*$F$18) | AU32: =IF(42<$D$9,0,$C$9*(1+Hipótesis!$D$12)*(1+Hipótesis!$E$12)*(1+Hipótesis!$F$12)*1.5*$F$18) | AV32: =IF(43<$D$9,0,$C$9*(1+Hipótesis!$D$12)*(1+Hipótesis!$E$12)*(1+Hipótesis!$F$12)*1*$F$18) | AW32: =IF(44<$D$9,0,$C$9*(1+Hipótesis!$D$12)*(1+Hipótesis!$E$12)*(1+Hipótesis!$F$12)*1*$F$18) | AX32: =IF(45<$D$9,0,$C$9*(1+Hipótesis!$D$12)*(1+Hipótesis!$E$12)*(1+Hipótesis!$F$12)*1*$F$18) | AY32: =IF(46<$D$9,0,$C$9*(1+Hipótesis!$D$12)*(1+Hipótesis!$E$12)*(1+Hipótesis!$F$12)*1*$F$18) | AZ32: =IF(47<$D$9,0,$C$9*(1+Hipótesis!$D$12)*(1+Hipótesis!$E$12)*(1+Hipótesis!$F$12)*1*$F$18) | BA32: =IF(48<$D$9,0,$C$9*(1+Hipótesis!$D$12)*(1+Hipótesis!$E$12)*(1+Hipótesis!$F$12)*1.5*$F$18) | BB32: =SUM(AP32:BA32)
B33: Responsable de Soporte y Onboarding | C33: =IF(1<$D$10,0,$C$10*1*1) | D33: =IF(2<$D$10,0,$C$10*1*1) | E33: =IF(3<$D$10,0,$C$10*1*1) | F33: =IF(4<$D$10,0,$C$10*1*1) | G33: =IF(5<$D$10,0,$C$10*1*1) | H33: =IF(6<$D$10,0,$C$10*1*1.5) | I33: =IF(7<$D$10,0,$C$10*1*1) | J33: =IF(8<$D$10,0,$C$10*1*1) | K33: =IF(9<$D$10,0,$C$10*1*1) | L33: =IF(10<$D$10,0,$C$10*1*1) | M33: =IF(11<$D$10,0,$C$10*1*1) | N33: =IF(12<$D$10,0,$C$10*1*1.5) | O33: =SUM(C33:N33) | P33: =IF(13<$D$10,0,$C$10*(1+Hipótesis!$D$12)*1) | Q33: =IF(14<$D$10,0,$C$10*(1+Hipótesis!$D$12)*1) | R33: =IF(15<$D$10,0,$C$10*(1+Hipótesis!$D$12)*1) | S33: =IF(16<$D$10,0,$C$10*(1+Hipótesis!$D$12)*1) | T33: =IF(17<$D$10,0,$C$10*(1+Hipótesis!$D$12)*1) | U33: =IF(18<$D$10,0,$C$10*(1+Hipótesis!$D$12)*1.5) | V33: =IF(19<$D$10,0,$C$10*(1+Hipótesis!$D$12)*1) | W33: =IF(20<$D$10,0,$C$10*(1+Hipótesis!$D$12)*1) | X33: =IF(21<$D$10,0,$C$10*(1+Hipótesis!$D$12)*1) | Y33: =IF(22<$D$10,0,$C$10*(1+Hipótesis!$D$12)*1) | Z33: =IF(23<$D$10,0,$C$10*(1+Hipótesis!$D$12)*1) | AA33: =IF(24<$D$10,0,$C$10*(1+Hipótesis!$D$12)*1.5) | AB33: =SUM(P33:AA33) | AC33: =IF(25<$D$10,0,$C$10*(1+Hipótesis!$D$12)*(1+Hipótesis!$E$12)*1) | AD33: =IF(26<$D$10,0,$C$10*(1+Hipótesis!$D$12)*(1+Hipótesis!$E$12)*1) | AE33: =IF(27<$D$10,0,$C$10*(1+Hipótesis!$D$12)*(1+Hipótesis!$E$12)*1) | AF33: =IF(28<$D$10,0,$C$10*(1+Hipótesis!$D$12)*(1+Hipótesis!$E$12)*1) | AG33: =IF(29<$D$10,0,$C$10*(1+Hipótesis!$D$12)*(1+Hipótesis!$E$12)*1) | AH33: =IF(30<$D$10,0,$C$10*(1+Hipótesis!$D$12)*(1+Hipótesis!$E$12)*1.5) | AI33: =IF(31<$D$10,0,$C$10*(1+Hipótesis!$D$12)*(1+Hipótesis!$E$12)*1) | AJ33: =IF(32<$D$10,0,$C$10*(1+Hipótesis!$D$12)*(1+Hipótesis!$E$12)*1) | AK33: =IF(33<$D$10,0,$C$10*(1+Hipótesis!$D$12)*(1+Hipótesis!$E$12)*1) | AL33: =IF(34<$D$10,0,$C$10*(1+Hipótesis!$D$12)*(1+Hipótesis!$E$12)*1) | AM33: =IF(35<$D$10,0,$C$10*(1+Hipótesis!$D$12)*(1+Hipótesis!$E$12)*1) | AN33: =IF(36<$D$10,0,$C$10*(1+Hipótesis!$D$12)*(1+Hipótesis!$E$12)*1.5) | AO33: =SUM(AC33:AN33) | AP33: =IF(37<$D$10,0,$C$10*(1+Hipótesis!$D$12)*(1+Hipótesis!$E$12)*(1+Hipótesis!$F$12)*1) | AQ33: =IF(38<$D$10,0,$C$10*(1+Hipótesis!$D$12)*(1+Hipótesis!$E$12)*(1+Hipótesis!$F$12)*1) | AR33: =IF(39<$D$10,0,$C$10*(1+Hipótesis!$D$12)*(1+Hipótesis!$E$12)*(1+Hipótesis!$F$12)*1) | AS33: =IF(40<$D$10,0,$C$10*(1+Hipótesis!$D$12)*(1+Hipótesis!$E$12)*(1+Hipótesis!$F$12)*1) | AT33: =IF(41<$D$10,0,$C$10*(1+Hipótesis!$D$12)*(1+Hipótesis!$E$12)*(1+Hipótesis!$F$12)*1) | AU33: =IF(42<$D$10,0,$C$10*(1+Hipótesis!$D$12)*(1+Hipótesis!$E$12)*(1+Hipótesis!$F$12)*1.5) | AV33: =IF(43<$D$10,0,$C$10*(1+Hipótesis!$D$12)*(1+Hipótesis!$E$12)*(1+Hipótesis!$F$12)*1) | AW33: =IF(44<$D$10,0,$C$10*(1+Hipótesis!$D$12)*(1+Hipótesis!$E$12)*(1+Hipótesis!$F$12)*1) | AX33: =IF(45<$D$10,0,$C$10*(1+Hipótesis!$D$12)*(1+Hipótesis!$E$12)*(1+Hipótesis!$F$12)*1) | AY33: =IF(46<$D$10,0,$C$10*(1+Hipótesis!$D$12)*(1+Hipótesis!$E$12)*(1+Hipótesis!$F$12)*1) | AZ33: =IF(47<$D$10,0,$C$10*(1+Hipótesis!$D$12)*(1+Hipótesis!$E$12)*(1+Hipótesis!$F$12)*1) | BA33: =IF(48<$D$10,0,$C$10*(1+Hipótesis!$D$12)*(1+Hipótesis!$E$12)*(1+Hipótesis!$F$12)*1.5) | BB33: =SUM(AP33:BA33)
B34: Responsable de Marketing y Contenidos | C34: =IF(1<$D$11,0,$C$11*1*1) | D34: =IF(2<$D$11,0,$C$11*1*1) | E34: =IF(3<$D$11,0,$C$11*1*1) | F34: =IF(4<$D$11,0,$C$11*1*1) | G34: =IF(5<$D$11,0,$C$11*1*1) | H34: =IF(6<$D$11,0,$C$11*1*1.5) | I34: =IF(7<$D$11,0,$C$11*1*1) | J34: =IF(8<$D$11,0,$C$11*1*1) | K34: =IF(9<$D$11,0,$C$11*1*1) | L34: =IF(10<$D$11,0,$C$11*1*1) | M34: =IF(11<$D$11,0,$C$11*1*1) | N34: =IF(12<$D$11,0,$C$11*1*1.5) | O34: =SUM(C34:N34) | P34: =IF(13<$D$11,0,$C$11*(1+Hipótesis!$D$12)*1) | Q34: =IF(14<$D$11,0,$C$11*(1+Hipótesis!$D$12)*1) | R34: =IF(15<$D$11,0,$C$11*(1+Hipótesis!$D$12)*1) | S34: =IF(16<$D$11,0,$C$11*(1+Hipótesis!$D$12)*1) | T34: =IF(17<$D$11,0,$C$11*(1+Hipótesis!$D$12)*1) | U34: =IF(18<$D$11,0,$C$11*(1+Hipótesis!$D$12)*1.5) | V34: =IF(19<$D$11,0,$C$11*(1+Hipótesis!$D$12)*1) | W34: =IF(20<$D$11,0,$C$11*(1+Hipótesis!$D$12)*1) | X34: =IF(21<$D$11,0,$C$11*(1+Hipótesis!$D$12)*1) | Y34: =IF(22<$D$11,0,$C$11*(1+Hipótesis!$D$12)*1) | Z34: =IF(23<$D$11,0,$C$11*(1+Hipótesis!$D$12)*1) | AA34: =IF(24<$D$11,0,$C$11*(1+Hipótesis!$D$12)*1.5) | AB34: =SUM(P34:AA34) | AC34: =IF(25<$D$11,0,$C$11*(1+Hipótesis!$D$12)*(1+Hipótesis!$E$12)*1) | AD34: =IF(26<$D$11,0,$C$11*(1+Hipótesis!$D$12)*(1+Hipótesis!$E$12)*1) | AE34: =IF(27<$D$11,0,$C$11*(1+Hipótesis!$D$12)*(1+Hipótesis!$E$12)*1) | AF34: =IF(28<$D$11,0,$C$11*(1+Hipótesis!$D$12)*(1+Hipótesis!$E$12)*1) | AG34: =IF(29<$D$11,0,$C$11*(1+Hipótesis!$D$12)*(1+Hipótesis!$E$12)*1) | AH34: =IF(30<$D$11,0,$C$11*(1+Hipótesis!$D$12)*(1+Hipótesis!$E$12)*1.5) | AI34: =IF(31<$D$11,0,$C$11*(1+Hipótesis!$D$12)*(1+Hipótesis!$E$12)*1) | AJ34: =IF(32<$D$11,0,$C$11*(1+Hipótesis!$D$12)*(1+Hipótesis!$E$12)*1) | AK34: =IF(33<$D$11,0,$C$11*(1+Hipótesis!$D$12)*(1+Hipótesis!$E$12)*1) | AL34: =IF(34<$D$11,0,$C$11*(1+Hipótesis!$D$12)*(1+Hipótesis!$E$12)*1) | AM34: =IF(35<$D$11,0,$C$11*(1+Hipótesis!$D$12)*(1+Hipótesis!$E$12)*1) | AN34: =IF(36<$D$11,0,$C$11*(1+Hipótesis!$D$12)*(1+Hipótesis!$E$12)*1.5) | AO34: =SUM(AC34:AN34) | AP34: =IF(37<$D$11,0,$C$11*(1+Hipótesis!$D$12)*(1+Hipótesis!$E$12)*(1+Hipótesis!$F$12)*1) | AQ34: =IF(38<$D$11,0,$C$11*(1+Hipótesis!$D$12)*(1+Hipótesis!$E$12)*(1+Hipótesis!$F$12)*1) | AR34: =IF(39<$D$11,0,$C$11*(1+Hipótesis!$D$12)*(1+Hipótesis!$E$12)*(1+Hipótesis!$F$12)*1) | AS34: =IF(40<$D$11,0,$C$11*(1+Hipótesis!$D$12)*(1+Hipótesis!$E$12)*(1+Hipótesis!$F$12)*1) | AT34: =IF(41<$D$11,0,$C$11*(1+Hipótesis!$D$12)*(1+Hipótesis!$E$12)*(1+Hipótesis!$F$12)*1) | AU34: =IF(42<$D$11,0,$C$11*(1+Hipótesis!$D$12)*(1+Hipótesis!$E$12)*(1+Hipótesis!$F$12)*1.5) | AV34: =IF(43<$D$11,0,$C$11*(1+Hipótesis!$D$12)*(1+Hipótesis!$E$12)*(1+Hipótesis!$F$12)*1) | AW34: =IF(44<$D$11,0,$C$11*(1+Hipótesis!$D$12)*(1+Hipótesis!$E$12)*(1+Hipótesis!$F$12)*1) | AX34: =IF(45<$D$11,0,$C$11*(1+Hipótesis!$D$12)*(1+Hipótesis!$E$12)*(1+Hipótesis!$F$12)*1) | AY34: =IF(46<$D$11,0,$C$11*(1+Hipótesis!$D$12)*(1+Hipótesis!$E$12)*(1+Hipótesis!$F$12)*1) | AZ34: =IF(47<$D$11,0,$C$11*(1+Hipótesis!$D$12)*(1+Hipótesis!$E$12)*(1+Hipótesis!$F$12)*1) | BA34: =IF(48<$D$11,0,$C$11*(1+Hipótesis!$D$12)*(1+Hipótesis!$E$12)*(1+Hipótesis!$F$12)*1.5) | BB34: =SUM(AP34:BA34)
B35: Colaborador de desarrollo | C35: =IF(1<$D$12,0,$C$12*1*1) | D35: =IF(2<$D$12,0,$C$12*1*1) | E35: =IF(3<$D$12,0,$C$12*1*1) | F35: =IF(4<$D$12,0,$C$12*1*1) | G35: =IF(5<$D$12,0,$C$12*1*1) | H35: =IF(6<$D$12,0,$C$12*1*1.5) | I35: =IF(7<$D$12,0,$C$12*1*1) | J35: =IF(8<$D$12,0,$C$12*1*1) | K35: =IF(9<$D$12,0,$C$12*1*1) | L35: =IF(10<$D$12,0,$C$12*1*1) | M35: =IF(11<$D$12,0,$C$12*1*1) | N35: =IF(12<$D$12,0,$C$12*1*1.5) | O35: =SUM(C35:N35) | P35: =IF(13<$D$12,0,$C$12*(1+Hipótesis!$D$12)*1) | Q35: =IF(14<$D$12,0,$C$12*(1+Hipótesis!$D$12)*1) | R35: =IF(15<$D$12,0,$C$12*(1+Hipótesis!$D$12)*1) | S35: =IF(16<$D$12,0,$C$12*(1+Hipótesis!$D$12)*1) | T35: =IF(17<$D$12,0,$C$12*(1+Hipótesis!$D$12)*1) | U35: =IF(18<$D$12,0,$C$12*(1+Hipótesis!$D$12)*1.5) | V35: =IF(19<$D$12,0,$C$12*(1+Hipótesis!$D$12)*1) | W35: =IF(20<$D$12,0,$C$12*(1+Hipótesis!$D$12)*1) | X35: =IF(21<$D$12,0,$C$12*(1+Hipótesis!$D$12)*1) | Y35: =IF(22<$D$12,0,$C$12*(1+Hipótesis!$D$12)*1) | Z35: =IF(23<$D$12,0,$C$12*(1+Hipótesis!$D$12)*1) | AA35: =IF(24<$D$12,0,$C$12*(1+Hipótesis!$D$12)*1.5) | AB35: =SUM(P35:AA35) | AC35: =IF(25<$D$12,0,$C$12*(1+Hipótesis!$D$12)*(1+Hipótesis!$E$12)*1) | AD35: =IF(26<$D$12,0,$C$12*(1+Hipótesis!$D$12)*(1+Hipótesis!$E$12)*1) | AE35: =IF(27<$D$12,0,$C$12*(1+Hipótesis!$D$12)*(1+Hipótesis!$E$12)*1) | AF35: =IF(28<$D$12,0,$C$12*(1+Hipótesis!$D$12)*(1+Hipótesis!$E$12)*1) | AG35: =IF(29<$D$12,0,$C$12*(1+Hipótesis!$D$12)*(1+Hipótesis!$E$12)*1) | AH35: =IF(30<$D$12,0,$C$12*(1+Hipótesis!$D$12)*(1+Hipótesis!$E$12)*1.5) | AI35: =IF(31<$D$12,0,$C$12*(1+Hipótesis!$D$12)*(1+Hipótesis!$E$12)*1) | AJ35: =IF(32<$D$12,0,$C$12*(1+Hipótesis!$D$12)*(1+Hipótesis!$E$12)*1) | AK35: =IF(33<$D$12,0,$C$12*(1+Hipótesis!$D$12)*(1+Hipótesis!$E$12)*1) | AL35: =IF(34<$D$12,0,$C$12*(1+Hipótesis!$D$12)*(1+Hipótesis!$E$12)*1) | AM35: =IF(35<$D$12,0,$C$12*(1+Hipótesis!$D$12)*(1+Hipótesis!$E$12)*1) | AN35: =IF(36<$D$12,0,$C$12*(1+Hipótesis!$D$12)*(1+Hipótesis!$E$12)*1.5) | AO35: =SUM(AC35:AN35) | AP35: =IF(37<$D$12,0,$C$12*(1+Hipótesis!$D$12)*(1+Hipótesis!$E$12)*(1+Hipótesis!$F$12)*1) | AQ35: =IF(38<$D$12,0,$C$12*(1+Hipótesis!$D$12)*(1+Hipótesis!$E$12)*(1+Hipótesis!$F$12)*1) | AR35: =IF(39<$D$12,0,$C$12*(1+Hipótesis!$D$12)*(1+Hipótesis!$E$12)*(1+Hipótesis!$F$12)*1) | AS35: =IF(40<$D$12,0,$C$12*(1+Hipótesis!$D$12)*(1+Hipótesis!$E$12)*(1+Hipótesis!$F$12)*1) | AT35: =IF(41<$D$12,0,$C$12*(1+Hipótesis!$D$12)*(1+Hipótesis!$E$12)*(1+Hipótesis!$F$12)*1) | AU35: =IF(42<$D$12,0,$C$12*(1+Hipótesis!$D$12)*(1+Hipótesis!$E$12)*(1+Hipótesis!$F$12)*1.5) | AV35: =IF(43<$D$12,0,$C$12*(1+Hipótesis!$D$12)*(1+Hipótesis!$E$12)*(1+Hipótesis!$F$12)*1) | AW35: =IF(44<$D$12,0,$C$12*(1+Hipótesis!$D$12)*(1+Hipótesis!$E$12)*(1+Hipótesis!$F$12)*1) | AX35: =IF(45<$D$12,0,$C$12*(1+Hipótesis!$D$12)*(1+Hipótesis!$E$12)*(1+Hipótesis!$F$12)*1) | AY35: =IF(46<$D$12,0,$C$12*(1+Hipótesis!$D$12)*(1+Hipótesis!$E$12)*(1+Hipótesis!$F$12)*1) | AZ35: =IF(47<$D$12,0,$C$12*(1+Hipótesis!$D$12)*(1+Hipótesis!$E$12)*(1+Hipótesis!$F$12)*1) | BA35: =IF(48<$D$12,0,$C$12*(1+Hipótesis!$D$12)*(1+Hipótesis!$E$12)*(1+Hipótesis!$F$12)*1.5) | BB35: =SUM(AP35:BA35)
B36: Segundo colaborador de soporte | C36: =IF(1<$D$13,0,$C$13*1*1) | D36: =IF(2<$D$13,0,$C$13*1*1) | E36: =IF(3<$D$13,0,$C$13*1*1) | F36: =IF(4<$D$13,0,$C$13*1*1) | G36: =IF(5<$D$13,0,$C$13*1*1) | H36: =IF(6<$D$13,0,$C$13*1*1.5) | I36: =IF(7<$D$13,0,$C$13*1*1) | J36: =IF(8<$D$13,0,$C$13*1*1) | K36: =IF(9<$D$13,0,$C$13*1*1) | L36: =IF(10<$D$13,0,$C$13*1*1) | M36: =IF(11<$D$13,0,$C$13*1*1) | N36: =IF(12<$D$13,0,$C$13*1*1.5) | O36: =SUM(C36:N36) | P36: =IF(13<$D$13,0,$C$13*(1+Hipótesis!$D$12)*1) | Q36: =IF(14<$D$13,0,$C$13*(1+Hipótesis!$D$12)*1) | R36: =IF(15<$D$13,0,$C$13*(1+Hipótesis!$D$12)*1) | S36: =IF(16<$D$13,0,$C$13*(1+Hipótesis!$D$12)*1) | T36: =IF(17<$D$13,0,$C$13*(1+Hipótesis!$D$12)*1) | U36: =IF(18<$D$13,0,$C$13*(1+Hipótesis!$D$12)*1.5) | V36: =IF(19<$D$13,0,$C$13*(1+Hipótesis!$D$12)*1) | W36: =IF(20<$D$13,0,$C$13*(1+Hipótesis!$D$12)*1) | X36: =IF(21<$D$13,0,$C$13*(1+Hipótesis!$D$12)*1) | Y36: =IF(22<$D$13,0,$C$13*(1+Hipótesis!$D$12)*1) | Z36: =IF(23<$D$13,0,$C$13*(1+Hipótesis!$D$12)*1) | AA36: =IF(24<$D$13,0,$C$13*(1+Hipótesis!$D$12)*1.5) | AB36: =SUM(P36:AA36) | AC36: =IF(25<$D$13,0,$C$13*(1+Hipótesis!$D$12)*(1+Hipótesis!$E$12)*1) | AD36: =IF(26<$D$13,0,$C$13*(1+Hipótesis!$D$12)*(1+Hipótesis!$E$12)*1) | AE36: =IF(27<$D$13,0,$C$13*(1+Hipótesis!$D$12)*(1+Hipótesis!$E$12)*1) | AF36: =IF(28<$D$13,0,$C$13*(1+Hipótesis!$D$12)*(1+Hipótesis!$E$12)*1) | AG36: =IF(29<$D$13,0,$C$13*(1+Hipótesis!$D$12)*(1+Hipótesis!$E$12)*1) | AH36: =IF(30<$D$13,0,$C$13*(1+Hipótesis!$D$12)*(1+Hipótesis!$E$12)*1.5) | AI36: =IF(31<$D$13,0,$C$13*(1+Hipótesis!$D$12)*(1+Hipótesis!$E$12)*1) | AJ36: =IF(32<$D$13,0,$C$13*(1+Hipótesis!$D$12)*(1+Hipótesis!$E$12)*1) | AK36: =IF(33<$D$13,0,$C$13*(1+Hipótesis!$D$12)*(1+Hipótesis!$E$12)*1) | AL36: =IF(34<$D$13,0,$C$13*(1+Hipótesis!$D$12)*(1+Hipótesis!$E$12)*1) | AM36: =IF(35<$D$13,0,$C$13*(1+Hipótesis!$D$12)*(1+Hipótesis!$E$12)*1) | AN36: =IF(36<$D$13,0,$C$13*(1+Hipótesis!$D$12)*(1+Hipótesis!$E$12)*1.5) | AO36: =SUM(AC36:AN36) | AP36: =IF(37<$D$13,0,$C$13*(1+Hipótesis!$D$12)*(1+Hipótesis!$E$12)*(1+Hipótesis!$F$12)*1) | AQ36: =IF(38<$D$13,0,$C$13*(1+Hipótesis!$D$12)*(1+Hipótesis!$E$12)*(1+Hipótesis!$F$12)*1) | AR36: =IF(39<$D$13,0,$C$13*(1+Hipótesis!$D$12)*(1+Hipótesis!$E$12)*(1+Hipótesis!$F$12)*1) | AS36: =IF(40<$D$13,0,$C$13*(1+Hipótesis!$D$12)*(1+Hipótesis!$E$12)*(1+Hipótesis!$F$12)*1) | AT36: =IF(41<$D$13,0,$C$13*(1+Hipótesis!$D$12)*(1+Hipótesis!$E$12)*(1+Hipótesis!$F$12)*1) | AU36: =IF(42<$D$13,0,$C$13*(1+Hipótesis!$D$12)*(1+Hipótesis!$E$12)*(1+Hipótesis!$F$12)*1.5) | AV36: =IF(43<$D$13,0,$C$13*(1+Hipótesis!$D$12)*(1+Hipótesis!$E$12)*(1+Hipótesis!$F$12)*1) | AW36: =IF(44<$D$13,0,$C$13*(1+Hipótesis!$D$12)*(1+Hipótesis!$E$12)*(1+Hipótesis!$F$12)*1) | AX36: =IF(45<$D$13,0,$C$13*(1+Hipótesis!$D$12)*(1+Hipótesis!$E$12)*(1+Hipótesis!$F$12)*1) | AY36: =IF(46<$D$13,0,$C$13*(1+Hipótesis!$D$12)*(1+Hipótesis!$E$12)*(1+Hipótesis!$F$12)*1) | AZ36: =IF(47<$D$13,0,$C$13*(1+Hipótesis!$D$12)*(1+Hipótesis!$E$12)*(1+Hipótesis!$F$12)*1) | BA36: =IF(48<$D$13,0,$C$13*(1+Hipótesis!$D$12)*(1+Hipótesis!$E$12)*(1+Hipótesis!$F$12)*1.5) | BB36: =SUM(AP36:BA36)
B37: Total de salarios brutos | C37: =SUM(C31:C36) | D37: =SUM(D31:D36) | E37: =SUM(E31:E36) | F37: =SUM(F31:F36) | G37: =SUM(G31:G36) | H37: =SUM(H31:H36) | I37: =SUM(I31:I36) | J37: =SUM(J31:J36) | ... N37: =SUM(N31:N36) | O37: =SUM(C37:N37) | P37: =SUM(P31:P36) | Q37: =SUM(Q31:Q36) | R37: =SUM(R31:R36) | S37: =SUM(S31:S36) | T37: =SUM(T31:T36) | U37: =SUM(U31:U36) | V37: =SUM(V31:V36) | W37: =SUM(W31:W36) | ... AA37: =SUM(AA31:AA36) | AB37: =SUM(P37:AA37) | AC37: =SUM(AC31:AC36) | AD37: =SUM(AD31:AD36) | AE37: =SUM(AE31:AE36) | AF37: =SUM(AF31:AF36) | AG37: =SUM(AG31:AG36) | AH37: =SUM(AH31:AH36) | AI37: =SUM(AI31:AI36) | AJ37: =SUM(AJ31:AJ36) | ... AN37: =SUM(AN31:AN36) | AO37: =SUM(AC37:AN37) | AP37: =SUM(AP31:AP36) | AQ37: =SUM(AQ31:AQ36) | AR37: =SUM(AR31:AR36) | AS37: =SUM(AS31:AS36) | AT37: =SUM(AT31:AT36) | AU37: =SUM(AU31:AU36) | AV37: =SUM(AV31:AV36) | AW37: =SUM(AW31:AW36) | ... BA37: =SUM(BA31:BA36) | BB37: =SUM(AP37:BA37)
B38: Cargas sociales | C38: =C37*$C$26 | D38: =D37*$C$26 | E38: =E37*$C$26 | F38: =F37*$C$26 | G38: =G37*$C$26 | H38: =H37*$C$26 | I38: =I37*$C$26 | J38: =J37*$C$26 | ... N38: =N37*$C$26 | O38: =SUM(C38:N38) | P38: =P37*$C$26 | Q38: =Q37*$C$26 | R38: =R37*$C$26 | S38: =S37*$C$26 | T38: =T37*$C$26 | U38: =U37*$C$26 | V38: =V37*$C$26 | W38: =W37*$C$26 | ... AA38: =AA37*$C$26 | AB38: =SUM(P38:AA38) | AC38: =AC37*$C$26 | AD38: =AD37*$C$26 | AE38: =AE37*$C$26 | AF38: =AF37*$C$26 | AG38: =AG37*$C$26 | AH38: =AH37*$C$26 | AI38: =AI37*$C$26 | AJ38: =AJ37*$C$26 | ... AN38: =AN37*$C$26 | AO38: =SUM(AC38:AN38) | AP38: =AP37*$C$26 | AQ38: =AQ37*$C$26 | AR38: =AR37*$C$26 | AS38: =AS37*$C$26 | AT38: =AT37*$C$26 | AU38: =AU37*$C$26 | AV38: =AV37*$C$26 | AW38: =AW37*$C$26 | ... BA38: =BA37*$C$26 | BB38: =SUM(AP38:BA38)
A39: TOTAL | B39: Costo total de RRHH | C39: =C37+C38 | D39: =D37+D38 | E39: =E37+E38 | F39: =F37+F38 | G39: =G37+G38 | H39: =H37+H38 | I39: =I37+I38 | J39: =J37+J38 | ... N39: =N37+N38 | O39: =SUM(C39:N39) | P39: =P37+P38 | Q39: =Q37+Q38 | R39: =R37+R38 | S39: =S37+S38 | T39: =T37+T38 | U39: =U37+U38 | V39: =V37+V38 | W39: =W37+W38 | ... AA39: =AA37+AA38 | AB39: =SUM(P39:AA39) | AC39: =AC37+AC38 | AD39: =AD37+AD38 | AE39: =AE37+AE38 | AF39: =AF37+AF38 | AG39: =AG37+AG38 | AH39: =AH37+AH38 | AI39: =AI37+AI38 | AJ39: =AJ37+AJ38 | ... AN39: =AN37+AN38 | AO39: =SUM(AC39:AN39) | AP39: =AP37+AP38 | AQ39: =AQ37+AQ38 | AR39: =AR37+AR38 | AS39: =AS37+AS38 | AT39: =AT37+AT38 | AU39: =AU37+AU38 | AV39: =AV37+AV38 | AW39: =AW37+AW38 | ... BA39: =BA37+BA38 | BB39: =SUM(AP39:BA39)
B40: Personas en la plantilla | C40: =COUNTIF(C31:C36,">0") | D40: =COUNTIF(D31:D36,">0") | E40: =COUNTIF(E31:E36,">0") | F40: =COUNTIF(F31:F36,">0") | G40: =COUNTIF(G31:G36,">0") | H40: =COUNTIF(H31:H36,">0") | I40: =COUNTIF(I31:I36,">0") | J40: =COUNTIF(J31:J36,">0") | ... N40: =COUNTIF(N31:N36,">0") | O40: =N40 | P40: =COUNTIF(P31:P36,">0") | Q40: =COUNTIF(Q31:Q36,">0") | R40: =COUNTIF(R31:R36,">0") | S40: =COUNTIF(S31:S36,">0") | T40: =COUNTIF(T31:T36,">0") | U40: =COUNTIF(U31:U36,">0") | V40: =COUNTIF(V31:V36,">0") | W40: =COUNTIF(W31:W36,">0") | ... AA40: =COUNTIF(AA31:AA36,">0") | AB40: =AA40 | AC40: =COUNTIF(AC31:AC36,">0") | AD40: =COUNTIF(AD31:AD36,">0") | AE40: =COUNTIF(AE31:AE36,">0") | AF40: =COUNTIF(AF31:AF36,">0") | AG40: =COUNTIF(AG31:AG36,">0") | AH40: =COUNTIF(AH31:AH36,">0") | AI40: =COUNTIF(AI31:AI36,">0") | AJ40: =COUNTIF(AJ31:AJ36,">0") | ... AN40: =COUNTIF(AN31:AN36,">0") | AO40: =AN40 | AP40: =COUNTIF(AP31:AP36,">0") | AQ40: =COUNTIF(AQ31:AQ36,">0") | AR40: =COUNTIF(AR31:AR36,">0") | AS40: =COUNTIF(AS31:AS36,">0") | AT40: =COUNTIF(AT31:AT36,">0") | AU40: =COUNTIF(AU31:AU36,">0") | AV40: =COUNTIF(AV31:AV36,">0") | AW40: =COUNTIF(AW31:AW36,">0") | ... BA40: =COUNTIF(BA31:BA36,">0") | BB40: =BA40
